Workbook
Name _DLX1: [1]Rates!#REF!
Name _DLX1.INC: '[2]Car Air'!#REF!
Name _DLX10_INC: #REF!
Name _DLX10.INC: '[3]US&Europe'!#REF!
Name _DLX100.INC: '[3]Bonds Data BIS'!#REF!
Name _DLX14.INC: #REF!
Name _DLX15.INC: '[3]Bonds Data BIS'!#REF!
Name _DLX16.INC: '[3]Bonds Data BIS'!#REF!
Name _DLX2.INC: #REF!
Name _DLX20.INC: #REF!
Name _DLX3.INC: #REF!
Name _DLX4.INC: #REF!
Name _DLX5_INC: #REF!
Name _DLX5.INC: #REF!
Name _DLX50.INC: '[3]US&Europe'!#REF!
Name _DLX52.INC: #REF!
Name _DLX53.INC: '[3]US&Europe'!#REF!
Name _DLX54.INC: '[3]US&Europe'!#REF!
Name _DLX56.INC: '[3]US&Europe'!#REF!
Name _DLX6.INC: #REF!
Name _DLX60.INC: #REF!
Name _DLX7.INC: '[3]US&Europe'!#REF!
Name _DLX8.INC: '[3]US&Europe'!#REF!
Name _DLX80.INC: '[3]Bonds Data BIS'!#REF!
Name _DLX9.INC: '[3]US&Europe'!#REF!
Name AUD_Nom: #REF!
Name AUD_Tenor: #REF!
Name AUD_yr: #REF!
Name CAD_Nom: #REF!
Name CAD_Tenor: #REF!
Name CAD_yr: #REF!
Name CHF_Nom: #REF!
Name CHF_Tenor: #REF!
Name CHF_yr: #REF!
Name cn_asia: [4]Weights!$J$5
Name code: [5]CONSTANT!#REF!
Name Currency_cusip: '[6]Currency bucketing mapping'!$B$35:$B$160
Name Currency_name: '[6]Currency bucketing mapping'!$B$35:$BF$35
Name Currency_table: '[6]Currency bucketing mapping'!$B$35:$BF$160
Name D_0: #REF!
Name D_0_DE: #REF!
Name D_0_FR: #REF!
Name D_0_IT: #REF!
Name D_0_JP: #REF!
Name D_0_UK: #REF!
Name DaysInYear: [7]C!$B$29
Name DE_gwth: #REF!
Name DE_S: #REF!
Name ERP: [8]CF20!$C$18
Name EUR_Nom: #REF!
Name EUR_Tenor: #REF!
Name EUR_yr: #REF!
Name FR_gwth: #REF!
Name FR_S: #REF!
Name GBP_Nom: #REF!
Name GBP_Tenor: #REF!
Name GBP_yr: #REF!
Name gGDP: [8]CF20!$C$14
Name hk_asia: [4]Weights!$J$6
Name hk_nie: [4]Weights!$K$6

Sheet Front Page
B1: Description
B5: TOC Colour Coding
B6: Inputs
B7: Calculation
B8: Raw Report
B9: Raw Report with Key
B11: Table Colors
B12: Uploaded to Python
B13: Not Uploaded to Python
B16: Table of Contents
B17: Salary Model
B18: Model Parameters
... B29: Loop used when executing the python script

Sheet Salary Variables
B2: Inflation | C2: =2%*(1+10%) -> 0.022
B3: Salary Growth
B4: Salary Raise | C4: 0.03
B5: Real Salary Raise | C5: =C4-C2 -> 0.008
B6: Job Hopping "Bonus" | C6: 0.06
B7: Real Job Hopping "Bonus" | C7: =C6-C2 -> 0.038
B8: % of salary dedicated to investments | C8: 0.2
B9: Initial Salary P1 | C9: 43871
B10: Initial Salary P2 | C10: 72000
B11: Contribution to pension
B12: Personal | C12: 0.05
B13: Company | C13: 0.1
B14: Aldersopsparing maximum contribution | C14: 9400
B15: Tax
B16: AM (%) | C16: 0.08
B17: Personal Allowance | C17: 51600
B18: Bottom-Bracket State Tax rate (%) | C18: 0.1201
B19: Top-bracket State Tax rate (%) | C19: 0.15
B20: State Tax Bracket Threshold | C20: 618400
B21: Municipal Tax (%) | C21: 0.25
B22: Capital Gains < 67,500DKK | C22: 0.27
B23: Capital Gains > 67,500DKK | C23: 0.42
B24: Capital Gains Threshold | C24: 67500

Sheet Income - P2 Helper
B2: Inflation | C2: =Income!I2 -> 0.022 | G2: GrossMonthlyInflationAdjustedP2 | H2: GrossMonthlySalaryP2 | I2: SwitchP2 | J2: Inverse | K2: Year | M2: Year | N2: GrossMonthlyInflationAdjustedP2 | O2: GrossMonthlySalaryP2
B3: Salary Raise | C3: =Income!I3 -> 0.03 | G3: =TableIncomeCalculations11[[#This Row],[GrossMonthlySalaryP2]]/(1+C2) -> 72731.908 | H3: =TableIncomeCalculations[[#This Row],[GrossMonthlySalaryP2]] -> 74332.01 | I3: =JobHopping[[#This Row],[SwitchP2Static]] -> N | J3: {=INDEX($I$3:$I$18,ROWS($I$3:$I$18)+ROW($I$3)-ROW())} -> N | K3: 2025 | M3: {=INDEX($K$3:$K$18,ROWS($K$3:$K$18)+ROW($K$3)-ROW())} -> 2010 | N3: {=INDEX($G$3:$G$18,ROWS($G$3:$G$18)+ROW($G$3)-ROW())} -> 55203.706 | O3: {=INDEX($H$3:$H$18,ROWS($H$3:$H$18)+ROW($H$3)-ROW())} -> 36965.724 | Q3: =Table11[[#This Row],[GrossMonthlyInflationAdjustedP2]]*0.2 -> 11040.741
B4: Real Salary Raise | C4: =Income!I4 -> 0.008 | G4: =(G3/(1+$C$4))-IF(TableIncomeCalculations11[[#This Row],[Inverse]]="Y",G3*$C$6,0) -> 72154.671 | H4: =(H3/(1+$C$3))-IF(TableIncomeCalculations11[[#This Row],[Inverse]]="Y",H3*$C$5,0) -> 72167 | I4: =JobHopping[[#This Row],[SwitchP2Static]] -> N | J4: {=INDEX($I$3:$I$18,ROWS($I$3:$I$18)+ROW($I$3)-ROW())} -> N | K4: 2024 | M4: {=INDEX($K$3:$K$18,ROWS($K$3:$K$18)+ROW($K$3)-ROW())} -> 2011 | N4: {=INDEX($G$3:$G$18,ROWS($G$3:$G$18)+ROW($G$3)-ROW())} -> 55645.336 | O4: {=INDEX($H$3:$H$18,ROWS($H$3:$H$18)+ROW($H$3)-ROW())} -> 38074.696 | Q4: =Table11[[#This Row],[GrossMonthlyInflationAdjustedP2]]*0.2 -> 11129.067
B5: Job Hopping "Bonus" | C5: =Income!I5 -> 0.06 | G5: =(G4/(1+$C$4))-IF(TableIncomeCalculations11[[#This Row],[Inverse]]="Y",G4*$C$6,0) -> 68840.137 | H5: =(H4/(1+$C$3))-IF(TableIncomeCalculations11[[#This Row],[Inverse]]="Y",H4*$C$5,0) -> 65735.029 | I5: =JobHopping[[#This Row],[SwitchP2Static]] -> Y | J5: {=INDEX($I$3:$I$18,ROWS($I$3:$I$18)+ROW($I$3)-ROW())} -> Y | K5: 2023 | M5: {=INDEX($K$3:$K$18,ROWS($K$3:$K$18)+ROW($K$3)-ROW())} -> 2012 | N5: {=INDEX($G$3:$G$18,ROWS($G$3:$G$18)+ROW($G$3)-ROW())} -> 56090.499 | O5: {=INDEX($H$3:$H$18,ROWS($H$3:$H$18)+ROW($H$3)-ROW())} -> 39216.937 | Q5: =Table11[[#This Row],[GrossMonthlyInflationAdjustedP2]]*0.2 -> 11218.1
B6: Real Job Hopping "Bonus" | C6: =Income!I6 -> 0.038 | G6: =(G5/(1+$C$4))-IF(TableIncomeCalculations11[[#This Row],[Inverse]]="Y",G5*$C$6,0) -> 68293.787 | H6: =(H5/(1+$C$3))-IF(TableIncomeCalculations11[[#This Row],[Inverse]]="Y",H5*$C$5,0) -> 63820.416 | I6: =JobHopping[[#This Row],[SwitchP2Static]] -> N | J6: {=INDEX($I$3:$I$18,ROWS($I$3:$I$18)+ROW($I$3)-ROW())} -> N | K6: 2022 | M6: {=INDEX($K$3:$K$18,ROWS($K$3:$K$18)+ROW($K$3)-ROW())} -> 2013 | N6: {=INDEX($G$3:$G$18,ROWS($G$3:$G$18)+ROW($G$3)-ROW())} -> 58791.159 | O6: {=INDEX($H$3:$H$18,ROWS($H$3:$H$18)+ROW($H$3)-ROW())} -> 43054.194 | Q6: =Table11[[#This Row],[GrossMonthlyInflationAdjustedP2]]*0.2 -> 11758.232
B7: % of salary dedicated to investments | C7: =Income!I7 -> 0.2 | G7: =(G6/(1+$C$4))-IF(TableIncomeCalculations11[[#This Row],[Inverse]]="Y",G6*$C$6,0) -> 67751.773 | H7: =(H6/(1+$C$3))-IF(TableIncomeCalculations11[[#This Row],[Inverse]]="Y",H6*$C$5,0) -> 61961.569 | I7: =JobHopping[[#This Row],[SwitchP2Static]] -> N | J7: {=INDEX($I$3:$I$18,ROWS($I$3:$I$18)+ROW($I$3)-ROW())} -> N | K7: 2021 | M7: {=INDEX($K$3:$K$18,ROWS($K$3:$K$18)+ROW($K$3)-ROW())} -> 2014 | N7: {=INDEX($G$3:$G$18,ROWS($G$3:$G$18)+ROW($G$3)-ROW())} -> 59261.489 | O7: {=INDEX($H$3:$H$18,ROWS($H$3:$H$18)+ROW($H$3)-ROW())} -> 44345.82 | Q7: =Table11[[#This Row],[GrossMonthlyInflationAdjustedP2]]*0.2 -> 11852.298
G8: =(G7/(1+$C$4))-IF(TableIncomeCalculations11[[#This Row],[Inverse]]="Y",G7*$C$6,0) -> 64639.493 | H8: =(H7/(1+$C$3))-IF(TableIncomeCalculations11[[#This Row],[Inverse]]="Y",H7*$C$5,0) -> 56439.169 | I8: =JobHopping[[#This Row],[SwitchP2Static]] -> N | J8: {=INDEX($I$3:$I$18,ROWS($I$3:$I$18)+ROW($I$3)-ROW())} -> Y | K8: 2020 | M8: {=INDEX($K$3:$K$18,ROWS($K$3:$K$18)+ROW($K$3)-ROW())} -> 2015 | N8: {=INDEX($G$3:$G$18,ROWS($G$3:$G$18)+ROW($G$3)-ROW())} -> 59735.581 | O8: {=INDEX($H$3:$H$18,ROWS($H$3:$H$18)+ROW($H$3)-ROW())} -> 45676.195 | Q8: =Table11[[#This Row],[GrossMonthlyInflationAdjustedP2]]*0.2 -> 11947.116
G9: =(G8/(1+$C$4))-IF(TableIncomeCalculations11[[#This Row],[Inverse]]="Y",G8*$C$6,0) -> 64126.481 | H9: =(H8/(1+$C$3))-IF(TableIncomeCalculations11[[#This Row],[Inverse]]="Y",H8*$C$5,0) -> 54795.31 | I9: =JobHopping[[#This Row],[SwitchP2Static]] -> Y | J9: {=INDEX($I$3:$I$18,ROWS($I$3:$I$18)+ROW($I$3)-ROW())} -> N | K9: 2019 | M9: {=INDEX($K$3:$K$18,ROWS($K$3:$K$18)+ROW($K$3)-ROW())} -> 2016 | N9: {=INDEX($G$3:$G$18,ROWS($G$3:$G$18)+ROW($G$3)-ROW())} -> 60213.465 | O9: {=INDEX($H$3:$H$18,ROWS($H$3:$H$18)+ROW($H$3)-ROW())} -> 47046.481 | Q9: =Table11[[#This Row],[GrossMonthlyInflationAdjustedP2]]*0.2 -> 12042.693
G10: =(G9/(1+$C$4))-IF(TableIncomeCalculations11[[#This Row],[Inverse]]="Y",G9*$C$6,0) -> 63617.541 | H10: =(H9/(1+$C$3))-IF(TableIncomeCalculations11[[#This Row],[Inverse]]="Y",H9*$C$5,0) -> 53199.33 | I10: =JobHopping[[#This Row],[SwitchP2Static]] -> N | J10: {=INDEX($I$3:$I$18,ROWS($I$3:$I$18)+ROW($I$3)-ROW())} -> N | K10: 2018 | M10: {=INDEX($K$3:$K$18,ROWS($K$3:$K$18)+ROW($K$3)-ROW())} -> 2017 | N10: {=INDEX($G$3:$G$18,ROWS($G$3:$G$18)+ROW($G$3)-ROW())} -> 63112.639 | O10: {=INDEX($H$3:$H$18,ROWS($H$3:$H$18)+ROW($H$3)-ROW())} -> 51649.835 | Q10: =Table11[[#This Row],[GrossMonthlyInflationAdjustedP2]]*0.2 -> 12622.528
G11: =(G10/(1+$C$4))-IF(TableIncomeCalculations11[[#This Row],[Inverse]]="Y",G10*$C$6,0) -> 63112.639 | H11: =(H10/(1+$C$3))-IF(TableIncomeCalculations11[[#This Row],[Inverse]]="Y",H10*$C$5,0) -> 51649.835 | I11: =JobHopping[[#This Row],[SwitchP2Static]] -> N | J11: {=INDEX($I$3:$I$18,ROWS($I$3:$I$18)+ROW($I$3)-ROW())} -> N | K11: 2017 | M11: {=INDEX($K$3:$K$18,ROWS($K$3:$K$18)+ROW($K$3)-ROW())} -> 2018 | N11: {=INDEX($G$3:$G$18,ROWS($G$3:$G$18)+ROW($G$3)-ROW())} -> 63617.541 | O11: {=INDEX($H$3:$H$18,ROWS($H$3:$H$18)+ROW($H$3)-ROW())} -> 53199.33 | Q11: =Table11[[#This Row],[GrossMonthlyInflationAdjustedP2]]*0.2 -> 12723.508
G12: =(G11/(1+$C$4))-IF(TableIncomeCalculations11[[#This Row],[Inverse]]="Y",G11*$C$6,0) -> 60213.465 | H12: =(H11/(1+$C$3))-IF(TableIncomeCalculations11[[#This Row],[Inverse]]="Y",H11*$C$5,0) -> 47046.481 | I12: =JobHopping[[#This Row],[SwitchP2Static]] -> N | J12: {=INDEX($I$3:$I$18,ROWS($I$3:$I$18)+ROW($I$3)-ROW())} -> Y | K12: 2016 | M12: {=INDEX($K$3:$K$18,ROWS($K$3:$K$18)+ROW($K$3)-ROW())} -> 2019 | N12: {=INDEX($G$3:$G$18,ROWS($G$3:$G$18)+ROW($G$3)-ROW())} -> 64126.481 | O12: {=INDEX($H$3:$H$18,ROWS($H$3:$H$18)+ROW($H$3)-ROW())} -> 54795.31 | Q12: =Table11[[#This Row],[GrossMonthlyInflationAdjustedP2]]*0.2 -> 12825.296
G13: =(G12/(1+$C$4))-IF(TableIncomeCalculations11[[#This Row],[Inverse]]="Y",G12*$C$6,0) -> 59735.581 | H13: =(H12/(1+$C$3))-IF(TableIncomeCalculations11[[#This Row],[Inverse]]="Y",H12*$C$5,0) -> 45676.195 | I13: =JobHopping[[#This Row],[SwitchP2Static]] -> Y | J13: {=INDEX($I$3:$I$18,ROWS($I$3:$I$18)+ROW($I$3)-ROW())} -> N | K13: 2015 | M13: {=INDEX($K$3:$K$18,ROWS($K$3:$K$18)+ROW($K$3)-ROW())} -> 2020 | N13: {=INDEX($G$3:$G$18,ROWS($G$3:$G$18)+ROW($G$3)-ROW())} -> 64639.493 | O13: {=INDEX($H$3:$H$18,ROWS($H$3:$H$18)+ROW($H$3)-ROW())} -> 56439.169 | Q13: =Table11[[#This Row],[GrossMonthlyInflationAdjustedP2]]*0.2 -> 12927.899
G14: =(G13/(1+$C$4))-IF(TableIncomeCalculations11[[#This Row],[Inverse]]="Y",G13*$C$6,0) -> 59261.489 | H14: =(H13/(1+$C$3))-IF(TableIncomeCalculations11[[#This Row],[Inverse]]="Y",H13*$C$5,0) -> 44345.82 | I14: =JobHopping[[#This Row],[SwitchP2Static]] -> N | J14: {=INDEX($I$3:$I$18,ROWS($I$3:$I$18)+ROW($I$3)-ROW())} -> N | K14: 2014 | M14: {=INDEX($K$3:$K$18,ROWS($K$3:$K$18)+ROW($K$3)-ROW())} -> 2021 | N14: {=INDEX($G$3:$G$18,ROWS($G$3:$G$18)+ROW($G$3)-ROW())} -> 67751.773 | O14: {=INDEX($H$3:$H$18,ROWS($H$3:$H$18)+ROW($H$3)-ROW())} -> 61961.569 | Q14: =Table11[[#This Row],[GrossMonthlyInflationAdjustedP2]]*0.2 -> 13550.355
G15: =(G14/(1+$C$4))-IF(TableIncomeCalculations11[[#This Row],[Inverse]]="Y",G14*$C$6,0) -> 58791.159 | H15: =(H14/(1+$C$3))-IF(TableIncomeCalculations11[[#This Row],[Inverse]]="Y",H14*$C$5,0) -> 43054.194 | I15: =JobHopping[[#This Row],[SwitchP2Static]] -> N | J15: {=INDEX($I$3:$I$18,ROWS($I$3:$I$18)+ROW($I$3)-ROW())} -> N | K15: 2013 | M15: {=INDEX($K$3:$K$18,ROWS($K$3:$K$18)+ROW($K$3)-ROW())} -> 2022 | N15: {=INDEX($G$3:$G$18,ROWS($G$3:$G$18)+ROW($G$3)-ROW())} -> 68293.787 | O15: {=INDEX($H$3:$H$18,ROWS($H$3:$H$18)+ROW($H$3)-ROW())} -> 63820.416 | Q15: =Table11[[#This Row],[GrossMonthlyInflationAdjustedP2]]*0.2 -> 13658.757
G16: =(G15/(1+$C$4))-IF(TableIncomeCalculations11[[#This Row],[Inverse]]="Y",G15*$C$6,0) -> 56090.499 | H16: =(H15/(1+$C$3))-IF(TableIncomeCalculations11[[#This Row],[Inverse]]="Y",H15*$C$5,0) -> 39216.937 | I16: =JobHopping[[#This Row],[SwitchP2Static]] -> Y | J16: {=INDEX($I$3:$I$18,ROWS($I$3:$I$18)+ROW($I$3)-ROW())} -> Y | K16: 2012 | M16: {=INDEX($K$3:$K$18,ROWS($K$3:$K$18)+ROW($K$3)-ROW())} -> 2023 | N16: {=INDEX($G$3:$G$18,ROWS($G$3:$G$18)+ROW($G$3)-ROW())} -> 68840.137 | O16: {=INDEX($H$3:$H$18,ROWS($H$3:$H$18)+ROW($H$3)-ROW())} -> 65735.029 | Q16: =Table11[[#This Row],[GrossMonthlyInflationAdjustedP2]]*0.2 -> 13768.027
G17: =(G16/(1+$C$4))-IF(TableIncomeCalculations11[[#This Row],[Inverse]]="Y",G16*$C$6,0) -> 55645.336 | H17: =(H16/(1+$C$3))-IF(TableIncomeCalculations11[[#This Row],[Inverse]]="Y",H16*$C$5,0) -> 38074.696 | I17: =JobHopping[[#This Row],[SwitchP2Static]] -> N | J17: {=INDEX($I$3:$I$18,ROWS($I$3:$I$18)+ROW($I$3)-ROW())} -> N | K17: 2011 | M17: {=INDEX($K$3:$K$18,ROWS($K$3:$K$18)+ROW($K$3)-ROW())} -> 2024 | N17: {=INDEX($G$3:$G$18,ROWS($G$3:$G$18)+ROW($G$3)-ROW())} -> 72154.671 | O17: {=INDEX($H$3:$H$18,ROWS($H$3:$H$18)+ROW($H$3)-ROW())} -> 72167 | Q17: =Table11[[#This Row],[GrossMonthlyInflationAdjustedP2]]*0.2 -> 14430.934
G18: =(G17/(1+$C$4))-IF(TableIncomeCalculations11[[#This Row],[Inverse]]="Y",G17*$C$6,0) -> 55203.706 | H18: =(H17/(1+$C$3))-IF(TableIncomeCalculations11[[#This Row],[Inverse]]="Y",H17*$C$5,0) -> 36965.724 | I18: =JobHopping[[#This Row],[SwitchP2Static]] -> N | J18: {=INDEX($I$3:$I$18,ROWS($I$3:$I$18)+ROW($I$3)-ROW())} -> N | K18: 2010 | M18: {=INDEX($K$3:$K$18,ROWS($K$3:$K$18)+ROW($K$3)-ROW())} -> 2025 | N18: {=INDEX($G$3:$G$18,ROWS($G$3:$G$18)+ROW($G$3)-ROW())} -> 72731.908 | O18: {=INDEX($H$3:$H$18,ROWS($H$3:$H$18)+ROW($H$3)-ROW())} -> 74332.01 | Q18: =Table11[[#This Row],[GrossMonthlyInflationAdjustedP2]]*0.2 -> 14546.382
Q21: =SUM(Q3:Q18) -> 202041.93

Sheet Income
A1: Income!A1
B2: Year | C2: SalaryP1 | D2: SalaryP2 | E2: InvestmentP1 | F2: InvestmentP2 | H2: Inflation | I2: ='Salary Variables'!$C$2 -> 0.022 | K2: Post Investing | L2: Post Investing | M2: NetMonthlySalaryP1 | N2: NetMonthlySalaryP2 | O2: GrossMonthlyInflationAdjustedP1 | P2: GrossMonthlyInflationAdjustedP2 | Q2: GrossMonthlySalaryP1 | R2: GrossMonthlySalaryP2 | S2: SwitchP1 | T2: SwitchP2
B3: 2025 | C3: =(TableIncomeCalculations[[#This Row],[NetMonthlySalaryP1]]*12) -> 282407.2 | D3: =(TableIncomeCalculations[[#This Row],[NetMonthlySalaryP2]]*12) -> 462846.25 | E3: =TableIncome[[#This Row],[SalaryP1]]*$I$7 -> 56481.441 | F3: =TableIncome[[#This Row],[SalaryP2]]*$I$7 -> 92569.25 | H3: Salary Raise | I3: {='Salary Variables'!$C$4:$C$8} -> 0.03 | K3: =(TableIncome[[#This Row],[SalaryP1]]-TableIncome[[#This Row],[InvestmentP1]])/12 -> 18827.147 | L3: =(TableIncome[[#This Row],[SalaryP2]]-TableIncome[[#This Row],[InvestmentP2]])/12 -> 30856.417 | M3: ='Net Salary P1'!BI2 -> 23533.934 | N3: ='Net Salary P2'!BI2 -> 38570.521 | O3: =TableIncomeCalculations[[#This Row],[GrossMonthlySalaryP1]]/(1+I2) -> 43336.595 | P3: =TableIncomeCalculations[[#This Row],[GrossMonthlySalaryP2]]/(1+I2) -> 72731.908 | Q3: =43000*(1+I3) -> 44290 | R3: =72167*(1+I3) -> 74332.01 | S3: =JobHopping[[#This Row],[SwitchP1Static]] -> N | T3: =JobHopping[[#This Row],[SwitchP2Static]] -> N
B4: 2026 | C4: =(TableIncomeCalculations[[#This Row],[NetMonthlySalaryP1]]*12) -> 284697.59 | D4: =(TableIncomeCalculations[[#This Row],[NetMonthlySalaryP2]]*12) -> 465774.84 | E4: =TableIncome[[#This Row],[SalaryP1]]*$I$7 -> 56939.518 | F4: =TableIncome[[#This Row],[SalaryP2]]*$I$7 -> 93154.967 | H4: Real Salary Raise | I4: 0.008 | K4: =(TableIncome[[#This Row],[SalaryP1]]-TableIncome[[#This Row],[InvestmentP1]])/12 -> 18979.839 | L4: =(TableIncome[[#This Row],[SalaryP2]]-TableIncome[[#This Row],[InvestmentP2]])/12 -> 31051.656 | M4: ='Net Salary P1'!BI3 -> 23724.799 | N4: ='Net Salary P2'!BI3 -> 38814.57 | O4: =IF(_xlfn.XLOOKUP(TableIncome[[#This Row],[Year]],Loop!C:C,Loop!D:D)<75,(O3*(1+$I$4))+IF(TableIncomeCalculations[[#This Row],[SwitchP1]]="Y",O3*$I$6,0),0) -> 43683.288 | P4: =IF(_xlfn.XLOOKUP(TableIncome[[#This Row],[Year]],Loop!C:C,Loop!E:E)<75,(P3*(1+$I$4))+IF(TableIncomeCalculations[[#This Row],[SwitchP2]]="Y",P3*$I$6,0),0) -> 73313.763 | Q4: =IF(_xlfn.XLOOKUP(TableIncome[[#This Row],[Year]],Loop!C:C,Loop!D:D)<75,(Q3*(1+$I$3))+IF(TableIncomeCalculations[[#This Row],[SwitchP1]]="Y",Q3*$I$5,0),0) -> 45618.7 | R4: =IF(_xlfn.XLOOKUP(TableIncome[[#This Row],[Year]],Loop!C:C,Loop!E:E)<75,(R3*(1+$I$3))+IF(TableIncomeCalculations[[#This Row],[SwitchP2]]="Y",R3*$I$5,0),0) -> 76561.97 | S4: =JobHopping[[#This Row],[SwitchP1Static]] -> N | T4: =JobHopping[[#This Row],[SwitchP2Static]] -> N
B5: 2027 | C5: =(TableIncomeCalculations[[#This Row],[NetMonthlySalaryP1]]*12) -> 297972.68 | D5: =(TableIncomeCalculations[[#This Row],[NetMonthlySalaryP2]]*12) -> 482748.94 | E5: =TableIncome[[#This Row],[SalaryP1]]*$I$7 -> 59594.536 | F5: =TableIncome[[#This Row],[SalaryP2]]*$I$7 -> 96549.787 | H5: Job Hopping "Bonus" | I5: 0.06 | K5: =(TableIncome[[#This Row],[SalaryP1]]-TableIncome[[#This Row],[InvestmentP1]])/12 -> 19864.845 | L5: =(TableIncome[[#This Row],[SalaryP2]]-TableIncome[[#This Row],[InvestmentP2]])/12 -> 32183.262 | M5: ='Net Salary P1'!BI4 -> 24831.057 | N5: ='Net Salary P2'!BI4 -> 40229.078 | O5: =IF(_xlfn.XLOOKUP(TableIncome[[#This Row],[Year]],Loop!C:C,Loop!D:D)<75,(O4*(1+$I$4))+IF(TableIncomeCalculations[[#This Row],[SwitchP1]]="Y",O4*$I$6,0),0) -> 45692.719 | P5: =IF(_xlfn.XLOOKUP(TableIncome[[#This Row],[Year]],Loop!C:C,Loop!E:E)<75,(P4*(1+$I$4))+IF(TableIncomeCalculations[[#This Row],[SwitchP2]]="Y",P4*$I$6,0),0) -> 76686.196 | Q5: =IF(_xlfn.XLOOKUP(TableIncome[[#This Row],[Year]],Loop!C:C,Loop!D:D)<75,(Q4*(1+$I$3))+IF(TableIncomeCalculations[[#This Row],[SwitchP1]]="Y",Q4*$I$5,0),0) -> 49724.383 | R5: =IF(_xlfn.XLOOKUP(TableIncome[[#This Row],[Year]],Loop!C:C,Loop!E:E)<75,(R4*(1+$I$3))+IF(TableIncomeCalculations[[#This Row],[SwitchP2]]="Y",R4*$I$5,0),0) -> 83452.548 | S5: =JobHopping[[#This Row],[SwitchP1Static]] -> Y | T5: =JobHopping[[#This Row],[SwitchP2Static]] -> Y
B6: 2028 | C6: =(TableIncomeCalculations[[#This Row],[NetMonthlySalaryP1]]*12) -> 300387.59 | D6: =(TableIncomeCalculations[[#This Row],[NetMonthlySalaryP2]]*12) -> 485836.75 | E6: =TableIncome[[#This Row],[SalaryP1]]*$I$7 -> 60077.518 | F6: =TableIncome[[#This Row],[SalaryP2]]*$I$7 -> 97167.35 | H6: Real Job Hopping "Bonus" | I6: 0.038 | K6: =(TableIncome[[#This Row],[SalaryP1]]-TableIncome[[#This Row],[InvestmentP1]])/12 -> 20025.839 | L6: =(TableIncome[[#This Row],[SalaryP2]]-TableIncome[[#This Row],[InvestmentP2]])/12 -> 32389.117 | M6: ='Net Salary P1'!BI5 -> 25032.299 | N6: ='Net Salary P2'!BI5 -> 40486.396 | O6: =IF(_xlfn.XLOOKUP(TableIncome[[#This Row],[Year]],Loop!C:C,Loop!D:D)<75,(O5*(1+$I$4))+IF(TableIncomeCalculations[[#This Row],[SwitchP1]]="Y",O5*$I$6,0),0) -> 46058.261 | P6: =IF(_xlfn.XLOOKUP(TableIncome[[#This Row],[Year]],Loop!C:C,Loop!E:E)<75,(P5*(1+$I$4))+IF(TableIncomeCalculations[[#This Row],[SwitchP2]]="Y",P5*$I$6,0),0) -> 77299.686 | Q6: =IF(_xlfn.XLOOKUP(TableIncome[[#This Row],[Year]],Loop!C:C,Loop!D:D)<75,(Q5*(1+$I$3))+IF(TableIncomeCalculations[[#This Row],[SwitchP1]]="Y",Q5*$I$5,0),0) -> 51216.114 | R6: =IF(_xlfn.XLOOKUP(TableIncome[[#This Row],[Year]],Loop!C:C,Loop!E:E)<75,(R5*(1+$I$3))+IF(TableIncomeCalculations[[#This Row],[SwitchP2]]="Y",R5*$I$5,0),0) -> 85956.124 | S6: =JobHopping[[#This Row],[SwitchP1Static]] -> N | T6: =JobHopping[[#This Row],[SwitchP2Static]] -> N
B7: 2029 | C7: =(TableIncomeCalculations[[#This Row],[NetMonthlySalaryP1]]*12) -> 302821.82 | D7: =(TableIncomeCalculations[[#This Row],[NetMonthlySalaryP2]]*12) -> 488949.26 | E7: =TableIncome[[#This Row],[SalaryP1]]*$I$7 -> 60564.365 | F7: =TableIncome[[#This Row],[SalaryP2]]*$I$7 -> 97789.852 | H7: % of salary dedicated to investments | I7: 0.2 | K7: =(TableIncome[[#This Row],[SalaryP1]]-TableIncome[[#This Row],[InvestmentP1]])/12 -> 20188.122 | L7: =(TableIncome[[#This Row],[SalaryP2]]-TableIncome[[#This Row],[InvestmentP2]])/12 -> 32596.617 | M7: ='Net Salary P1'!BI6 -> 25235.152 | N7: ='Net Salary P2'!BI6 -> 40745.772 | O7: =IF(_xlfn.XLOOKUP(TableIncome[[#This Row],[Year]],Loop!C:C,Loop!D:D)<75,(O6*(1+$I$4))+IF(TableIncomeCalculations[[#This Row],[SwitchP1]]="Y",O6*$I$6,0),0) -> 46426.727 | P7: =IF(_xlfn.XLOOKUP(TableIncome[[#This Row],[Year]],Loop!C:C,Loop!E:E)<75,(P6*(1+$I$4))+IF(TableIncomeCalculations[[#This Row],[SwitchP2]]="Y",P6*$I$6,0),0) -> 77918.083 | Q7: =IF(_xlfn.XLOOKUP(TableIncome[[#This Row],[Year]],Loop!C:C,Loop!D:D)<75,(Q6*(1+$I$3))+IF(TableIncomeCalculations[[#This Row],[SwitchP1]]="Y",Q6*$I$5,0),0) -> 52752.598 | R7: =IF(_xlfn.XLOOKUP(TableIncome[[#This Row],[Year]],Loop!C:C,Loop!E:E)<75,(R6*(1+$I$3))+IF(TableIncomeCalculations[[#This Row],[SwitchP2]]="Y",R6*$I$5,0),0) -> 88534.808 | S7: =JobHopping[[#This Row],[SwitchP1Static]] -> N | T7: =JobHopping[[#This Row],[SwitchP2Static]] -> N
B8: 2030 | C8: =(TableIncomeCalculations[[#This Row],[NetMonthlySalaryP1]]*12) -> 305275.53 | D8: =(TableIncomeCalculations[[#This Row],[NetMonthlySalaryP2]]*12) -> 492086.67 | E8: =TableIncome[[#This Row],[SalaryP1]]*$I$7 -> 61055.106 | F8: =TableIncome[[#This Row],[SalaryP2]]*$I$7 -> 98417.335 | K8: =(TableIncome[[#This Row],[SalaryP1]]-TableIncome[[#This Row],[InvestmentP1]])/12 -> 20351.702 | L8: =(TableIncome[[#This Row],[SalaryP2]]-TableIncome[[#This Row],[InvestmentP2]])/12 -> 32805.778 | M8: ='Net Salary P1'!BI7 -> 25439.627 | N8: ='Net Salary P2'!BI7 -> 41007.223 | O8: =IF(_xlfn.XLOOKUP(TableIncome[[#This Row],[Year]],Loop!C:C,Loop!D:D)<75,(O7*(1+$I$4))+IF(TableIncomeCalculations[[#This Row],[SwitchP1]]="Y",O7*$I$6,0),0) -> 46798.141 | P8: =IF(_xlfn.XLOOKUP(TableIncome[[#This Row],[Year]],Loop!C:C,Loop!E:E)<75,(P7*(1+$I$4))+IF(TableIncomeCalculations[[#This Row],[SwitchP2]]="Y",P7*$I$6,0),0) -> 78541.428 | Q8: =IF(_xlfn.XLOOKUP(TableIncome[[#This Row],[Year]],Loop!C:C,Loop!D:D)<75,(Q7*(1+$I$3))+IF(TableIncomeCalculations[[#This Row],[SwitchP1]]="Y",Q7*$I$5,0),0) -> 54335.176 | R8: =IF(_xlfn.XLOOKUP(TableIncome[[#This Row],[Year]],Loop!C:C,Loop!E:E)<75,(R7*(1+$I$3))+IF(TableIncomeCalculations[[#This Row],[SwitchP2]]="Y",R7*$I$5,0),0) -> 91190.852 | S8: =JobHopping[[#This Row],[SwitchP1Static]] -> N | T8: =JobHopping[[#This Row],[SwitchP2Static]] -> N
B9: 2031 | C9: =(TableIncomeCalculations[[#This Row],[NetMonthlySalaryP1]]*12) -> 319497.2 | D9: =(TableIncomeCalculations[[#This Row],[NetMonthlySalaryP2]]*12) -> 510271.12 | E9: =TableIncome[[#This Row],[SalaryP1]]*$I$7 -> 63899.44 | F9: =TableIncome[[#This Row],[SalaryP2]]*$I$7 -> 102054.22 | K9: =(TableIncome[[#This Row],[SalaryP1]]-TableIncome[[#This Row],[InvestmentP1]])/12 -> 21299.813 | L9: =(TableIncome[[#This Row],[SalaryP2]]-TableIncome[[#This Row],[InvestmentP2]])/12 -> 34018.075 | M9: ='Net Salary P1'!BI8 -> 26624.767 | N9: ='Net Salary P2'!BI8 -> 42522.593 | O9: =IF(_xlfn.XLOOKUP(TableIncome[[#This Row],[Year]],Loop!C:C,Loop!D:D)<75,(O8*(1+$I$4))+IF(TableIncomeCalculations[[#This Row],[SwitchP1]]="Y",O8*$I$6,0),0) -> 48950.855 | P9: =IF(_xlfn.XLOOKUP(TableIncome[[#This Row],[Year]],Loop!C:C,Loop!E:E)<75,(P8*(1+$I$4))+IF(TableIncomeCalculations[[#This Row],[SwitchP2]]="Y",P8*$I$6,0),0) -> 82154.334 | Q9: =IF(_xlfn.XLOOKUP(TableIncome[[#This Row],[Year]],Loop!C:C,Loop!D:D)<75,(Q8*(1+$I$3))+IF(TableIncomeCalculations[[#This Row],[SwitchP1]]="Y",Q8*$I$5,0),0) -> 59225.342 | R9: =IF(_xlfn.XLOOKUP(TableIncome[[#This Row],[Year]],Loop!C:C,Loop!E:E)<75,(R8*(1+$I$3))+IF(TableIncomeCalculations[[#This Row],[SwitchP2]]="Y",R8*$I$5,0),0) -> 99398.029 | S9: =JobHopping[[#This Row],[SwitchP1Static]] -> Y | T9: =JobHopping[[#This Row],[SwitchP2Static]] -> Y
B10: 2032 | C10: =(TableIncomeCalculations[[#This Row],[NetMonthlySalaryP1]]*12) -> 322084.31 | D10: =(TableIncomeCalculations[[#This Row],[NetMonthlySalaryP2]]*12) -> 513579.11 | E10: =TableIncome[[#This Row],[SalaryP1]]*$I$7 -> 64416.862 | F10: =TableIncome[[#This Row],[SalaryP2]]*$I$7 -> 102715.82 | K10: =(TableIncome[[#This Row],[SalaryP1]]-TableIncome[[#This Row],[InvestmentP1]])/12 -> 21472.287 | L10: =(TableIncome[[#This Row],[SalaryP2]]-TableIncome[[#This Row],[InvestmentP2]])/12 -> 34238.607 | M10: ='Net Salary P1'!BI9 -> 26840.359 | N10: ='Net Salary P2'!BI9 -> 42798.259 | O10: =IF(_xlfn.XLOOKUP(TableIncome[[#This Row],[Year]],Loop!C:C,Loop!D:D)<75,(O9*(1+$I$4))+IF(TableIncomeCalculations[[#This Row],[SwitchP1]]="Y",O9*$I$6,0),0) -> 49342.462 | P10: =IF(_xlfn.XLOOKUP(TableIncome[[#This Row],[Year]],Loop!C:C,Loop!E:E)<75,(P9*(1+$I$4))+IF(TableIncomeCalculations[[#This Row],[SwitchP2]]="Y",P9*$I$6,0),0) -> 82811.568 | Q10: =IF(_xlfn.XLOOKUP(TableIncome[[#This Row],[Year]],Loop!C:C,Loop!D:D)<75,(Q9*(1+$I$3))+IF(TableIncomeCalculations[[#This Row],[SwitchP1]]="Y",Q9*$I$5,0),0) -> 61002.102 | R10: =IF(_xlfn.XLOOKUP(TableIncome[[#This Row],[Year]],Loop!C:C,Loop!E:E)<75,(R9*(1+$I$3))+IF(TableIncomeCalculations[[#This Row],[SwitchP2]]="Y",R9*$I$5,0),0) -> 102379.97 | S10: =JobHopping[[#This Row],[SwitchP1Static]] -> N | T10: =JobHopping[[#This Row],[SwitchP2Static]] -> N
B11: 2033 | C11: =(TableIncomeCalculations[[#This Row],[NetMonthlySalaryP1]]*12) -> 324692.12 | D11: =(TableIncomeCalculations[[#This Row],[NetMonthlySalaryP2]]*12) -> 516913.56 | E11: =TableIncome[[#This Row],[SalaryP1]]*$I$7 -> 64938.423 | F11: =TableIncome[[#This Row],[SalaryP2]]*$I$7 -> 103382.71 | K11: =(TableIncome[[#This Row],[SalaryP1]]-TableIncome[[#This Row],[InvestmentP1]])/12 -> 21646.141 | L11: =(TableIncome[[#This Row],[SalaryP2]]-TableIncome[[#This Row],[InvestmentP2]])/12 -> 34460.904 | M11: ='Net Salary P1'!BI10 -> 27057.676 | N11: ='Net Salary P2'!BI10 -> 43076.13 | O11: =IF(_xlfn.XLOOKUP(TableIncome[[#This Row],[Year]],Loop!C:C,Loop!D:D)<75,(O10*(1+$I$4))+IF(TableIncomeCalculations[[#This Row],[SwitchP1]]="Y",O10*$I$6,0),0) -> 49737.202 | P11: =IF(_xlfn.XLOOKUP(TableIncome[[#This Row],[Year]],Loop!C:C,Loop!E:E)<75,(P10*(1+$I$4))+IF(TableIncomeCalculations[[#This Row],[SwitchP2]]="Y",P10*$I$6,0),0) -> 83474.061 | Q11: =IF(_xlfn.XLOOKUP(TableIncome[[#This Row],[Year]],Loop!C:C,Loop!D:D)<75,(Q10*(1+$I$3))+IF(TableIncomeCalculations[[#This Row],[SwitchP1]]="Y",Q10*$I$5,0),0) -> 62832.165 | R11: =IF(_xlfn.XLOOKUP(TableIncome[[#This Row],[Year]],Loop!C:C,Loop!E:E)<75,(R10*(1+$I$3))+IF(TableIncomeCalculations[[#This Row],[SwitchP2]]="Y",R10*$I$5,0),0) -> 105451.37 | S11: =JobHopping[[#This Row],[SwitchP1Static]] -> N | T11: =JobHopping[[#This Row],[SwitchP2Static]] -> N
B12: 2034 | C12: =(TableIncomeCalculations[[#This Row],[NetMonthlySalaryP1]]*12) -> 327320.78 | D12: =(TableIncomeCalculations[[#This Row],[NetMonthlySalaryP2]]*12) -> 520274.69 | E12: =TableIncome[[#This Row],[SalaryP1]]*$I$7 -> 65464.156 | F12: =TableIncome[[#This Row],[SalaryP2]]*$I$7 -> 104054.94 | K12: =(TableIncome[[#This Row],[SalaryP1]]-TableIncome[[#This Row],[InvestmentP1]])/12 -> 21821.385 | L12: =(TableIncome[[#This Row],[SalaryP2]]-TableIncome[[#This Row],[InvestmentP2]])/12 -> 34684.979 | M12: ='Net Salary P1'!BI11 -> 27276.732 | N12: ='Net Salary P2'!BI11 -> 43356.224 | O12: =IF(_xlfn.XLOOKUP(TableIncome[[#This Row],[Year]],Loop!C:C,Loop!D:D)<75,(O11*(1+$I$4))+IF(TableIncomeCalculations[[#This Row],[SwitchP1]]="Y",O11*$I$6,0),0) -> 50135.099 | P12: =IF(_xlfn.XLOOKUP(TableIncome[[#This Row],[Year]],Loop!C:C,Loop!E:E)<75,(P11*(1+$I$4))+IF(TableIncomeCalculations[[#This Row],[SwitchP2]]="Y",P11*$I$6,0),0) -> 84141.854 | Q12: =IF(_xlfn.XLOOKUP(TableIncome[[#This Row],[Year]],Loop!C:C,Loop!D:D)<75,(Q11*(1+$I$3))+IF(TableIncomeCalculations[[#This Row],[SwitchP1]]="Y",Q11*$I$5,0),0) -> 64717.13 | R12: =IF(_xlfn.XLOOKUP(TableIncome[[#This Row],[Year]],Loop!C:C,Loop!E:E)<75,(R11*(1+$I$3))+IF(TableIncomeCalculations[[#This Row],[SwitchP2]]="Y",R11*$I$5,0),0) -> 108614.91 | S12: =JobHopping[[#This Row],[SwitchP1Static]] -> N | T12: =JobHopping[[#This Row],[SwitchP2Static]] -> N
B13: 2035 | C13: =(TableIncomeCalculations[[#This Row],[NetMonthlySalaryP1]]*12) -> 342556.54 | D13: =(TableIncomeCalculations[[#This Row],[NetMonthlySalaryP2]]*12) -> 539755.78 | E13: =TableIncome[[#This Row],[SalaryP1]]*$I$7 -> 68511.308 | F13: =TableIncome[[#This Row],[SalaryP2]]*$I$7 -> 107951.16 | K13: =(TableIncome[[#This Row],[SalaryP1]]-TableIncome[[#This Row],[InvestmentP1]])/12 -> 22837.103 | L13: =(TableIncome[[#This Row],[SalaryP2]]-TableIncome[[#This Row],[InvestmentP2]])/12 -> 35983.719 | M13: ='Net Salary P1'!BI12 -> 28546.378 | N13: ='Net Salary P2'!BI12 -> 44979.648 | O13: =IF(_xlfn.XLOOKUP(TableIncome[[#This Row],[Year]],Loop!C:C,Loop!D:D)<75,(O12*(1+$I$4))+IF(TableIncomeCalculations[[#This Row],[SwitchP1]]="Y",O12*$I$6,0),0) -> 52441.314 | P13: =IF(_xlfn.XLOOKUP(TableIncome[[#This Row],[Year]],Loop!C:C,Loop!E:E)<75,(P12*(1+$I$4))+IF(TableIncomeCalculations[[#This Row],[SwitchP2]]="Y",P12*$I$6,0),0) -> 88012.379 | Q13: =IF(_xlfn.XLOOKUP(TableIncome[[#This Row],[Year]],Loop!C:C,Loop!D:D)<75,(Q12*(1+$I$3))+IF(TableIncomeCalculations[[#This Row],[SwitchP1]]="Y",Q12*$I$5,0),0) -> 70541.672 | R13: =IF(_xlfn.XLOOKUP(TableIncome[[#This Row],[Year]],Loop!C:C,Loop!E:E)<75,(R12*(1+$I$3))+IF(TableIncomeCalculations[[#This Row],[SwitchP2]]="Y",R12*$I$5,0),0) -> 118390.25 | S13: =JobHopping[[#This Row],[SwitchP1Static]] -> Y | T13: =JobHopping[[#This Row],[SwitchP2Static]] -> Y
B14: 2036 | C14: =(TableIncomeCalculations[[#This Row],[NetMonthlySalaryP1]]*12) -> 345328.12 | D14: =(TableIncomeCalculations[[#This Row],[NetMonthlySalaryP2]]*12) -> 543299.64 | E14: =TableIncome[[#This Row],[SalaryP1]]*$I$7 -> 69065.624 | F14: =TableIncome[[#This Row],[SalaryP2]]*$I$7 -> 108659.93 | K14: =(TableIncome[[#This Row],[SalaryP1]]-TableIncome[[#This Row],[InvestmentP1]])/12 -> 23021.875 | L14: =(TableIncome[[#This Row],[SalaryP2]]-TableIncome[[#This Row],[InvestmentP2]])/12 -> 36219.976 | M14: ='Net Salary P1'!BI13 -> 28777.343 | N14: ='Net Salary P2'!BI13 -> 45274.97 | O14: =IF(_xlfn.XLOOKUP(TableIncome[[#This Row],[Year]],Loop!C:C,Loop!D:D)<75,(O13*(1+$I$4))+IF(TableIncomeCalculations[[#This Row],[SwitchP1]]="Y",O13*$I$6,0),0) -> 52860.844 | P14: =IF(_xlfn.XLOOKUP(TableIncome[[#This Row],[Year]],Loop!C:C,Loop!E:E)<75,(P13*(1+$I$4))+IF(TableIncomeCalculations[[#This Row],[SwitchP2]]="Y",P13*$I$6,0),0) -> 88716.478 | Q14: =IF(_xlfn.XLOOKUP(TableIncome[[#This Row],[Year]],Loop!C:C,Loop!D:D)<75,(Q13*(1+$I$3))+IF(TableIncomeCalculations[[#This Row],[SwitchP1]]="Y",Q13*$I$5,0),0) -> 72657.922 | R14: =IF(_xlfn.XLOOKUP(TableIncome[[#This Row],[Year]],Loop!C:C,Loop!E:E)<75,(R13*(1+$I$3))+IF(TableIncomeCalculations[[#This Row],[SwitchP2]]="Y",R13*$I$5,0),0) -> 121941.96 | S14: =JobHopping[[#This Row],[SwitchP1Static]] -> N | T14: =JobHopping[[#This Row],[SwitchP2Static]] -> N
B15: 2037 | C15: =(TableIncomeCalculations[[#This Row],[NetMonthlySalaryP1]]*12) -> 348121.88 | D15: =(TableIncomeCalculations[[#This Row],[NetMonthlySalaryP2]]*12) -> 546871.86 | E15: =TableIncome[[#This Row],[SalaryP1]]*$I$7 -> 69624.375 | F15: =TableIncome[[#This Row],[SalaryP2]]*$I$7 -> 109374.37 | K15: =(TableIncome[[#This Row],[SalaryP1]]-TableIncome[[#This Row],[InvestmentP1]])/12 -> 23208.125 | L15: =(TableIncome[[#This Row],[SalaryP2]]-TableIncome[[#This Row],[InvestmentP2]])/12 -> 36458.124 | M15: ='Net Salary P1'!BI14 -> 29010.156 | N15: ='Net Salary P2'!BI14 -> 45572.655 | O15: =IF(_xlfn.XLOOKUP(TableIncome[[#This Row],[Year]],Loop!C:C,Loop!D:D)<75,(O14*(1+$I$4))+IF(TableIncomeCalculations[[#This Row],[SwitchP1]]="Y",O14*$I$6,0),0) -> 53283.731 | P15: =IF(_xlfn.XLOOKUP(TableIncome[[#This Row],[Year]],Loop!C:C,Loop!E:E)<75,(P14*(1+$I$4))+IF(TableIncomeCalculations[[#This Row],[SwitchP2]]="Y",P14*$I$6,0),0) -> 89426.21 | Q15: =IF(_xlfn.XLOOKUP(TableIncome[[#This Row],[Year]],Loop!C:C,Loop!D:D)<75,(Q14*(1+$I$3))+IF(TableIncomeCalculations[[#This Row],[SwitchP1]]="Y",Q14*$I$5,0),0) -> 74837.659 | R15: =IF(_xlfn.XLOOKUP(TableIncome[[#This Row],[Year]],Loop!C:C,Loop!E:E)<75,(R14*(1+$I$3))+IF(TableIncomeCalculations[[#This Row],[SwitchP2]]="Y",R14*$I$5,0),0) -> 125600.22 | S15: =JobHopping[[#This Row],[SwitchP1Static]] -> N | T15: =JobHopping[[#This Row],[SwitchP2Static]] -> N
B16: 2038 | C16: =(TableIncomeCalculations[[#This Row],[NetMonthlySalaryP1]]*12) -> 364314.48 | D16: =(TableIncomeCalculations[[#This Row],[NetMonthlySalaryP2]]*12) -> 567576.42 | E16: =TableIncome[[#This Row],[SalaryP1]]*$I$7 -> 72862.896 | F16: =TableIncome[[#This Row],[SalaryP2]]*$I$7 -> 113515.28 | K16: =(TableIncome[[#This Row],[SalaryP1]]-TableIncome[[#This Row],[InvestmentP1]])/12 -> 24287.632 | L16: =(TableIncome[[#This Row],[SalaryP2]]-TableIncome[[#This Row],[InvestmentP2]])/12 -> 37838.428 | M16: ='Net Salary P1'!BI15 -> 30359.54 | N16: ='Net Salary P2'!BI15 -> 47298.035 | O16: =IF(_xlfn.XLOOKUP(TableIncome[[#This Row],[Year]],Loop!C:C,Loop!D:D)<75,(O15*(1+$I$4))+IF(TableIncomeCalculations[[#This Row],[SwitchP1]]="Y",O15*$I$6,0),0) -> 55734.783 | P16: =IF(_xlfn.XLOOKUP(TableIncome[[#This Row],[Year]],Loop!C:C,Loop!E:E)<75,(P15*(1+$I$4))+IF(TableIncomeCalculations[[#This Row],[SwitchP2]]="Y",P15*$I$6,0),0) -> 93539.815 | Q16: =IF(_xlfn.XLOOKUP(TableIncome[[#This Row],[Year]],Loop!C:C,Loop!D:D)<75,(Q15*(1+$I$3))+IF(TableIncomeCalculations[[#This Row],[SwitchP1]]="Y",Q15*$I$5,0),0) -> 81573.049 | R16: =IF(_xlfn.XLOOKUP(TableIncome[[#This Row],[Year]],Loop!C:C,Loop!E:E)<75,(R15*(1+$I$3))+IF(TableIncomeCalculations[[#This Row],[SwitchP2]]="Y",R15*$I$5,0),0) -> 136904.24 | S16: =JobHopping[[#This Row],[SwitchP1Static]] -> Y | T16: =JobHopping[[#This Row],[SwitchP2Static]] -> Y
B17: 2039 | C17: =(TableIncomeCalculations[[#This Row],[NetMonthlySalaryP1]]*12) -> 367260.13 | D17: =(TableIncomeCalculations[[#This Row],[NetMonthlySalaryP2]]*12) -> 571342.85 | E17: =TableIncome[[#This Row],[SalaryP1]]*$I$7 -> 73452.026 | F17: =TableIncome[[#This Row],[SalaryP2]]*$I$7 -> 114268.57 | K17: =(TableIncome[[#This Row],[SalaryP1]]-TableIncome[[#This Row],[InvestmentP1]])/12 -> 24484.009 | L17: =(TableIncome[[#This Row],[SalaryP2]]-TableIncome[[#This Row],[InvestmentP2]])/12 -> 38089.524 | M17: ='Net Salary P1'!BI16 -> 30605.011 | N17: ='Net Salary P2'!BI16 -> 47611.904 | O17: =IF(_xlfn.XLOOKUP(TableIncome[[#This Row],[Year]],Loop!C:C,Loop!D:D)<75,(O16*(1+$I$4))+IF(TableIncomeCalculations[[#This Row],[SwitchP1]]="Y",O16*$I$6,0),0) -> 56180.661 | P17: =IF(_xlfn.XLOOKUP(TableIncome[[#This Row],[Year]],Loop!C:C,Loop!E:E)<75,(P16*(1+$I$4))+IF(TableIncomeCalculations[[#This Row],[SwitchP2]]="Y",P16*$I$6,0),0) -> 94288.134 | Q17: =IF(_xlfn.XLOOKUP(TableIncome[[#This Row],[Year]],Loop!C:C,Loop!D:D)<75,(Q16*(1+$I$3))+IF(TableIncomeCalculations[[#This Row],[SwitchP1]]="Y",Q16*$I$5,0),0) -> 84020.24 | R17: =IF(_xlfn.XLOOKUP(TableIncome[[#This Row],[Year]],Loop!C:C,Loop!E:E)<75,(R16*(1+$I$3))+IF(TableIncomeCalculations[[#This Row],[SwitchP2]]="Y",R16*$I$5,0),0) -> 141011.36 | S17: =JobHopping[[#This Row],[SwitchP1Static]] -> N | T17: =JobHopping[[#This Row],[SwitchP2Static]] -> N
B18: 2040 | C18: =(TableIncomeCalculations[[#This Row],[NetMonthlySalaryP1]]*12) -> 370229.34 | D18: =(TableIncomeCalculations[[#This Row],[NetMonthlySalaryP2]]*12) -> 575139.42 | E18: =TableIncome[[#This Row],[SalaryP1]]*$I$7 -> 74045.868 | F18: =TableIncome[[#This Row],[SalaryP2]]*$I$7 -> 115027.88 | K18: =(TableIncome[[#This Row],[SalaryP1]]-TableIncome[[#This Row],[InvestmentP1]])/12 -> 24681.956 | L18: =(TableIncome[[#This Row],[SalaryP2]]-TableIncome[[#This Row],[InvestmentP2]])/12 -> 38342.628 | M18: ='Net Salary P1'!BI17 -> 30852.445 | N18: ='Net Salary P2'!BI17 -> 47928.285 | O18: =IF(_xlfn.XLOOKUP(TableIncome[[#This Row],[Year]],Loop!C:C,Loop!D:D)<75,(O17*(1+$I$4))+IF(TableIncomeCalculations[[#This Row],[SwitchP1]]="Y",O17*$I$6,0),0) -> 56630.106 | P18: =IF(_xlfn.XLOOKUP(TableIncome[[#This Row],[Year]],Loop!C:C,Loop!E:E)<75,(P17*(1+$I$4))+IF(TableIncomeCalculations[[#This Row],[SwitchP2]]="Y",P17*$I$6,0),0) -> 95042.439 | Q18: =IF(_xlfn.XLOOKUP(TableIncome[[#This Row],[Year]],Loop!C:C,Loop!D:D)<75,(Q17*(1+$I$3))+IF(TableIncomeCalculations[[#This Row],[SwitchP1]]="Y",Q17*$I$5,0),0) -> 86540.847 | R18: =IF(_xlfn.XLOOKUP(TableIncome[[#This Row],[Year]],Loop!C:C,Loop!E:E)<75,(R17*(1+$I$3))+IF(TableIncomeCalculations[[#This Row],[SwitchP2]]="Y",R17*$I$5,0),0) -> 145241.71 | S18: =JobHopping[[#This Row],[SwitchP1Static]] -> N | T18: =JobHopping[[#This Row],[SwitchP2Static]] -> N
B19: 2041 | C19: =(TableIncomeCalculations[[#This Row],[NetMonthlySalaryP1]]*12) -> 373222.3 | D19: =(TableIncomeCalculations[[#This Row],[NetMonthlySalaryP2]]*12) -> 578966.35 | E19: =TableIncome[[#This Row],[SalaryP1]]*$I$7 -> 74644.461 | F19: =TableIncome[[#This Row],[SalaryP2]]*$I$7 -> 115793.27 | K19: =(TableIncome[[#This Row],[SalaryP1]]-TableIncome[[#This Row],[InvestmentP1]])/12 -> 24881.487 | L19: =(TableIncome[[#This Row],[SalaryP2]]-TableIncome[[#This Row],[InvestmentP2]])/12 -> 38597.757 | M19: ='Net Salary P1'!BI18 -> 31101.859 | N19: ='Net Salary P2'!BI18 -> 48247.196 | O19: =IF(_xlfn.XLOOKUP(TableIncome[[#This Row],[Year]],Loop!C:C,Loop!D:D)<75,(O18*(1+$I$4))+IF(TableIncomeCalculations[[#This Row],[SwitchP1]]="Y",O18*$I$6,0),0) -> 57083.147 | P19: =IF(_xlfn.XLOOKUP(TableIncome[[#This Row],[Year]],Loop!C:C,Loop!E:E)<75,(P18*(1+$I$4))+IF(TableIncomeCalculations[[#This Row],[SwitchP2]]="Y",P18*$I$6,0),0) -> 95802.778 | Q19: =IF(_xlfn.XLOOKUP(TableIncome[[#This Row],[Year]],Loop!C:C,Loop!D:D)<75,(Q18*(1+$I$3))+IF(TableIncomeCalculations[[#This Row],[SwitchP1]]="Y",Q18*$I$5,0),0) -> 89137.073 | R19: =IF(_xlfn.XLOOKUP(TableIncome[[#This Row],[Year]],Loop!C:C,Loop!E:E)<75,(R18*(1+$I$3))+IF(TableIncomeCalculations[[#This Row],[SwitchP2]]="Y",R18*$I$5,0),0) -> 149598.96 | S19: =JobHopping[[#This Row],[SwitchP1Static]] -> N | T19: =JobHopping[[#This Row],[SwitchP2Static]] -> N
... B48: 2070 | C48: =(TableIncomeCalculations[[#This Row],[NetMonthlySalaryP1]]*12) -> 501274.23 | D48: =(TableIncomeCalculations[[#This Row],[NetMonthlySalaryP2]]*12) -> 0 | E48: =TableIncome[[#This Row],[SalaryP1]]*$I$7 -> 100254.85 | F48: =TableIncome[[#This Row],[SalaryP2]]*$I$7 -> 0 | K48: =(TableIncome[[#This Row],[SalaryP1]]-TableIncome[[#This Row],[InvestmentP1]])/12 -> 33418.282 | L48: =(TableIncome[[#This Row],[SalaryP2]]-TableIncome[[#This Row],[InvestmentP2]])/12 -> 0 | M48: ='Net Salary P1'!BI47 -> 41772.853 | N48: ='Net Salary P2'!BI47 -> 0 | O48: =IF(_xlfn.XLOOKUP(TableIncome[[#This Row],[Year]],Loop!C:C,Loop!D:D)<75,(O47*(1+$I$4))+IF(TableIncomeCalculations[[#This Row],[SwitchP1]]="Y",O47*$I$6,0),0) -> 80366.822 | P48: =IF(_xlfn.XLOOKUP(TableIncome[[#This Row],[Year]],Loop!C:C,Loop!E:E)<75,(P47*(1+$I$4))+IF(TableIncomeCalculations[[#This Row],[SwitchP2]]="Y",P47*$I$6,0),0) -> 0 | Q48: =IF(_xlfn.XLOOKUP(TableIncome[[#This Row],[Year]],Loop!C:C,Loop!D:D)<75,(Q47*(1+$I$3))+IF(TableIncomeCalculations[[#This Row],[SwitchP1]]="Y",Q47*$I$5,0),0) -> 248946.32 | R48: =IF(_xlfn.XLOOKUP(TableIncome[[#This Row],[Year]],Loop!C:C,Loop!E:E)<75,(R47*(1+$I$3))+IF(TableIncomeCalculations[[#This Row],[SwitchP2]]="Y",R47*$I$5,0),0) -> 0 | S48: =JobHopping[[#This Row],[SwitchP1Static]] -> N | T48: =JobHopping[[#This Row],[SwitchP2Static]] -> N
B49: 2071 | C49: =(TableIncomeCalculations[[#This Row],[NetMonthlySalaryP1]]*12) -> 504510.24 | D49: =(TableIncomeCalculations[[#This Row],[NetMonthlySalaryP2]]*12) -> 0 | E49: =TableIncome[[#This Row],[SalaryP1]]*$I$7 -> 100902.05 | F49: =TableIncome[[#This Row],[SalaryP2]]*$I$7 -> 0 | K49: =(TableIncome[[#This Row],[SalaryP1]]-TableIncome[[#This Row],[InvestmentP1]])/12 -> 33634.016 | L49: =(TableIncome[[#This Row],[SalaryP2]]-TableIncome[[#This Row],[InvestmentP2]])/12 -> 0 | M49: ='Net Salary P1'!BI48 -> 42042.52 | N49: ='Net Salary P2'!BI48 -> 0 | O49: =IF(_xlfn.XLOOKUP(TableIncome[[#This Row],[Year]],Loop!C:C,Loop!D:D)<75,(O48*(1+$I$4))+IF(TableIncomeCalculations[[#This Row],[SwitchP1]]="Y",O48*$I$6,0),0) -> 81009.757 | P49: =IF(_xlfn.XLOOKUP(TableIncome[[#This Row],[Year]],Loop!C:C,Loop!E:E)<75,(P48*(1+$I$4))+IF(TableIncomeCalculations[[#This Row],[SwitchP2]]="Y",P48*$I$6,0),0) -> 0 | Q49: =IF(_xlfn.XLOOKUP(TableIncome[[#This Row],[Year]],Loop!C:C,Loop!D:D)<75,(Q48*(1+$I$3))+IF(TableIncomeCalculations[[#This Row],[SwitchP1]]="Y",Q48*$I$5,0),0) -> 256414.71 | S49: =JobHopping[[#This Row],[SwitchP1Static]] -> N | T49: =JobHopping[[#This Row],[SwitchP2Static]] -> N
B50: 2072 | C50: =(TableIncomeCalculations[[#This Row],[NetMonthlySalaryP1]]*12) -> 507772.14 | D50: =(TableIncomeCalculations[[#This Row],[NetMonthlySalaryP2]]*12) -> 0 | E50: =TableIncome[[#This Row],[SalaryP1]]*$I$7 -> 101554.43 | F50: =TableIncome[[#This Row],[SalaryP2]]*$I$7 -> 0 | K50: =(TableIncome[[#This Row],[SalaryP1]]-TableIncome[[#This Row],[InvestmentP1]])/12 -> 33851.476 | L50: =(TableIncome[[#This Row],[SalaryP2]]-TableIncome[[#This Row],[InvestmentP2]])/12 -> 0 | M50: ='Net Salary P1'!BI49 -> 42314.345 | N50: ='Net Salary P2'!BI49 -> 0 | O50: =IF(_xlfn.XLOOKUP(TableIncome[[#This Row],[Year]],Loop!C:C,Loop!D:D)<75,(O49*(1+$I$4))+IF(TableIncomeCalculations[[#This Row],[SwitchP1]]="Y",O49*$I$6,0),0) -> 81657.835 | P50: =IF(_xlfn.XLOOKUP(TableIncome[[#This Row],[Year]],Loop!C:C,Loop!E:E)<75,(P49*(1+$I$4))+IF(TableIncomeCalculations[[#This Row],[SwitchP2]]="Y",P49*$I$6,0),0) -> 0 | Q50: =IF(_xlfn.XLOOKUP(TableIncome[[#This Row],[Year]],Loop!C:C,Loop!D:D)<75,(Q49*(1+$I$3))+IF(TableIncomeCalculations[[#This Row],[SwitchP1]]="Y",Q49*$I$5,0),0) -> 264107.15 | S50: =JobHopping[[#This Row],[SwitchP1Static]] -> N | T50: =JobHopping[[#This Row],[SwitchP2Static]] -> N
B51: 2073 | C51: =(TableIncomeCalculations[[#This Row],[NetMonthlySalaryP1]]*12) -> 511060.14 | D51: =(TableIncomeCalculations[[#This Row],[NetMonthlySalaryP2]]*12) -> 0 | E51: =TableIncome[[#This Row],[SalaryP1]]*$I$7 -> 102212.03 | F51: =TableIncome[[#This Row],[SalaryP2]]*$I$7 -> 0 | K51: =(TableIncome[[#This Row],[SalaryP1]]-TableIncome[[#This Row],[InvestmentP1]])/12 -> 34070.676 | L51: =(TableIncome[[#This Row],[SalaryP2]]-TableIncome[[#This Row],[InvestmentP2]])/12 -> 0 | M51: ='Net Salary P1'!BI50 -> 42588.345 | N51: ='Net Salary P2'!BI50 -> 0 | O51: =IF(_xlfn.XLOOKUP(TableIncome[[#This Row],[Year]],Loop!C:C,Loop!D:D)<75,(O50*(1+$I$4))+IF(TableIncomeCalculations[[#This Row],[SwitchP1]]="Y",O50*$I$6,0),0) -> 82311.098 | P51: =IF(_xlfn.XLOOKUP(TableIncome[[#This Row],[Year]],Loop!C:C,Loop!E:E)<75,(P50*(1+$I$4))+IF(TableIncomeCalculations[[#This Row],[SwitchP2]]="Y",P50*$I$6,0),0) -> 0 | Q51: =IF(_xlfn.XLOOKUP(TableIncome[[#This Row],[Year]],Loop!C:C,Loop!D:D)<75,(Q50*(1+$I$3))+IF(TableIncomeCalculations[[#This Row],[SwitchP1]]="Y",Q50*$I$5,0),0) -> 272030.36 | S51: =JobHopping[[#This Row],[SwitchP1Static]] -> N | T51: =JobHopping[[#This Row],[SwitchP2Static]] -> N
B52: 2074 | C52: =(TableIncomeCalculations[[#This Row],[NetMonthlySalaryP1]]*12) -> 514374.44 | D52: =(TableIncomeCalculations[[#This Row],[NetMonthlySalaryP2]]*12) -> 0 | E52: =TableIncome[[#This Row],[SalaryP1]]*$I$7 -> 102874.89 | F52: =TableIncome[[#This Row],[SalaryP2]]*$I$7 -> 0 | K52: =(TableIncome[[#This Row],[SalaryP1]]-TableIncome[[#This Row],[InvestmentP1]])/12 -> 34291.629 | L52: =(TableIncome[[#This Row],[SalaryP2]]-TableIncome[[#This Row],[InvestmentP2]])/12 -> 0 | M52: ='Net Salary P1'!BI51 -> 42864.537 | N52: ='Net Salary P2'!BI51 -> 0 | O52: =IF(_xlfn.XLOOKUP(TableIncome[[#This Row],[Year]],Loop!C:C,Loop!D:D)<75,(O51*(1+$I$4))+IF(TableIncomeCalculations[[#This Row],[SwitchP1]]="Y",O51*$I$6,0),0) -> 82969.586 | P52: =IF(_xlfn.XLOOKUP(TableIncome[[#This Row],[Year]],Loop!C:C,Loop!E:E)<75,(P51*(1+$I$4))+IF(TableIncomeCalculations[[#This Row],[SwitchP2]]="Y",P51*$I$6,0),0) -> 0 | Q52: =IF(_xlfn.XLOOKUP(TableIncome[[#This Row],[Year]],Loop!C:C,Loop!D:D)<75,(Q51*(1+$I$3))+IF(TableIncomeCalculations[[#This Row],[SwitchP1]]="Y",Q51*$I$5,0),0) -> 280191.27 | S52: =JobHopping[[#This Row],[SwitchP1Static]] -> N | T52: =JobHopping[[#This Row],[SwitchP2Static]] -> N
B53: 2075 | C53: =(TableIncomeCalculations[[#This Row],[NetMonthlySalaryP1]]*12) -> 0 | D53: =(TableIncomeCalculations[[#This Row],[NetMonthlySalaryP2]]*12) -> 0 | E53: =TableIncome[[#This Row],[SalaryP1]]*$I$7 -> 0 | F53: =TableIncome[[#This Row],[SalaryP2]]*$I$7 -> 0 | K53: =(TableIncome[[#This Row],[SalaryP1]]-TableIncome[[#This Row],[InvestmentP1]])/12 -> 0 | L53: =(TableIncome[[#This Row],[SalaryP2]]-TableIncome[[#This Row],[InvestmentP2]])/12 -> 0 | M53: ='Net Salary P1'!BI52 -> 0 | N53: ='Net Salary P2'!BI52 -> 0 | O53: =IF(_xlfn.XLOOKUP(TableIncome[[#This Row],[Year]],Loop!C:C,Loop!D:D)<75,(O52*(1+$I$4))+IF(TableIncomeCalculations[[#This Row],[SwitchP1]]="Y",O52*$I$6,0),0) -> 0 | P53: =IF(_xlfn.XLOOKUP(TableIncome[[#This Row],[Year]],Loop!C:C,Loop!E:E)<75,(P52*(1+$I$4))+IF(TableIncomeCalculations[[#This Row],[SwitchP2]]="Y",P52*$I$6,0),0) -> 0 | Q53: =IF(_xlfn.XLOOKUP(TableIncome[[#This Row],[Year]],Loop!C:C,Loop!D:D)<75,(Q52*(1+$I$3))+IF(TableIncomeCalculations[[#This Row],[SwitchP1]]="Y",Q52*$I$5,0),0) -> 0 | S53: =JobHopping[[#This Row],[SwitchP1Static]] -> N | T53: =JobHopping[[#This Row],[SwitchP2Static]] -> N

Sheet Pensions P1
A1: Year | B1: 2025 | C1: 2026 | D1: 2027 | E1: 2028 | F1: 2029 | G1: 2030 | H1: 2031 | I1: 2032 | J1: 2033 | K1: 2034 | L1: 2035 | M1: 2036 | N1: 2037 | O1: 2038 | P1: 2039 | Q1: 2040 | R1: 2041 | S1: 2042 | T1: 2043 | U1: 2044 | V1: 2045 | W1: 2046 | X1: 2047 | Y1: 2048 | Z1: 2049 | AA1: 2050 | AB1: 2051 | AC1: 2052 | AD1: 2053 | AE1: 2054 | AF1: 2055 | AG1: 2056 | AH1: 2057 | AI1: 2058 | AJ1: 2059 | AK1: 2060 | AL1: 2061 | AM1: 2062 | AN1: 2063 | AO1: 2064 | AP1: 2065 | AQ1: 2066 | AR1: 2067 | AS1: 2068 | AT1: 2069 | AU1: 2070 | AV1: 2071 | AW1: 2072 | AX1: 2073 | AY1: 2074
A2: Month Salary | B2: {=TRANSPOSE(Income!O3:O52)} -> 43336.595 | C2: 43683.288 | D2: 45692.719 | E2: 46058.261 | F2: 46426.727 | G2: 46798.141 | H2: 48950.855 | I2: 49342.462 | J2: 49737.202 | K2: 50135.099 | L2: 52441.314 | M2: 52860.844 | N2: 53283.731 | O2: 55734.783 | P2: 56180.661 | Q2: 56630.106 | R2: 57083.147 | S2: 57539.812 | T2: 60186.644 | U2: 60668.137 | V2: 61153.482 | W2: 61642.71 | X2: 64478.274 | Y2: 64994.1 | Z2: 65514.053 | AA2: 66038.166 | AB2: 66566.471 | AC2: 67099.003 | AD2: 67635.795 | AE2: 68176.881 | AF2: 68722.296 | AG2: 69272.075 | AH2: 69826.251 | AI2: 70384.861 | AJ2: 70947.94 | AK2: 74211.545 | AL2: 74805.238 | AM2: 75403.68 | AN2: 76006.909 | AO2: 76614.964 | AP2: 77227.884 | AQ2: 77845.707 | AR2: 78468.473 | AS2: 79096.221 | AT2: 79728.99 | AU2: 80366.822 | AV2: 81009.757 | AW2: 81657.835 | AX2: 82311.098 | AY2: 82969.586
A3: Personal Contribution (%) | B3: ='Salary Variables'!$C$12 -> 0.05 | C3: ='Salary Variables'!$C$12 -> 0.05 | D3: ='Salary Variables'!$C$12 -> 0.05 | E3: ='Salary Variables'!$C$12 -> 0.05 | F3: ='Salary Variables'!$C$12 -> 0.05 | G3: ='Salary Variables'!$C$12 -> 0.05 | H3: ='Salary Variables'!$C$12 -> 0.05 | I3: ='Salary Variables'!$C$12 -> 0.05 | ... AY3: ='Salary Variables'!$C$12 -> 0.05
A4: Personal Contribution | B4: =B3*B2 -> 2166.8297 | C4: =C3*C2 -> 2184.1644 | D4: =D3*D2 -> 2284.6359 | E4: =E3*E2 -> 2302.913 | F4: =F3*F2 -> 2321.3363 | G4: =G3*G2 -> 2339.907 | H4: =H3*H2 -> 2447.5428 | I4: =I3*I2 -> 2467.1231 | ... AY4: =AY3*AY2 -> 4148.4793
A5: Company Contribution (%) | B5: ='Salary Variables'!$C$13 -> 0.1 | C5: ='Salary Variables'!$C$13 -> 0.1 | D5: ='Salary Variables'!$C$13 -> 0.1 | E5: ='Salary Variables'!$C$13 -> 0.1 | F5: ='Salary Variables'!$C$13 -> 0.1 | G5: ='Salary Variables'!$C$13 -> 0.1 | H5: ='Salary Variables'!$C$13 -> 0.1 | I5: ='Salary Variables'!$C$13 -> 0.1 | ... AY5: ='Salary Variables'!$C$13 -> 0.1
A6: Company Contribution | B6: =B2*B5 -> 4333.6595 | C6: =C4*2 -> 4368.3288 | D6: =D4*2 -> 4569.2719 | E6: =E4*2 -> 4605.8261 | F6: =F4*2 -> 4642.6727 | G6: =G4*2 -> 4679.8141 | H6: =H4*2 -> 4895.0855 | I6: =I4*2 -> 4934.2462 | J6: =J4*2 -> 4973.7202 | ... AY6: =AY4*2 -> 8296.9586
A7: Total Contribution (Monthly) | B7: =SUM(B6,B4) -> 6500.4892 | C7: =SUM(C6,C4) -> 6552.4932 | D7: =SUM(D6,D4) -> 6853.9078 | E7: =SUM(E6,E4) -> 6908.7391 | F7: =SUM(F6,F4) -> 6964.009 | G7: =SUM(G6,G4) -> 7019.7211 | H7: =SUM(H6,H4) -> 7342.6283 | I7: =SUM(I6,I4) -> 7401.3693 | ... AY7: =SUM(AY6,AY4) -> 12445.438
A8: Total Contribution (Yearly) | B8: =B7*12 -> 78005.871 | C8: =C7*12 -> 78629.918 | D8: =D7*12 -> 82246.894 | E8: =E7*12 -> 82904.869 | F8: =F7*12 -> 83568.108 | G8: =G7*12 -> 84236.653 | H8: =H7*12 -> 88111.539 | I8: =I7*12 -> 88816.431 | ... AY8: =AY7*12 -> 149345.26
A11: Aldersopsparing Total | B11: =AY54 -> 950809.37
A12: Divided by 25 | B12: =B11/25 -> 38032.375
A13: Monthly | B13: =B12/12 -> 3169.3646
A14: Taxed in retirement? | B14: No
A16: Total Contribution (Work Pension) | B16: =AY38 -> 10928906
A17: Divided by 25 years | B17: =B16/25 -> 437156.25 | C17: per year
A18: Monthly | B18: =B17/12 -> 36429.688 | C18: per month (gross)
A19: Taxed in Retirement? | B19: Yes | C19: Income tax
C21: base | D21: supplement
A22: Public Pension Average Monthly | B22: =C22 -> 7198 | C22: 7198 | D22: =8329*(1-30.9%) -> 5755.339
A23: Public Pension Average Yearly | B23: =B22*12 -> 86376
A24: Taxed in Retirement? | B24: Yes
A25: Inflation | B25: ='Salary Variables'!C2 -> 0.022
A26: Pension growth | B26: 0.03
A27: PAL tax | B27: 0.153
A29: ATP | B29: =AY47 -> 360498.36
A30: ATP Yearly | B30: =B29/25 -> 14419.934
A31: ATP Monthly | B31: =B30/12 -> 1201.6612
A33: Year | B33: 2025 | C33: 2026 | D33: 2027 | E33: 2028 | F33: 2029 | G33: 2030 | H33: 2031 | I33: 2032 | J33: 2033 | K33: 2034 | L33: 2035 | M33: 2036 | N33: 2037 | O33: 2038 | P33: 2039 | Q33: 2040 | R33: 2041 | S33: 2042 | T33: 2043 | U33: 2044 | V33: 2045 | W33: 2046 | X33: 2047 | Y33: 2048 | Z33: 2049 | AA33: 2050 | AB33: 2051 | AC33: 2052 | AD33: 2053 | AE33: 2054 | AF33: 2055 | AG33: 2056 | AH33: 2057 | AI33: 2058 | AJ33: 2059 | AK33: 2060 | AL33: 2061 | AM33: 2062 | AN33: 2063 | AO33: 2064 | AP33: 2065 | AQ33: 2066 | AR33: 2067 | AS33: 2068 | AT33: 2069 | AU33: 2070 | AV33: 2071 | AW33: 2072 | AX33: 2073 | AY33: 2074
A34: Work Pension Start of Year | B34: =B8 -> 78005.871 | C34: =B38+C8 -> 158617.92 | D34: =C38+D8 -> 244895.29 | E34: =D38+E8 -> 334022.95 | F34: =E38+F8 -> 426078.58 | G34: =F38+G8 -> 521141.89 | H34: =G38+H8 -> 622495.65 | I34: =H38+I8 -> 727129.69 | J34: =I38+J8 -> 835133.02 | ... AY34: =AX38+AY8 -> 10658084
A35: Work Pension growth (%) | B35: =$B$26 -> 0.03 | C35: =$B$26 -> 0.03 | D35: =$B$26 -> 0.03 | E35: =$B$26 -> 0.03 | F35: =$B$26 -> 0.03 | G35: =$B$26 -> 0.03 | H35: =$B$26 -> 0.03 | I35: =$B$26 -> 0.03 | ... AY35: =$B$26 -> 0.03
A36: Work pension growth | B36: =B35*B34 -> 2340.1761 | C36: =C35*C34 -> 4758.5375 | D36: =D35*D34 -> 7346.8588 | E36: =E35*E34 -> 10020.689 | F36: =F35*F34 -> 12782.357 | G36: =G35*G34 -> 15634.257 | H36: =H35*H34 -> 18674.869 | I36: =I35*I34 -> 21813.891 | ... AY36: =AY35*AY34 -> 319742.53
A37: Tax | B37: =B36*$B$27 -> 358.04695 | C37: =C36*$B$27 -> 728.05624 | D37: =D36*$B$27 -> 1124.0694 | E37: =E36*$B$27 -> 1533.1653 | F37: =F36*$B$27 -> 1955.7007 | G37: =G36*$B$27 -> 2392.0413 | H37: =H36*$B$27 -> 2857.255 | I37: =I36*$B$27 -> 3337.5253 | ... AY37: =AY36*$B$27 -> 48920.607
A38: Work Pension End of Year | B38: =B34+(B36-B37) -> 79988 | C38: =C34+(C36-C37) -> 162648.4 | D38: =D34+(D36-D37) -> 251118.08 | E38: =E34+(E36-E37) -> 342510.47 | F38: =F34+(F36-F37) -> 436905.24 | G38: =G34+(G36-G37) -> 534384.11 | H38: =H34+(H36-H37) -> 638313.26 | I38: =I34+(I36-I37) -> 745606.06 | ... AY38: =AY34+(AY36-AY37) -> 10928906
A40: Total Work Pension | B40: =AT38 -> 8941111.1
A42: ATP | B42: https://businessindenmark.virk.dk/guidance/atp-livslang-pension-bid/atp-employer/atp-contribution-rates2024/
A43: ATP start of year | B43: ='Net Salary P1'!B14*3 -> 3564 | C43: =B47+$B$43 -> 7218.5612 | D43: =C47+$B$43 -> 10965.985 | E43: =D47+$B$43 -> 14808.631 | F43: =E47+$B$43 -> 18748.918 | G43: =F47+$B$43 -> 22789.328 | H43: =G47+$B$43 -> 26932.405 | I43: =H47+$B$43 -> 31180.757 | J43: =I47+$B$43 -> 35537.06 | ... AY43: =AX47+$B$43 -> 351565.09
A44: Pension growth (%) | B44: =$B$26 -> 0.03 | C44: =$B$26 -> 0.03 | D44: =$B$26 -> 0.03 | E44: =$B$26 -> 0.03 | F44: =$B$26 -> 0.03 | G44: =$B$26 -> 0.03 | H44: =$B$26 -> 0.03 | I44: =$B$26 -> 0.03 | ... AY44: =$B$26 -> 0.03
A45: Pension growth | B45: =B44*B43 -> 106.92 | C45: =C44*C43 -> 216.55684 | D45: =D44*D43 -> 328.97955 | E45: =E44*E43 -> 444.25892 | F45: =F44*F43 -> 562.46754 | G45: =G44*G43 -> 683.67984 | H45: =H44*H43 -> 807.97214 | I45: =I44*I43 -> 935.42271 | ... AY45: =AY44*AY43 -> 10546.953
A46: Tax | B46: =B45*$B$27 -> 16.35876 | C46: =C45*$B$27 -> 33.133196 | D46: =D45*$B$27 -> 50.333871 | E46: =E45*$B$27 -> 67.971614 | F46: =F45*$B$27 -> 86.057533 | G46: =G45*$B$27 -> 104.60301 | H46: =H45*$B$27 -> 123.61974 | I46: =I45*$B$27 -> 143.11968 | ... AY46: =AY45*$B$27 -> 1613.6838
A47: Post Tax | B47: =B43+(B45-B46) -> 3654.5612 | C47: =C43+(C45-C46) -> 7401.9849 | D47: =D43+(D45-D46) -> 11244.631 | E47: =E43+(E45-E46) -> 15184.918 | F47: =F43+(F45-F46) -> 19225.328 | G47: =G43+(G45-G46) -> 23368.405 | H47: =H43+(H45-H46) -> 27616.757 | I47: =I43+(I45-I46) -> 31973.06 | ... AY47: =AY43+(AY45-AY46) -> 360498.36
A49: Aldersopsparing
A50: Start of year | B50: ='Net Salary P1'!$B$2 -> 9400 | C50: =B54+$B$50 -> 19038.854 | D50: =C54+$B$50 -> 28922.631 | E50: =D54+$B$50 -> 39057.555 | F50: =E54+$B$50 -> 49450.008 | G50: =F54+$B$50 -> 60106.533 | H50: =G54+$B$50 -> 71033.84 | I50: =H54+$B$50 -> 82238.809 | J50: =I54+$B$50 -> 93728.498 | ... AY50: =AX54+$B$50 -> 927248
A51: Pension growth (%) | B51: =$B$26 -> 0.03 | C51: =$B$26 -> 0.03 | D51: =$B$26 -> 0.03 | E51: =$B$26 -> 0.03 | F51: =$B$26 -> 0.03 | G51: =$B$26 -> 0.03 | H51: =$B$26 -> 0.03 | I51: =$B$26 -> 0.03 | ... AY51: =$B$26 -> 0.03
A52: Pension growth | B52: =B51*B50 -> 282 | C52: =C51*C50 -> 571.16562 | D52: =D51*D50 -> 867.67894 | E52: =E51*E50 -> 1171.7267 | F52: =F51*F50 -> 1483.5002 | G52: =G51*G50 -> 1803.196 | H52: =H51*H50 -> 2131.0152 | I52: =I51*I50 -> 2467.1643 | ... AY52: =AY51*AY50 -> 27817.44
A53: Tax | B53: =B52*$B$27 -> 43.146 | C53: =C52*$B$27 -> 87.38834 | D53: =D52*$B$27 -> 132.75488 | E53: =E52*$B$27 -> 179.27418 | F53: =F52*$B$27 -> 226.97554 | G53: =G52*$B$27 -> 275.88898 | H53: =H52*$B$27 -> 326.04532 | I53: =I52*$B$27 -> 377.47614 | ... AY53: =AY52*$B$27 -> 4256.0683
A54: Post Tax | B54: =B50+(B52-B53) -> 9638.854 | C54: =C50+(C52-C53) -> 19522.631 | D54: =D50+(D52-D53) -> 29657.555 | E54: =E50+(E52-E53) -> 40050.008 | F54: =F50+(F52-F53) -> 50706.533 | G54: =G50+(G52-G53) -> 61633.84 | H54: =H50+(H52-H53) -> 72838.809 | I54: =I50+(I52-I53) -> 84328.498 | ... AY54: =AY50+(AY52-AY53) -> 950809.37

Sheet Pensions P2
A1: Year | B1: 2010 | C1: 2011 | D1: 2012 | E1: 2013 | F1: 2014 | G1: 2015 | H1: 2016 | I1: 2017 | J1: 2018 | K1: 2019 | L1: 2020 | M1: 2021 | N1: 2022 | O1: 2023 | P1: 2024 | Q1: 2025 | R1: 2026 | S1: 2027 | T1: 2028 | U1: 2029 | V1: 2030 | W1: 2031 | X1: 2032 | Y1: 2033 | Z1: 2034 | AA1: 2035 | AB1: 2036 | AC1: 2037 | AD1: 2038 | AE1: 2039 | AF1: 2040 | AG1: 2041 | AH1: 2042 | AI1: 2043 | AJ1: 2044 | AK1: 2045 | AL1: 2046 | AM1: 2047 | AN1: 2048 | AO1: 2049 | AP1: 2050 | AQ1: 2051 | AR1: 2052 | AS1: 2053 | AT1: 2054 | AU1: 2055 | AV1: 2056 | AW1: 2057 | AX1: 2058 | AY1: 2059
A2: Month Salary | B2: {=TRANSPOSE('Income - P2 Helper'!N3:N17)} -> 55203.706 | C2: 55645.336 | D2: 56090.499 | E2: 58791.159 | F2: 59261.489 | G2: 59735.581 | H2: 60213.465 | I2: 63112.639 | J2: 63617.541 | K2: 64126.481 | L2: 64639.493 | M2: 67751.773 | N2: 68293.787 | O2: 68840.137 | P2: 72154.671 | Q2: {=TRANSPOSE(Income!P3:P37)} -> 72731.908 | R2: 73313.763 | S2: 76686.196 | T2: 77299.686 | U2: 77918.083 | V2: 78541.428 | W2: 82154.334 | X2: 82811.568 | Y2: 83474.061 | Z2: 84141.854 | AA2: 88012.379 | AB2: 88716.478 | AC2: 89426.21 | AD2: 93539.815 | AE2: 94288.134 | AF2: 95042.439 | AG2: 95802.778 | AH2: 96569.201 | AI2: 101011.38 | AJ2: 101819.47 | AK2: 102634.03 | AL2: 103455.1 | AM2: 108214.04 | AN2: 109079.75 | AO2: 109952.39 | AP2: 110832.01 | AQ2: 111718.66 | AR2: 112612.41 | AS2: 113513.31 | AT2: 114421.42 | AU2: 115336.79 | AV2: 116259.48 | AW2: 117189.56 | AX2: 118127.08 | AY2: 119072.09
A3: Personal Contribution (%) | B3: ='Salary Variables'!$C$12 -> 0.05 | C3: ='Salary Variables'!$C$12 -> 0.05 | D3: ='Salary Variables'!$C$12 -> 0.05 | E3: ='Salary Variables'!$C$12 -> 0.05 | F3: ='Salary Variables'!$C$12 -> 0.05 | G3: ='Salary Variables'!$C$12 -> 0.05 | H3: ='Salary Variables'!$C$12 -> 0.05 | I3: ='Salary Variables'!$C$12 -> 0.05 | ... AY3: ='Salary Variables'!$C$12 -> 0.05
A4: Personal Contribution | B4: =B3*B2 -> 2760.1853 | C4: =C3*C2 -> 2782.2668 | D4: =D3*D2 -> 2804.5249 | E4: =E3*E2 -> 2939.558 | F4: =F3*F2 -> 2963.0744 | G4: =G3*G2 -> 2986.779 | H4: =H3*H2 -> 3010.6733 | I4: =I3*I2 -> 3155.632 | ... AY4: =AY3*AY2 -> 5953.6046
A5: Company Contribution (%) | B5: ='Salary Variables'!$C$13 -> 0.1 | C5: ='Salary Variables'!$C$13 -> 0.1 | D5: ='Salary Variables'!$C$13 -> 0.1 | E5: ='Salary Variables'!$C$13 -> 0.1 | F5: ='Salary Variables'!$C$13 -> 0.1 | G5: ='Salary Variables'!$C$13 -> 0.1 | H5: ='Salary Variables'!$C$13 -> 0.1 | I5: ='Salary Variables'!$C$13 -> 0.1 | ... AY5: ='Salary Variables'!$C$13 -> 0.1
A6: Company Contribution | B6: =B2*B5 -> 5520.3706 | C6: =C4*2 -> 5564.5336 | D6: =D4*2 -> 5609.0499 | E6: =E4*2 -> 5879.1159 | F6: =F4*2 -> 5926.1489 | G6: =G4*2 -> 5973.5581 | H6: =H4*2 -> 6021.3465 | I6: =I4*2 -> 6311.2639 | J6: =J4*2 -> 6361.7541 | ... AY6: =AY4*2 -> 11907.209
A7: Total Contribution (Monthly) | B7: =SUM(B6,B4) -> 8280.556 | C7: =SUM(C6,C4) -> 8346.8004 | D7: =SUM(D6,D4) -> 8413.5748 | E7: =SUM(E6,E4) -> 8818.6739 | F7: =SUM(F6,F4) -> 8889.2233 | G7: =SUM(G6,G4) -> 8960.3371 | H7: =SUM(H6,H4) -> 9032.0198 | I7: =SUM(I6,I4) -> 9466.8959 | ... AY7: =SUM(AY6,AY4) -> 17860.814
A8: Total Contribution (Yearly) | B8: =B7*12 -> 99366.672 | C8: =C7*12 -> 100161.61 | D8: =D7*12 -> 100962.9 | E8: =E7*12 -> 105824.09 | F8: =F7*12 -> 106670.68 | G8: =G7*12 -> 107524.04 | H8: =H7*12 -> 108384.24 | I8: =I7*12 -> 113602.75 | ... AY8: =AY7*12 -> 214329.77
A11: Aldersopsparing Total | B11: =AY54 -> 950809.37
A12: Divided by 25 | B12: =B11/25 -> 38032.375
A13: Monthly | B13: =B12/12 -> 3169.3646
A14: Taxed in retirement? | B14: No
A16: Total Contribution (Work Pension) | B16: =AY38 -> 14547921
A17: Divided by 25 years | B17: =B16/25 -> 581916.84 | C17: per year
A18: Monthly | B18: =B17/12 -> 48493.07 | C18: per month (gross)
A19: Taxed in Retirement? | B19: Yes | C19: Income tax
C21: base | D21: supplement
A22: Public Pension Average Monthly | B22: =C22 -> 7198 | C22: 7198 | D22: =8329*(1-30.9%) -> 5755.339
A23: Public Pension Average Yearly | B23: =B22*12 -> 86376
A24: Taxed in Retirement? | B24: Yes
A25: Inflation | B25: ='Salary Variables'!C2 -> 0.022
A26: Pension growth | B26: 0.03
A27: PAL tax | B27: 0.153
A29: ATP | B29: =AY47 -> 360498.36
A30: ATP Yearly | B30: =B29/25 -> 14419.934
A31: ATP Monthly | B31: =B30/12 -> 1201.6612
A33: Year | B33: 2010 | C33: 2011 | D33: 2012 | E33: 2013 | F33: 2014 | G33: 2015 | H33: 2016 | I33: 2017 | J33: 2018 | K33: 2019 | L33: 2020 | M33: 2021 | N33: 2022 | O33: 2023 | P33: 2024 | Q33: 2025 | R33: 2026 | S33: 2027 | T33: 2028 | U33: 2029 | V33: 2030 | W33: 2031 | X33: 2032 | Y33: 2033 | Z33: 2034 | AA33: 2035 | AB33: 2036 | AC33: 2037 | AD33: 2038 | AE33: 2039 | AF33: 2040 | AG33: 2041 | AH33: 2042 | AI33: 2043 | AJ33: 2044 | AK33: 2045 | AL33: 2046 | AM33: 2047 | AN33: 2048 | AO33: 2049 | AP33: 2050 | AQ33: 2051 | AR33: 2052 | AS33: 2053 | AT33: 2054 | AU33: 2055 | AV33: 2056 | AW33: 2057 | AX33: 2058 | AY33: 2059
A34: Work Pension Start of Year | B34: =B8 -> 99366.672 | C34: =B38+C8 -> 202053.18 | D34: =C38+D8 -> 308150.25 | E34: =D38+E8 -> 421804.44 | F34: =E38+F8 -> 539193.17 | G34: =F38+G8 -> 660418.11 | H34: =G38+H8 -> 785583.57 | I34: =H38+I8 -> 919148 | J34: =I38+J8 -> 1057015.1 | ... AY34: =AX38+AY8 -> 14187419
A35: Work Pension growth (%) | B35: =$B$26 -> 0.03 | C35: =$B$26 -> 0.03 | D35: =$B$26 -> 0.03 | E35: =$B$26 -> 0.03 | F35: =$B$26 -> 0.03 | G35: =$B$26 -> 0.03 | H35: =$B$26 -> 0.03 | I35: =$B$26 -> 0.03 | ... AY35: =$B$26 -> 0.03
A36: Work pension growth | B36: =B35*B34 -> 2981.0001 | C36: =C35*C34 -> 6061.5955 | D36: =D35*D34 -> 9244.5076 | E36: =E35*E34 -> 12654.133 | F36: =F35*F34 -> 16175.795 | G36: =G35*G34 -> 19812.543 | H36: =H35*H34 -> 23567.507 | I36: =I35*I34 -> 27574.44 | ... AY36: =AY35*AY34 -> 425622.56
A37: Tax | B37: =B36*$B$27 -> 456.09302 | C37: =C36*$B$27 -> 927.42411 | D37: =D36*$B$27 -> 1414.4097 | E37: =E36*$B$27 -> 1936.0824 | F37: =F36*$B$27 -> 2474.8966 | G37: =G36*$B$27 -> 3031.3191 | H37: =H36*$B$27 -> 3605.8286 | I37: =I36*$B$27 -> 4218.8893 | ... AY37: =AY36*$B$27 -> 65120.251
A38: Work Pension End of Year | B38: =B34+(B36-B37) -> 101891.58 | C38: =C34+(C36-C37) -> 207187.36 | D38: =D34+(D36-D37) -> 315980.35 | E38: =E34+(E36-E37) -> 432522.49 | F38: =F34+(F36-F37) -> 552894.07 | G38: =G34+(G36-G37) -> 677199.34 | H38: =H34+(H36-H37) -> 805545.25 | I38: =I34+(I36-I37) -> 942503.55 | ... AY38: =AY34+(AY36-AY37) -> 14547921
A42: ATP | B42: https://businessindenmark.virk.dk/guidance/atp-livslang-pension-bid/atp-employer/atp-contribution-rates2024/
A43: ATP start of year | B43: ='Net Salary P2'!B14*3 -> 3564 | C43: =B47+$B$43 -> 7218.5612 | D43: =C47+$B$43 -> 10965.985 | E43: =D47+$B$43 -> 14808.631 | F43: =E47+$B$43 -> 18748.918 | G43: =F47+$B$43 -> 22789.328 | H43: =G47+$B$43 -> 26932.405 | I43: =H47+$B$43 -> 31180.757 | J43: =I47+$B$43 -> 35537.06 | ... AY43: =AX47+$B$43 -> 351565.09
A44: Pension growth (%) | B44: =$B$26 -> 0.03 | C44: =$B$26 -> 0.03 | D44: =$B$26 -> 0.03 | E44: =$B$26 -> 0.03 | F44: =$B$26 -> 0.03 | G44: =$B$26 -> 0.03 | H44: =$B$26 -> 0.03 | I44: =$B$26 -> 0.03 | ... AY44: =$B$26 -> 0.03
A45: Pension growth | B45: =B44*B43 -> 106.92 | C45: =C44*C43 -> 216.55684 | D45: =D44*D43 -> 328.97955 | E45: =E44*E43 -> 444.25892 | F45: =F44*F43 -> 562.46754 | G45: =G44*G43 -> 683.67984 | H45: =H44*H43 -> 807.97214 | I45: =I44*I43 -> 935.42271 | ... AY45: =AY44*AY43 -> 10546.953
A46: Tax | B46: =B45*$B$27 -> 16.35876 | C46: =C45*$B$27 -> 33.133196 | D46: =D45*$B$27 -> 50.333871 | E46: =E45*$B$27 -> 67.971614 | F46: =F45*$B$27 -> 86.057533 | G46: =G45*$B$27 -> 104.60301 | H46: =H45*$B$27 -> 123.61974 | I46: =I45*$B$27 -> 143.11968 | ... AY46: =AY45*$B$27 -> 1613.6838
A47: Post Tax | B47: =B43+(B45-B46) -> 3654.5612 | C47: =C43+(C45-C46) -> 7401.9849 | D47: =D43+(D45-D46) -> 11244.631 | E47: =E43+(E45-E46) -> 15184.918 | F47: =F43+(F45-F46) -> 19225.328 | G47: =G43+(G45-G46) -> 23368.405 | H47: =H43+(H45-H46) -> 27616.757 | I47: =I43+(I45-I46) -> 31973.06 | ... AY47: =AY43+(AY45-AY46) -> 360498.36
A49: Aldersopsparing
A50: Start of year | B50: ='Net Salary P2'!$B$2 -> 9400 | C50: =B54+$B$50 -> 19038.854 | D50: =C54+$B$50 -> 28922.631 | E50: =D54+$B$50 -> 39057.555 | F50: =E54+$B$50 -> 49450.008 | G50: =F54+$B$50 -> 60106.533 | H50: =G54+$B$50 -> 71033.84 | I50: =H54+$B$50 -> 82238.809 | J50: =I54+$B$50 -> 93728.498 | ... AY50: =AX54+$B$50 -> 927248
A51: Pension growth (%) | B51: =$B$26 -> 0.03 | C51: =$B$26 -> 0.03 | D51: =$B$26 -> 0.03 | E51: =$B$26 -> 0.03 | F51: =$B$26 -> 0.03 | G51: =$B$26 -> 0.03 | H51: =$B$26 -> 0.03 | I51: =$B$26 -> 0.03 | ... AY51: =$B$26 -> 0.03
A52: Pension growth | B52: =B51*B50 -> 282 | C52: =C51*C50 -> 571.16562 | D52: =D51*D50 -> 867.67894 | E52: =E51*E50 -> 1171.7267 | F52: =F51*F50 -> 1483.5002 | G52: =G51*G50 -> 1803.196 | H52: =H51*H50 -> 2131.0152 | I52: =I51*I50 -> 2467.1643 | ... AY52: =AY51*AY50 -> 27817.44
A53: Tax | B53: =B52*$B$27 -> 43.146 | C53: =C52*$B$27 -> 87.38834 | D53: =D52*$B$27 -> 132.75488 | E53: =E52*$B$27 -> 179.27418 | F53: =F52*$B$27 -> 226.97554 | G53: =G52*$B$27 -> 275.88898 | H53: =H52*$B$27 -> 326.04532 | I53: =I52*$B$27 -> 377.47614 | ... AY53: =AY52*$B$27 -> 4256.0683
A54: Post Tax | B54: =B50+(B52-B53) -> 9638.854 | C54: =C50+(C52-C53) -> 19522.631 | D54: =D50+(D52-D53) -> 29657.555 | E54: =E50+(E52-E53) -> 40050.008 | F54: =F50+(F52-F53) -> 50706.533 | G54: =G50+(G52-G53) -> 61633.84 | H54: =H50+(H52-H53) -> 72838.809 | I54: =I50+(I52-I53) -> 84328.498 | ... AY54: =AY50+(AY52-AY53) -> 950809.37

Sheet Net Salary P2
A1: Inflation | B1: ='Salary Variables'!$C$2 -> 0.022 | D1: Year | E1: 2010 | F1: 2011 | G1: 2012 | H1: 2013 | I1: 2014 | J1: 2015 | K1: 2016 | L1: 2017 | M1: 2018 | N1: 2019 | O1: 2020 | P1: 2021 | Q1: 2022 | R1: 2023 | S1: 2024 | T1: 2025 | U1: 2026 | V1: 2027 | W1: 2028 | X1: 2029 | Y1: 2030 | Z1: 2031 | AA1: 2032 | AB1: 2033 | AC1: 2034 | AD1: 2035 | AE1: 2036 | AF1: 2037 | AG1: 2038 | AH1: 2039 | AI1: 2040 | AJ1: 2041 | AK1: 2042 | AL1: 2043 | AM1: 2044 | AN1: 2045 | AO1: 2046 | AP1: 2047 | AQ1: 2048 | AR1: 2049 | AS1: 2050 | AT1: 2051 | AU1: 2052 | AV1: 2053 | AW1: 2054 | AX1: 2055 | AY1: 2056 | AZ1: 2057 | BA1: 2058 | BB1: 2059
A2: Aldersopsparing max | B2: ='Salary Variables'!$C$14 -> 9400 | D2: Month Salary (Inflation Adjusted) | E2: {=TRANSPOSE('Income - P2 Helper'!N3:N17)} -> 55203.706 | F2: 55645.336 | G2: 56090.499 | H2: 58791.159 | I2: 59261.489 | J2: 59735.581 | K2: 60213.465 | L2: 63112.639 | M2: 63617.541 | N2: 64126.481 | O2: 64639.493 | P2: 67751.773 | Q2: 68293.787 | R2: 68840.137 | S2: 72154.671 | T2: {=TRANSPOSE(Income!P3:P37)} -> 72731.908 | U2: 73313.763 | V2: 76686.196 | W2: 77299.686 | X2: 77918.083 | Y2: 78541.428 | Z2: 82154.334 | AA2: 82811.568 | AB2: 83474.061 | AC2: 84141.854 | AD2: 88012.379 | AE2: 88716.478 | AF2: 89426.21 | AG2: 93539.815 | AH2: 94288.134 | AI2: 95042.439 | AJ2: 95802.778 | AK2: 96569.201 | AL2: 101011.38 | AM2: 101819.47 | AN2: 102634.03 | AO2: 103455.1 | AP2: 108214.04 | AQ2: 109079.75 | AR2: 109952.39 | AS2: 110832.01 | AT2: 111718.66 | AU2: 112612.41 | AV2: 113513.31 | AW2: 114421.42 | AX2: 115336.79 | AY2: 116259.48 | AZ2: 117189.56 | BA2: 118127.08 | BB2: 119072.09 | BH2: helper for other column, do not remove --> | BI2: {=TRANSPOSE(T17:BC17)} -> 38570.521
D3: Yearly Salary | E3: =E2*12 -> 662444.48 | F3: =F2*12 -> 667744.03 | G3: =G2*12 -> 673085.99 | H3: =H2*12 -> 705493.91 | I3: =I2*12 -> 711137.86 | J3: =J2*12 -> 716826.97 | K3: =K2*12 -> 722561.58 | L3: =L2*12 -> 757351.67 | ... BB3: =BB2*12 -> 1428865.1 | BI3: 38814.57
A4: {='Salary Variables'!$B$16:$C$24} -> AM (%) | B4: 0.08 | D4: Work Pension | E4: ='Pensions P2'!B4*12 -> 33122.224 | F4: ='Pensions P2'!C4*12 -> 33387.202 | G4: ='Pensions P2'!D4*12 -> 33654.299 | H4: ='Pensions P2'!E4*12 -> 35274.696 | I4: ='Pensions P2'!F4*12 -> 35556.893 | J4: ='Pensions P2'!G4*12 -> 35841.348 | K4: ='Pensions P2'!H4*12 -> 36128.079 | L4: ='Pensions P2'!I4*12 -> 37867.584 | ... BB4: ='Pensions P2'!AY4*12 -> 71443.256 | BI4: 40229.078
A5: Personal Allowance | B5: 51600 | D5: Post Pension | E5: =E3-E4 -> 629322.25 | F5: =F3-F4 -> 634356.83 | G5: =G3-G4 -> 639431.69 | H5: =H3-H4 -> 670219.22 | I5: =I3-I4 -> 675580.97 | J5: =J3-J4 -> 680985.62 | K5: =K3-K4 -> 686433.5 | L5: =L3-L4 -> 719484.09 | ... BB5: =BB3-BB4 -> 1357421.9 | BI5: 40486.396
A6: Bottom-Bracket State Tax rate (%) | B6: 0.1201 | D6: Post ATP | E6: =E5-$B$14 -> 628134.25 | F6: =F5-$B$14 -> 633168.83 | G6: =G5-$B$14 -> 638243.69 | H6: =H5-$B$14 -> 669031.22 | I6: =I5-$B$14 -> 674392.97 | J6: =J5-$B$14 -> 679797.62 | K6: =K5-$B$14 -> 685245.5 | L6: =L5-$B$14 -> 718296.09 | ... BB6: =BB5-$B$14 -> 1356233.9 | BI6: 40745.772
A7: Top-bracket State Tax rate (%) | B7: 0.15 | D7: Post AM (Taxable Personal Income) | E7: =E6*(1-$B$4) -> 577883.51 | F7: =F6*(1-$B$4) -> 582515.33 | G7: =G6*(1-$B$4) -> 587184.19 | H7: =H6*(1-$B$4) -> 615508.72 | I7: =I6*(1-$B$4) -> 620441.53 | J7: =J6*(1-$B$4) -> 625413.81 | K7: =K6*(1-$B$4) -> 630425.86 | L7: =L6*(1-$B$4) -> 660832.4 | ... BB7: =BB6*(1-$B$4) -> 1247735.2 | BI7: 41007.223
A8: State Tax Bracket Threshold | B8: 618400 | D8: Personal Allowance | E8: =$B$5 -> 51600 | F8: =$B$5 -> 51600 | G8: =$B$5 -> 51600 | H8: =$B$5 -> 51600 | I8: =$B$5 -> 51600 | J8: =$B$5 -> 51600 | K8: =$B$5 -> 51600 | L8: =$B$5 -> 51600 | ... BB8: =$B$5 -> 51600 | BI8: 42522.593
A9: Municipal Tax (%) | B9: 0.25 | D9: TPI exceed PA | E9: =E7-E8 -> 526283.51 | F9: =F7-F8 -> 530915.33 | G9: =G7-G8 -> 535584.19 | H9: =H7-H8 -> 563908.72 | I9: =I7-I8 -> 568841.53 | J9: =J7-J8 -> 573813.81 | K9: =K7-K8 -> 578825.86 | L9: =L7-L8 -> 609232.4 | ... BB9: =BB7-BB8 -> 1196135.2 | BI9: 42798.259
A10: Capital Gains < 67,500DKK | B10: 0.27 | D10: Municipal Tax | E10: =E7*$B$9 -> 144470.88 | F10: =F7*$B$9 -> 145628.83 | G10: =G7*$B$9 -> 146796.05 | H10: =H7*$B$9 -> 153877.18 | I10: =I7*$B$9 -> 155110.38 | J10: =J7*$B$9 -> 156353.45 | K10: =K7*$B$9 -> 157606.47 | L10: =L7*$B$9 -> 165208.1 | ... BB10: =BB7*$B$9 -> 311933.79 | BI10: 43076.13
A11: Capital Gains > 67,500DKK | B11: 0.42 | D11: Top State Tax | E11: =MAX(E9-$B$8,0)*$B$7 -> 0 | F11: =MAX(F9-$B$8,0)*$B$7 -> 0 | G11: =MAX(G9-$B$8,0)*$B$7 -> 0 | H11: =MAX(H9-$B$8,0)*$B$7 -> 0 | I11: =MAX(I9-$B$8,0)*$B$7 -> 0 | J11: =MAX(J9-$B$8,0)*$B$7 -> 0 | K11: =MAX(K9-$B$8,0)*$B$7 -> 0 | L11: =MAX(L9-$B$8,0)*$B$7 -> 0 | ... BB11: =MAX(BB9-$B$8,0)*$B$7 -> 86660.273 | BI11: 43356.224
A12: Capital Gains Threshold | B12: 67500 | D12: Bottom State Tax | E12: =E9*$B$6 -> 63206.65 | F12: =F9*$B$6 -> 63762.931 | G12: =G9*$B$6 -> 64323.661 | H12: =H9*$B$6 -> 67725.437 | I12: =I9*$B$6 -> 68317.868 | J12: =J9*$B$6 -> 68915.038 | K12: =K9*$B$6 -> 69516.986 | L12: =L9*$B$6 -> 73168.812 | ... BB12: =BB9*$B$6 -> 143655.83 | BI12: 44979.648
A13: ATP monthly | B13: 99 | D13: Total Tax | E13: =SUM(E10:E12) -> 207677.53 | F13: =SUM(F10:F12) -> 209391.76 | G13: =SUM(G10:G12) -> 211119.71 | H13: =SUM(H10:H12) -> 221602.62 | I13: =SUM(I10:I12) -> 223428.25 | J13: =SUM(J10:J12) -> 225268.49 | K13: =SUM(K10:K12) -> 227123.45 | L13: =SUM(L10:L12) -> 238376.91 | ... BB13: =SUM(BB10:BB12) -> 542249.89 | BI13: 45274.97
A14: ATP yearly | B14: =B13*12 -> 1188 | D14: Post Tax Salary | E14: =E7-E13 -> 370205.99 | F14: =F7-F13 -> 373123.56 | G14: =G7-G13 -> 376064.48 | H14: =H7-H13 -> 393906.1 | I14: =I7-I13 -> 397013.28 | J14: =J7-J13 -> 400145.32 | K14: =K7-K13 -> 403302.41 | L14: =L7-L13 -> 422455.49 | ... BB14: =BB7-BB13 -> 705485.26 | BI14: 45572.655
D15: Alderopsparing | E15: =$B$2 -> 9400 | F15: =$B$2 -> 9400 | G15: =$B$2 -> 9400 | H15: =$B$2 -> 9400 | I15: =$B$2 -> 9400 | J15: =$B$2 -> 9400 | K15: =$B$2 -> 9400 | L15: =$B$2 -> 9400 | ... BB15: =$B$2 -> 9400 | BI15: 47298.035
D16: Net Salary (Yearly) | E16: =E14-E15 -> 360805.99 | F16: =F14-F15 -> 363723.56 | G16: =G14-G15 -> 366664.48 | H16: =H14-H15 -> 384506.1 | I16: =I14-I15 -> 387613.28 | J16: =J14-J15 -> 390745.32 | K16: =K14-K15 -> 393902.41 | L16: =L14-L15 -> 413055.49 | ... BB16: =BB14-BB15 -> 696085.26 | BI16: 47611.904
D17: Net Salary (Monthly) | E17: =E16/12 -> 30067.165 | F17: =F16/12 -> 30310.297 | G17: =G16/12 -> 30555.374 | H17: =H16/12 -> 32042.175 | I17: =I16/12 -> 32301.107 | J17: =J16/12 -> 32562.11 | K17: =K16/12 -> 32825.201 | L17: =L16/12 -> 34421.291 | ... BB17: =BB16/12 -> 58007.105 | BI17: 47928.285
BI18: 48247.196
BI19: 48568.658
BI20: 50431.855
D21: Year | E21: 2060 | F21: 2061 | G21: 2061 | H21: 2061 | I21: 2061 | J21: 2061 | K21: 2061 | L21: 2061 | M21: 2061 | N21: 2061 | O21: 2061 | P21: 2061 | Q21: 2061 | R21: 2061 | S21: 2061 | T21: 2061 | U21: 2061 | V21: 2061 | W21: 2061 | X21: 2061 | Y21: 2061 | Z21: 2061 | AA21: 2061 | AB21: 2061 | AC21: 2061 | BI21: 50770.794
D22: Monthly Salary | E22: ='Pensions P2'!$B$18+'Pensions P2'!$B$22+'Pensions P2'!$B$31 -> 56892.731 | F22: ='Pensions P2'!$B$18+'Pensions P2'!$B$22+'Pensions P2'!$B$31 -> 56892.731 | G22: ='Pensions P2'!$B$18+'Pensions P2'!$B$22+'Pensions P2'!$B$31 -> 56892.731 | H22: ='Pensions P2'!$B$18+'Pensions P2'!$B$22+'Pensions P2'!$B$31 -> 56892.731 | I22: ='Pensions P2'!$B$18+'Pensions P2'!$B$22+'Pensions P2'!$B$31 -> 56892.731 | J22: ='Pensions P2'!$B$18+'Pensions P2'!$B$22+'Pensions P2'!$B$31 -> 56892.731 | K22: ='Pensions P2'!$B$18+'Pensions P2'!$B$22+'Pensions P2'!$B$31 -> 56892.731 | L22: ='Pensions P2'!$B$18+'Pensions P2'!$B$22+'Pensions P2'!$B$31 -> 56892.731 | ... AC22: ='Pensions P2'!$B$18+'Pensions P2'!$B$22+'Pensions P2'!$B$31 -> 56892.731 | BI22: 51112.446
BI23: 51456.83
D24: Yearly Salary Inflation Adjusted | E24: =E22*12 -> 682712.77 | F24: =F22*12 -> 682712.77 | G24: =G22*12 -> 682712.77 | H24: =H22*12 -> 682712.77 | I24: =I22*12 -> 682712.77 | J24: =J22*12 -> 682712.77 | K24: =K22*12 -> 682712.77 | L24: =L22*12 -> 682712.77 | ... AC24: =AC22*12 -> 682712.77 | BI24: 53452.883
D25: Municipal Tax | E25: =E24*$B$9 -> 170678.19 | F25: =F24*$B$9 -> 170678.19 | G25: =G24*$B$9 -> 170678.19 | H25: =H24*$B$9 -> 170678.19 | I25: =I24*$B$9 -> 170678.19 | J25: =J24*$B$9 -> 170678.19 | K25: =K24*$B$9 -> 170678.19 | L25: =L24*$B$9 -> 170678.19 | ... AC25: =AC24*$B$9 -> 170678.19 | BI25: 53815.991
D26: Top State Tax | E26: =MAX(E24-$B$8,0)*$B$7 -> 9646.9158 | F26: =MAX(F24-$B$8,0)*$B$7 -> 9646.9158 | G26: =MAX(G24-$B$8,0)*$B$7 -> 9646.9158 | H26: =MAX(H24-$B$8,0)*$B$7 -> 9646.9158 | I26: =MAX(I24-$B$8,0)*$B$7 -> 9646.9158 | J26: =MAX(J24-$B$8,0)*$B$7 -> 9646.9158 | K26: =MAX(K24-$B$8,0)*$B$7 -> 9646.9158 | L26: =MAX(L24-$B$8,0)*$B$7 -> 9646.9158 | ... AC26: =MAX(AC24-$B$8,0)*$B$7 -> 9646.9158 | BI26: 54182.003
D27: Bottom State Tax | E27: =E24*$B$6 -> 81993.804 | F27: =F24*$B$6 -> 81993.804 | G27: =G24*$B$6 -> 81993.804 | H27: =H24*$B$6 -> 81993.804 | I27: =I24*$B$6 -> 81993.804 | J27: =J24*$B$6 -> 81993.804 | K27: =K24*$B$6 -> 81993.804 | L27: =L24*$B$6 -> 81993.804 | ... AC27: =AC24*$B$6 -> 81993.804 | BI27: 54550.944
D28: Total Tax | E28: =SUM(E25:E27) -> 262318.91 | F28: =SUM(F25:F27) -> 262318.91 | G28: =SUM(G25:G27) -> 262318.91 | H28: =SUM(H25:H27) -> 262318.91 | I28: =SUM(I25:I27) -> 262318.91 | J28: =SUM(J25:J27) -> 262318.91 | K28: =SUM(K25:K27) -> 262318.91 | L28: =SUM(L25:L27) -> 262318.91 | ... AC28: =SUM(AC25:AC27) -> 262318.91 | BI28: 54922.837
D29: Post Tax Salary | E29: =E24-E28 -> 420393.86 | F29: =F24-F28 -> 420393.86 | G29: =G24-G28 -> 420393.86 | H29: =H24-H28 -> 420393.86 | I29: =I24-I28 -> 420393.86 | J29: =J24-J28 -> 420393.86 | K29: =K24-K28 -> 420393.86 | L29: =L24-L28 -> 420393.86 | ... AC29: =AC24-AC28 -> 420393.86 | BI29: 55297.704
D30: Aldersopsparing | E30: ='Pensions P2'!$B$13 -> 3169.3646 | F30: ='Pensions P2'!$B$13 -> 3169.3646 | G30: ='Pensions P2'!$B$13 -> 3169.3646 | H30: ='Pensions P2'!$B$13 -> 3169.3646 | I30: ='Pensions P2'!$B$13 -> 3169.3646 | J30: ='Pensions P2'!$B$13 -> 3169.3646 | K30: ='Pensions P2'!$B$13 -> 3169.3646 | L30: ='Pensions P2'!$B$13 -> 3169.3646 | ... AC30: ='Pensions P2'!$B$13 -> 3169.3646 | BI30: 55675.571
D31: Net Salary (Monthly) | E31: =(E29/12)+E30 -> 38202.186 | F31: =(F29/12)+F30 -> 38202.186 | G31: =(G29/12)+G30 -> 38202.186 | H31: =(H29/12)+H30 -> 38202.186 | I31: =(I29/12)+I30 -> 38202.186 | J31: =(J29/12)+J30 -> 38202.186 | K31: =(K29/12)+K30 -> 38202.186 | L31: =(L29/12)+L30 -> 38202.186 | ... AC31: =(AC29/12)+AC30 -> 38202.186 | BI31: 56056.46
D32: Last Net Income from Work | E32: =Income!$L$37 -> 46405.684 | F32: =Income!$L$37 -> 46405.684 | G32: =Income!$L$37 -> 46405.684 | H32: =Income!$L$37 -> 46405.684 | I32: =Income!$L$37 -> 46405.684 | J32: =Income!$L$37 -> 46405.684 | K32: =Income!$L$37 -> 46405.684 | L32: =Income!$L$37 -> 46405.684 | ... AC32: =Income!$L$37 -> 46405.684 | BI32: 56440.397
D33: Diff | E33: =E32-E31 -> 8203.4977 | F33: =F32-F31 -> 8203.4977 | G33: =G32-G31 -> 8203.4977 | H33: =H32-H31 -> 8203.4977 | I33: =I32-I31 -> 8203.4977 | J33: =J32-J31 -> 8203.4977 | K33: =K32-K31 -> 8203.4977 | L33: =L32-L31 -> 8203.4977 | ... AC33: =AC32-AC31 -> 8203.4977 | BI33: 56827.405
D34: Monthly Target | E34: =E33*(1+$B$10) -> 10418.442 | F34: =F33*(1+$B$10) -> 10418.442 | G34: =G33*(1+$B$10) -> 10418.442 | H34: =H33*(1+$B$10) -> 10418.442 | I34: =I33*(1+$B$10) -> 10418.442 | J34: =J33*(1+$B$10) -> 10418.442 | K34: =K33*(1+$B$10) -> 10418.442 | L34: =L33*(1+$B$10) -> 10418.442 | ... AC34: =AC33*(1+$B$10) -> 10418.442 | BI34: 57217.509
D35: Yearly Target | E35: =E34*12 -> 125021.31 | F35: =F34*12 -> 125021.31 | G35: =G34*12 -> 125021.31 | H35: =H34*12 -> 125021.31 | I35: =I34*12 -> 125021.31 | J35: =J34*12 -> 125021.31 | K35: =K34*12 -> 125021.31 | L35: =L34*12 -> 125021.31 | ... AC35: =AC34*12 -> 125021.31 | BI35: 57610.734
BI36: 58007.105
D37: To be financed | E37: =SUM(E35:AC35) -> 3125532.6 | BI37: 0
E39: =1500000 -> 1500000 | F39: =E39/25 -> 60000

Sheet Net Salary P1
A1: Inflation | B1: ='Salary Variables'!$C$2 -> 0.022 | D1: Year | E1: 2025 | F1: 2026 | G1: 2027 | H1: 2028 | I1: 2029 | J1: 2030 | K1: 2031 | L1: 2032 | M1: 2033 | N1: 2034 | O1: 2035 | P1: 2036 | Q1: 2037 | R1: 2038 | S1: 2039 | T1: 2040 | U1: 2041 | V1: 2042 | W1: 2043 | X1: 2044 | Y1: 2045 | Z1: 2046 | AA1: 2047 | AB1: 2048 | AC1: 2049 | AD1: 2050 | AE1: 2051 | AF1: 2052 | AG1: 2053 | AH1: 2054 | AI1: 2055 | AJ1: 2056 | AK1: 2057 | AL1: 2058 | AM1: 2059 | AN1: 2060 | AO1: 2061 | AP1: 2062 | AQ1: 2063 | AR1: 2064 | AS1: 2065 | AT1: 2066 | AU1: 2067 | AV1: 2068 | AW1: 2069 | AX1: 2070 | AY1: 2071 | AZ1: 2072 | BA1: 2073 | BB1: 2074
A2: Aldersopsparing max | B2: ='Salary Variables'!$C$14 -> 9400 | D2: Month Salary (Inflation Adjusted) | E2: {=TRANSPOSE(Income!O3:O52)} -> 43336.595 | F2: 43683.288 | G2: 45692.719 | H2: 46058.261 | I2: 46426.727 | J2: 46798.141 | K2: 48950.855 | L2: 49342.462 | M2: 49737.202 | N2: 50135.099 | O2: 52441.314 | P2: 52860.844 | Q2: 53283.731 | R2: 55734.783 | S2: 56180.661 | T2: 56630.106 | U2: 57083.147 | V2: 57539.812 | W2: 60186.644 | X2: 60668.137 | Y2: 61153.482 | Z2: 61642.71 | AA2: 64478.274 | AB2: 64994.1 | AC2: 65514.053 | AD2: 66038.166 | AE2: 66566.471 | AF2: 67099.003 | AG2: 67635.795 | AH2: 68176.881 | AI2: 68722.296 | AJ2: 69272.075 | AK2: 69826.251 | AL2: 70384.861 | AM2: 70947.94 | AN2: 74211.545 | AO2: 74805.238 | AP2: 75403.68 | AQ2: 76006.909 | AR2: 76614.964 | AS2: 77227.884 | AT2: 77845.707 | AU2: 78468.473 | AV2: 79096.221 | AW2: 79728.99 | AX2: 80366.822 | AY2: 81009.757 | AZ2: 81657.835 | BA2: 82311.098 | BB2: 82969.586 | BH2: helper for other column, do not remove --> | BI2: {=TRANSPOSE(E17:BC17)} -> 23533.934
D3: Yearly Salary | E3: =E2*12 -> 520039.14 | F3: =F2*12 -> 524199.45 | G3: =G2*12 -> 548312.63 | H3: =H2*12 -> 552699.13 | I3: =I2*12 -> 557120.72 | J3: =J2*12 -> 561577.69 | K3: =K2*12 -> 587410.26 | L3: =L2*12 -> 592109.54 | ... BB3: =BB2*12 -> 995635.04 | BI3: 23724.799
A4: {='Salary Variables'!$B$16:$C$24} -> AM (%) | B4: 0.08 | D4: Work Pension | E4: ='Pensions P1'!B4*12 -> 26001.957 | F4: ='Pensions P1'!C4*12 -> 26209.973 | G4: ='Pensions P1'!D4*12 -> 27415.631 | H4: ='Pensions P1'!E4*12 -> 27634.956 | I4: ='Pensions P1'!F4*12 -> 27856.036 | J4: ='Pensions P1'!G4*12 -> 28078.884 | K4: ='Pensions P1'!H4*12 -> 29370.513 | L4: ='Pensions P1'!I4*12 -> 29605.477 | ... BB4: ='Pensions P1'!AY4*12 -> 49781.752 | BI4: 24831.057
A5: Personal Allowance | B5: 51600 | D5: Post Pension | E5: =E3-E4 -> 494037.18 | F5: =F3-F4 -> 497989.48 | G5: =G3-G4 -> 520897 | H5: =H3-H4 -> 525064.17 | I5: =I3-I4 -> 529264.68 | J5: =J3-J4 -> 533498.8 | K5: =K3-K4 -> 558039.75 | L5: =L3-L4 -> 562504.07 | ... BB5: =BB3-BB4 -> 945853.28 | BI5: 25032.299
A6: Bottom-Bracket State Tax rate (%) | B6: 0.1201 | D6: Post ATP | E6: =E5-$B$14 -> 492849.18 | F6: =F5-$B$14 -> 496801.48 | G6: =G5-$B$14 -> 519709 | H6: =H5-$B$14 -> 523876.17 | I6: =I5-$B$14 -> 528076.68 | J6: =J5-$B$14 -> 532310.8 | K6: =K5-$B$14 -> 556851.75 | L6: =L5-$B$14 -> 561316.07 | ... BB6: =BB5-$B$14 -> 944665.28 | BI6: 25235.152
A7: Top-bracket State Tax rate (%) | B7: 0.15 | D7: Post AM (Taxable Personal Income) | E7: =E6*(1-$B$4) -> 453421.25 | F7: =F6*(1-$B$4) -> 457057.36 | G7: =G6*(1-$B$4) -> 478132.28 | H7: =H6*(1-$B$4) -> 481966.08 | I7: =I6*(1-$B$4) -> 485830.55 | J7: =J6*(1-$B$4) -> 489725.94 | K7: =K6*(1-$B$4) -> 512303.61 | L7: =L6*(1-$B$4) -> 516410.78 | ... BB7: =BB6*(1-$B$4) -> 869092.06 | BI7: 25439.627
A8: State Tax Bracket Threshold | B8: 618400 | D8: Personal Allowance | E8: =$B$5 -> 51600 | F8: =$B$5 -> 51600 | G8: =$B$5 -> 51600 | H8: =$B$5 -> 51600 | I8: =$B$5 -> 51600 | J8: =$B$5 -> 51600 | K8: =$B$5 -> 51600 | L8: =$B$5 -> 51600 | ... BB8: =$B$5 -> 51600 | BI8: 26624.767
A9: Municipal Tax (%) | B9: 0.25 | D9: TPI exceed PA | E9: =E7-E8 -> 401821.25 | F9: =F7-F8 -> 405457.36 | G9: =G7-G8 -> 426532.28 | H9: =H7-H8 -> 430366.08 | I9: =I7-I8 -> 434230.55 | J9: =J7-J8 -> 438125.94 | K9: =K7-K8 -> 460703.61 | L9: =L7-L8 -> 464810.78 | ... BB9: =BB7-BB8 -> 817492.06 | BI9: 26840.359
A10: Capital Gains < 67,500DKK | B10: 0.27 | D10: Municipal Tax | E10: =E7*$B$9 -> 113355.31 | F10: =F7*$B$9 -> 114264.34 | G10: =G7*$B$9 -> 119533.07 | H10: =H7*$B$9 -> 120491.52 | I10: =I7*$B$9 -> 121457.64 | J10: =J7*$B$9 -> 122431.48 | K10: =K7*$B$9 -> 128075.9 | L10: =L7*$B$9 -> 129102.69 | ... BB10: =BB7*$B$9 -> 217273.02 | BI10: 27057.676
A11: Capital Gains > 67,500DKK | B11: 0.42 | D11: Top State Tax | E11: =MAX(E9-$B$8,0)*$B$7 -> 0 | F11: =MAX(F9-$B$8,0)*$B$7 -> 0 | G11: =MAX(G9-$B$8,0)*$B$7 -> 0 | H11: =MAX(H9-$B$8,0)*$B$7 -> 0 | I11: =MAX(I9-$B$8,0)*$B$7 -> 0 | J11: =MAX(J9-$B$8,0)*$B$7 -> 0 | K11: =MAX(K9-$B$8,0)*$B$7 -> 0 | L11: =MAX(L9-$B$8,0)*$B$7 -> 0 | ... BB11: =MAX(BB9-$B$8,0)*$B$7 -> 29863.809 | BI11: 27276.732
A12: Capital Gains Threshold | B12: 67500 | D12: Bottom State Tax | E12: =E9*$B$6 -> 48258.732 | F12: =F9*$B$6 -> 48695.429 | G12: =G9*$B$6 -> 51226.526 | H12: =H9*$B$6 -> 51686.966 | I12: =I9*$B$6 -> 52151.089 | J12: =J9*$B$6 -> 52618.925 | K12: =K9*$B$6 -> 55330.503 | L12: =L9*$B$6 -> 55823.775 | ... BB12: =BB9*$B$6 -> 98180.797 | BI12: 28546.378
A13: ATP monthly | B13: 99 | D13: Total Tax | E13: =SUM(E10:E12) -> 161614.04 | F13: =SUM(F10:F12) -> 162959.77 | G13: =SUM(G10:G12) -> 170759.6 | H13: =SUM(H10:H12) -> 172178.49 | I13: =SUM(I10:I12) -> 173608.73 | J13: =SUM(J10:J12) -> 175050.41 | K13: =SUM(K10:K12) -> 183406.41 | L13: =SUM(L10:L12) -> 184926.47 | ... BB13: =SUM(BB10:BB12) -> 345317.62 | BI13: 28777.343
A14: ATP yearly | B14: =B13*12 -> 1188 | D14: Post Tax Salary | E14: =E7-E13 -> 291807.2 | F14: =F7-F13 -> 294097.59 | G14: =G7-G13 -> 307372.68 | H14: =H7-H13 -> 309787.59 | I14: =I7-I13 -> 312221.82 | J14: =J7-J13 -> 314675.53 | K14: =K7-K13 -> 328897.2 | L14: =L7-L13 -> 331484.31 | ... BB14: =BB7-BB13 -> 523774.44 | BI14: 29010.156
D15: Alderopsparing | E15: =$B$2 -> 9400 | F15: =$B$2 -> 9400 | G15: =$B$2 -> 9400 | H15: =$B$2 -> 9400 | I15: =$B$2 -> 9400 | J15: =$B$2 -> 9400 | K15: =$B$2 -> 9400 | L15: =$B$2 -> 9400 | ... BB15: =$B$2 -> 9400 | BI15: 30359.54
D16: Net Salary (Yearly) | E16: =E14-E15 -> 282407.2 | F16: =F14-F15 -> 284697.59 | G16: =G14-G15 -> 297972.68 | H16: =H14-H15 -> 300387.59 | I16: =I14-I15 -> 302821.82 | J16: =J14-J15 -> 305275.53 | K16: =K14-K15 -> 319497.2 | L16: =L14-L15 -> 322084.31 | ... BB16: =BB14-BB15 -> 514374.44 | BI16: 30605.011
D17: Net Salary (Monthly) | E17: =E16/12 -> 23533.934 | F17: =F16/12 -> 23724.799 | G17: =G16/12 -> 24831.057 | H17: =H16/12 -> 25032.299 | I17: =I16/12 -> 25235.152 | J17: =J16/12 -> 25439.627 | K17: =K16/12 -> 26624.767 | L17: =L16/12 -> 26840.359 | ... BB17: =BB16/12 -> 42864.537 | BI17: 30852.445
BI18: 31101.859
BI19: 31353.268
BI20: 32810.435
D21: Year | E21: 2075 | F21: 2076 | G21: 2077 | H21: 2078 | I21: 2079 | J21: 2080 | K21: 2081 | L21: 2082 | M21: 2083 | N21: 2084 | O21: 2085 | P21: 2086 | Q21: 2087 | R21: 2088 | S21: 2089 | T21: 2090 | U21: 2091 | V21: 2092 | W21: 2093 | X21: 2094 | Y21: 2095 | Z21: 2096 | AA21: 2097 | AB21: 2098 | AC21: 2099 | BI21: 33075.512
D22: Monthly Salary | E22: ='Pensions P1'!$B$18+'Pensions P1'!$B$22+'Pensions P1'!$B$31 -> 44829.349 | F22: ='Pensions P1'!$B$18+'Pensions P1'!$B$22+'Pensions P1'!$B$31 -> 44829.349 | G22: ='Pensions P1'!$B$18+'Pensions P1'!$B$22+'Pensions P1'!$B$31 -> 44829.349 | H22: ='Pensions P1'!$B$18+'Pensions P1'!$B$22+'Pensions P1'!$B$31 -> 44829.349 | I22: ='Pensions P1'!$B$18+'Pensions P1'!$B$22+'Pensions P1'!$B$31 -> 44829.349 | J22: ='Pensions P1'!$B$18+'Pensions P1'!$B$22+'Pensions P1'!$B$31 -> 44829.349 | K22: ='Pensions P1'!$B$18+'Pensions P1'!$B$22+'Pensions P1'!$B$31 -> 44829.349 | L22: ='Pensions P1'!$B$18+'Pensions P1'!$B$22+'Pensions P1'!$B$31 -> 44829.349 | ... AC22: ='Pensions P1'!$B$18+'Pensions P1'!$B$22+'Pensions P1'!$B$31 -> 44829.349 | BI22: 33342.711
BI23: 33612.047
D24: Yearly Salary Inflation Adjusted | E24: =E22*12 -> 537952.19 | F24: =F22*12 -> 537952.19 | G24: =G22*12 -> 537952.19 | H24: =H22*12 -> 537952.19 | I24: =I22*12 -> 537952.19 | J24: =J22*12 -> 537952.19 | K24: =K22*12 -> 537952.19 | L24: =L22*12 -> 537952.19 | ... AC24: =AC22*12 -> 537952.19 | BI24: 35108.678
D25: Municipal Tax | E25: =E24*$B$9 -> 134488.05 | F25: =F24*$B$9 -> 134488.05 | G25: =G24*$B$9 -> 134488.05 | H25: =H24*$B$9 -> 134488.05 | I25: =I24*$B$9 -> 134488.05 | J25: =J24*$B$9 -> 134488.05 | K25: =K24*$B$9 -> 134488.05 | L25: =L24*$B$9 -> 134488.05 | ... AC25: =AC24*$B$9 -> 134488.05 | BI25: 35325.032
D26: Top State Tax | E26: =MAX(E24-$B$8,0)*$B$7 -> 0 | F26: =MAX(F24-$B$8,0)*$B$7 -> 0 | G26: =MAX(G24-$B$8,0)*$B$7 -> 0 | H26: =MAX(H24-$B$8,0)*$B$7 -> 0 | I26: =MAX(I24-$B$8,0)*$B$7 -> 0 | J26: =MAX(J24-$B$8,0)*$B$7 -> 0 | K26: =MAX(K24-$B$8,0)*$B$7 -> 0 | L26: =MAX(L24-$B$8,0)*$B$7 -> 0 | ... AC26: =MAX(AC24-$B$8,0)*$B$7 -> 0 | BI26: 35543.117
D27: Bottom State Tax | E27: =E24*$B$6 -> 64608.058 | F27: =F24*$B$6 -> 64608.058 | G27: =G24*$B$6 -> 64608.058 | H27: =H24*$B$6 -> 64608.058 | I27: =I24*$B$6 -> 64608.058 | J27: =J24*$B$6 -> 64608.058 | K27: =K24*$B$6 -> 64608.058 | L27: =L24*$B$6 -> 64608.058 | ... AC27: =AC24*$B$6 -> 64608.058 | BI27: 35762.947
D28: Total Tax | E28: =SUM(E25:E27) -> 199096.1 | F28: =SUM(F25:F27) -> 199096.1 | G28: =SUM(G25:G27) -> 199096.1 | H28: =SUM(H25:H27) -> 199096.1 | I28: =SUM(I25:I27) -> 199096.1 | J28: =SUM(J25:J27) -> 199096.1 | K28: =SUM(K25:K27) -> 199096.1 | L28: =SUM(L25:L27) -> 199096.1 | ... AC28: =SUM(AC25:AC27) -> 199096.1 | BI28: 35984.535
D29: Post Tax Salary | E29: =E24-E28 -> 338856.08 | F29: =F24-F28 -> 338856.08 | G29: =G24-G28 -> 338856.08 | H29: =H24-H28 -> 338856.08 | I29: =I24-I28 -> 338856.08 | J29: =J24-J28 -> 338856.08 | K29: =K24-K28 -> 338856.08 | L29: =L24-L28 -> 338856.08 | ... AC29: =AC24-AC28 -> 338856.08 | BI29: 36207.897
D30: Aldersopsparing | E30: ='Pensions P1'!$B$13 -> 3169.3646 | F30: ='Pensions P1'!$B$13 -> 3169.3646 | G30: ='Pensions P1'!$B$13 -> 3169.3646 | H30: ='Pensions P1'!$B$13 -> 3169.3646 | I30: ='Pensions P1'!$B$13 -> 3169.3646 | J30: ='Pensions P1'!$B$13 -> 3169.3646 | K30: ='Pensions P1'!$B$13 -> 3169.3646 | L30: ='Pensions P1'!$B$13 -> 3169.3646 | ... AC30: ='Pensions P1'!$B$13 -> 3169.3646 | BI30: 36433.045
D31: Net Salary (Monthly) | E31: =(E29/12)+E30 -> 31407.371 | F31: =(F29/12)+F30 -> 31407.371 | G31: =(G29/12)+G30 -> 31407.371 | H31: =(H29/12)+H30 -> 31407.371 | I31: =(I29/12)+I30 -> 31407.371 | J31: =(J29/12)+J30 -> 31407.371 | K31: =(K29/12)+K30 -> 31407.371 | L31: =(L29/12)+L30 -> 31407.371 | ... AC31: =(AC29/12)+AC30 -> 31407.371 | BI31: 36659.994
D32: Last Net Income from Work | E32: =Income!$K$52 -> 34291.629 | F32: =Income!$K$52 -> 34291.629 | G32: =Income!$K$52 -> 34291.629 | H32: =Income!$K$52 -> 34291.629 | I32: =Income!$K$52 -> 34291.629 | J32: =Income!$K$52 -> 34291.629 | K32: =Income!$K$52 -> 34291.629 | L32: =Income!$K$52 -> 34291.629 | ... AC32: =Income!$K$52 -> 34291.629 | BI32: 36888.759
D33: Diff | E33: =E32-E31 -> 2884.258 | F33: =F32-F31 -> 2884.258 | G33: =G32-G31 -> 2884.258 | H33: =H32-H31 -> 2884.258 | I33: =I32-I31 -> 2884.258 | J33: =J32-J31 -> 2884.258 | K33: =K32-K31 -> 2884.258 | L33: =L32-L31 -> 2884.258 | ... AC33: =AC32-AC31 -> 2884.258 | BI33: 37119.354
D34: Monthly Target | E34: =E33*(1+$B$10) -> 3663.0076 | F34: =F33*(1+$B$10) -> 3663.0076 | G34: =G33*(1+$B$10) -> 3663.0076 | H34: =H33*(1+$B$10) -> 3663.0076 | I34: =I33*(1+$B$10) -> 3663.0076 | J34: =J33*(1+$B$10) -> 3663.0076 | K34: =K33*(1+$B$10) -> 3663.0076 | L34: =L33*(1+$B$10) -> 3663.0076 | ... AC34: =AC33*(1+$B$10) -> 3663.0076 | BI34: 37351.793
D35: Yearly Target | E35: =E34*12 -> 43956.091 | F35: =F34*12 -> 43956.091 | G35: =G34*12 -> 43956.091 | H35: =H34*12 -> 43956.091 | I35: =I34*12 -> 43956.091 | J35: =J34*12 -> 43956.091 | K35: =K34*12 -> 43956.091 | L35: =L34*12 -> 43956.091 | ... AC35: =AC34*12 -> 43956.091 | BI35: 37586.093
BI36: 37822.266
D37: To be financed | E37: =SUM(E35:AC35) -> 1098902.3 | BI37: 39191.129
BI38: 39440.143
E39: =1500000 -> 1500000 | F39: =E39/25 -> 60000 | BI39: 39691.149
BI40: 39944.163
BI41: 40199.201
BI42: 40456.28
BI43: 40715.415
BI44: 40976.623
BI45: 41239.921
BI46: 41505.325
BI47: 41772.853
BI48: 42042.52
BI49: 42314.345
BI50: 42588.345
BI51: 42864.537
BI52: 0

Sheet Job Hopping
B2: Age | C2: Age Group | D2: FH/FW | E2: Switch | F2: SwitchP1Static | G2: SwitchP2Static | M2: Year | N2: Age Group | O2: Finance Workers | P2: Finance Hoppers | Q2: FH/FW | S2: Age Group | T2: FH/FV
B3: 25 | C3: =IF(B3<30, "25-29 år", IF(B3<35, "30-34 år", IF(B3<40, "35-39 år", IF(B3<45, "40-44 år", IF(B3<50, "45-49 år", IF(B3<55, "50-54 år", IF(B3<60, "55-59 år", IF(B3<65, "60-64 år", "65+ år")))))))) -> 25-29 år | D3: =_xlfn.XLOOKUP(C3,S:S,T:T) -> 0.51651948 | E3: =IF(OR(JobHopping[[#This Row],[Age]]=25,JobHopping[[#This Row],[Age]]>69),"N",IF(AND(E1="N",E2="N", RAND()<=D3), "Y", "N")) -> N | F3: N | G3: N | M3: 2013 | N3: 25-29 år | O3: =_xlfn.XLOOKUP(M3&"-"&N3,'Djøf Finance Workers'!D:D,'Djøf Finance Workers'!C:C,0,1) -> 6202 | P3: =_xlfn.XLOOKUP(M3&"-"&N3,'Djøf Finance Hoppers'!D:D,'Djøf Finance Hoppers'!C:C,0,1) -> 2524 | Q3: =IF(O3>0, P3/O3, 0) -> 0.4069655 | S3: 25-29 år | T3: =SUMIFS(Q:Q,N:N,S3)/(MAX($M$3:$M$101)-MIN($M$3:$M$101)) -> 0.51651948
B4: 26 | C4: =IF(B4<30, "25-29 år", IF(B4<35, "30-34 år", IF(B4<40, "35-39 år", IF(B4<45, "40-44 år", IF(B4<50, "45-49 år", IF(B4<55, "50-54 år", IF(B4<60, "55-59 år", IF(B4<65, "60-64 år", "65+ år")))))))) -> 25-29 år | D4: =_xlfn.XLOOKUP(C4,S:S,T:T) -> 0.51651948 | E4: =IF(OR(JobHopping[[#This Row],[Age]]=25,JobHopping[[#This Row],[Age]]>69),"N",IF(AND(E2="N",E3="N", RAND()<=D4), "Y", "N")) -> N | F4: N | G4: N | M4: 2013 | N4: 30-34 år | O4: =_xlfn.XLOOKUP(M4&"-"&N4,'Djøf Finance Workers'!D:D,'Djøf Finance Workers'!C:C,0,1) -> 8560 | P4: =_xlfn.XLOOKUP(M4&"-"&N4,'Djøf Finance Hoppers'!D:D,'Djøf Finance Hoppers'!C:C,0,1) -> 2176 | Q4: =IF(O4>0, P4/O4, 0) -> 0.25420561 | S4: 30-34 år | T4: =SUMIFS(Q:Q,N:N,S4)/(MAX($M$3:$M$101)-MIN($M$3:$M$101)) -> 0.3390802
B5: 27 | C5: =IF(B5<30, "25-29 år", IF(B5<35, "30-34 år", IF(B5<40, "35-39 år", IF(B5<45, "40-44 år", IF(B5<50, "45-49 år", IF(B5<55, "50-54 år", IF(B5<60, "55-59 år", IF(B5<65, "60-64 år", "65+ år")))))))) -> 25-29 år | D5: =_xlfn.XLOOKUP(C5,S:S,T:T) -> 0.51651948 | E5: =IF(OR(JobHopping[[#This Row],[Age]]=25,JobHopping[[#This Row],[Age]]>69),"N",IF(AND(E3="N",E4="N", RAND()<=D5), "Y", "N")) -> Y | F5: Y | G5: Y | M5: 2013 | N5: 35-39 år | O5: =_xlfn.XLOOKUP(M5&"-"&N5,'Djøf Finance Workers'!D:D,'Djøf Finance Workers'!C:C,0,1) -> 9790 | P5: =_xlfn.XLOOKUP(M5&"-"&N5,'Djøf Finance Hoppers'!D:D,'Djøf Finance Hoppers'!C:C,0,1) -> 1896 | Q5: =IF(O5>0, P5/O5, 0) -> 0.19366701 | S5: 35-39 år | T5: =SUMIFS(Q:Q,N:N,S5)/(MAX($M$3:$M$101)-MIN($M$3:$M$101)) -> 0.26240269
B6: 28 | C6: =IF(B6<30, "25-29 år", IF(B6<35, "30-34 år", IF(B6<40, "35-39 år", IF(B6<45, "40-44 år", IF(B6<50, "45-49 år", IF(B6<55, "50-54 år", IF(B6<60, "55-59 år", IF(B6<65, "60-64 år", "65+ år")))))))) -> 25-29 år | D6: =_xlfn.XLOOKUP(C6,S:S,T:T) -> 0.51651948 | E6: =IF(OR(JobHopping[[#This Row],[Age]]=25,JobHopping[[#This Row],[Age]]>69),"N",IF(AND(E4="N",E5="N", RAND()<=D6), "Y", "N")) -> N | F6: N | G6: N | M6: 2013 | N6: 40-44 år | O6: =_xlfn.XLOOKUP(M6&"-"&N6,'Djøf Finance Workers'!D:D,'Djøf Finance Workers'!C:C,0,1) -> 9383 | P6: =_xlfn.XLOOKUP(M6&"-"&N6,'Djøf Finance Hoppers'!D:D,'Djøf Finance Hoppers'!C:C,0,1) -> 1579 | Q6: =IF(O6>0, P6/O6, 0) -> 0.16828307 | S6: 40-44 år | T6: =SUMIFS(Q:Q,N:N,S6)/(MAX($M$3:$M$101)-MIN($M$3:$M$101)) -> 0.22131873
B7: 29 | C7: =IF(B7<30, "25-29 år", IF(B7<35, "30-34 år", IF(B7<40, "35-39 år", IF(B7<45, "40-44 år", IF(B7<50, "45-49 år", IF(B7<55, "50-54 år", IF(B7<60, "55-59 år", IF(B7<65, "60-64 år", "65+ år")))))))) -> 25-29 år | D7: =_xlfn.XLOOKUP(C7,S:S,T:T) -> 0.51651948 | E7: =IF(OR(JobHopping[[#This Row],[Age]]=25,JobHopping[[#This Row],[Age]]>69),"N",IF(AND(E5="N",E6="N", RAND()<=D7), "Y", "N")) -> N | F7: N | G7: N | M7: 2013 | N7: 45-49 år | O7: =_xlfn.XLOOKUP(M7&"-"&N7,'Djøf Finance Workers'!D:D,'Djøf Finance Workers'!C:C,0,1) -> 12762 | P7: =_xlfn.XLOOKUP(M7&"-"&N7,'Djøf Finance Hoppers'!D:D,'Djøf Finance Hoppers'!C:C,0,1) -> 1915 | Q7: =IF(O7>0, P7/O7, 0) -> 0.15005485 | S7: 45-49 år | T7: =SUMIFS(Q:Q,N:N,S7)/(MAX($M$3:$M$101)-MIN($M$3:$M$101)) -> 0.1992948
B8: 30 | C8: =IF(B8<30, "25-29 år", IF(B8<35, "30-34 år", IF(B8<40, "35-39 år", IF(B8<45, "40-44 år", IF(B8<50, "45-49 år", IF(B8<55, "50-54 år", IF(B8<60, "55-59 år", IF(B8<65, "60-64 år", "65+ år")))))))) -> 30-34 år | D8: =_xlfn.XLOOKUP(C8,S:S,T:T) -> 0.3390802 | E8: =IF(OR(JobHopping[[#This Row],[Age]]=25,JobHopping[[#This Row],[Age]]>69),"N",IF(AND(E6="N",E7="N", RAND()<=D8), "Y", "N")) -> Y | F8: N | G8: N | M8: 2013 | N8: 50-54 år | O8: =_xlfn.XLOOKUP(M8&"-"&N8,'Djøf Finance Workers'!D:D,'Djøf Finance Workers'!C:C,0,1) -> 10587 | P8: =_xlfn.XLOOKUP(M8&"-"&N8,'Djøf Finance Hoppers'!D:D,'Djøf Finance Hoppers'!C:C,0,1) -> 1462 | Q8: =IF(O8>0, P8/O8, 0) -> 0.13809389 | S8: 50-54 år | T8: =SUMIFS(Q:Q,N:N,S8)/(MAX($M$3:$M$101)-MIN($M$3:$M$101)) -> 0.17668929
B9: 31 | C9: =IF(B9<30, "25-29 år", IF(B9<35, "30-34 år", IF(B9<40, "35-39 år", IF(B9<45, "40-44 år", IF(B9<50, "45-49 år", IF(B9<55, "50-54 år", IF(B9<60, "55-59 år", IF(B9<65, "60-64 år", "65+ år")))))))) -> 30-34 år | D9: =_xlfn.XLOOKUP(C9,S:S,T:T) -> 0.3390802 | E9: =IF(OR(JobHopping[[#This Row],[Age]]=25,JobHopping[[#This Row],[Age]]>69),"N",IF(AND(E7="N",E8="N", RAND()<=D9), "Y", "N")) -> N | F9: Y | G9: Y | M9: 2013 | N9: 55-59 år | O9: =_xlfn.XLOOKUP(M9&"-"&N9,'Djøf Finance Workers'!D:D,'Djøf Finance Workers'!C:C,0,1) -> 8811 | P9: =_xlfn.XLOOKUP(M9&"-"&N9,'Djøf Finance Hoppers'!D:D,'Djøf Finance Hoppers'!C:C,0,1) -> 1227 | Q9: =IF(O9>0, P9/O9, 0) -> 0.13925775 | S9: 55-59 år | T9: =SUMIFS(Q:Q,N:N,S9)/(MAX($M$3:$M$101)-MIN($M$3:$M$101)) -> 0.15515675
B10: 32 | C10: =IF(B10<30, "25-29 år", IF(B10<35, "30-34 år", IF(B10<40, "35-39 år", IF(B10<45, "40-44 år", IF(B10<50, "45-49 år", IF(B10<55, "50-54 år", IF(B10<60, "55-59 år", IF(B10<65, "60-64 år", "65+ år")))))))) -> 30-34 år | D10: =_xlfn.XLOOKUP(C10,S:S,T:T) -> 0.3390802 | E10: =IF(OR(JobHopping[[#This Row],[Age]]=25,JobHopping[[#This Row],[Age]]>69),"N",IF(AND(E8="N",E9="N", RAND()<=D10), "Y", "N")) -> N | F10: N | G10: N | M10: 2013 | N10: 60-64 år | O10: =_xlfn.XLOOKUP(M10&"-"&N10,'Djøf Finance Workers'!D:D,'Djøf Finance Workers'!C:C,0,1) -> 5072 | P10: =_xlfn.XLOOKUP(M10&"-"&N10,'Djøf Finance Hoppers'!D:D,'Djøf Finance Hoppers'!C:C,0,1) -> 667 | Q10: =IF(O10>0, P10/O10, 0) -> 0.13150631 | S10: 60-64 år | T10: =SUMIFS(Q:Q,N:N,S10)/(MAX($M$3:$M$101)-MIN($M$3:$M$101)) -> 0.13997312
B11: 33 | C11: =IF(B11<30, "25-29 år", IF(B11<35, "30-34 år", IF(B11<40, "35-39 år", IF(B11<45, "40-44 år", IF(B11<50, "45-49 år", IF(B11<55, "50-54 år", IF(B11<60, "55-59 år", IF(B11<65, "60-64 år", "65+ år")))))))) -> 30-34 år | D11: =_xlfn.XLOOKUP(C11,S:S,T:T) -> 0.3390802 | E11: =IF(OR(JobHopping[[#This Row],[Age]]=25,JobHopping[[#This Row],[Age]]>69),"N",IF(AND(E9="N",E10="N", RAND()<=D11), "Y", "N")) -> N | F11: N | G11: N | M11: 2013 | N11: 65+ år | O11: =_xlfn.XLOOKUP(M11&"-"&N11,'Djøf Finance Workers'!D:D,'Djøf Finance Workers'!C:C,0,1) -> 1539 | P11: =_xlfn.XLOOKUP(M11&"-"&N11,'Djøf Finance Hoppers'!D:D,'Djøf Finance Hoppers'!C:C,0,1) -> 2521 | Q11: =IF(O11>0, P11/O11, 0) -> 1.6380767 | S11: 65+ år | T11: =SUMIFS(Q:Q,N:N,S11)/(MAX($M$3:$M$101)-MIN($M$3:$M$101)) -> 1.6692164
B12: 34 | C12: =IF(B12<30, "25-29 år", IF(B12<35, "30-34 år", IF(B12<40, "35-39 år", IF(B12<45, "40-44 år", IF(B12<50, "45-49 år", IF(B12<55, "50-54 år", IF(B12<60, "55-59 år", IF(B12<65, "60-64 år", "65+ år")))))))) -> 30-34 år | D12: =_xlfn.XLOOKUP(C12,S:S,T:T) -> 0.3390802 | E12: =IF(OR(JobHopping[[#This Row],[Age]]=25,JobHopping[[#This Row],[Age]]>69),"N",IF(AND(E10="N",E11="N", RAND()<=D12), "Y", "N")) -> N | F12: N | G12: N | M12: 2014 | N12: 25-29 år | O12: =_xlfn.XLOOKUP(M12&"-"&N12,'Djøf Finance Workers'!D:D,'Djøf Finance Workers'!C:C,0,1) -> 6041 | P12: =_xlfn.XLOOKUP(M12&"-"&N12,'Djøf Finance Hoppers'!D:D,'Djøf Finance Hoppers'!C:C,0,1) -> 2521 | Q12: =IF(O12>0, P12/O12, 0) -> 0.41731501
B13: 35 | C13: =IF(B13<30, "25-29 år", IF(B13<35, "30-34 år", IF(B13<40, "35-39 år", IF(B13<45, "40-44 år", IF(B13<50, "45-49 år", IF(B13<55, "50-54 år", IF(B13<60, "55-59 år", IF(B13<65, "60-64 år", "65+ år")))))))) -> 35-39 år | D13: =_xlfn.XLOOKUP(C13,S:S,T:T) -> 0.26240269 | E13: =IF(OR(JobHopping[[#This Row],[Age]]=25,JobHopping[[#This Row],[Age]]>69),"N",IF(AND(E11="N",E12="N", RAND()<=D13), "Y", "N")) -> N | F13: Y | G13: Y | M13: 2014 | N13: 30-34 år | O13: =_xlfn.XLOOKUP(M13&"-"&N13,'Djøf Finance Workers'!D:D,'Djøf Finance Workers'!C:C,0,1) -> 8203 | P13: =_xlfn.XLOOKUP(M13&"-"&N13,'Djøf Finance Hoppers'!D:D,'Djøf Finance Hoppers'!C:C,0,1) -> 2178 | Q13: =IF(O13>0, P13/O13, 0) -> 0.26551262
B14: 36 | C14: =IF(B14<30, "25-29 år", IF(B14<35, "30-34 år", IF(B14<40, "35-39 år", IF(B14<45, "40-44 år", IF(B14<50, "45-49 år", IF(B14<55, "50-54 år", IF(B14<60, "55-59 år", IF(B14<65, "60-64 år", "65+ år")))))))) -> 35-39 år | D14: =_xlfn.XLOOKUP(C14,S:S,T:T) -> 0.26240269 | E14: =IF(OR(JobHopping[[#This Row],[Age]]=25,JobHopping[[#This Row],[Age]]>69),"N",IF(AND(E12="N",E13="N", RAND()<=D14), "Y", "N")) -> N | F14: N | G14: N | M14: 2014 | N14: 35-39 år | O14: =_xlfn.XLOOKUP(M14&"-"&N14,'Djøf Finance Workers'!D:D,'Djøf Finance Workers'!C:C,0,1) -> 9972 | P14: =_xlfn.XLOOKUP(M14&"-"&N14,'Djøf Finance Hoppers'!D:D,'Djøf Finance Hoppers'!C:C,0,1) -> 2066 | Q14: =IF(O14>0, P14/O14, 0) -> 0.2071801
B15: 37 | C15: =IF(B15<30, "25-29 år", IF(B15<35, "30-34 år", IF(B15<40, "35-39 år", IF(B15<45, "40-44 år", IF(B15<50, "45-49 år", IF(B15<55, "50-54 år", IF(B15<60, "55-59 år", IF(B15<65, "60-64 år", "65+ år")))))))) -> 35-39 år | D15: =_xlfn.XLOOKUP(C15,S:S,T:T) -> 0.26240269 | E15: =IF(OR(JobHopping[[#This Row],[Age]]=25,JobHopping[[#This Row],[Age]]>69),"N",IF(AND(E13="N",E14="N", RAND()<=D15), "Y", "N")) -> N | F15: N | G15: N | M15: 2014 | N15: 40-44 år | O15: =_xlfn.XLOOKUP(M15&"-"&N15,'Djøf Finance Workers'!D:D,'Djøf Finance Workers'!C:C,0,1) -> 9409 | P15: =_xlfn.XLOOKUP(M15&"-"&N15,'Djøf Finance Hoppers'!D:D,'Djøf Finance Hoppers'!C:C,0,1) -> 1647 | Q15: =IF(O15>0, P15/O15, 0) -> 0.17504517
B16: 38 | C16: =IF(B16<30, "25-29 år", IF(B16<35, "30-34 år", IF(B16<40, "35-39 år", IF(B16<45, "40-44 år", IF(B16<50, "45-49 år", IF(B16<55, "50-54 år", IF(B16<60, "55-59 år", IF(B16<65, "60-64 år", "65+ år")))))))) -> 35-39 år | D16: =_xlfn.XLOOKUP(C16,S:S,T:T) -> 0.26240269 | E16: =IF(OR(JobHopping[[#This Row],[Age]]=25,JobHopping[[#This Row],[Age]]>69),"N",IF(AND(E14="N",E15="N", RAND()<=D16), "Y", "N")) -> N | F16: Y | G16: Y | M16: 2014 | N16: 45-49 år | O16: =_xlfn.XLOOKUP(M16&"-"&N16,'Djøf Finance Workers'!D:D,'Djøf Finance Workers'!C:C,0,1) -> 12377 | P16: =_xlfn.XLOOKUP(M16&"-"&N16,'Djøf Finance Hoppers'!D:D,'Djøf Finance Hoppers'!C:C,0,1) -> 1953 | Q16: =IF(O16>0, P16/O16, 0) -> 0.15779268
B17: 39 | C17: =IF(B17<30, "25-29 år", IF(B17<35, "30-34 år", IF(B17<40, "35-39 år", IF(B17<45, "40-44 år", IF(B17<50, "45-49 år", IF(B17<55, "50-54 år", IF(B17<60, "55-59 år", IF(B17<65, "60-64 år", "65+ år")))))))) -> 35-39 år | D17: =_xlfn.XLOOKUP(C17,S:S,T:T) -> 0.26240269 | E17: =IF(OR(JobHopping[[#This Row],[Age]]=25,JobHopping[[#This Row],[Age]]>69),"N",IF(AND(E15="N",E16="N", RAND()<=D17), "Y", "N")) -> N | F17: N | G17: N | M17: 2014 | N17: 50-54 år | O17: =_xlfn.XLOOKUP(M17&"-"&N17,'Djøf Finance Workers'!D:D,'Djøf Finance Workers'!C:C,0,1) -> 10828 | P17: =_xlfn.XLOOKUP(M17&"-"&N17,'Djøf Finance Hoppers'!D:D,'Djøf Finance Hoppers'!C:C,0,1) -> 1636 | Q17: =IF(O17>0, P17/O17, 0) -> 0.15108977
B18: 40 | C18: =IF(B18<30, "25-29 år", IF(B18<35, "30-34 år", IF(B18<40, "35-39 år", IF(B18<45, "40-44 år", IF(B18<50, "45-49 år", IF(B18<55, "50-54 år", IF(B18<60, "55-59 år", IF(B18<65, "60-64 år", "65+ år")))))))) -> 40-44 år | D18: =_xlfn.XLOOKUP(C18,S:S,T:T) -> 0.22131873 | E18: =IF(OR(JobHopping[[#This Row],[Age]]=25,JobHopping[[#This Row],[Age]]>69),"N",IF(AND(E16="N",E17="N", RAND()<=D18), "Y", "N")) -> N | F18: N | G18: N | M18: 2014 | N18: 55-59 år | O18: =_xlfn.XLOOKUP(M18&"-"&N18,'Djøf Finance Workers'!D:D,'Djøf Finance Workers'!C:C,0,1) -> 8888 | P18: =_xlfn.XLOOKUP(M18&"-"&N18,'Djøf Finance Hoppers'!D:D,'Djøf Finance Hoppers'!C:C,0,1) -> 1231 | Q18: =IF(O18>0, P18/O18, 0) -> 0.13850135
B19: 41 | C19: =IF(B19<30, "25-29 år", IF(B19<35, "30-34 år", IF(B19<40, "35-39 år", IF(B19<45, "40-44 år", IF(B19<50, "45-49 år", IF(B19<55, "50-54 år", IF(B19<60, "55-59 år", IF(B19<65, "60-64 år", "65+ år")))))))) -> 40-44 år | D19: =_xlfn.XLOOKUP(C19,S:S,T:T) -> 0.22131873 | E19: =IF(OR(JobHopping[[#This Row],[Age]]=25,JobHopping[[#This Row],[Age]]>69),"N",IF(AND(E17="N",E18="N", RAND()<=D19), "Y", "N")) -> N | F19: N | G19: N | M19: 2014 | N19: 60-64 år | O19: =_xlfn.XLOOKUP(M19&"-"&N19,'Djøf Finance Workers'!D:D,'Djøf Finance Workers'!C:C,0,1) -> 5141 | P19: =_xlfn.XLOOKUP(M19&"-"&N19,'Djøf Finance Hoppers'!D:D,'Djøf Finance Hoppers'!C:C,0,1) -> 706 | Q19: =IF(O19>0, P19/O19, 0) -> 0.13732737
B20: 42 | C20: =IF(B20<30, "25-29 år", IF(B20<35, "30-34 år", IF(B20<40, "35-39 år", IF(B20<45, "40-44 år", IF(B20<50, "45-49 år", IF(B20<55, "50-54 år", IF(B20<60, "55-59 år", IF(B20<65, "60-64 år", "65+ år")))))))) -> 40-44 år | D20: =_xlfn.XLOOKUP(C20,S:S,T:T) -> 0.22131873 | E20: =IF(OR(JobHopping[[#This Row],[Age]]=25,JobHopping[[#This Row],[Age]]>69),"N",IF(AND(E18="N",E19="N", RAND()<=D20), "Y", "N")) -> N | F20: N | G20: N | M20: 2014 | N20: 65+ år | O20: =_xlfn.XLOOKUP(M20&"-"&N20,'Djøf Finance Workers'!D:D,'Djøf Finance Workers'!C:C,0,1) -> 1600 | P20: =_xlfn.XLOOKUP(M20&"-"&N20,'Djøf Finance Hoppers'!D:D,'Djøf Finance Hoppers'!C:C,0,1) -> 2715 | Q20: =IF(O20>0, P20/O20, 0) -> 1.696875
B21: 43 | C21: =IF(B21<30, "25-29 år", IF(B21<35, "30-34 år", IF(B21<40, "35-39 år", IF(B21<45, "40-44 år", IF(B21<50, "45-49 år", IF(B21<55, "50-54 år", IF(B21<60, "55-59 år", IF(B21<65, "60-64 år", "65+ år")))))))) -> 40-44 år | D21: =_xlfn.XLOOKUP(C21,S:S,T:T) -> 0.22131873 | E21: =IF(OR(JobHopping[[#This Row],[Age]]=25,JobHopping[[#This Row],[Age]]>69),"N",IF(AND(E19="N",E20="N", RAND()<=D21), "Y", "N")) -> N | F21: Y | G21: Y | M21: 2015 | N21: 25-29 år | O21: =_xlfn.XLOOKUP(M21&"-"&N21,'Djøf Finance Workers'!D:D,'Djøf Finance Workers'!C:C,0,1) -> 5834 | P21: =_xlfn.XLOOKUP(M21&"-"&N21,'Djøf Finance Hoppers'!D:D,'Djøf Finance Hoppers'!C:C,0,1) -> 2715 | Q21: =IF(O21>0, P21/O21, 0) -> 0.46537539
B22: 44 | C22: =IF(B22<30, "25-29 år", IF(B22<35, "30-34 år", IF(B22<40, "35-39 år", IF(B22<45, "40-44 år", IF(B22<50, "45-49 år", IF(B22<55, "50-54 år", IF(B22<60, "55-59 år", IF(B22<65, "60-64 år", "65+ år")))))))) -> 40-44 år | D22: =_xlfn.XLOOKUP(C22,S:S,T:T) -> 0.22131873 | E22: =IF(OR(JobHopping[[#This Row],[Age]]=25,JobHopping[[#This Row],[Age]]>69),"N",IF(AND(E20="N",E21="N", RAND()<=D22), "Y", "N")) -> N | F22: N | G22: N | M22: 2015 | N22: 30-34 år | O22: =_xlfn.XLOOKUP(M22&"-"&N22,'Djøf Finance Workers'!D:D,'Djøf Finance Workers'!C:C,0,1) -> 7834 | P22: =_xlfn.XLOOKUP(M22&"-"&N22,'Djøf Finance Hoppers'!D:D,'Djøf Finance Hoppers'!C:C,0,1) -> 2473 | Q22: =IF(O22>0, P22/O22, 0) -> 0.31567526
B23: 45 | C23: =IF(B23<30, "25-29 år", IF(B23<35, "30-34 år", IF(B23<40, "35-39 år", IF(B23<45, "40-44 år", IF(B23<50, "45-49 år", IF(B23<55, "50-54 år", IF(B23<60, "55-59 år", IF(B23<65, "60-64 år", "65+ år")))))))) -> 45-49 år | D23: =_xlfn.XLOOKUP(C23,S:S,T:T) -> 0.1992948 | E23: =IF(OR(JobHopping[[#This Row],[Age]]=25,JobHopping[[#This Row],[Age]]>69),"N",IF(AND(E21="N",E22="N", RAND()<=D23), "Y", "N")) -> N | F23: N | G23: N | M23: 2015 | N23: 35-39 år | O23: =_xlfn.XLOOKUP(M23&"-"&N23,'Djøf Finance Workers'!D:D,'Djøf Finance Workers'!C:C,0,1) -> 9897 | P23: =_xlfn.XLOOKUP(M23&"-"&N23,'Djøf Finance Hoppers'!D:D,'Djøf Finance Hoppers'!C:C,0,1) -> 2378 | Q23: =IF(O23>0, P23/O23, 0) -> 0.24027483
... B78: 100 | C78: =IF(B78<30, "25-29 år", IF(B78<35, "30-34 år", IF(B78<40, "35-39 år", IF(B78<45, "40-44 år", IF(B78<50, "45-49 år", IF(B78<55, "50-54 år", IF(B78<60, "55-59 år", IF(B78<65, "60-64 år", "65+ år")))))))) -> 65+ år | D78: =_xlfn.XLOOKUP(C78,S:S,T:T) -> 1.6692164 | E78: =IF(OR(JobHopping[[#This Row],[Age]]=25,JobHopping[[#This Row],[Age]]>69),"N",IF(AND(E76="N",E77="N", RAND()<=D78), "Y", "N")) -> N | F78: N | G78: N | M78: 2021 | N78: 40-44 år | O78: =_xlfn.XLOOKUP(M78&"-"&N78,'Djøf Finance Workers'!D:D,'Djøf Finance Workers'!C:C,0,1) -> 10002 | P78: =_xlfn.XLOOKUP(M78&"-"&N78,'Djøf Finance Hoppers'!D:D,'Djøf Finance Hoppers'!C:C,0,1) -> 2220 | Q78: =IF(O78>0, P78/O78, 0) -> 0.22195561
M79: 2021 | N79: 45-49 år | O79: =_xlfn.XLOOKUP(M79&"-"&N79,'Djøf Finance Workers'!D:D,'Djøf Finance Workers'!C:C,0,1) -> 10036 | P79: =_xlfn.XLOOKUP(M79&"-"&N79,'Djøf Finance Hoppers'!D:D,'Djøf Finance Hoppers'!C:C,0,1) -> 1980 | Q79: =IF(O79>0, P79/O79, 0) -> 0.19728976
M80: 2021 | N80: 50-54 år | O80: =_xlfn.XLOOKUP(M80&"-"&N80,'Djøf Finance Workers'!D:D,'Djøf Finance Workers'!C:C,0,1) -> 10467 | P80: =_xlfn.XLOOKUP(M80&"-"&N80,'Djøf Finance Hoppers'!D:D,'Djøf Finance Hoppers'!C:C,0,1) -> 1810 | Q80: =IF(O80>0, P80/O80, 0) -> 0.17292443
M81: 2021 | N81: 55-59 år | O81: =_xlfn.XLOOKUP(M81&"-"&N81,'Djøf Finance Workers'!D:D,'Djøf Finance Workers'!C:C,0,1) -> 10749 | P81: =_xlfn.XLOOKUP(M81&"-"&N81,'Djøf Finance Hoppers'!D:D,'Djøf Finance Hoppers'!C:C,0,1) -> 1631 | Q81: =IF(O81>0, P81/O81, 0) -> 0.15173505
M82: 2021 | N82: 60-64 år | O82: =_xlfn.XLOOKUP(M82&"-"&N82,'Djøf Finance Workers'!D:D,'Djøf Finance Workers'!C:C,0,1) -> 6688 | P82: =_xlfn.XLOOKUP(M82&"-"&N82,'Djøf Finance Hoppers'!D:D,'Djøf Finance Hoppers'!C:C,0,1) -> 962 | Q82: =IF(O82>0, P82/O82, 0) -> 0.14383971
M83: 2021 | N83: 65+ år | O83: =_xlfn.XLOOKUP(M83&"-"&N83,'Djøf Finance Workers'!D:D,'Djøf Finance Workers'!C:C,0,1) -> 2522 | P83: =_xlfn.XLOOKUP(M83&"-"&N83,'Djøf Finance Hoppers'!D:D,'Djøf Finance Hoppers'!C:C,0,1) -> 3870 | Q83: =IF(O83>0, P83/O83, 0) -> 1.5344964
M84: 2022 | N84: 25-29 år | O84: =_xlfn.XLOOKUP(M84&"-"&N84,'Djøf Finance Workers'!D:D,'Djøf Finance Workers'!C:C,0,1) -> 8107 | P84: =_xlfn.XLOOKUP(M84&"-"&N84,'Djøf Finance Hoppers'!D:D,'Djøf Finance Hoppers'!C:C,0,1) -> 3870 | Q84: =IF(O84>0, P84/O84, 0) -> 0.47736524
M85: 2022 | N85: 30-34 år | O85: =_xlfn.XLOOKUP(M85&"-"&N85,'Djøf Finance Workers'!D:D,'Djøf Finance Workers'!C:C,0,1) -> 9307 | P85: =_xlfn.XLOOKUP(M85&"-"&N85,'Djøf Finance Hoppers'!D:D,'Djøf Finance Hoppers'!C:C,0,1) -> 3004 | Q85: =IF(O85>0, P85/O85, 0) -> 0.32276781
M86: 2022 | N86: 35-39 år | O86: =_xlfn.XLOOKUP(M86&"-"&N86,'Djøf Finance Workers'!D:D,'Djøf Finance Workers'!C:C,0,1) -> 9287 | P86: =_xlfn.XLOOKUP(M86&"-"&N86,'Djøf Finance Hoppers'!D:D,'Djøf Finance Hoppers'!C:C,0,1) -> 2511 | Q86: =IF(O86>0, P86/O86, 0) -> 0.27037795
M87: 2022 | N87: 40-44 år | O87: =_xlfn.XLOOKUP(M87&"-"&N87,'Djøf Finance Workers'!D:D,'Djøf Finance Workers'!C:C,0,1) -> 9808 | P87: =_xlfn.XLOOKUP(M87&"-"&N87,'Djøf Finance Hoppers'!D:D,'Djøf Finance Hoppers'!C:C,0,1) -> 2191 | Q87: =IF(O87>0, P87/O87, 0) -> 0.22338907
M88: 2022 | N88: 45-49 år | O88: =_xlfn.XLOOKUP(M88&"-"&N88,'Djøf Finance Workers'!D:D,'Djøf Finance Workers'!C:C,0,1) -> 10063 | P88: =_xlfn.XLOOKUP(M88&"-"&N88,'Djøf Finance Hoppers'!D:D,'Djøf Finance Hoppers'!C:C,0,1) -> 2044 | Q88: =IF(O88>0, P88/O88, 0) -> 0.20312034
M89: 2022 | N89: 50-54 år | O89: =_xlfn.XLOOKUP(M89&"-"&N89,'Djøf Finance Workers'!D:D,'Djøf Finance Workers'!C:C,0,1) -> 9799 | P89: =_xlfn.XLOOKUP(M89&"-"&N89,'Djøf Finance Hoppers'!D:D,'Djøf Finance Hoppers'!C:C,0,1) -> 1683 | Q89: =IF(O89>0, P89/O89, 0) -> 0.17175222
M90: 2022 | N90: 55-59 år | O90: =_xlfn.XLOOKUP(M90&"-"&N90,'Djøf Finance Workers'!D:D,'Djøf Finance Workers'!C:C,0,1) -> 11340 | P90: =_xlfn.XLOOKUP(M90&"-"&N90,'Djøf Finance Hoppers'!D:D,'Djøf Finance Hoppers'!C:C,0,1) -> 1578 | Q90: =IF(O90>0, P90/O90, 0) -> 0.13915344
... M101: 2023 | N101: 65+ år | O101: =_xlfn.XLOOKUP(M101&"-"&N101,'Djøf Finance Workers'!D:D,'Djøf Finance Workers'!C:C,0,1) -> 3139 | P101: =_xlfn.XLOOKUP(M101&"-"&N101,'Djøf Finance Hoppers'!D:D,'Djøf Finance Hoppers'!C:C,0,1) -> 0 | Q101: =IF(O101>0, P101/O101, 0) -> 0

Sheet Djøf Finance Hoppers
A1: Status på arbejdsmarkedet/ Beskæftigelse og jobskifte/ Antal personer der har skiftet eller startet i nyt job (jobomsætning)
C2: Hele landet
C3: Privat sektor
C4: Herkomst i alt
C5: Køn i alt
C6: Finansiering og forsikring
C7: Jobomsætning
A8: 2009 | B8: 25-29 år | C8: 3410 | D8: =A8&"-"&B8 -> 2009-25-29 år
A9: 2009 | B9: 30-34 år | C9: 3525 | D9: =A9&"-"&B9 -> 2009-30-34 år
A10: 2009 | B10: 35-39 år | C10: 3090 | D10: =A10&"-"&B10 -> 2009-35-39 år
A11: 2009 | B11: 40-44 år | C11: 4180 | D11: =A11&"-"&B11 -> 2009-40-44 år
A12: 2009 | B12: 45-49 år | C12: 3533 | D12: =A12&"-"&B12 -> 2009-45-49 år
A13: 2009 | B13: 50-54 år | C13: 2940 | D13: =A13&"-"&B13 -> 2009-50-54 år
A14: 2009 | B14: 55-59 år | C14: 2419 | D14: =A14&"-"&B14 -> 2009-55-59 år
A15: 2009 | B15: 60-64 år | C15: 1263 | D15: =A15&"-"&B15 -> 2009-60-64 år
A16: 2009 | B16: 65-69 år | C16: 196 | D16: =A16&"-"&B16 -> 2009-65-69 år
A17: 2010 | B17: 25-29 år | C17: 2457 | D17: =A17&"-"&B17 -> 2010-25-29 år
A18: 2010 | B18: 30-34 år | C18: 2382 | D18: =A18&"-"&B18 -> 2010-30-34 år
A19: 2010 | B19: 35-39 år | C19: 1880 | D19: =A19&"-"&B19 -> 2010-35-39 år
... A142: 2023 | B142: 65-69 år | C142: 295 | D142: =A142&"-"&B142 -> 2023-65-69 år
A145: Kilde: CPR-registeret, CVR-registeret og DetailCOR
A146: Anm.: Pga. efterregistreringer kan tallene for især den seneste periode stige ved næste opdatering.

Sheet Djøf Finance Workers
A1: Status på arbejdsmarkedet/ Beskæftigelse og jobskifte/ Antal lønmodtagere efter bopæl
C2: Hele landet
C3: Herkomst i alt
C4: Køn i alt
C5: Finansiering og forsikring
C6: Antal fuldtidsbeskæftigede lønmodtagere efter bopæl
A7: 2008 | B7: 25-29 år | C7: 6876 | D7: =A7&"-"&B7 -> 2008-25-29 år
A8: 2008 | B8: 30-34 år | C8: 8541 | D8: =A8&"-"&B8 -> 2008-30-34 år
A9: 2008 | B9: 35-39 år | C9: 8222 | D9: =A9&"-"&B9 -> 2008-35-39 år
A10: 2008 | B10: 40-44 år | C10: 11172 | D10: =A10&"-"&B10 -> 2008-40-44 år
A11: 2008 | B11: 45-49 år | C11: 9399 | D11: =A11&"-"&B11 -> 2008-45-49 år
A12: 2008 | B12: 50-54 år | C12: 8459 | D12: =A12&"-"&B12 -> 2008-50-54 år
A13: 2008 | B13: 55-59 år | C13: 7916 | D13: =A13&"-"&B13 -> 2008-55-59 år
A14: 2008 | B14: 60-64 år | C14: 4371 | D14: =A14&"-"&B14 -> 2008-60-64 år
A15: 2008 | B15: 65+ år | C15: 857 | D15: =A15&"-"&B15 -> 2008-65+ år
A16: 2009 | B16: 25-29 år | C16: 7284 | D16: =A16&"-"&B16 -> 2009-25-29 år
A17: 2009 | B17: 30-34 år | C17: 9750 | D17: =A17&"-"&B17 -> 2009-30-34 år
A18: 2009 | B18: 35-39 år | C18: 9328 | D18: =A18&"-"&B18 -> 2009-35-39 år
... A159: 2024 | B159: 65+ år | C159: 3573 | D159: =A159&"-"&B159 -> 2024-65+ år
A162: Kilde: CPR-registeret, CVR-registeret og DetailCOR
A163: Anm.: Pga. efterregistreringer kan tallene for især den seneste periode stige ved næste opdatering.

Sheet Goals
B2: Goal Info | C2: GOAL A | D2: GOAL B | E2: GOAL C | F2: GOAL D | G2: P1
B3: Value Ratio | C3: 1 | D3: 0.75 | E3: 0.5 | F3: 0.25
B4: Funding Requirement | C4: ='Net Salary P1'!E37 -> 1098902.3 | D4: =3500000*0.2 -> 700000 | E4: 72530 | F4: =2500000*0.3 -> 750000
B5: Time Horizon | C5: 50 | D5: 10 | E5: 20 | F5: 30
B7: Goal Info | C7: GOAL A | D7: GOAL B | E7: GOAL C | F7: GOAL D | G7: P2
B8: Value Ratio | C8: 1 | D8: 0.75 | E8: 0.5 | F8: 0.25
B9: Funding Requirement | C9: 4212659.3 | D9: =3500000*0.2 -> 700000 | E9: 75176 | F9: =2500000*0.3 -> 750000
B10: Time Horizon | C10: 35 | D10: 10 | E10: 5 | F10: 15

Sheet Loop
B2: N | C2: Year | D2: AgeP1 | E2: AgeP2 | F2: LoopStatus
B3: 1 | C3: 2025 | D3: 25 | E3: 40 | F3: N
B4: 2 | C4: 2026 | D4: =D3+1 -> 26 | E4: =E3+1 -> 41 | F4: N
B5: 3 | C5: 2027 | D5: =D4+1 -> 27 | E5: =E4+1 -> 42 | F5: N
B6: 4 | C6: 2028 | D6: =D5+1 -> 28 | E6: =E5+1 -> 43 | F6: N
B7: 5 | C7: 2029 | D7: =D6+1 -> 29 | E7: =E6+1 -> 44 | F7: N
B8: 6 | C8: 2030 | D8: =D7+1 -> 30 | E8: =E7+1 -> 45 | F8: N
B9: 7 | C9: 2031 | D9: =D8+1 -> 31 | E9: =E8+1 -> 46 | F9: N
B10: 8 | C10: 2032 | D10: =D9+1 -> 32 | E10: =E9+1 -> 47 | F10: N
B11: 9 | C11: 2033 | D11: =D10+1 -> 33 | E11: =E10+1 -> 48 | F11: N
B12: 10 | C12: 2034 | D12: =D11+1 -> 34 | E12: =E11+1 -> 49 | F12: N
B13: 11 | C13: 2035 | D13: =D12+1 -> 35 | E13: =E12+1 -> 50 | F13: N
B14: 12 | C14: 2036 | D14: =D13+1 -> 36 | E14: =E13+1 -> 51 | F14: N
B15: 13 | C15: 2037 | D15: =D14+1 -> 37 | E15: =E14+1 -> 52 | F15: N
... B53: 51 | C53: 2075 | D53: =D52+1 -> 75 | E53: =E52+1 -> 90 | F53: N

Sheet Aktiesparekonto Increase
A1: https://skat.dk/borger/aktier-og-andre-vaerdipapirer/aktiesparekonto?
A2: Year | B2: Max cap | C2: Change (%)
A3: 2019 | B3: 50000
A4: 2020 | B4: =100000 -> 100000 | C4: =(B4-B3)/B3 -> 1
A5: 2021 | B5: 102300 | C5: =(B5-B4)/B4 -> 0.023
A6: 2022 | B6: 103500 | C6: =(B6-B5)/B5 -> 0.011730205 | E6: median: | F6: without 2020:
A7: 2023 | B7: 106600 | C7: =(B7-B6)/B6 -> 0.029951691 | E7: =MEDIAN(C4:C9) -> 0.12645487 | F7: =MEDIAN(C5:C9) -> 0.029951691
A8: 2024 | B8: 135900 | C8: =(B8-B7)/B7 -> 0.27485929
A9: 2025 | B9: 166200 | C9: =(B9-B8)/B8 -> 0.22295806

Sheet Salary
B1: 2025 | C1: 2026 | D1: 2027 | E1: 2028 | F1: 2029 | G1: 2030 | H1: 2031 | I1: 2032 | J1: 2033 | K1: 2034 | L1: 2035 | M1: 2036 | N1: 2037 | O1: 2038 | P1: 2039 | Q1: 2040 | R1: 2041 | S1: 2042 | T1: 2043 | U1: 2044 | V1: 2045 | W1: 2046 | X1: 2047 | Y1: 2048 | Z1: 2049 | AA1: 2050 | AB1: 2051 | AC1: 2052 | AD1: 2053 | AE1: 2054 | AF1: 2055 | AG1: 2056 | AH1: 2057 | AI1: 2058 | AJ1: 2059 | AK1: 2060 | AL1: 2061 | AM1: 2062 | AN1: 2063 | AO1: 2064 | AP1: 2065 | AQ1: 2066 | AR1: 2067 | AS1: 2068 | AT1: 2069 | AU1: 2070 | AV1: 2071 | AW1: 2072 | AX1: 2073 | AY1: 2074 | AZ1: 2075
A2: P1 | B2: 0 | C2: {=TRANSPOSE(TableIncome[InvestmentP1])} -> 56481.441 | D2: 56939.518 | E2: 59594.536 | F2: 60077.518 | G2: 60564.365 | H2: 61055.106 | I2: 63899.44 | J2: 64416.862 | K2: 64938.423 | L2: 65464.156 | M2: 68511.308 | N2: 69065.624 | O2: 69624.375 | P2: 72862.896 | Q2: 73452.026 | R2: 74045.868 | S2: 74644.461 | T2: 75247.843 | U2: 78745.043 | V2: 79381.23 | W2: 80022.506 | X2: 80668.912 | Y2: 84260.826 | Z2: 84780.077 | AA2: 85303.481 | AB2: 85831.073 | AC2: 86362.885 | AD2: 86898.952 | AE2: 87439.307 | AF2: 87983.985 | AG2: 88533.021 | AH2: 89086.449 | AI2: 89644.304 | AJ2: 90206.623 | AK2: 90773.439 | AL2: 94058.709 | AM2: 94656.343 | AN2: 95258.757 | AO2: 95865.991 | AP2: 96478.083 | AQ2: 97095.071 | AR2: 97716.995 | AS2: 98343.895 | AT2: 98975.81 | AU2: 99612.78 | AV2: 100254.85 | AW2: 100902.05 | AX2: 101554.43 | AY2: 102212.03 | AZ2: 102874.89 | BA2: 0
A3: P2 | B3: 200000 | C3: {=TRANSPOSE(TableIncome[InvestmentP2])} -> 92569.25 | D3: 93154.967 | E3: 96549.787 | F3: 97167.35 | G3: 97789.852 | H3: 98417.335 | I3: 102054.22 | J3: 102715.82 | K3: 103382.71 | L3: 104054.94 | M3: 107951.16 | N3: 108659.93 | O3: 109374.37 | P3: 113515.28 | Q3: 114268.57 | R3: 115027.88 | S3: 115793.27 | T3: 116564.78 | U3: 121036.45 | V3: 121849.91 | W3: 122669.87 | X3: 123496.39 | Y3: 128286.92 | Z3: 129158.38 | AA3: 130036.81 | AB3: 130922.27 | AC3: 131814.81 | AD3: 132714.49 | AE3: 133621.37 | AF3: 134535.5 | AG3: 135456.95 | AH3: 136385.77 | AI3: 137322.02 | AJ3: 138265.76 | AK3: 139217.05 | AL3: 0 | AM3: 0 | AN3: 0 | AO3: 0 | AP3: 0 | AQ3: 0 | AR3: 0 | AS3: 0 | AT3: 0 | AU3: 0 | AV3: 0 | AW3: 0 | AX3: 0 | AY3: 0 | AZ3: 0 | BA3: 0

Sheet Wealth
B1: 2025 | C1: 2026 | D1: 2027 | E1: 2028 | F1: 2029 | G1: 2030 | H1: 2031 | I1: 2032 | J1: 2033 | K1: 2034 | L1: 2035 | M1: 2036 | N1: 2037 | O1: 2038 | P1: 2039 | Q1: 2040 | R1: 2041 | S1: 2042 | T1: 2043 | U1: 2044 | V1: 2045 | W1: 2046 | X1: 2047 | Y1: 2048 | Z1: 2049 | AA1: 2050 | AB1: 2051 | AC1: 2052 | AD1: 2053 | AE1: 2054 | AF1: 2055 | AG1: 2056 | AH1: 2057 | AI1: 2058 | AJ1: 2059 | AK1: 2060 | AL1: 2061 | AM1: 2062 | AN1: 2063 | AO1: 2064 | AP1: 2065 | AQ1: 2066 | AR1: 2067 | AS1: 2068 | AT1: 2069 | AU1: 2070 | AV1: 2071 | AW1: 2072 | AX1: 2073 | AY1: 2074 | AZ1: 2075
A2: P1 | B2: =SUMIF(TableIncome[Year], "<=" & B1, TableIncome[InvestmentP1]) -> 56481.441 | C2: =SUMIF(TableIncome[Year], "<=" & C1, TableIncome[InvestmentP1]) -> 113420.96 | D2: =SUMIF(TableIncome[Year], "<=" & D1, TableIncome[InvestmentP1]) -> 173015.5 | E2: =SUMIF(TableIncome[Year], "<=" & E1, TableIncome[InvestmentP1]) -> 233093.01 | F2: =SUMIF(TableIncome[Year], "<=" & F1, TableIncome[InvestmentP1]) -> 293657.38 | G2: =SUMIF(TableIncome[Year], "<=" & G1, TableIncome[InvestmentP1]) -> 354712.48 | H2: =SUMIF(TableIncome[Year], "<=" & H1, TableIncome[InvestmentP1]) -> 418611.92 | I2: =SUMIF(TableIncome[Year], "<=" & I1, TableIncome[InvestmentP1]) -> 483028.79 | ... AZ2: =SUMIF(TableIncome[Year], "<=" & AZ1, TableIncome[InvestmentP1]) -> 4122668.6
A3: P2 | B3: =SUMIF(TableIncome[Year], "<=" & B1, TableIncome[InvestmentP2]) -> 92569.25 | C3: =SUMIF(TableIncome[Year], "<=" & C1, TableIncome[InvestmentP2]) -> 185724.22 | D3: =SUMIF(TableIncome[Year], "<=" & D1, TableIncome[InvestmentP2]) -> 282274 | E3: =SUMIF(TableIncome[Year], "<=" & E1, TableIncome[InvestmentP2]) -> 379441.35 | F3: =SUMIF(TableIncome[Year], "<=" & F1, TableIncome[InvestmentP2]) -> 477231.21 | G3: =SUMIF(TableIncome[Year], "<=" & G1, TableIncome[InvestmentP2]) -> 575648.54 | H3: =SUMIF(TableIncome[Year], "<=" & H1, TableIncome[InvestmentP2]) -> 677702.76 | I3: =SUMIF(TableIncome[Year], "<=" & I1, TableIncome[InvestmentP2]) -> 780418.59 | ... AZ3: =SUMIF(TableIncome[Year], "<=" & AZ1, TableIncome[InvestmentP2]) -> 4115802.2

Sheet notes next time talk
B3: Excel side:
B4: Goal calculation
B5: Investment income calculation
B6: For retirement goal: Calculate what the amount needed is and also research from denmark statistik what is the median returns by retirement age.
B7: Returns input with samsseewfwfuweerhugf for long term, and simulation for short term
B9: Python side:
B13: Question for Johan:
B14: Vasicek ready, what do we use bond simulation for? How does it correlate to bond ETF
B18: From last meeting Johan mentioned you can put the tax money back into the account???? What does this mean I am not sure: Saxo bank shows this below which might explain
B37: Update: I KNOW WHAT HE MEANT AHAHAHA IM A GENIOUS!!!! So basically it means that (from what I understand) the 17% tax deducts from your available input amount, allowing to deposit more into the account.
C41: Here
D42: Return | E42: Vol
C43: ZC Bond | D43: 0.03 | E43: 0.01 | H43: 2025 | I43: 2026 | J43: 2027 | M43: Use value simulated for each year or the average | N43: Split each goal into a per year goal, so achieve a % of the total goal in that year, and then the model would actually work as is
C44: SP | D44: 0.1 | E44: 0.03 | H44: 0.03 | I44: 0.04 | J44: 0.06 | K44: 0.07 | L44: 0.1
H46: =AVERAGE(H44:L44) -> 0.06 | I46: =AVERAGE(I44:L44) -> 0.0675
J51: Goal: House | L51: in 10 years
J53: 2025 | K53: 2026 | L53: 2027 | M53: 2028 | N53: 2029 | O53: 2030 | P53: 2031 | Q53: 2032 | R53: 2033 | S53: 2034 | U53: Total
J54: =$U$54*10% -> 200000 | K54: =$U$54*10% -> 200000 | L54: =$U$54*10% -> 200000 | M54: =$U$54*10% -> 200000 | N54: =$U$54*10% -> 200000 | O54: =$U$54*10% -> 200000 | P54: =$U$54*10% -> 200000 | Q54: =$U$54*10% -> 200000 | ... S54: =$U$54*10% -> 200000 | U54: 2000000
B57: Task for the master file

Sheet Real Returns
B1: 2025 | C1: 2026 | D1: 2027 | E1: 2028 | F1: 2029 | G1: 2030 | H1: 2031 | I1: 2032 | J1: 2033 | K1: 2034 | L1: 2035 | M1: 2036 | N1: 2037 | O1: 2038 | P1: 2039 | Q1: 2040 | R1: 2041 | S1: 2042 | T1: 2043 | U1: 2044 | V1: 2045 | W1: 2046 | X1: 2047 | Y1: 2048 | Z1: 2049 | AA1: 2050 | AB1: 2051 | AC1: 2052 | AD1: 2053 | AE1: 2054 | AF1: 2055 | AG1: 2056 | AH1: 2057 | AI1: 2058 | AJ1: 2059 | AK1: 2060 | AL1: 2061 | AM1: 2062 | AN1: 2063 | AO1: 2064 | AP1: 2065 | AQ1: 2066 | AR1: 2067 | AS1: 2068 | AT1: 2069 | AU1: 2070 | AV1: 2071 | AW1: 2072 | AX1: 2073 | AY1: 2074 | AZ1: 2075
A2: Emerging Markets - Equities | B2: 0.001 | C2: =B2 -> 0.001 | D2: =C2 -> 0.001 | E2: =D2 -> 0.001 | F2: =E2 -> 0.001 | G2: =F2 -> 0.001 | H2: =G2 -> 0.001 | I2: =H2 -> 0.001 | J2: =I2 -> 0.001 | K2: =J2 -> 0.001 | L2: 0.04 | M2: =L2 -> 0.04 | N2: =M2 -> 0.04 | O2: =N2 -> 0.04 | P2: =O2 -> 0.04 | Q2: =P2 -> 0.04 | R2: =Q2 -> 0.04 | S2: =R2 -> 0.04 | T2: =S2 -> 0.04 | ... AZ2: =AY2 -> 0.04
A3: Developed Markets - Equities | B3: 0.001 | C3: =B3 -> 0.001 | D3: =C3 -> 0.001 | E3: =D3 -> 0.001 | F3: =E3 -> 0.001 | G3: =F3 -> 0.001 | H3: =G3 -> 0.001 | I3: =H3 -> 0.001 | J3: =I3 -> 0.001 | K3: =J3 -> 0.001 | L3: 0.04 | M3: =L3 -> 0.04 | N3: =M3 -> 0.04 | O3: =N3 -> 0.04 | P3: =O3 -> 0.04 | Q3: =P3 -> 0.04 | R3: =Q3 -> 0.04 | S3: =R3 -> 0.04 | T3: =S3 -> 0.04 | ... AZ3: =AY3 -> 0.04
A4: Emerging Markets State - Obligations | B4: 0.001 | C4: =B4 -> 0.001 | D4: =C4 -> 0.001 | E4: =D4 -> 0.001 | F4: =E4 -> 0.001 | G4: =F4 -> 0.001 | H4: =G4 -> 0.001 | I4: =H4 -> 0.001 | J4: =I4 -> 0.001 | K4: =J4 -> 0.001 | L4: 0.04 | M4: =L4 -> 0.04 | N4: =M4 -> 0.04 | O4: =N4 -> 0.04 | P4: =O4 -> 0.04 | Q4: =P4 -> 0.04 | R4: =Q4 -> 0.04 | S4: =R4 -> 0.04 | T4: =S4 -> 0.04 | ... AZ4: =AY4 -> 0.04
A5: High Yield Bonds - Obligations | B5: 0.001 | C5: =B5 -> 0.001 | D5: =C5 -> 0.001 | E5: =D5 -> 0.001 | F5: =E5 -> 0.001 | G5: =F5 -> 0.001 | H5: =G5 -> 0.001 | I5: =H5 -> 0.001 | J5: =I5 -> 0.001 | K5: =J5 -> 0.001 | L5: 0.04 | M5: =L5 -> 0.04 | N5: =M5 -> 0.04 | O5: =N5 -> 0.04 | P5: =O5 -> 0.04 | Q5: =P5 -> 0.04 | R5: =Q5 -> 0.04 | S5: =R5 -> 0.04 | T5: =S5 -> 0.04 | ... AZ5: =AY5 -> 0.04
A6: Investment Grade Bonds - Obligations | B6: 0.001 | C6: =B6 -> 0.001 | D6: =C6 -> 0.001 | E6: =D6 -> 0.001 | F6: =E6 -> 0.001 | G6: =F6 -> 0.001 | H6: =G6 -> 0.001 | I6: =H6 -> 0.001 | J6: =I6 -> 0.001 | K6: =J6 -> 0.001 | L6: 0.04 | M6: =L6 -> 0.04 | N6: =M6 -> 0.04 | O6: =N6 -> 0.04 | P6: =O6 -> 0.04 | Q6: =P6 -> 0.04 | R6: =Q6 -> 0.04 | S6: =R6 -> 0.04 | T6: =S6 -> 0.04 | ... AZ6: =AY6 -> 0.04
A7: Government ZC Bonds - Obligations | B7: 0.001 | C7: =B7 -> 0.001 | D7: =C7 -> 0.001 | E7: =D7 -> 0.001 | F7: =E7 -> 0.001 | G7: =F7 -> 0.001 | H7: =G7 -> 0.001 | I7: =H7 -> 0.001 | J7: =I7 -> 0.001 | K7: =J7 -> 0.001 | L7: 0.04 | M7: =L7 -> 0.04 | N7: =M7 -> 0.04 | O7: =N7 -> 0.04 | P7: =O7 -> 0.04 | Q7: =P7 -> 0.04 | R7: =Q7 -> 0.04 | S7: =R7 -> 0.04 | T7: =S7 -> 0.04 | ... AZ7: =AY7 -> 0.04

Sheet Returns
B1: 2025 | C1: 2026 | D1: 2027 | E1: 2028 | F1: 2029 | G1: 2030 | H1: 2031 | I1: 2032 | J1: 2033 | K1: 2034 | L1: 2035 | M1: 2036 | N1: 2037 | O1: 2038 | P1: 2039 | Q1: 2040 | R1: 2041 | S1: 2042 | T1: 2043 | U1: 2044 | V1: 2045 | W1: 2046 | X1: 2047 | Y1: 2048 | Z1: 2049 | AA1: 2050 | AB1: 2051 | AC1: 2052 | AD1: 2053 | AE1: 2054 | AF1: 2055 | AG1: 2056 | AH1: 2057 | AI1: 2058 | AJ1: 2059 | AK1: 2060 | AL1: 2061 | AM1: 2062 | AN1: 2063 | AO1: 2064 | AP1: 2065 | AQ1: 2066 | AR1: 2067 | AS1: 2068 | AT1: 2069 | AU1: 2070 | AV1: 2071 | AW1: 2072 | AX1: 2073 | AY1: 2074 | AZ1: 2075
A2: Emerging Markets - Equities | B2: =8.6%-_xlfn.XLOOKUP(A2,BasisPointCost!$A:$A,BasisPointCost!$B:$B) -> 0.084 | C2: =B2 -> 0.084 | D2: =C2 -> 0.084 | E2: =D2 -> 0.084 | F2: =E2 -> 0.084 | G2: =F2 -> 0.084 | H2: =G2 -> 0.084 | I2: =H2 -> 0.084 | J2: =I2 -> 0.084 | K2: =J2 -> 0.084 | L2: =6.5%-0.2% -> 0.063 | M2: =L2 -> 0.063 | N2: =M2 -> 0.063 | O2: =N2 -> 0.063 | P2: =O2 -> 0.063 | Q2: =P2 -> 0.063 | R2: =Q2 -> 0.063 | S2: =R2 -> 0.063 | T2: =S2 -> 0.063 | ... AZ2: =AY2 -> 0.063
A3: Developed Markets - Equities | B3: =7%-_xlfn.XLOOKUP(A3,BasisPointCost!$A:$A,BasisPointCost!$B:$B) -> 0.068 | C3: =B3 -> 0.068 | D3: =C3 -> 0.068 | E3: =D3 -> 0.068 | F3: =E3 -> 0.068 | G3: =F3 -> 0.068 | H3: =G3 -> 0.068 | I3: =H3 -> 0.068 | J3: =I3 -> 0.068 | K3: =J3 -> 0.068 | L3: =6.5%-0.2% -> 0.063 | M3: =L3 -> 0.063 | N3: =M3 -> 0.063 | O3: =N3 -> 0.063 | P3: =O3 -> 0.063 | Q3: =P3 -> 0.063 | R3: =Q3 -> 0.063 | S3: =R3 -> 0.063 | T3: =S3 -> 0.063 | ... AZ3: =AY3 -> 0.063
A4: Emerging Markets State - Obligations | B4: =4.9%-_xlfn.XLOOKUP(A4,BasisPointCost!$A:$A,BasisPointCost!$B:$B) -> 0.0483 | C4: =B4 -> 0.0483 | D4: =C4 -> 0.0483 | E4: =D4 -> 0.0483 | F4: =E4 -> 0.0483 | G4: =F4 -> 0.0483 | H4: =G4 -> 0.0483 | I4: =H4 -> 0.0483 | J4: =I4 -> 0.0483 | K4: =J4 -> 0.0483 | L4: =3.5%-0.07% -> 0.0343 | M4: =L4 -> 0.0343 | N4: =M4 -> 0.0343 | O4: =N4 -> 0.0343 | P4: =O4 -> 0.0343 | Q4: =P4 -> 0.0343 | R4: =Q4 -> 0.0343 | S4: =R4 -> 0.0343 | T4: =S4 -> 0.0343 | ... AZ4: =AY4 -> 0.0343
A5: High Yield Bonds - Obligations | B5: =5%-_xlfn.XLOOKUP(A5,BasisPointCost!$A:$A,BasisPointCost!$B:$B) -> 0.0493 | C5: =B5 -> 0.0493 | D5: =C5 -> 0.0493 | E5: =D5 -> 0.0493 | F5: =E5 -> 0.0493 | G5: =F5 -> 0.0493 | H5: =G5 -> 0.0493 | I5: =H5 -> 0.0493 | J5: =I5 -> 0.0493 | K5: =J5 -> 0.0493 | L5: =3.5%-0.07% -> 0.0343 | M5: =L5 -> 0.0343 | N5: =M5 -> 0.0343 | O5: =N5 -> 0.0343 | P5: =O5 -> 0.0343 | Q5: =P5 -> 0.0343 | R5: =Q5 -> 0.0343 | S5: =R5 -> 0.0343 | T5: =S5 -> 0.0343 | ... AZ5: =AY5 -> 0.0343
A6: Investment Grade Bonds - Obligations | B6: =3.7%-_xlfn.XLOOKUP(A6,BasisPointCost!$A:$A,BasisPointCost!$B:$B) -> 0.0363 | C6: =B6 -> 0.0363 | D6: =C6 -> 0.0363 | E6: =D6 -> 0.0363 | F6: =E6 -> 0.0363 | G6: =F6 -> 0.0363 | H6: =G6 -> 0.0363 | I6: =H6 -> 0.0363 | J6: =I6 -> 0.0363 | K6: =J6 -> 0.0363 | L6: =3.5%-0.07% -> 0.0343 | M6: =L6 -> 0.0343 | N6: =M6 -> 0.0343 | O6: =N6 -> 0.0343 | P6: =O6 -> 0.0343 | Q6: =P6 -> 0.0343 | R6: =Q6 -> 0.0343 | S6: =R6 -> 0.0343 | T6: =S6 -> 0.0343 | ... AZ6: =AY6 -> 0.0343
A7: Government ZC Bonds - Obligations | B7: =2.9%-_xlfn.XLOOKUP($A7,BasisPointCost!$A:$A,BasisPointCost!$B:$B) -> 0.0283 | C7: =B7 -> 0.0283 | D7: =C7 -> 0.0283 | E7: =D7 -> 0.0283 | F7: =E7 -> 0.0283 | G7: =F7 -> 0.0283 | H7: =G7 -> 0.0283 | I7: =H7 -> 0.0283 | J7: =I7 -> 0.0283 | K7: =J7 -> 0.0283 | L7: =3.5%-0.07% -> 0.0343 | M7: =L7 -> 0.0343 | N7: =M7 -> 0.0343 | O7: =N7 -> 0.0343 | P7: =O7 -> 0.0343 | Q7: =P7 -> 0.0343 | R7: =Q7 -> 0.0343 | S7: =R7 -> 0.0343 | T7: =S7 -> 0.0343 | ... AZ7: =AY7 -> 0.0343

Sheet BasisPointCost
A1: Asset | B1: Cost (Basis Point) | C1: Link
A2: Emerging Markets - Equities | B2: =0.2% -> 0.002
A3: Developed Markets - Equities | B3: =0.2% -> 0.002
A4: Emerging Markets State - Obligations | B4: =0.07% -> 0.0007
A5: High Yield Bonds - Obligations | B5: =0.07% -> 0.0007
A6: Investment Grade Bonds - Obligations | B6: =0.07% -> 0.0007
A7: Government ZC Bonds - Obligations | B7: =0.07% -> 0.0007

Sheet Returns2
B1: 2035 | C1: 2036 | D1: 2037 | E1: 2038 | F1: 2039 | G1: 2040 | H1: 2041 | I1: 2042 | J1: 2043 | K1: 2044 | L1: 2045 | M1: 2046 | N1: 2047 | O1: 2048 | P1: 2049 | Q1: 2050 | R1: 2051 | S1: 2052 | T1: 2053 | U1: 2054 | V1: 2055 | W1: 2056 | X1: 2057 | Y1: 2058 | Z1: 2059 | AA1: 2060 | AB1: 2061 | AC1: 2062 | AD1: 2063 | AE1: 2064 | AF1: 2065 | AG1: 2066 | AH1: 2067 | AI1: 2068 | AJ1: 2069 | AK1: 2070 | AL1: 2071 | AM1: 2072 | AN1: 2073 | AO1: 2074 | AP1: 2075
A2: Equities | B2: =6.5%-0.2% -> 0.063 | C2: =B2 -> 0.063 | D2: =C2 -> 0.063 | E2: =D2 -> 0.063 | F2: =E2 -> 0.063 | G2: =F2 -> 0.063 | H2: =G2 -> 0.063 | I2: =H2 -> 0.063 | J2: =I2 -> 0.063 | ... AP2: =AO2 -> 0.063
A3: Obligations | B3: =3.5%-0.07% -> 0.0343 | C3: =B3 -> 0.0343 | D3: =C3 -> 0.0343 | E3: =D3 -> 0.0343 | F3: =E3 -> 0.0343 | G3: =F3 -> 0.0343 | H3: =G3 -> 0.0343 | I3: =H3 -> 0.0343 | J3: =I3 -> 0.0343 | ... AP3: =AO3 -> 0.0343

Sheet Volatilities
B1: volatility
A2: Emerging Markets - Equities | B2: 0.086
A3: Developed Markets - Equities | B3: 0.07
A4: Emerging Markets State - Obligations | B4: 0.049
A5: High Yield Bonds - Obligations | B5: 0.05
A6: Investment Grade Bonds - Obligations | B6: 0.037
A7: Government ZC Bonds - Obligations | B7: 0.029

Sheet Volatilities2
B1: volatility
A2: Equities | B2: 0.18
A3: Obligations | B3: 0.08

Sheet Correlation
B1: Government ZC Bonds - Obligations | C1: Investment Grade Bonds - Obligations | D1: High Yield Bonds - Obligations | E1: Emerging Markets State - Obligations | F1: Developed Markets - Equities | G1: Emerging Markets - Equities
A2: Government ZC Bonds - Obligations | B2: 1 | C2: 0.6 | D2: 0.2 | E2: 0.4 | F2: 0 | G2: 0
A3: Investment Grade Bonds - Obligations | B3: 0.6 | C3: 1 | D3: 0.7 | E3: 0.6 | F3: 0.3 | G3: 0.3
A4: High Yield Bonds - Obligations | B4: 0.2 | C4: 0.7 | D4: 1 | E4: 0.7 | F4: 0.7 | G4: 0.6
A5: Emerging Markets State - Obligations | B5: 0.4 | C5: 0.6 | D5: 0.7 | E5: 1 | F5: 0.5 | G5: 0.7
A6: Developed Markets - Equities | B6: 0 | C6: 0.3 | D6: 0.7 | E6: 0.5 | F6: 1 | G6: 0.7
A7: Emerging Markets - Equities | B7: 0 | C7: 0.3 | D7: 0.6 | E7: 0.7 | F7: 0.7 | G7: 1

Sheet Correlation2
B1: Obligations | C1: Equities
A2: {=TRANSPOSE(B1:C1)} -> Obligations | B2: 1 | C2: 0
A3: Equities | B3: 0 | C3: 1
