Workbook
Name _DLX1: [1]Rates!#REF!
Name _DLX1.INC: '[2]Car Air'!#REF!
Name _DLX10.INC: '[3]US&Europe'!#REF!
Name _DLX10_INC: #REF!
Name _DLX100.INC: '[3]Bonds Data BIS'!#REF!
Name _DLX14.INC: #REF!
Name _DLX15.INC: '[3]Bonds Data BIS'!#REF!
Name _DLX16.INC: '[3]Bonds Data BIS'!#REF!
Name _DLX2.INC: #REF!
Name _DLX20.INC: #REF!
Name _DLX3.INC: #REF!
Name _DLX4.INC: #REF!
Name _DLX5.INC: #REF!
Name _DLX5_INC: #REF!
Name _DLX50.INC: '[3]US&Europe'!#REF!
Name _DLX52.INC: #REF!
Name _DLX53.INC: '[3]US&Europe'!#REF!
Name _DLX54.INC: '[3]US&Europe'!#REF!
Name _DLX56.INC: '[3]US&Europe'!#REF!
Name _DLX6.INC: #REF!
Name _DLX60.INC: #REF!
Name _DLX7.INC: '[3]US&Europe'!#REF!
Name _DLX8.INC: '[3]US&Europe'!#REF!
Name _DLX80.INC: '[3]Bonds Data BIS'!#REF!
Name _DLX9.INC: '[3]US&Europe'!#REF!
Name AUD_Nom: #REF!
Name AUD_Tenor: #REF!
Name AUD_yr: #REF!
Name CAD_Nom: #REF!
Name CAD_Tenor: #REF!
Name CAD_yr: #REF!
Name CHF_Nom: #REF!
Name CHF_Tenor: #REF!
Name CHF_yr: #REF!
Name cn_asia: [4]Weights!$J$5
Name code: [5]CONSTANT!#REF!
Name Currency_cusip: '[6]Currency bucketing mapping'!$B$35:$B$160
Name Currency_name: '[6]Currency bucketing mapping'!$B$35:$BF$35
Name Currency_table: '[6]Currency bucketing mapping'!$B$35:$BF$160
Name D_0: #REF!
Name D_0_DE: #REF!
Name D_0_FR: #REF!
Name D_0_IT: #REF!
Name D_0_JP: #REF!
Name D_0_UK: #REF!
Name DaysInYear: [7]C!$B$29
Name DE_gwth: #REF!
Name DE_S: #REF!
Name ERP: [8]CF20!$C$18
Name EUR_Nom: #REF!
Name EUR_Tenor: #REF!
Name EUR_yr: #REF!
Name FR_gwth: #REF!
Name FR_S: #REF!
Name GBP_Nom: #REF!
Name GBP_Tenor: #REF!
Name GBP_yr: #REF!
Name gGDP: [8]CF20!$C$14
Name hk_asia: [4]Weights!$J$6
Name hk_nie: [4]Weights!$K$6

Sheet Front Page
B1: Description
B5: TOC Colour Coding
B6: Inputs
B7: Calculation
B8: Raw Report
B9: Raw Report with Key
B11: Table Colors
B12: Uploaded to Python
B13: Not Uploaded to Python
B16: Table of Contents
B17: Salary Model
B18: Model Parameters
... B29: Loop used when executing the python script

Sheet Salary Variables
B2: Inflation | C2: 0.03
B3: Salary Growth
B4: Salary Raise | C4: 0.03
B5: Real Salary Raise | C5: =C4-C2 -> 0
B6: Job Hopping "Bonus" | C6: 0.06
B7: Real Job Hopping "Bonus" | C7: =C6-C2 -> 0.03
B8: % of salary dedicated to investments | C8: 0.2
B9: Initial Salary P1 | C9: 43871
B10: Initial Salary P2 | C10: 72000
B11: Contribution to pension
B12: Personal | C12: 0.05
B13: Company | C13: 0.1
B14: Aldersopsparing maximum contribution | C14: 9400
B15: Tax
B16: AM (%) | C16: 0.08
B17: Personal Allowance | C17: 51600
B18: Bottom-Bracket State Tax rate (%) | C18: 0.1201
B19: Top-bracket State Tax rate (%) | C19: 0.15
B20: State Tax Bracket Threshold | C20: 618400
B21: Municipal Tax (%) | C21: 0.25
B22: Capital Gains < 67,500DKK | C22: 0.27
B23: Capital Gains > 67,500DKK | C23: 0.42
B24: Capital Gains Threshold | C24: 67500

Sheet Income - P2 Helper
B2: Inflation | C2: =Income!I2 -> 0.03 | G2: GrossMonthlyInflationAdjustedP2 | H2: GrossMonthlySalaryP2 | I2: SwitchP2 | J2: Inverse | K2: Year | M2: Year | N2: GrossMonthlyInflationAdjustedP2 | O2: GrossMonthlySalaryP2
B3: Salary Raise | C3: =Income!I3 -> 0.03 | G3: =TableIncomeCalculations11[[#This Row],[GrossMonthlySalaryP2]]/(1+C2) -> 72167 | H3: =TableIncomeCalculations[[#This Row],[GrossMonthlySalaryP2]] -> 74332.01 | I3: =JobHopping[[#This Row],[SwitchP2Static]] -> N | J3: {=INDEX($I$3:$I$18,ROWS($I$3:$I$18)+ROW($I$3)-ROW())} -> N | K3: 2025 | M3: {=INDEX($K$3:$K$18,ROWS($K$3:$K$18)+ROW($K$3)-ROW())} -> 2010 | N3: {=INDEX($G$3:$G$18,ROWS($G$3:$G$18)+ROW($G$3)-ROW())} -> 63888.926 | O3: {=INDEX($H$3:$H$18,ROWS($H$3:$H$18)+ROW($H$3)-ROW())} -> 36965.724 | Q3: =Table11[[#This Row],[GrossMonthlyInflationAdjustedP2]]*0.2 -> 12777.785
B4: Real Salary Raise | C4: =Income!I4 -> 0 | G4: =(G3/(1+$C$4))-IF(TableIncomeCalculations11[[#This Row],[Inverse]]="Y",G3*$C$6,0) -> 72167 | H4: =(H3/(1+$C$3))-IF(TableIncomeCalculations11[[#This Row],[Inverse]]="Y",H3*$C$5,0) -> 72167 | I4: =JobHopping[[#This Row],[SwitchP2Static]] -> N | J4: {=INDEX($I$3:$I$18,ROWS($I$3:$I$18)+ROW($I$3)-ROW())} -> N | K4: 2024 | M4: {=INDEX($K$3:$K$18,ROWS($K$3:$K$18)+ROW($K$3)-ROW())} -> 2011 | N4: {=INDEX($G$3:$G$18,ROWS($G$3:$G$18)+ROW($G$3)-ROW())} -> 63888.926 | O4: {=INDEX($H$3:$H$18,ROWS($H$3:$H$18)+ROW($H$3)-ROW())} -> 38074.696 | Q4: =Table11[[#This Row],[GrossMonthlyInflationAdjustedP2]]*0.2 -> 12777.785
B5: Job Hopping "Bonus" | C5: =Income!I5 -> 0.06 | G5: =(G4/(1+$C$4))-IF(TableIncomeCalculations11[[#This Row],[Inverse]]="Y",G4*$C$6,0) -> 70001.99 | H5: =(H4/(1+$C$3))-IF(TableIncomeCalculations11[[#This Row],[Inverse]]="Y",H4*$C$5,0) -> 65735.029 | I5: =JobHopping[[#This Row],[SwitchP2Static]] -> Y | J5: {=INDEX($I$3:$I$18,ROWS($I$3:$I$18)+ROW($I$3)-ROW())} -> Y | K5: 2023 | M5: {=INDEX($K$3:$K$18,ROWS($K$3:$K$18)+ROW($K$3)-ROW())} -> 2012 | N5: {=INDEX($G$3:$G$18,ROWS($G$3:$G$18)+ROW($G$3)-ROW())} -> 63888.926 | O5: {=INDEX($H$3:$H$18,ROWS($H$3:$H$18)+ROW($H$3)-ROW())} -> 39216.937 | Q5: =Table11[[#This Row],[GrossMonthlyInflationAdjustedP2]]*0.2 -> 12777.785
B6: Real Job Hopping "Bonus" | C6: =Income!I6 -> 0.03 | G6: =(G5/(1+$C$4))-IF(TableIncomeCalculations11[[#This Row],[Inverse]]="Y",G5*$C$6,0) -> 70001.99 | H6: =(H5/(1+$C$3))-IF(TableIncomeCalculations11[[#This Row],[Inverse]]="Y",H5*$C$5,0) -> 63820.416 | I6: =JobHopping[[#This Row],[SwitchP2Static]] -> N | J6: {=INDEX($I$3:$I$18,ROWS($I$3:$I$18)+ROW($I$3)-ROW())} -> N | K6: 2022 | M6: {=INDEX($K$3:$K$18,ROWS($K$3:$K$18)+ROW($K$3)-ROW())} -> 2013 | N6: {=INDEX($G$3:$G$18,ROWS($G$3:$G$18)+ROW($G$3)-ROW())} -> 65864.872 | O6: {=INDEX($H$3:$H$18,ROWS($H$3:$H$18)+ROW($H$3)-ROW())} -> 43054.194 | Q6: =Table11[[#This Row],[GrossMonthlyInflationAdjustedP2]]*0.2 -> 13172.974
B7: % of salary dedicated to investments | C7: =Income!I7 -> 0.2 | G7: =(G6/(1+$C$4))-IF(TableIncomeCalculations11[[#This Row],[Inverse]]="Y",G6*$C$6,0) -> 70001.99 | H7: =(H6/(1+$C$3))-IF(TableIncomeCalculations11[[#This Row],[Inverse]]="Y",H6*$C$5,0) -> 61961.569 | I7: =JobHopping[[#This Row],[SwitchP2Static]] -> N | J7: {=INDEX($I$3:$I$18,ROWS($I$3:$I$18)+ROW($I$3)-ROW())} -> N | K7: 2021 | M7: {=INDEX($K$3:$K$18,ROWS($K$3:$K$18)+ROW($K$3)-ROW())} -> 2014 | N7: {=INDEX($G$3:$G$18,ROWS($G$3:$G$18)+ROW($G$3)-ROW())} -> 65864.872 | O7: {=INDEX($H$3:$H$18,ROWS($H$3:$H$18)+ROW($H$3)-ROW())} -> 44345.82 | Q7: =Table11[[#This Row],[GrossMonthlyInflationAdjustedP2]]*0.2 -> 13172.974
G8: =(G7/(1+$C$4))-IF(TableIncomeCalculations11[[#This Row],[Inverse]]="Y",G7*$C$6,0) -> 67901.93 | H8: =(H7/(1+$C$3))-IF(TableIncomeCalculations11[[#This Row],[Inverse]]="Y",H7*$C$5,0) -> 56439.169 | I8: =JobHopping[[#This Row],[SwitchP2Static]] -> N | J8: {=INDEX($I$3:$I$18,ROWS($I$3:$I$18)+ROW($I$3)-ROW())} -> Y | K8: 2020 | M8: {=INDEX($K$3:$K$18,ROWS($K$3:$K$18)+ROW($K$3)-ROW())} -> 2015 | N8: {=INDEX($G$3:$G$18,ROWS($G$3:$G$18)+ROW($G$3)-ROW())} -> 65864.872 | O8: {=INDEX($H$3:$H$18,ROWS($H$3:$H$18)+ROW($H$3)-ROW())} -> 45676.195 | Q8: =Table11[[#This Row],[GrossMonthlyInflationAdjustedP2]]*0.2 -> 13172.974
G9: =(G8/(1+$C$4))-IF(TableIncomeCalculations11[[#This Row],[Inverse]]="Y",G8*$C$6,0) -> 67901.93 | H9: =(H8/(1+$C$3))-IF(TableIncomeCalculations11[[#This Row],[Inverse]]="Y",H8*$C$5,0) -> 54795.31 | I9: =JobHopping[[#This Row],[SwitchP2Static]] -> Y | J9: {=INDEX($I$3:$I$18,ROWS($I$3:$I$18)+ROW($I$3)-ROW())} -> N | K9: 2019 | M9: {=INDEX($K$3:$K$18,ROWS($K$3:$K$18)+ROW($K$3)-ROW())} -> 2016 | N9: {=INDEX($G$3:$G$18,ROWS($G$3:$G$18)+ROW($G$3)-ROW())} -> 65864.872 | O9: {=INDEX($H$3:$H$18,ROWS($H$3:$H$18)+ROW($H$3)-ROW())} -> 47046.481 | Q9: =Table11[[#This Row],[GrossMonthlyInflationAdjustedP2]]*0.2 -> 13172.974
G10: =(G9/(1+$C$4))-IF(TableIncomeCalculations11[[#This Row],[Inverse]]="Y",G9*$C$6,0) -> 67901.93 | H10: =(H9/(1+$C$3))-IF(TableIncomeCalculations11[[#This Row],[Inverse]]="Y",H9*$C$5,0) -> 53199.33 | I10: =JobHopping[[#This Row],[SwitchP2Static]] -> N | J10: {=INDEX($I$3:$I$18,ROWS($I$3:$I$18)+ROW($I$3)-ROW())} -> N | K10: 2018 | M10: {=INDEX($K$3:$K$18,ROWS($K$3:$K$18)+ROW($K$3)-ROW())} -> 2017 | N10: {=INDEX($G$3:$G$18,ROWS($G$3:$G$18)+ROW($G$3)-ROW())} -> 67901.93 | O10: {=INDEX($H$3:$H$18,ROWS($H$3:$H$18)+ROW($H$3)-ROW())} -> 51649.835 | Q10: =Table11[[#This Row],[GrossMonthlyInflationAdjustedP2]]*0.2 -> 13580.386
G11: =(G10/(1+$C$4))-IF(TableIncomeCalculations11[[#This Row],[Inverse]]="Y",G10*$C$6,0) -> 67901.93 | H11: =(H10/(1+$C$3))-IF(TableIncomeCalculations11[[#This Row],[Inverse]]="Y",H10*$C$5,0) -> 51649.835 | I11: =JobHopping[[#This Row],[SwitchP2Static]] -> N | J11: {=INDEX($I$3:$I$18,ROWS($I$3:$I$18)+ROW($I$3)-ROW())} -> N | K11: 2017 | M11: {=INDEX($K$3:$K$18,ROWS($K$3:$K$18)+ROW($K$3)-ROW())} -> 2018 | N11: {=INDEX($G$3:$G$18,ROWS($G$3:$G$18)+ROW($G$3)-ROW())} -> 67901.93 | O11: {=INDEX($H$3:$H$18,ROWS($H$3:$H$18)+ROW($H$3)-ROW())} -> 53199.33 | Q11: =Table11[[#This Row],[GrossMonthlyInflationAdjustedP2]]*0.2 -> 13580.386
G12: =(G11/(1+$C$4))-IF(TableIncomeCalculations11[[#This Row],[Inverse]]="Y",G11*$C$6,0) -> 65864.872 | H12: =(H11/(1+$C$3))-IF(TableIncomeCalculations11[[#This Row],[Inverse]]="Y",H11*$C$5,0) -> 47046.481 | I12: =JobHopping[[#This Row],[SwitchP2Static]] -> N | J12: {=INDEX($I$3:$I$18,ROWS($I$3:$I$18)+ROW($I$3)-ROW())} -> Y | K12: 2016 | M12: {=INDEX($K$3:$K$18,ROWS($K$3:$K$18)+ROW($K$3)-ROW())} -> 2019 | N12: {=INDEX($G$3:$G$18,ROWS($G$3:$G$18)+ROW($G$3)-ROW())} -> 67901.93 | O12: {=INDEX($H$3:$H$18,ROWS($H$3:$H$18)+ROW($H$3)-ROW())} -> 54795.31 | Q12: =Table11[[#This Row],[GrossMonthlyInflationAdjustedP2]]*0.2 -> 13580.386
G13: =(G12/(1+$C$4))-IF(TableIncomeCalculations11[[#This Row],[Inverse]]="Y",G12*$C$6,0) -> 65864.872 | H13: =(H12/(1+$C$3))-IF(TableIncomeCalculations11[[#This Row],[Inverse]]="Y",H12*$C$5,0) -> 45676.195 | I13: =JobHopping[[#This Row],[SwitchP2Static]] -> Y | J13: {=INDEX($I$3:$I$18,ROWS($I$3:$I$18)+ROW($I$3)-ROW())} -> N | K13: 2015 | M13: {=INDEX($K$3:$K$18,ROWS($K$3:$K$18)+ROW($K$3)-ROW())} -> 2020 | N13: {=INDEX($G$3:$G$18,ROWS($G$3:$G$18)+ROW($G$3)-ROW())} -> 67901.93 | O13: {=INDEX($H$3:$H$18,ROWS($H$3:$H$18)+ROW($H$3)-ROW())} -> 56439.169 | Q13: =Table11[[#This Row],[GrossMonthlyInflationAdjustedP2]]*0.2 -> 13580.386
G14: =(G13/(1+$C$4))-IF(TableIncomeCalculations11[[#This Row],[Inverse]]="Y",G13*$C$6,0) -> 65864.872 | H14: =(H13/(1+$C$3))-IF(TableIncomeCalculations11[[#This Row],[Inverse]]="Y",H13*$C$5,0) -> 44345.82 | I14: =JobHopping[[#This Row],[SwitchP2Static]] -> N | J14: {=INDEX($I$3:$I$18,ROWS($I$3:$I$18)+ROW($I$3)-ROW())} -> N | K14: 2014 | M14: {=INDEX($K$3:$K$18,ROWS($K$3:$K$18)+ROW($K$3)-ROW())} -> 2021 | N14: {=INDEX($G$3:$G$18,ROWS($G$3:$G$18)+ROW($G$3)-ROW())} -> 70001.99 | O14: {=INDEX($H$3:$H$18,ROWS($H$3:$H$18)+ROW($H$3)-ROW())} -> 61961.569 | Q14: =Table11[[#This Row],[GrossMonthlyInflationAdjustedP2]]*0.2 -> 14000.398
G15: =(G14/(1+$C$4))-IF(TableIncomeCalculations11[[#This Row],[Inverse]]="Y",G14*$C$6,0) -> 65864.872 | H15: =(H14/(1+$C$3))-IF(TableIncomeCalculations11[[#This Row],[Inverse]]="Y",H14*$C$5,0) -> 43054.194 | I15: =JobHopping[[#This Row],[SwitchP2Static]] -> N | J15: {=INDEX($I$3:$I$18,ROWS($I$3:$I$18)+ROW($I$3)-ROW())} -> N | K15: 2013 | M15: {=INDEX($K$3:$K$18,ROWS($K$3:$K$18)+ROW($K$3)-ROW())} -> 2022 | N15: {=INDEX($G$3:$G$18,ROWS($G$3:$G$18)+ROW($G$3)-ROW())} -> 70001.99 | O15: {=INDEX($H$3:$H$18,ROWS($H$3:$H$18)+ROW($H$3)-ROW())} -> 63820.416 | Q15: =Table11[[#This Row],[GrossMonthlyInflationAdjustedP2]]*0.2 -> 14000.398
G16: =(G15/(1+$C$4))-IF(TableIncomeCalculations11[[#This Row],[Inverse]]="Y",G15*$C$6,0) -> 63888.926 | H16: =(H15/(1+$C$3))-IF(TableIncomeCalculations11[[#This Row],[Inverse]]="Y",H15*$C$5,0) -> 39216.937 | I16: =JobHopping[[#This Row],[SwitchP2Static]] -> Y | J16: {=INDEX($I$3:$I$18,ROWS($I$3:$I$18)+ROW($I$3)-ROW())} -> Y | K16: 2012 | M16: {=INDEX($K$3:$K$18,ROWS($K$3:$K$18)+ROW($K$3)-ROW())} -> 2023 | N16: {=INDEX($G$3:$G$18,ROWS($G$3:$G$18)+ROW($G$3)-ROW())} -> 70001.99 | O16: {=INDEX($H$3:$H$18,ROWS($H$3:$H$18)+ROW($H$3)-ROW())} -> 65735.029 | Q16: =Table11[[#This Row],[GrossMonthlyInflationAdjustedP2]]*0.2 -> 14000.398
G17: =(G16/(1+$C$4))-IF(TableIncomeCalculations11[[#This Row],[Inverse]]="Y",G16*$C$6,0) -> 63888.926 | H17: =(H16/(1+$C$3))-IF(TableIncomeCalculations11[[#This Row],[Inverse]]="Y",H16*$C$5,0) -> 38074.696 | I17: =JobHopping[[#This Row],[SwitchP2Static]] -> N | J17: {=INDEX($I$3:$I$18,ROWS($I$3:$I$18)+ROW($I$3)-ROW())} -> N | K17: 2011 | M17: {=INDEX($K$3:$K$18,ROWS($K$3:$K$18)+ROW($K$3)-ROW())} -> 2024 | N17: {=INDEX($G$3:$G$18,ROWS($G$3:$G$18)+ROW($G$3)-ROW())} -> 72167 | O17: {=INDEX($H$3:$H$18,ROWS($H$3:$H$18)+ROW($H$3)-ROW())} -> 72167 | Q17: =Table11[[#This Row],[GrossMonthlyInflationAdjustedP2]]*0.2 -> 14433.4
G18: =(G17/(1+$C$4))-IF(TableIncomeCalculations11[[#This Row],[Inverse]]="Y",G17*$C$6,0) -> 63888.926 | H18: =(H17/(1+$C$3))-IF(TableIncomeCalculations11[[#This Row],[Inverse]]="Y",H17*$C$5,0) -> 36965.724 | I18: =JobHopping[[#This Row],[SwitchP2Static]] -> N | J18: {=INDEX($I$3:$I$18,ROWS($I$3:$I$18)+ROW($I$3)-ROW())} -> N | K18: 2010 | M18: {=INDEX($K$3:$K$18,ROWS($K$3:$K$18)+ROW($K$3)-ROW())} -> 2025 | N18: {=INDEX($G$3:$G$18,ROWS($G$3:$G$18)+ROW($G$3)-ROW())} -> 72167 | O18: {=INDEX($H$3:$H$18,ROWS($H$3:$H$18)+ROW($H$3)-ROW())} -> 74332.01 | Q18: =Table11[[#This Row],[GrossMonthlyInflationAdjustedP2]]*0.2 -> 14433.4
Q21: =SUM(Q3:Q18) -> 216214.79

Sheet Income
A1: Income!A1
B2: Year | C2: SalaryP1 | D2: SalaryP2 | E2: InvestmentP1 | F2: InvestmentP2 | H2: Inflation | I2: ='Salary Variables'!$C$2 -> 0.03 | K2: Post Investing | L2: Post Investing | M2: NetMonthlySalaryP1 | N2: NetMonthlySalaryP2 | O2: GrossMonthlyInflationAdjustedP1 | P2: GrossMonthlyInflationAdjustedP2 | Q2: GrossMonthlySalaryP1 | R2: GrossMonthlySalaryP2 | S2: SwitchP1 | T2: SwitchP2
B3: 2025 | C3: =(TableIncomeCalculations[[#This Row],[NetMonthlySalaryP1]]*12) -> 280183.53 | D3: =(TableIncomeCalculations[[#This Row],[NetMonthlySalaryP2]]*12) -> 460002.96 | E3: =TableIncome[[#This Row],[SalaryP1]]*$I$7 -> 56036.705 | F3: =TableIncome[[#This Row],[SalaryP2]]*$I$7 -> 92000.592 | H3: Salary Raise | I3: {='Salary Variables'!$C$4:$C$8} -> 0.03 | K3: =(TableIncome[[#This Row],[SalaryP1]]-TableIncome[[#This Row],[InvestmentP1]])/12 -> 18678.902 | L3: =(TableIncome[[#This Row],[SalaryP2]]-TableIncome[[#This Row],[InvestmentP2]])/12 -> 30666.864 | M3: ='Net Salary P1'!BI2 -> 23348.627 | N3: ='Net Salary P2'!BI2 -> 38333.58 | O3: =TableIncomeCalculations[[#This Row],[GrossMonthlySalaryP1]]/(1+I2) -> 43000 | P3: =TableIncomeCalculations[[#This Row],[GrossMonthlySalaryP2]]/(1+I2) -> 72167 | Q3: =43000*(1+I3) -> 44290 | R3: =72167*(1+I3) -> 74332.01 | S3: =JobHopping[[#This Row],[SwitchP1Static]] -> N | T3: =JobHopping[[#This Row],[SwitchP2Static]] -> N
B4: 2026 | C4: =(TableIncomeCalculations[[#This Row],[NetMonthlySalaryP1]]*12) -> 280183.53 | D4: =(TableIncomeCalculations[[#This Row],[NetMonthlySalaryP2]]*12) -> 460002.96 | E4: =TableIncome[[#This Row],[SalaryP1]]*$I$7 -> 56036.705 | F4: =TableIncome[[#This Row],[SalaryP2]]*$I$7 -> 92000.592 | H4: Real Salary Raise | I4: 0 | K4: =(TableIncome[[#This Row],[SalaryP1]]-TableIncome[[#This Row],[InvestmentP1]])/12 -> 18678.902 | L4: =(TableIncome[[#This Row],[SalaryP2]]-TableIncome[[#This Row],[InvestmentP2]])/12 -> 30666.864 | M4: ='Net Salary P1'!BI3 -> 23348.627 | N4: ='Net Salary P2'!BI3 -> 38333.58 | O4: =IF(_xlfn.XLOOKUP(TableIncome[[#This Row],[Year]],Loop!C:C,Loop!D:D)<75,(O3*(1+$I$4))+IF(TableIncomeCalculations[[#This Row],[SwitchP1]]="Y",O3*$I$6,0),0) -> 43000 | P4: =IF(_xlfn.XLOOKUP(TableIncome[[#This Row],[Year]],Loop!C:C,Loop!E:E)<75,(P3*(1+$I$4))+IF(TableIncomeCalculations[[#This Row],[SwitchP2]]="Y",P3*$I$6,0),0) -> 72167 | Q4: =IF(_xlfn.XLOOKUP(TableIncome[[#This Row],[Year]],Loop!C:C,Loop!D:D)<75,(Q3*(1+$I$3))+IF(TableIncomeCalculations[[#This Row],[SwitchP1]]="Y",Q3*$I$5,0),0) -> 45618.7 | R4: =IF(_xlfn.XLOOKUP(TableIncome[[#This Row],[Year]],Loop!C:C,Loop!E:E)<75,(R3*(1+$I$3))+IF(TableIncomeCalculations[[#This Row],[SwitchP2]]="Y",R3*$I$5,0),0) -> 76561.97 | S4: =JobHopping[[#This Row],[SwitchP1Static]] -> N | T4: =JobHopping[[#This Row],[SwitchP2Static]] -> N
B5: 2027 | C5: =(TableIncomeCalculations[[#This Row],[NetMonthlySalaryP1]]*12) -> 288705.77 | D5: =(TableIncomeCalculations[[#This Row],[NetMonthlySalaryP2]]*12) -> 470899.87 | E5: =TableIncome[[#This Row],[SalaryP1]]*$I$7 -> 57741.154 | F5: =TableIncome[[#This Row],[SalaryP2]]*$I$7 -> 94179.973 | H5: Job Hopping "Bonus" | I5: 0.06 | K5: =(TableIncome[[#This Row],[SalaryP1]]-TableIncome[[#This Row],[InvestmentP1]])/12 -> 19247.051 | L5: =(TableIncome[[#This Row],[SalaryP2]]-TableIncome[[#This Row],[InvestmentP2]])/12 -> 31393.324 | M5: ='Net Salary P1'!BI4 -> 24058.814 | N5: ='Net Salary P2'!BI4 -> 39241.656 | O5: =IF(_xlfn.XLOOKUP(TableIncome[[#This Row],[Year]],Loop!C:C,Loop!D:D)<75,(O4*(1+$I$4))+IF(TableIncomeCalculations[[#This Row],[SwitchP1]]="Y",O4*$I$6,0),0) -> 44290 | P5: =IF(_xlfn.XLOOKUP(TableIncome[[#This Row],[Year]],Loop!C:C,Loop!E:E)<75,(P4*(1+$I$4))+IF(TableIncomeCalculations[[#This Row],[SwitchP2]]="Y",P4*$I$6,0),0) -> 74332.01 | Q5: =IF(_xlfn.XLOOKUP(TableIncome[[#This Row],[Year]],Loop!C:C,Loop!D:D)<75,(Q4*(1+$I$3))+IF(TableIncomeCalculations[[#This Row],[SwitchP1]]="Y",Q4*$I$5,0),0) -> 49724.383 | R5: =IF(_xlfn.XLOOKUP(TableIncome[[#This Row],[Year]],Loop!C:C,Loop!E:E)<75,(R4*(1+$I$3))+IF(TableIncomeCalculations[[#This Row],[SwitchP2]]="Y",R4*$I$5,0),0) -> 83452.548 | S5: =JobHopping[[#This Row],[SwitchP1Static]] -> Y | T5: =JobHopping[[#This Row],[SwitchP2Static]] -> Y
B6: 2028 | C6: =(TableIncomeCalculations[[#This Row],[NetMonthlySalaryP1]]*12) -> 288705.77 | D6: =(TableIncomeCalculations[[#This Row],[NetMonthlySalaryP2]]*12) -> 470899.87 | E6: =TableIncome[[#This Row],[SalaryP1]]*$I$7 -> 57741.154 | F6: =TableIncome[[#This Row],[SalaryP2]]*$I$7 -> 94179.973 | H6: Real Job Hopping "Bonus" | I6: 0.03 | K6: =(TableIncome[[#This Row],[SalaryP1]]-TableIncome[[#This Row],[InvestmentP1]])/12 -> 19247.051 | L6: =(TableIncome[[#This Row],[SalaryP2]]-TableIncome[[#This Row],[InvestmentP2]])/12 -> 31393.324 | M6: ='Net Salary P1'!BI5 -> 24058.814 | N6: ='Net Salary P2'!BI5 -> 39241.656 | O6: =IF(_xlfn.XLOOKUP(TableIncome[[#This Row],[Year]],Loop!C:C,Loop!D:D)<75,(O5*(1+$I$4))+IF(TableIncomeCalculations[[#This Row],[SwitchP1]]="Y",O5*$I$6,0),0) -> 44290 | P6: =IF(_xlfn.XLOOKUP(TableIncome[[#This Row],[Year]],Loop!C:C,Loop!E:E)<75,(P5*(1+$I$4))+IF(TableIncomeCalculations[[#This Row],[SwitchP2]]="Y",P5*$I$6,0),0) -> 74332.01 | Q6: =IF(_xlfn.XLOOKUP(TableIncome[[#This Row],[Year]],Loop!C:C,Loop!D:D)<75,(Q5*(1+$I$3))+IF(TableIncomeCalculations[[#This Row],[SwitchP1]]="Y",Q5*$I$5,0),0) -> 51216.114 | R6: =IF(_xlfn.XLOOKUP(TableIncome[[#This Row],[Year]],Loop!C:C,Loop!E:E)<75,(R5*(1+$I$3))+IF(TableIncomeCalculations[[#This Row],[SwitchP2]]="Y",R5*$I$5,0),0) -> 85956.124 | S6: =JobHopping[[#This Row],[SwitchP1Static]] -> N | T6: =JobHopping[[#This Row],[SwitchP2Static]] -> N
B7: 2029 | C7: =(TableIncomeCalculations[[#This Row],[NetMonthlySalaryP1]]*12) -> 288705.77 | D7: =(TableIncomeCalculations[[#This Row],[NetMonthlySalaryP2]]*12) -> 470899.87 | E7: =TableIncome[[#This Row],[SalaryP1]]*$I$7 -> 57741.154 | F7: =TableIncome[[#This Row],[SalaryP2]]*$I$7 -> 94179.973 | H7: % of salary dedicated to investments | I7: 0.2 | K7: =(TableIncome[[#This Row],[SalaryP1]]-TableIncome[[#This Row],[InvestmentP1]])/12 -> 19247.051 | L7: =(TableIncome[[#This Row],[SalaryP2]]-TableIncome[[#This Row],[InvestmentP2]])/12 -> 31393.324 | M7: ='Net Salary P1'!BI6 -> 24058.814 | N7: ='Net Salary P2'!BI6 -> 39241.656 | O7: =IF(_xlfn.XLOOKUP(TableIncome[[#This Row],[Year]],Loop!C:C,Loop!D:D)<75,(O6*(1+$I$4))+IF(TableIncomeCalculations[[#This Row],[SwitchP1]]="Y",O6*$I$6,0),0) -> 44290 | P7: =IF(_xlfn.XLOOKUP(TableIncome[[#This Row],[Year]],Loop!C:C,Loop!E:E)<75,(P6*(1+$I$4))+IF(TableIncomeCalculations[[#This Row],[SwitchP2]]="Y",P6*$I$6,0),0) -> 74332.01 | Q7: =IF(_xlfn.XLOOKUP(TableIncome[[#This Row],[Year]],Loop!C:C,Loop!D:D)<75,(Q6*(1+$I$3))+IF(TableIncomeCalculations[[#This Row],[SwitchP1]]="Y",Q6*$I$5,0),0) -> 52752.598 | R7: =IF(_xlfn.XLOOKUP(TableIncome[[#This Row],[Year]],Loop!C:C,Loop!E:E)<75,(R6*(1+$I$3))+IF(TableIncomeCalculations[[#This Row],[SwitchP2]]="Y",R6*$I$5,0),0) -> 88534.808 | S7: =JobHopping[[#This Row],[SwitchP1Static]] -> N | T7: =JobHopping[[#This Row],[SwitchP2Static]] -> N
B8: 2030 | C8: =(TableIncomeCalculations[[#This Row],[NetMonthlySalaryP1]]*12) -> 288705.77 | D8: =(TableIncomeCalculations[[#This Row],[NetMonthlySalaryP2]]*12) -> 470899.87 | E8: =TableIncome[[#This Row],[SalaryP1]]*$I$7 -> 57741.154 | F8: =TableIncome[[#This Row],[SalaryP2]]*$I$7 -> 94179.973 | K8: =(TableIncome[[#This Row],[SalaryP1]]-TableIncome[[#This Row],[InvestmentP1]])/12 -> 19247.051 | L8: =(TableIncome[[#This Row],[SalaryP2]]-TableIncome[[#This Row],[InvestmentP2]])/12 -> 31393.324 | M8: ='Net Salary P1'!BI7 -> 24058.814 | N8: ='Net Salary P2'!BI7 -> 39241.656 | O8: =IF(_xlfn.XLOOKUP(TableIncome[[#This Row],[Year]],Loop!C:C,Loop!D:D)<75,(O7*(1+$I$4))+IF(TableIncomeCalculations[[#This Row],[SwitchP1]]="Y",O7*$I$6,0),0) -> 44290 | P8: =IF(_xlfn.XLOOKUP(TableIncome[[#This Row],[Year]],Loop!C:C,Loop!E:E)<75,(P7*(1+$I$4))+IF(TableIncomeCalculations[[#This Row],[SwitchP2]]="Y",P7*$I$6,0),0) -> 74332.01 | Q8: =IF(_xlfn.XLOOKUP(TableIncome[[#This Row],[Year]],Loop!C:C,Loop!D:D)<75,(Q7*(1+$I$3))+IF(TableIncomeCalculations[[#This Row],[SwitchP1]]="Y",Q7*$I$5,0),0) -> 54335.176 | R8: =IF(_xlfn.XLOOKUP(TableIncome[[#This Row],[Year]],Loop!C:C,Loop!E:E)<75,(R7*(1+$I$3))+IF(TableIncomeCalculations[[#This Row],[SwitchP2]]="Y",R7*$I$5,0),0) -> 91190.852 | S8: =JobHopping[[#This Row],[SwitchP1Static]] -> N | T8: =JobHopping[[#This Row],[SwitchP2Static]] -> N
B9: 2031 | C9: =(TableIncomeCalculations[[#This Row],[NetMonthlySalaryP1]]*12) -> 297483.68 | D9: =(TableIncomeCalculations[[#This Row],[NetMonthlySalaryP2]]*12) -> 482123.68 | E9: =TableIncome[[#This Row],[SalaryP1]]*$I$7 -> 59496.737 | F9: =TableIncome[[#This Row],[SalaryP2]]*$I$7 -> 96424.737 | K9: =(TableIncome[[#This Row],[SalaryP1]]-TableIncome[[#This Row],[InvestmentP1]])/12 -> 19832.246 | L9: =(TableIncome[[#This Row],[SalaryP2]]-TableIncome[[#This Row],[InvestmentP2]])/12 -> 32141.579 | M9: ='Net Salary P1'!BI8 -> 24790.307 | N9: ='Net Salary P2'!BI8 -> 40176.974 | O9: =IF(_xlfn.XLOOKUP(TableIncome[[#This Row],[Year]],Loop!C:C,Loop!D:D)<75,(O8*(1+$I$4))+IF(TableIncomeCalculations[[#This Row],[SwitchP1]]="Y",O8*$I$6,0),0) -> 45618.7 | P9: =IF(_xlfn.XLOOKUP(TableIncome[[#This Row],[Year]],Loop!C:C,Loop!E:E)<75,(P8*(1+$I$4))+IF(TableIncomeCalculations[[#This Row],[SwitchP2]]="Y",P8*$I$6,0),0) -> 76561.97 | Q9: =IF(_xlfn.XLOOKUP(TableIncome[[#This Row],[Year]],Loop!C:C,Loop!D:D)<75,(Q8*(1+$I$3))+IF(TableIncomeCalculations[[#This Row],[SwitchP1]]="Y",Q8*$I$5,0),0) -> 59225.342 | R9: =IF(_xlfn.XLOOKUP(TableIncome[[#This Row],[Year]],Loop!C:C,Loop!E:E)<75,(R8*(1+$I$3))+IF(TableIncomeCalculations[[#This Row],[SwitchP2]]="Y",R8*$I$5,0),0) -> 99398.029 | S9: =JobHopping[[#This Row],[SwitchP1Static]] -> Y | T9: =JobHopping[[#This Row],[SwitchP2Static]] -> Y
B10: 2032 | C10: =(TableIncomeCalculations[[#This Row],[NetMonthlySalaryP1]]*12) -> 297483.68 | D10: =(TableIncomeCalculations[[#This Row],[NetMonthlySalaryP2]]*12) -> 482123.68 | E10: =TableIncome[[#This Row],[SalaryP1]]*$I$7 -> 59496.737 | F10: =TableIncome[[#This Row],[SalaryP2]]*$I$7 -> 96424.737 | K10: =(TableIncome[[#This Row],[SalaryP1]]-TableIncome[[#This Row],[InvestmentP1]])/12 -> 19832.246 | L10: =(TableIncome[[#This Row],[SalaryP2]]-TableIncome[[#This Row],[InvestmentP2]])/12 -> 32141.579 | M10: ='Net Salary P1'!BI9 -> 24790.307 | N10: ='Net Salary P2'!BI9 -> 40176.974 | O10: =IF(_xlfn.XLOOKUP(TableIncome[[#This Row],[Year]],Loop!C:C,Loop!D:D)<75,(O9*(1+$I$4))+IF(TableIncomeCalculations[[#This Row],[SwitchP1]]="Y",O9*$I$6,0),0) -> 45618.7 | P10: =IF(_xlfn.XLOOKUP(TableIncome[[#This Row],[Year]],Loop!C:C,Loop!E:E)<75,(P9*(1+$I$4))+IF(TableIncomeCalculations[[#This Row],[SwitchP2]]="Y",P9*$I$6,0),0) -> 76561.97 | Q10: =IF(_xlfn.XLOOKUP(TableIncome[[#This Row],[Year]],Loop!C:C,Loop!D:D)<75,(Q9*(1+$I$3))+IF(TableIncomeCalculations[[#This Row],[SwitchP1]]="Y",Q9*$I$5,0),0) -> 61002.102 | R10: =IF(_xlfn.XLOOKUP(TableIncome[[#This Row],[Year]],Loop!C:C,Loop!E:E)<75,(R9*(1+$I$3))+IF(TableIncomeCalculations[[#This Row],[SwitchP2]]="Y",R9*$I$5,0),0) -> 102379.97 | S10: =JobHopping[[#This Row],[SwitchP1Static]] -> N | T10: =JobHopping[[#This Row],[SwitchP2Static]] -> N
B11: 2033 | C11: =(TableIncomeCalculations[[#This Row],[NetMonthlySalaryP1]]*12) -> 297483.68 | D11: =(TableIncomeCalculations[[#This Row],[NetMonthlySalaryP2]]*12) -> 482123.68 | E11: =TableIncome[[#This Row],[SalaryP1]]*$I$7 -> 59496.737 | F11: =TableIncome[[#This Row],[SalaryP2]]*$I$7 -> 96424.737 | K11: =(TableIncome[[#This Row],[SalaryP1]]-TableIncome[[#This Row],[InvestmentP1]])/12 -> 19832.246 | L11: =(TableIncome[[#This Row],[SalaryP2]]-TableIncome[[#This Row],[InvestmentP2]])/12 -> 32141.579 | M11: ='Net Salary P1'!BI10 -> 24790.307 | N11: ='Net Salary P2'!BI10 -> 40176.974 | O11: =IF(_xlfn.XLOOKUP(TableIncome[[#This Row],[Year]],Loop!C:C,Loop!D:D)<75,(O10*(1+$I$4))+IF(TableIncomeCalculations[[#This Row],[SwitchP1]]="Y",O10*$I$6,0),0) -> 45618.7 | P11: =IF(_xlfn.XLOOKUP(TableIncome[[#This Row],[Year]],Loop!C:C,Loop!E:E)<75,(P10*(1+$I$4))+IF(TableIncomeCalculations[[#This Row],[SwitchP2]]="Y",P10*$I$6,0),0) -> 76561.97 | Q11: =IF(_xlfn.XLOOKUP(TableIncome[[#This Row],[Year]],Loop!C:C,Loop!D:D)<75,(Q10*(1+$I$3))+IF(TableIncomeCalculations[[#This Row],[SwitchP1]]="Y",Q10*$I$5,0),0) -> 62832.165 | R11: =IF(_xlfn.XLOOKUP(TableIncome[[#This Row],[Year]],Loop!C:C,Loop!E:E)<75,(R10*(1+$I$3))+IF(TableIncomeCalculations[[#This Row],[SwitchP2]]="Y",R10*$I$5,0),0) -> 105451.37 | S11: =JobHopping[[#This Row],[SwitchP1Static]] -> N | T11: =JobHopping[[#This Row],[SwitchP2Static]] -> N
B12: 2034 | C12: =(TableIncomeCalculations[[#This Row],[NetMonthlySalaryP1]]*12) -> 297483.68 | D12: =(TableIncomeCalculations[[#This Row],[NetMonthlySalaryP2]]*12) -> 482123.68 | E12: =TableIncome[[#This Row],[SalaryP1]]*$I$7 -> 59496.737 | F12: =TableIncome[[#This Row],[SalaryP2]]*$I$7 -> 96424.737 | K12: =(TableIncome[[#This Row],[SalaryP1]]-TableIncome[[#This Row],[InvestmentP1]])/12 -> 19832.246 | L12: =(TableIncome[[#This Row],[SalaryP2]]-TableIncome[[#This Row],[InvestmentP2]])/12 -> 32141.579 | M12: ='Net Salary P1'!BI11 -> 24790.307 | N12: ='Net Salary P2'!BI11 -> 40176.974 | O12: =IF(_xlfn.XLOOKUP(TableIncome[[#This Row],[Year]],Loop!C:C,Loop!D:D)<75,(O11*(1+$I$4))+IF(TableIncomeCalculations[[#This Row],[SwitchP1]]="Y",O11*$I$6,0),0) -> 45618.7 | P12: =IF(_xlfn.XLOOKUP(TableIncome[[#This Row],[Year]],Loop!C:C,Loop!E:E)<75,(P11*(1+$I$4))+IF(TableIncomeCalculations[[#This Row],[SwitchP2]]="Y",P11*$I$6,0),0) -> 76561.97 | Q12: =IF(_xlfn.XLOOKUP(TableIncome[[#This Row],[Year]],Loop!C:C,Loop!D:D)<75,(Q11*(1+$I$3))+IF(TableIncomeCalculations[[#This Row],[SwitchP1]]="Y",Q11*$I$5,0),0) -> 64717.13 | R12: =IF(_xlfn.XLOOKUP(TableIncome[[#This Row],[Year]],Loop!C:C,Loop!E:E)<75,(R11*(1+$I$3))+IF(TableIncomeCalculations[[#This Row],[SwitchP2]]="Y",R11*$I$5,0),0) -> 108614.91 | S12: =JobHopping[[#This Row],[SwitchP1Static]] -> N | T12: =JobHopping[[#This Row],[SwitchP2Static]] -> N
B13: 2035 | C13: =(TableIncomeCalculations[[#This Row],[NetMonthlySalaryP1]]*12) -> 306524.93 | D13: =(TableIncomeCalculations[[#This Row],[NetMonthlySalaryP2]]*12) -> 493684.21 | E13: =TableIncome[[#This Row],[SalaryP1]]*$I$7 -> 61304.986 | F13: =TableIncome[[#This Row],[SalaryP2]]*$I$7 -> 98736.843 | K13: =(TableIncome[[#This Row],[SalaryP1]]-TableIncome[[#This Row],[InvestmentP1]])/12 -> 20434.995 | L13: =(TableIncome[[#This Row],[SalaryP2]]-TableIncome[[#This Row],[InvestmentP2]])/12 -> 32912.281 | M13: ='Net Salary P1'!BI12 -> 25543.744 | N13: ='Net Salary P2'!BI12 -> 41140.351 | O13: =IF(_xlfn.XLOOKUP(TableIncome[[#This Row],[Year]],Loop!C:C,Loop!D:D)<75,(O12*(1+$I$4))+IF(TableIncomeCalculations[[#This Row],[SwitchP1]]="Y",O12*$I$6,0),0) -> 46987.261 | P13: =IF(_xlfn.XLOOKUP(TableIncome[[#This Row],[Year]],Loop!C:C,Loop!E:E)<75,(P12*(1+$I$4))+IF(TableIncomeCalculations[[#This Row],[SwitchP2]]="Y",P12*$I$6,0),0) -> 78858.829 | Q13: =IF(_xlfn.XLOOKUP(TableIncome[[#This Row],[Year]],Loop!C:C,Loop!D:D)<75,(Q12*(1+$I$3))+IF(TableIncomeCalculations[[#This Row],[SwitchP1]]="Y",Q12*$I$5,0),0) -> 70541.672 | R13: =IF(_xlfn.XLOOKUP(TableIncome[[#This Row],[Year]],Loop!C:C,Loop!E:E)<75,(R12*(1+$I$3))+IF(TableIncomeCalculations[[#This Row],[SwitchP2]]="Y",R12*$I$5,0),0) -> 118390.25 | S13: =JobHopping[[#This Row],[SwitchP1Static]] -> Y | T13: =JobHopping[[#This Row],[SwitchP2Static]] -> Y
B14: 2036 | C14: =(TableIncomeCalculations[[#This Row],[NetMonthlySalaryP1]]*12) -> 306524.93 | D14: =(TableIncomeCalculations[[#This Row],[NetMonthlySalaryP2]]*12) -> 493684.21 | E14: =TableIncome[[#This Row],[SalaryP1]]*$I$7 -> 61304.986 | F14: =TableIncome[[#This Row],[SalaryP2]]*$I$7 -> 98736.843 | K14: =(TableIncome[[#This Row],[SalaryP1]]-TableIncome[[#This Row],[InvestmentP1]])/12 -> 20434.995 | L14: =(TableIncome[[#This Row],[SalaryP2]]-TableIncome[[#This Row],[InvestmentP2]])/12 -> 32912.281 | M14: ='Net Salary P1'!BI13 -> 25543.744 | N14: ='Net Salary P2'!BI13 -> 41140.351 | O14: =IF(_xlfn.XLOOKUP(TableIncome[[#This Row],[Year]],Loop!C:C,Loop!D:D)<75,(O13*(1+$I$4))+IF(TableIncomeCalculations[[#This Row],[SwitchP1]]="Y",O13*$I$6,0),0) -> 46987.261 | P14: =IF(_xlfn.XLOOKUP(TableIncome[[#This Row],[Year]],Loop!C:C,Loop!E:E)<75,(P13*(1+$I$4))+IF(TableIncomeCalculations[[#This Row],[SwitchP2]]="Y",P13*$I$6,0),0) -> 78858.829 | Q14: =IF(_xlfn.XLOOKUP(TableIncome[[#This Row],[Year]],Loop!C:C,Loop!D:D)<75,(Q13*(1+$I$3))+IF(TableIncomeCalculations[[#This Row],[SwitchP1]]="Y",Q13*$I$5,0),0) -> 72657.922 | R14: =IF(_xlfn.XLOOKUP(TableIncome[[#This Row],[Year]],Loop!C:C,Loop!E:E)<75,(R13*(1+$I$3))+IF(TableIncomeCalculations[[#This Row],[SwitchP2]]="Y",R13*$I$5,0),0) -> 121941.96 | S14: =JobHopping[[#This Row],[SwitchP1Static]] -> N | T14: =JobHopping[[#This Row],[SwitchP2Static]] -> N
B15: 2037 | C15: =(TableIncomeCalculations[[#This Row],[NetMonthlySalaryP1]]*12) -> 306524.93 | D15: =(TableIncomeCalculations[[#This Row],[NetMonthlySalaryP2]]*12) -> 493684.21 | E15: =TableIncome[[#This Row],[SalaryP1]]*$I$7 -> 61304.986 | F15: =TableIncome[[#This Row],[SalaryP2]]*$I$7 -> 98736.843 | K15: =(TableIncome[[#This Row],[SalaryP1]]-TableIncome[[#This Row],[InvestmentP1]])/12 -> 20434.995 | L15: =(TableIncome[[#This Row],[SalaryP2]]-TableIncome[[#This Row],[InvestmentP2]])/12 -> 32912.281 | M15: ='Net Salary P1'!BI14 -> 25543.744 | N15: ='Net Salary P2'!BI14 -> 41140.351 | O15: =IF(_xlfn.XLOOKUP(TableIncome[[#This Row],[Year]],Loop!C:C,Loop!D:D)<75,(O14*(1+$I$4))+IF(TableIncomeCalculations[[#This Row],[SwitchP1]]="Y",O14*$I$6,0),0) -> 46987.261 | P15: =IF(_xlfn.XLOOKUP(TableIncome[[#This Row],[Year]],Loop!C:C,Loop!E:E)<75,(P14*(1+$I$4))+IF(TableIncomeCalculations[[#This Row],[SwitchP2]]="Y",P14*$I$6,0),0) -> 78858.829 | Q15: =IF(_xlfn.XLOOKUP(TableIncome[[#This Row],[Year]],Loop!C:C,Loop!D:D)<75,(Q14*(1+$I$3))+IF(TableIncomeCalculations[[#This Row],[SwitchP1]]="Y",Q14*$I$5,0),0) -> 74837.659 | R15: =IF(_xlfn.XLOOKUP(TableIncome[[#This Row],[Year]],Loop!C:C,Loop!E:E)<75,(R14*(1+$I$3))+IF(TableIncomeCalculations[[#This Row],[SwitchP2]]="Y",R14*$I$5,0),0) -> 125600.22 | S15: =JobHopping[[#This Row],[SwitchP1Static]] -> N | T15: =JobHopping[[#This Row],[SwitchP2Static]] -> N
B16: 2038 | C16: =(TableIncomeCalculations[[#This Row],[NetMonthlySalaryP1]]*12) -> 315837.42 | D16: =(TableIncomeCalculations[[#This Row],[NetMonthlySalaryP2]]*12) -> 505591.56 | E16: =TableIncome[[#This Row],[SalaryP1]]*$I$7 -> 63167.484 | F16: =TableIncome[[#This Row],[SalaryP2]]*$I$7 -> 101118.31 | K16: =(TableIncome[[#This Row],[SalaryP1]]-TableIncome[[#This Row],[InvestmentP1]])/12 -> 21055.828 | L16: =(TableIncome[[#This Row],[SalaryP2]]-TableIncome[[#This Row],[InvestmentP2]])/12 -> 33706.104 | M16: ='Net Salary P1'!BI15 -> 26319.785 | N16: ='Net Salary P2'!BI15 -> 42132.63 | O16: =IF(_xlfn.XLOOKUP(TableIncome[[#This Row],[Year]],Loop!C:C,Loop!D:D)<75,(O15*(1+$I$4))+IF(TableIncomeCalculations[[#This Row],[SwitchP1]]="Y",O15*$I$6,0),0) -> 48396.879 | P16: =IF(_xlfn.XLOOKUP(TableIncome[[#This Row],[Year]],Loop!C:C,Loop!E:E)<75,(P15*(1+$I$4))+IF(TableIncomeCalculations[[#This Row],[SwitchP2]]="Y",P15*$I$6,0),0) -> 81224.594 | Q16: =IF(_xlfn.XLOOKUP(TableIncome[[#This Row],[Year]],Loop!C:C,Loop!D:D)<75,(Q15*(1+$I$3))+IF(TableIncomeCalculations[[#This Row],[SwitchP1]]="Y",Q15*$I$5,0),0) -> 81573.049 | R16: =IF(_xlfn.XLOOKUP(TableIncome[[#This Row],[Year]],Loop!C:C,Loop!E:E)<75,(R15*(1+$I$3))+IF(TableIncomeCalculations[[#This Row],[SwitchP2]]="Y",R15*$I$5,0),0) -> 136904.24 | S16: =JobHopping[[#This Row],[SwitchP1Static]] -> Y | T16: =JobHopping[[#This Row],[SwitchP2Static]] -> Y
B17: 2039 | C17: =(TableIncomeCalculations[[#This Row],[NetMonthlySalaryP1]]*12) -> 315837.42 | D17: =(TableIncomeCalculations[[#This Row],[NetMonthlySalaryP2]]*12) -> 505591.56 | E17: =TableIncome[[#This Row],[SalaryP1]]*$I$7 -> 63167.484 | F17: =TableIncome[[#This Row],[SalaryP2]]*$I$7 -> 101118.31 | K17: =(TableIncome[[#This Row],[SalaryP1]]-TableIncome[[#This Row],[InvestmentP1]])/12 -> 21055.828 | L17: =(TableIncome[[#This Row],[SalaryP2]]-TableIncome[[#This Row],[InvestmentP2]])/12 -> 33706.104 | M17: ='Net Salary P1'!BI16 -> 26319.785 | N17: ='Net Salary P2'!BI16 -> 42132.63 | O17: =IF(_xlfn.XLOOKUP(TableIncome[[#This Row],[Year]],Loop!C:C,Loop!D:D)<75,(O16*(1+$I$4))+IF(TableIncomeCalculations[[#This Row],[SwitchP1]]="Y",O16*$I$6,0),0) -> 48396.879 | P17: =IF(_xlfn.XLOOKUP(TableIncome[[#This Row],[Year]],Loop!C:C,Loop!E:E)<75,(P16*(1+$I$4))+IF(TableIncomeCalculations[[#This Row],[SwitchP2]]="Y",P16*$I$6,0),0) -> 81224.594 | Q17: =IF(_xlfn.XLOOKUP(TableIncome[[#This Row],[Year]],Loop!C:C,Loop!D:D)<75,(Q16*(1+$I$3))+IF(TableIncomeCalculations[[#This Row],[SwitchP1]]="Y",Q16*$I$5,0),0) -> 84020.24 | R17: =IF(_xlfn.XLOOKUP(TableIncome[[#This Row],[Year]],Loop!C:C,Loop!E:E)<75,(R16*(1+$I$3))+IF(TableIncomeCalculations[[#This Row],[SwitchP2]]="Y",R16*$I$5,0),0) -> 141011.36 | S17: =JobHopping[[#This Row],[SwitchP1Static]] -> N | T17: =JobHopping[[#This Row],[SwitchP2Static]] -> N
B18: 2040 | C18: =(TableIncomeCalculations[[#This Row],[NetMonthlySalaryP1]]*12) -> 315837.42 | D18: =(TableIncomeCalculations[[#This Row],[NetMonthlySalaryP2]]*12) -> 505591.56 | E18: =TableIncome[[#This Row],[SalaryP1]]*$I$7 -> 63167.484 | F18: =TableIncome[[#This Row],[SalaryP2]]*$I$7 -> 101118.31 | K18: =(TableIncome[[#This Row],[SalaryP1]]-TableIncome[[#This Row],[InvestmentP1]])/12 -> 21055.828 | L18: =(TableIncome[[#This Row],[SalaryP2]]-TableIncome[[#This Row],[InvestmentP2]])/12 -> 33706.104 | M18: ='Net Salary P1'!BI17 -> 26319.785 | N18: ='Net Salary P2'!BI17 -> 42132.63 | O18: =IF(_xlfn.XLOOKUP(TableIncome[[#This Row],[Year]],Loop!C:C,Loop!D:D)<75,(O17*(1+$I$4))+IF(TableIncomeCalculations[[#This Row],[SwitchP1]]="Y",O17*$I$6,0),0) -> 48396.879 | P18: =IF(_xlfn.XLOOKUP(TableIncome[[#This Row],[Year]],Loop!C:C,Loop!E:E)<75,(P17*(1+$I$4))+IF(TableIncomeCalculations[[#This Row],[SwitchP2]]="Y",P17*$I$6,0),0) -> 81224.594 | Q18: =IF(_xlfn.XLOOKUP(TableIncome[[#This Row],[Year]],Loop!C:C,Loop!D:D)<75,(Q17*(1+$I$3))+IF(TableIncomeCalculations[[#This Row],[SwitchP1]]="Y",Q17*$I$5,0),0) -> 86540.847 | R18: =IF(_xlfn.XLOOKUP(TableIncome[[#This Row],[Year]],Loop!C:C,Loop!E:E)<75,(R17*(1+$I$3))+IF(TableIncomeCalculations[[#This Row],[SwitchP2]]="Y",R17*$I$5,0),0) -> 145241.71 | S18: =JobHopping[[#This Row],[SwitchP1Static]] -> N | T18: =JobHopping[[#This Row],[SwitchP2Static]] -> N
B19: 2041 | C19: =(TableIncomeCalculations[[#This Row],[NetMonthlySalaryP1]]*12) -> 315837.42 | D19: =(TableIncomeCalculations[[#This Row],[NetMonthlySalaryP2]]*12) -> 505591.56 | E19: =TableIncome[[#This Row],[SalaryP1]]*$I$7 -> 63167.484 | F19: =TableIncome[[#This Row],[SalaryP2]]*$I$7 -> 101118.31 | K19: =(TableIncome[[#This Row],[SalaryP1]]-TableIncome[[#This Row],[InvestmentP1]])/12 -> 21055.828 | L19: =(TableIncome[[#This Row],[SalaryP2]]-TableIncome[[#This Row],[InvestmentP2]])/12 -> 33706.104 | M19: ='Net Salary P1'!BI18 -> 26319.785 | N19: ='Net Salary P2'!BI18 -> 42132.63 | O19: =IF(_xlfn.XLOOKUP(TableIncome[[#This Row],[Year]],Loop!C:C,Loop!D:D)<75,(O18*(1+$I$4))+IF(TableIncomeCalculations[[#This Row],[SwitchP1]]="Y",O18*$I$6,0),0) -> 48396.879 | P19: =IF(_xlfn.XLOOKUP(TableIncome[[#This Row],[Year]],Loop!C:C,Loop!E:E)<75,(P18*(1+$I$4))+IF(TableIncomeCalculations[[#This Row],[SwitchP2]]="Y",P18*$I$6,0),0) -> 81224.594 | Q19: =IF(_xlfn.XLOOKUP(TableIncome[[#This Row],[Year]],Loop!C:C,Loop!D:D)<75,(Q18*(1+$I$3))+IF(TableIncomeCalculations[[#This Row],[SwitchP1]]="Y",Q18*$I$5,0),0) -> 89137.073 | R19: =IF(_xlfn.XLOOKUP(TableIncome[[#This Row],[Year]],Loop!C:C,Loop!E:E)<75,(R18*(1+$I$3))+IF(TableIncomeCalculations[[#This Row],[SwitchP2]]="Y",R18*$I$5,0),0) -> 149598.96 | S19: =JobHopping[[#This Row],[SwitchP1Static]] -> N | T19: =JobHopping[[#This Row],[SwitchP2Static]] -> N
... B48: 2070 | C48: =(TableIncomeCalculations[[#This Row],[NetMonthlySalaryP1]]*12) -> 345484.9 | D48: =(TableIncomeCalculations[[#This Row],[NetMonthlySalaryP2]]*12) -> 0 | E48: =TableIncome[[#This Row],[SalaryP1]]*$I$7 -> 69096.981 | F48: =TableIncome[[#This Row],[SalaryP2]]*$I$7 -> 0 | K48: =(TableIncome[[#This Row],[SalaryP1]]-TableIncome[[#This Row],[InvestmentP1]])/12 -> 23032.327 | L48: =(TableIncome[[#This Row],[SalaryP2]]-TableIncome[[#This Row],[InvestmentP2]])/12 -> 0 | M48: ='Net Salary P1'!BI47 -> 28790.409 | N48: ='Net Salary P2'!BI47 -> 0 | O48: =IF(_xlfn.XLOOKUP(TableIncome[[#This Row],[Year]],Loop!C:C,Loop!D:D)<75,(O47*(1+$I$4))+IF(TableIncomeCalculations[[#This Row],[SwitchP1]]="Y",O47*$I$6,0),0) -> 52884.576 | P48: =IF(_xlfn.XLOOKUP(TableIncome[[#This Row],[Year]],Loop!C:C,Loop!E:E)<75,(P47*(1+$I$4))+IF(TableIncomeCalculations[[#This Row],[SwitchP2]]="Y",P47*$I$6,0),0) -> 0 | Q48: =IF(_xlfn.XLOOKUP(TableIncome[[#This Row],[Year]],Loop!C:C,Loop!D:D)<75,(Q47*(1+$I$3))+IF(TableIncomeCalculations[[#This Row],[SwitchP1]]="Y",Q47*$I$5,0),0) -> 248946.32 | R48: =IF(_xlfn.XLOOKUP(TableIncome[[#This Row],[Year]],Loop!C:C,Loop!E:E)<75,(R47*(1+$I$3))+IF(TableIncomeCalculations[[#This Row],[SwitchP2]]="Y",R47*$I$5,0),0) -> 0 | S48: =JobHopping[[#This Row],[SwitchP1Static]] -> N | T48: =JobHopping[[#This Row],[SwitchP2Static]] -> N
B49: 2071 | C49: =(TableIncomeCalculations[[#This Row],[NetMonthlySalaryP1]]*12) -> 345484.9 | D49: =(TableIncomeCalculations[[#This Row],[NetMonthlySalaryP2]]*12) -> 0 | E49: =TableIncome[[#This Row],[SalaryP1]]*$I$7 -> 69096.981 | F49: =TableIncome[[#This Row],[SalaryP2]]*$I$7 -> 0 | K49: =(TableIncome[[#This Row],[SalaryP1]]-TableIncome[[#This Row],[InvestmentP1]])/12 -> 23032.327 | L49: =(TableIncome[[#This Row],[SalaryP2]]-TableIncome[[#This Row],[InvestmentP2]])/12 -> 0 | M49: ='Net Salary P1'!BI48 -> 28790.409 | N49: ='Net Salary P2'!BI48 -> 0 | O49: =IF(_xlfn.XLOOKUP(TableIncome[[#This Row],[Year]],Loop!C:C,Loop!D:D)<75,(O48*(1+$I$4))+IF(TableIncomeCalculations[[#This Row],[SwitchP1]]="Y",O48*$I$6,0),0) -> 52884.576 | P49: =IF(_xlfn.XLOOKUP(TableIncome[[#This Row],[Year]],Loop!C:C,Loop!E:E)<75,(P48*(1+$I$4))+IF(TableIncomeCalculations[[#This Row],[SwitchP2]]="Y",P48*$I$6,0),0) -> 0 | Q49: =IF(_xlfn.XLOOKUP(TableIncome[[#This Row],[Year]],Loop!C:C,Loop!D:D)<75,(Q48*(1+$I$3))+IF(TableIncomeCalculations[[#This Row],[SwitchP1]]="Y",Q48*$I$5,0),0) -> 256414.71 | S49: =JobHopping[[#This Row],[SwitchP1Static]] -> N | T49: =JobHopping[[#This Row],[SwitchP2Static]] -> N
B50: 2072 | C50: =(TableIncomeCalculations[[#This Row],[NetMonthlySalaryP1]]*12) -> 345484.9 | D50: =(TableIncomeCalculations[[#This Row],[NetMonthlySalaryP2]]*12) -> 0 | E50: =TableIncome[[#This Row],[SalaryP1]]*$I$7 -> 69096.981 | F50: =TableIncome[[#This Row],[SalaryP2]]*$I$7 -> 0 | K50: =(TableIncome[[#This Row],[SalaryP1]]-TableIncome[[#This Row],[InvestmentP1]])/12 -> 23032.327 | L50: =(TableIncome[[#This Row],[SalaryP2]]-TableIncome[[#This Row],[InvestmentP2]])/12 -> 0 | M50: ='Net Salary P1'!BI49 -> 28790.409 | N50: ='Net Salary P2'!BI49 -> 0 | O50: =IF(_xlfn.XLOOKUP(TableIncome[[#This Row],[Year]],Loop!C:C,Loop!D:D)<75,(O49*(1+$I$4))+IF(TableIncomeCalculations[[#This Row],[SwitchP1]]="Y",O49*$I$6,0),0) -> 52884.576 | P50: =IF(_xlfn.XLOOKUP(TableIncome[[#This Row],[Year]],Loop!C:C,Loop!E:E)<75,(P49*(1+$I$4))+IF(TableIncomeCalculations[[#This Row],[SwitchP2]]="Y",P49*$I$6,0),0) -> 0 | Q50: =IF(_xlfn.XLOOKUP(TableIncome[[#This Row],[Year]],Loop!C:C,Loop!D:D)<75,(Q49*(1+$I$3))+IF(TableIncomeCalculations[[#This Row],[SwitchP1]]="Y",Q49*$I$5,0),0) -> 264107.15 | S50: =JobHopping[[#This Row],[SwitchP1Static]] -> N | T50: =JobHopping[[#This Row],[SwitchP2Static]] -> N
B51: 2073 | C51: =(TableIncomeCalculations[[#This Row],[NetMonthlySalaryP1]]*12) -> 345484.9 | D51: =(TableIncomeCalculations[[#This Row],[NetMonthlySalaryP2]]*12) -> 0 | E51: =TableIncome[[#This Row],[SalaryP1]]*$I$7 -> 69096.981 | F51: =TableIncome[[#This Row],[SalaryP2]]*$I$7 -> 0 | K51: =(TableIncome[[#This Row],[SalaryP1]]-TableIncome[[#This Row],[InvestmentP1]])/12 -> 23032.327 | L51: =(TableIncome[[#This Row],[SalaryP2]]-TableIncome[[#This Row],[InvestmentP2]])/12 -> 0 | M51: ='Net Salary P1'!BI50 -> 28790.409 | N51: ='Net Salary P2'!BI50 -> 0 | O51: =IF(_xlfn.XLOOKUP(TableIncome[[#This Row],[Year]],Loop!C:C,Loop!D:D)<75,(O50*(1+$I$4))+IF(TableIncomeCalculations[[#This Row],[SwitchP1]]="Y",O50*$I$6,0),0) -> 52884.576 | P51: =IF(_xlfn.XLOOKUP(TableIncome[[#This Row],[Year]],Loop!C:C,Loop!E:E)<75,(P50*(1+$I$4))+IF(TableIncomeCalculations[[#This Row],[SwitchP2]]="Y",P50*$I$6,0),0) -> 0 | Q51: =IF(_xlfn.XLOOKUP(TableIncome[[#This Row],[Year]],Loop!C:C,Loop!D:D)<75,(Q50*(1+$I$3))+IF(TableIncomeCalculations[[#This Row],[SwitchP1]]="Y",Q50*$I$5,0),0) -> 272030.36 | S51: =JobHopping[[#This Row],[SwitchP1Static]] -> N | T51: =JobHopping[[#This Row],[SwitchP2Static]] -> N
B52: 2074 | C52: =(TableIncomeCalculations[[#This Row],[NetMonthlySalaryP1]]*12) -> 345484.9 | D52: =(TableIncomeCalculations[[#This Row],[NetMonthlySalaryP2]]*12) -> 0 | E52: =TableIncome[[#This Row],[SalaryP1]]*$I$7 -> 69096.981 | F52: =TableIncome[[#This Row],[SalaryP2]]*$I$7 -> 0 | K52: =(TableIncome[[#This Row],[SalaryP1]]-TableIncome[[#This Row],[InvestmentP1]])/12 -> 23032.327 | L52: =(TableIncome[[#This Row],[SalaryP2]]-TableIncome[[#This Row],[InvestmentP2]])/12 -> 0 | M52: ='Net Salary P1'!BI51 -> 28790.409 | N52: ='Net Salary P2'!BI51 -> 0 | O52: =IF(_xlfn.XLOOKUP(TableIncome[[#This Row],[Year]],Loop!C:C,Loop!D:D)<75,(O51*(1+$I$4))+IF(TableIncomeCalculations[[#This Row],[SwitchP1]]="Y",O51*$I$6,0),0) -> 52884.576 | P52: =IF(_xlfn.XLOOKUP(TableIncome[[#This Row],[Year]],Loop!C:C,Loop!E:E)<75,(P51*(1+$I$4))+IF(TableIncomeCalculations[[#This Row],[SwitchP2]]="Y",P51*$I$6,0),0) -> 0 | Q52: =IF(_xlfn.XLOOKUP(TableIncome[[#This Row],[Year]],Loop!C:C,Loop!D:D)<75,(Q51*(1+$I$3))+IF(TableIncomeCalculations[[#This Row],[SwitchP1]]="Y",Q51*$I$5,0),0) -> 280191.27 | S52: =JobHopping[[#This Row],[SwitchP1Static]] -> N | T52: =JobHopping[[#This Row],[SwitchP2Static]] -> N
B53: 2075 | C53: =(TableIncomeCalculations[[#This Row],[NetMonthlySalaryP1]]*12) -> 0 | D53: =(TableIncomeCalculations[[#This Row],[NetMonthlySalaryP2]]*12) -> 0 | E53: =TableIncome[[#This Row],[SalaryP1]]*$I$7 -> 0 | F53: =TableIncome[[#This Row],[SalaryP2]]*$I$7 -> 0 | K53: =(TableIncome[[#This Row],[SalaryP1]]-TableIncome[[#This Row],[InvestmentP1]])/12 -> 0 | L53: =(TableIncome[[#This Row],[SalaryP2]]-TableIncome[[#This Row],[InvestmentP2]])/12 -> 0 | M53: ='Net Salary P1'!BI52 -> 0 | N53: ='Net Salary P2'!BI52 -> 0 | O53: =IF(_xlfn.XLOOKUP(TableIncome[[#This Row],[Year]],Loop!C:C,Loop!D:D)<75,(O52*(1+$I$4))+IF(TableIncomeCalculations[[#This Row],[SwitchP1]]="Y",O52*$I$6,0),0) -> 0 | P53: =IF(_xlfn.XLOOKUP(TableIncome[[#This Row],[Year]],Loop!C:C,Loop!E:E)<75,(P52*(1+$I$4))+IF(TableIncomeCalculations[[#This Row],[SwitchP2]]="Y",P52*$I$6,0),0) -> 0 | Q53: =IF(_xlfn.XLOOKUP(TableIncome[[#This Row],[Year]],Loop!C:C,Loop!D:D)<75,(Q52*(1+$I$3))+IF(TableIncomeCalculations[[#This Row],[SwitchP1]]="Y",Q52*$I$5,0),0) -> 0 | S53: =JobHopping[[#This Row],[SwitchP1Static]] -> N | T53: =JobHopping[[#This Row],[SwitchP2Static]] -> N

Sheet Pensions P1
A1: Year | B1: 2025 | C1: 2026 | D1: 2027 | E1: 2028 | F1: 2029 | G1: 2030 | H1: 2031 | I1: 2032 | J1: 2033 | K1: 2034 | L1: 2035 | M1: 2036 | N1: 2037 | O1: 2038 | P1: 2039 | Q1: 2040 | R1: 2041 | S1: 2042 | T1: 2043 | U1: 2044 | V1: 2045 | W1: 2046 | X1: 2047 | Y1: 2048 | Z1: 2049 | AA1: 2050 | AB1: 2051 | AC1: 2052 | AD1: 2053 | AE1: 2054 | AF1: 2055 | AG1: 2056 | AH1: 2057 | AI1: 2058 | AJ1: 2059 | AK1: 2060 | AL1: 2061 | AM1: 2062 | AN1: 2063 | AO1: 2064 | AP1: 2065 | AQ1: 2066 | AR1: 2067 | AS1: 2068 | AT1: 2069 | AU1: 2070 | AV1: 2071 | AW1: 2072 | AX1: 2073 | AY1: 2074
A2: Month Salary | B2: {=TRANSPOSE(Income!O3:O52)} -> 43000 | C2: 43000 | D2: 44290 | E2: 44290 | F2: 44290 | G2: 44290 | H2: 45618.7 | I2: 45618.7 | J2: 45618.7 | K2: 45618.7 | L2: 46987.261 | M2: 46987.261 | N2: 46987.261 | O2: 48396.879 | P2: 48396.879 | Q2: 48396.879 | R2: 48396.879 | S2: 48396.879 | T2: 49848.785 | U2: 49848.785 | V2: 49848.785 | W2: 49848.785 | X2: 51344.249 | Y2: 51344.249 | Z2: 51344.249 | AA2: 51344.249 | AB2: 51344.249 | AC2: 51344.249 | AD2: 51344.249 | AE2: 51344.249 | AF2: 51344.249 | AG2: 51344.249 | AH2: 51344.249 | AI2: 51344.249 | AJ2: 51344.249 | AK2: 52884.576 | AL2: 52884.576 | AM2: 52884.576 | AN2: 52884.576 | AO2: 52884.576 | AP2: 52884.576 | AQ2: 52884.576 | AR2: 52884.576 | AS2: 52884.576 | AT2: 52884.576 | AU2: 52884.576 | AV2: 52884.576 | AW2: 52884.576 | AX2: 52884.576 | AY2: 52884.576
A3: Personal Contribution (%) | B3: ='Salary Variables'!$C$12 -> 0.05 | C3: ='Salary Variables'!$C$12 -> 0.05 | D3: ='Salary Variables'!$C$12 -> 0.05 | E3: ='Salary Variables'!$C$12 -> 0.05 | F3: ='Salary Variables'!$C$12 -> 0.05 | G3: ='Salary Variables'!$C$12 -> 0.05 | H3: ='Salary Variables'!$C$12 -> 0.05 | I3: ='Salary Variables'!$C$12 -> 0.05 | ... AY3: ='Salary Variables'!$C$12 -> 0.05
A4: Personal Contribution | B4: =B3*B2 -> 2150 | C4: =C3*C2 -> 2150 | D4: =D3*D2 -> 2214.5 | E4: =E3*E2 -> 2214.5 | F4: =F3*F2 -> 2214.5 | G4: =G3*G2 -> 2214.5 | H4: =H3*H2 -> 2280.935 | I4: =I3*I2 -> 2280.935 | ... AY4: =AY3*AY2 -> 2644.2288
A5: Company Contribution (%) | B5: ='Salary Variables'!$C$13 -> 0.1 | C5: ='Salary Variables'!$C$13 -> 0.1 | D5: ='Salary Variables'!$C$13 -> 0.1 | E5: ='Salary Variables'!$C$13 -> 0.1 | F5: ='Salary Variables'!$C$13 -> 0.1 | G5: ='Salary Variables'!$C$13 -> 0.1 | H5: ='Salary Variables'!$C$13 -> 0.1 | I5: ='Salary Variables'!$C$13 -> 0.1 | ... AY5: ='Salary Variables'!$C$13 -> 0.1
A6: Company Contribution | B6: =B2*B5 -> 4300 | C6: =C4*2 -> 4300 | D6: =D4*2 -> 4429 | E6: =E4*2 -> 4429 | F6: =F4*2 -> 4429 | G6: =G4*2 -> 4429 | H6: =H4*2 -> 4561.87 | I6: =I4*2 -> 4561.87 | J6: =J4*2 -> 4561.87 | ... AY6: =AY4*2 -> 5288.4576
A7: Total Contribution (Monthly) | B7: =SUM(B6,B4) -> 6450 | C7: =SUM(C6,C4) -> 6450 | D7: =SUM(D6,D4) -> 6643.5 | E7: =SUM(E6,E4) -> 6643.5 | F7: =SUM(F6,F4) -> 6643.5 | G7: =SUM(G6,G4) -> 6643.5 | H7: =SUM(H6,H4) -> 6842.805 | I7: =SUM(I6,I4) -> 6842.805 | ... AY7: =SUM(AY6,AY4) -> 7932.6864
A8: Total Contribution (Yearly) | B8: =B7*12 -> 77400 | C8: =C7*12 -> 77400 | D8: =D7*12 -> 79722 | E8: =E7*12 -> 79722 | F8: =F7*12 -> 79722 | G8: =G7*12 -> 79722 | H8: =H7*12 -> 82113.66 | I8: =I7*12 -> 82113.66 | ... AY8: =AY7*12 -> 95192.237
A11: Aldersopsparing Total | B11: =AY54 -> 950809.37
A12: Divided by 25 | B12: =B11/25 -> 38032.375
A13: Monthly | B13: =B12/12 -> 3169.3646
A14: Taxed in retirement? | B14: No
A16: Total Contribution (Work Pension) | B16: =AY38 -> 8862704.8
A17: Divided by 25 years | B17: =B16/25 -> 354508.19 | C17: per year
A18: Monthly | B18: =B17/12 -> 29542.349 | C18: per month (gross)
A19: Taxed in Retirement? | B19: Yes | C19: Income tax
C21: base | D21: supplement
A22: Public Pension Average Monthly | B22: =C22 -> 7198 | C22: 7198 | D22: =8329*(1-30.9%) -> 5755.339
A23: Public Pension Average Yearly | B23: =B22*12 -> 86376
A24: Taxed in Retirement? | B24: Yes
A25: Inflation | B25: ='Salary Variables'!C2 -> 0.03
A26: Pension growth | B26: 0.03
A27: PAL tax | B27: 0.153
A29: ATP | B29: =AY47 -> 360498.36
A30: ATP Yearly | B30: =B29/25 -> 14419.934
A31: ATP Monthly | B31: =B30/12 -> 1201.6612
A33: Year | B33: 2025 | C33: 2026 | D33: 2027 | E33: 2028 | F33: 2029 | G33: 2030 | H33: 2031 | I33: 2032 | J33: 2033 | K33: 2034 | L33: 2035 | M33: 2036 | N33: 2037 | O33: 2038 | P33: 2039 | Q33: 2040 | R33: 2041 | S33: 2042 | T33: 2043 | U33: 2044 | V33: 2045 | W33: 2046 | X33: 2047 | Y33: 2048 | Z33: 2049 | AA33: 2050 | AB33: 2051 | AC33: 2052 | AD33: 2053 | AE33: 2054 | AF33: 2055 | AG33: 2056 | AH33: 2057 | AI33: 2058 | AJ33: 2059 | AK33: 2060 | AL33: 2061 | AM33: 2062 | AN33: 2063 | AO33: 2064 | AP33: 2065 | AQ33: 2066 | AR33: 2067 | AS33: 2068 | AT33: 2069 | AU33: 2070 | AV33: 2071 | AW33: 2072 | AX33: 2073 | AY33: 2074
A34: Work Pension Start of Year | B34: =B8 -> 77400 | C34: =B38+C8 -> 156766.73 | D34: =C38+D8 -> 240472.18 | E34: =D38+E8 -> 326304.57 | F34: =E38+F8 -> 414317.97 | G34: =F38+G8 -> 504567.79 | H34: =G38+H8 -> 599502.52 | I34: =H38+I8 -> 696849.54 | J34: =I38+J8 -> 796670.15 | ... AY34: =AX38+AY8 -> 8643084
A35: Work Pension growth (%) | B35: =$B$26 -> 0.03 | C35: =$B$26 -> 0.03 | D35: =$B$26 -> 0.03 | E35: =$B$26 -> 0.03 | F35: =$B$26 -> 0.03 | G35: =$B$26 -> 0.03 | H35: =$B$26 -> 0.03 | I35: =$B$26 -> 0.03 | ... AY35: =$B$26 -> 0.03
A36: Work pension growth | B36: =B35*B34 -> 2322 | C36: =C35*C34 -> 4703.002 | D36: =D35*D34 -> 7214.1653 | E36: =E35*E34 -> 9789.1372 | F36: =F35*F34 -> 12429.539 | G36: =G35*G34 -> 15137.034 | H36: =H35*H34 -> 17985.076 | I36: =I35*I34 -> 20905.486 | ... AY36: =AY35*AY34 -> 259292.52
A37: Tax | B37: =B36*$B$27 -> 355.266 | C37: =C36*$B$27 -> 719.55931 | D37: =D36*$B$27 -> 1103.7673 | E37: =E36*$B$27 -> 1497.738 | F37: =F36*$B$27 -> 1901.7195 | G37: =G36*$B$27 -> 2315.9662 | H37: =H36*$B$27 -> 2751.7166 | I37: =I36*$B$27 -> 3198.5394 | ... AY37: =AY36*$B$27 -> 39671.756
A38: Work Pension End of Year | B38: =B34+(B36-B37) -> 79366.734 | C38: =C34+(C36-C37) -> 160750.18 | D38: =D34+(D36-D37) -> 246582.57 | E38: =E34+(E36-E37) -> 334595.97 | F38: =F34+(F36-F37) -> 424845.79 | G38: =G34+(G36-G37) -> 517388.86 | H38: =H34+(H36-H37) -> 614735.88 | I38: =I34+(I36-I37) -> 714556.49 | ... AY38: =AY34+(AY36-AY37) -> 8862704.8
A40: Total Work Pension | B40: =AT38 -> 7364742.2
A42: ATP | B42: https://businessindenmark.virk.dk/guidance/atp-livslang-pension-bid/atp-employer/atp-contribution-rates2024/
A43: ATP start of year | B43: ='Net Salary P1'!B14*3 -> 3564 | C43: =B47+$B$43 -> 7218.5612 | D43: =C47+$B$43 -> 10965.985 | E43: =D47+$B$43 -> 14808.631 | F43: =E47+$B$43 -> 18748.918 | G43: =F47+$B$43 -> 22789.328 | H43: =G47+$B$43 -> 26932.405 | I43: =H47+$B$43 -> 31180.757 | J43: =I47+$B$43 -> 35537.06 | ... AY43: =AX47+$B$43 -> 351565.09
A44: Pension growth (%) | B44: =$B$26 -> 0.03 | C44: =$B$26 -> 0.03 | D44: =$B$26 -> 0.03 | E44: =$B$26 -> 0.03 | F44: =$B$26 -> 0.03 | G44: =$B$26 -> 0.03 | H44: =$B$26 -> 0.03 | I44: =$B$26 -> 0.03 | ... AY44: =$B$26 -> 0.03
A45: Pension growth | B45: =B44*B43 -> 106.92 | C45: =C44*C43 -> 216.55684 | D45: =D44*D43 -> 328.97955 | E45: =E44*E43 -> 444.25892 | F45: =F44*F43 -> 562.46754 | G45: =G44*G43 -> 683.67984 | H45: =H44*H43 -> 807.97214 | I45: =I44*I43 -> 935.42271 | ... AY45: =AY44*AY43 -> 10546.953
A46: Tax | B46: =B45*$B$27 -> 16.35876 | C46: =C45*$B$27 -> 33.133196 | D46: =D45*$B$27 -> 50.333871 | E46: =E45*$B$27 -> 67.971614 | F46: =F45*$B$27 -> 86.057533 | G46: =G45*$B$27 -> 104.60301 | H46: =H45*$B$27 -> 123.61974 | I46: =I45*$B$27 -> 143.11968 | ... AY46: =AY45*$B$27 -> 1613.6838
A47: Post Tax | B47: =B43+(B45-B46) -> 3654.5612 | C47: =C43+(C45-C46) -> 7401.9849 | D47: =D43+(D45-D46) -> 11244.631 | E47: =E43+(E45-E46) -> 15184.918 | F47: =F43+(F45-F46) -> 19225.328 | G47: =G43+(G45-G46) -> 23368.405 | H47: =H43+(H45-H46) -> 27616.757 | I47: =I43+(I45-I46) -> 31973.06 | ... AY47: =AY43+(AY45-AY46) -> 360498.36
A49: Aldersopsparing
A50: Start of year | B50: ='Net Salary P1'!$B$2 -> 9400 | C50: =B54+$B$50 -> 19038.854 | D50: =C54+$B$50 -> 28922.631 | E50: =D54+$B$50 -> 39057.555 | F50: =E54+$B$50 -> 49450.008 | G50: =F54+$B$50 -> 60106.533 | H50: =G54+$B$50 -> 71033.84 | I50: =H54+$B$50 -> 82238.809 | J50: =I54+$B$50 -> 93728.498 | ... AY50: =AX54+$B$50 -> 927248
A51: Pension growth (%) | B51: =$B$26 -> 0.03 | C51: =$B$26 -> 0.03 | D51: =$B$26 -> 0.03 | E51: =$B$26 -> 0.03 | F51: =$B$26 -> 0.03 | G51: =$B$26 -> 0.03 | H51: =$B$26 -> 0.03 | I51: =$B$26 -> 0.03 | ... AY51: =$B$26 -> 0.03
A52: Pension growth | B52: =B51*B50 -> 282 | C52: =C51*C50 -> 571.16562 | D52: =D51*D50 -> 867.67894 | E52: =E51*E50 -> 1171.7267 | F52: =F51*F50 -> 1483.5002 | G52: =G51*G50 -> 1803.196 | H52: =H51*H50 -> 2131.0152 | I52: =I51*I50 -> 2467.1643 | ... AY52: =AY51*AY50 -> 27817.44
A53: Tax | B53: =B52*$B$27 -> 43.146 | C53: =C52*$B$27 -> 87.38834 | D53: =D52*$B$27 -> 132.75488 | E53: =E52*$B$27 -> 179.27418 | F53: =F52*$B$27 -> 226.97554 | G53: =G52*$B$27 -> 275.88898 | H53: =H52*$B$27 -> 326.04532 | I53: =I52*$B$27 -> 377.47614 | ... AY53: =AY52*$B$27 -> 4256.0683
A54: Post Tax | B54: =B50+(B52-B53) -> 9638.854 | C54: =C50+(C52-C53) -> 19522.631 | D54: =D50+(D52-D53) -> 29657.555 | E54: =E50+(E52-E53) -> 40050.008 | F54: =F50+(F52-F53) -> 50706.533 | G54: =G50+(G52-G53) -> 61633.84 | H54: =H50+(H52-H53) -> 72838.809 | I54: =I50+(I52-I53) -> 84328.498 | ... AY54: =AY50+(AY52-AY53) -> 950809.37

Sheet Pensions P2
A1: Year | B1: 2010 | C1: 2011 | D1: 2012 | E1: 2013 | F1: 2014 | G1: 2015 | H1: 2016 | I1: 2017 | J1: 2018 | K1: 2019 | L1: 2020 | M1: 2021 | N1: 2022 | O1: 2023 | P1: 2024 | Q1: 2025 | R1: 2026 | S1: 2027 | T1: 2028 | U1: 2029 | V1: 2030 | W1: 2031 | X1: 2032 | Y1: 2033 | Z1: 2034 | AA1: 2035 | AB1: 2036 | AC1: 2037 | AD1: 2038 | AE1: 2039 | AF1: 2040 | AG1: 2041 | AH1: 2042 | AI1: 2043 | AJ1: 2044 | AK1: 2045 | AL1: 2046 | AM1: 2047 | AN1: 2048 | AO1: 2049 | AP1: 2050 | AQ1: 2051 | AR1: 2052 | AS1: 2053 | AT1: 2054 | AU1: 2055 | AV1: 2056 | AW1: 2057 | AX1: 2058 | AY1: 2059
A2: Month Salary | B2: {=TRANSPOSE('Income - P2 Helper'!N3:N17)} -> 63888.926 | C2: 63888.926 | D2: 63888.926 | E2: 65864.872 | F2: 65864.872 | G2: 65864.872 | H2: 65864.872 | I2: 67901.93 | J2: 67901.93 | K2: 67901.93 | L2: 67901.93 | M2: 70001.99 | N2: 70001.99 | O2: 70001.99 | P2: 72167 | Q2: {=TRANSPOSE(Income!P3:P37)} -> 72167 | R2: 72167 | S2: 74332.01 | T2: 74332.01 | U2: 74332.01 | V2: 74332.01 | W2: 76561.97 | X2: 76561.97 | Y2: 76561.97 | Z2: 76561.97 | AA2: 78858.829 | AB2: 78858.829 | AC2: 78858.829 | AD2: 81224.594 | AE2: 81224.594 | AF2: 81224.594 | AG2: 81224.594 | AH2: 81224.594 | AI2: 83661.332 | AJ2: 83661.332 | AK2: 83661.332 | AL2: 83661.332 | AM2: 86171.172 | AN2: 86171.172 | AO2: 86171.172 | AP2: 86171.172 | AQ2: 86171.172 | AR2: 86171.172 | AS2: 86171.172 | AT2: 86171.172 | AU2: 86171.172 | AV2: 86171.172 | AW2: 86171.172 | AX2: 86171.172 | AY2: 86171.172
A3: Personal Contribution (%) | B3: ='Salary Variables'!$C$12 -> 0.05 | C3: ='Salary Variables'!$C$12 -> 0.05 | D3: ='Salary Variables'!$C$12 -> 0.05 | E3: ='Salary Variables'!$C$12 -> 0.05 | F3: ='Salary Variables'!$C$12 -> 0.05 | G3: ='Salary Variables'!$C$12 -> 0.05 | H3: ='Salary Variables'!$C$12 -> 0.05 | I3: ='Salary Variables'!$C$12 -> 0.05 | ... AY3: ='Salary Variables'!$C$12 -> 0.05
A4: Personal Contribution | B4: =B3*B2 -> 3194.4463 | C4: =C3*C2 -> 3194.4463 | D4: =D3*D2 -> 3194.4463 | E4: =E3*E2 -> 3293.2436 | F4: =F3*F2 -> 3293.2436 | G4: =G3*G2 -> 3293.2436 | H4: =H3*H2 -> 3293.2436 | I4: =I3*I2 -> 3395.0965 | ... AY4: =AY3*AY2 -> 4308.5586
A5: Company Contribution (%) | B5: ='Salary Variables'!$C$13 -> 0.1 | C5: ='Salary Variables'!$C$13 -> 0.1 | D5: ='Salary Variables'!$C$13 -> 0.1 | E5: ='Salary Variables'!$C$13 -> 0.1 | F5: ='Salary Variables'!$C$13 -> 0.1 | G5: ='Salary Variables'!$C$13 -> 0.1 | H5: ='Salary Variables'!$C$13 -> 0.1 | I5: ='Salary Variables'!$C$13 -> 0.1 | ... AY5: ='Salary Variables'!$C$13 -> 0.1
A6: Company Contribution | B6: =B2*B5 -> 6388.8926 | C6: =C4*2 -> 6388.8926 | D6: =D4*2 -> 6388.8926 | E6: =E4*2 -> 6586.4872 | F6: =F4*2 -> 6586.4872 | G6: =G4*2 -> 6586.4872 | H6: =H4*2 -> 6586.4872 | I6: =I4*2 -> 6790.193 | J6: =J4*2 -> 6790.193 | ... AY6: =AY4*2 -> 8617.1172
A7: Total Contribution (Monthly) | B7: =SUM(B6,B4) -> 9583.3389 | C7: =SUM(C6,C4) -> 9583.3389 | D7: =SUM(D6,D4) -> 9583.3389 | E7: =SUM(E6,E4) -> 9879.7309 | F7: =SUM(F6,F4) -> 9879.7309 | G7: =SUM(G6,G4) -> 9879.7309 | H7: =SUM(H6,H4) -> 9879.7309 | I7: =SUM(I6,I4) -> 10185.29 | ... AY7: =SUM(AY6,AY4) -> 12925.676
A8: Total Contribution (Yearly) | B8: =B7*12 -> 115000.07 | C8: =C7*12 -> 115000.07 | D8: =D7*12 -> 115000.07 | E8: =E7*12 -> 118556.77 | F8: =F7*12 -> 118556.77 | G8: =G7*12 -> 118556.77 | H8: =H7*12 -> 118556.77 | I8: =I7*12 -> 122223.47 | ... AY8: =AY7*12 -> 155108.11
A11: Aldersopsparing Total | B11: =AY54 -> 950809.37
A12: Divided by 25 | B12: =B11/25 -> 38032.375
A13: Monthly | B13: =B12/12 -> 3169.3646
A14: Taxed in retirement? | B14: No
A16: Total Contribution (Work Pension) | B16: =AY38 -> 13539717
A17: Divided by 25 years | B17: =B16/25 -> 541588.69 | C17: per year
A18: Monthly | B18: =B17/12 -> 45132.391 | C18: per month (gross)
A19: Taxed in Retirement? | B19: Yes | C19: Income tax
C21: base | D21: supplement
A22: Public Pension Average Monthly | B22: =C22 -> 7198 | C22: 7198 | D22: =8329*(1-30.9%) -> 5755.339
A23: Public Pension Average Yearly | B23: =B22*12 -> 86376
A24: Taxed in Retirement? | B24: Yes
A25: Inflation | B25: ='Salary Variables'!C2 -> 0.03
A26: Pension growth | B26: 0.03
A27: PAL tax | B27: 0.153
A29: ATP | B29: =AY47 -> 360498.36
A30: ATP Yearly | B30: =B29/25 -> 14419.934
A31: ATP Monthly | B31: =B30/12 -> 1201.6612
A33: Year | B33: 2010 | C33: 2011 | D33: 2012 | E33: 2013 | F33: 2014 | G33: 2015 | H33: 2016 | I33: 2017 | J33: 2018 | K33: 2019 | L33: 2020 | M33: 2021 | N33: 2022 | O33: 2023 | P33: 2024 | Q33: 2025 | R33: 2026 | S33: 2027 | T33: 2028 | U33: 2029 | V33: 2030 | W33: 2031 | X33: 2032 | Y33: 2033 | Z33: 2034 | AA33: 2035 | AB33: 2036 | AC33: 2037 | AD33: 2038 | AE33: 2039 | AF33: 2040 | AG33: 2041 | AH33: 2042 | AI33: 2043 | AJ33: 2044 | AK33: 2045 | AL33: 2046 | AM33: 2047 | AN33: 2048 | AO33: 2049 | AP33: 2050 | AQ33: 2051 | AR33: 2052 | AS33: 2053 | AT33: 2054 | AU33: 2055 | AV33: 2056 | AW33: 2057 | AX33: 2058 | AY33: 2059
A34: Work Pension Start of Year | B34: =B8 -> 115000.07 | C34: =B38+C8 -> 232922.29 | D34: =C38+D8 -> 353840.91 | E34: =D38+E8 -> 481388.78 | F34: =E38+F8 -> 612177.64 | G34: =F38+G8 -> 746289.84 | H34: =G38+H8 -> 883809.83 | I34: =H38+I8 -> 1028490.9 | J34: =I38+J8 -> 1176848.3 | ... AY34: =AX38+AY8 -> 13204199
A35: Work Pension growth (%) | B35: =$B$26 -> 0.03 | C35: =$B$26 -> 0.03 | D35: =$B$26 -> 0.03 | E35: =$B$26 -> 0.03 | F35: =$B$26 -> 0.03 | G35: =$B$26 -> 0.03 | H35: =$B$26 -> 0.03 | I35: =$B$26 -> 0.03 | ... AY35: =$B$26 -> 0.03
A36: Work pension growth | B36: =B35*B34 -> 3450.002 | C36: =C35*C34 -> 6987.6686 | D36: =D35*D34 -> 10615.227 | E36: =E35*E34 -> 14441.663 | F36: =F35*F34 -> 18365.329 | G36: =G35*G34 -> 22388.695 | H36: =H35*H34 -> 26514.295 | I36: =I35*I34 -> 30854.728 | ... AY36: =AY35*AY34 -> 396125.96
A37: Tax | B37: =B36*$B$27 -> 527.85031 | C37: =C36*$B$27 -> 1069.1133 | D37: =D36*$B$27 -> 1624.1298 | E37: =E36*$B$27 -> 2209.5745 | F37: =F36*$B$27 -> 2809.8953 | G37: =G36*$B$27 -> 3425.4704 | H37: =H36*$B$27 -> 4056.6871 | I37: =I36*$B$27 -> 4720.7733 | ... AY37: =AY36*$B$27 -> 60607.271
A38: Work Pension End of Year | B38: =B34+(B36-B37) -> 117922.22 | C38: =C34+(C36-C37) -> 238840.84 | D38: =D34+(D36-D37) -> 362832.01 | E38: =E34+(E36-E37) -> 493620.87 | F38: =F34+(F36-F37) -> 627733.07 | G38: =G34+(G36-G37) -> 765253.06 | H38: =H34+(H36-H37) -> 906267.44 | I38: =I34+(I36-I37) -> 1054624.9 | ... AY38: =AY34+(AY36-AY37) -> 13539717
A42: ATP | B42: https://businessindenmark.virk.dk/guidance/atp-livslang-pension-bid/atp-employer/atp-contribution-rates2024/
A43: ATP start of year | B43: ='Net Salary P2'!B14*3 -> 3564 | C43: =B47+$B$43 -> 7218.5612 | D43: =C47+$B$43 -> 10965.985 | E43: =D47+$B$43 -> 14808.631 | F43: =E47+$B$43 -> 18748.918 | G43: =F47+$B$43 -> 22789.328 | H43: =G47+$B$43 -> 26932.405 | I43: =H47+$B$43 -> 31180.757 | J43: =I47+$B$43 -> 35537.06 | ... AY43: =AX47+$B$43 -> 351565.09
A44: Pension growth (%) | B44: =$B$26 -> 0.03 | C44: =$B$26 -> 0.03 | D44: =$B$26 -> 0.03 | E44: =$B$26 -> 0.03 | F44: =$B$26 -> 0.03 | G44: =$B$26 -> 0.03 | H44: =$B$26 -> 0.03 | I44: =$B$26 -> 0.03 | ... AY44: =$B$26 -> 0.03
A45: Pension growth | B45: =B44*B43 -> 106.92 | C45: =C44*C43 -> 216.55684 | D45: =D44*D43 -> 328.97955 | E45: =E44*E43 -> 444.25892 | F45: =F44*F43 -> 562.46754 | G45: =G44*G43 -> 683.67984 | H45: =H44*H43 -> 807.97214 | I45: =I44*I43 -> 935.42271 | ... AY45: =AY44*AY43 -> 10546.953
A46: Tax | B46: =B45*$B$27 -> 16.35876 | C46: =C45*$B$27 -> 33.133196 | D46: =D45*$B$27 -> 50.333871 | E46: =E45*$B$27 -> 67.971614 | F46: =F45*$B$27 -> 86.057533 | G46: =G45*$B$27 -> 104.60301 | H46: =H45*$B$27 -> 123.61974 | I46: =I45*$B$27 -> 143.11968 | ... AY46: =AY45*$B$27 -> 1613.6838
A47: Post Tax | B47: =B43+(B45-B46) -> 3654.5612 | C47: =C43+(C45-C46) -> 7401.9849 | D47: =D43+(D45-D46) -> 11244.631 | E47: =E43+(E45-E46) -> 15184.918 | F47: =F43+(F45-F46) -> 19225.328 | G47: =G43+(G45-G46) -> 23368.405 | H47: =H43+(H45-H46) -> 27616.757 | I47: =I43+(I45-I46) -> 31973.06 | ... AY47: =AY43+(AY45-AY46) -> 360498.36
A49: Aldersopsparing
A50: Start of year | B50: ='Net Salary P2'!$B$2 -> 9400 | C50: =B54+$B$50 -> 19038.854 | D50: =C54+$B$50 -> 28922.631 | E50: =D54+$B$50 -> 39057.555 | F50: =E54+$B$50 -> 49450.008 | G50: =F54+$B$50 -> 60106.533 | H50: =G54+$B$50 -> 71033.84 | I50: =H54+$B$50 -> 82238.809 | J50: =I54+$B$50 -> 93728.498 | ... AY50: =AX54+$B$50 -> 927248
A51: Pension growth (%) | B51: =$B$26 -> 0.03 | C51: =$B$26 -> 0.03 | D51: =$B$26 -> 0.03 | E51: =$B$26 -> 0.03 | F51: =$B$26 -> 0.03 | G51: =$B$26 -> 0.03 | H51: =$B$26 -> 0.03 | I51: =$B$26 -> 0.03 | ... AY51: =$B$26 -> 0.03
A52: Pension growth | B52: =B51*B50 -> 282 | C52: =C51*C50 -> 571.16562 | D52: =D51*D50 -> 867.67894 | E52: =E51*E50 -> 1171.7267 | F52: =F51*F50 -> 1483.5002 | G52: =G51*G50 -> 1803.196 | H52: =H51*H50 -> 2131.0152 | I52: =I51*I50 -> 2467.1643 | ... AY52: =AY51*AY50 -> 27817.44
A53: Tax | B53: =B52*$B$27 -> 43.146 | C53: =C52*$B$27 -> 87.38834 | D53: =D52*$B$27 -> 132.75488 | E53: =E52*$B$27 -> 179.27418 | F53: =F52*$B$27 -> 226.97554 | G53: =G52*$B$27 -> 275.88898 | H53: =H52*$B$27 -> 326.04532 | I53: =I52*$B$27 -> 377.47614 | ... AY53: =AY52*$B$27 -> 4256.0683
A54: Post Tax | B54: =B50+(B52-B53) -> 9638.854 | C54: =C50+(C52-C53) -> 19522.631 | D54: =D50+(D52-D53) -> 29657.555 | E54: =E50+(E52-E53) -> 40050.008 | F54: =F50+(F52-F53) -> 50706.533 | G54: =G50+(G52-G53) -> 61633.84 | H54: =H50+(H52-H53) -> 72838.809 | I54: =I50+(I52-I53) -> 84328.498 | ... AY54: =AY50+(AY52-AY53) -> 950809.37

Sheet Net Salary P2
A1: Inflation | B1: ='Salary Variables'!$C$2 -> 0.03 | D1: Year | E1: 2010 | F1: 2011 | G1: 2012 | H1: 2013 | I1: 2014 | J1: 2015 | K1: 2016 | L1: 2017 | M1: 2018 | N1: 2019 | O1: 2020 | P1: 2021 | Q1: 2022 | R1: 2023 | S1: 2024 | T1: 2025 | U1: 2026 | V1: 2027 | W1: 2028 | X1: 2029 | Y1: 2030 | Z1: 2031 | AA1: 2032 | AB1: 2033 | AC1: 2034 | AD1: 2035 | AE1: 2036 | AF1: 2037 | AG1: 2038 | AH1: 2039 | AI1: 2040 | AJ1: 2041 | AK1: 2042 | AL1: 2043 | AM1: 2044 | AN1: 2045 | AO1: 2046 | AP1: 2047 | AQ1: 2048 | AR1: 2049 | AS1: 2050 | AT1: 2051 | AU1: 2052 | AV1: 2053 | AW1: 2054 | AX1: 2055 | AY1: 2056 | AZ1: 2057 | BA1: 2058 | BB1: 2059
A2: Aldersopsparing max | B2: ='Salary Variables'!$C$14 -> 9400 | D2: Month Salary (Inflation Adjusted) | E2: {=TRANSPOSE('Income - P2 Helper'!N3:N17)} -> 63888.926 | F2: 63888.926 | G2: 63888.926 | H2: 65864.872 | I2: 65864.872 | J2: 65864.872 | K2: 65864.872 | L2: 67901.93 | M2: 67901.93 | N2: 67901.93 | O2: 67901.93 | P2: 70001.99 | Q2: 70001.99 | R2: 70001.99 | S2: 72167 | T2: {=TRANSPOSE(Income!P3:P37)} -> 72167 | U2: 72167 | V2: 74332.01 | W2: 74332.01 | X2: 74332.01 | Y2: 74332.01 | Z2: 76561.97 | AA2: 76561.97 | AB2: 76561.97 | AC2: 76561.97 | AD2: 78858.829 | AE2: 78858.829 | AF2: 78858.829 | AG2: 81224.594 | AH2: 81224.594 | AI2: 81224.594 | AJ2: 81224.594 | AK2: 81224.594 | AL2: 83661.332 | AM2: 83661.332 | AN2: 83661.332 | AO2: 83661.332 | AP2: 86171.172 | AQ2: 86171.172 | AR2: 86171.172 | AS2: 86171.172 | AT2: 86171.172 | AU2: 86171.172 | AV2: 86171.172 | AW2: 86171.172 | AX2: 86171.172 | AY2: 86171.172 | AZ2: 86171.172 | BA2: 86171.172 | BB2: 86171.172 | BH2: helper for other column, do not remove --> | BI2: {=TRANSPOSE(T17:BC17)} -> 38333.58
D3: Yearly Salary | E3: =E2*12 -> 766667.11 | F3: =F2*12 -> 766667.11 | G3: =G2*12 -> 766667.11 | H3: =H2*12 -> 790378.47 | I3: =I2*12 -> 790378.47 | J3: =J2*12 -> 790378.47 | K3: =K2*12 -> 790378.47 | L3: =L2*12 -> 814823.16 | ... BB3: =BB2*12 -> 1034054.1 | BI3: 38333.58
A4: {='Salary Variables'!$B$16:$C$24} -> AM (%) | B4: 0.08 | D4: Work Pension | E4: ='Pensions P2'!B4*12 -> 38333.356 | F4: ='Pensions P2'!C4*12 -> 38333.356 | G4: ='Pensions P2'!D4*12 -> 38333.356 | H4: ='Pensions P2'!E4*12 -> 39518.923 | I4: ='Pensions P2'!F4*12 -> 39518.923 | J4: ='Pensions P2'!G4*12 -> 39518.923 | K4: ='Pensions P2'!H4*12 -> 39518.923 | L4: ='Pensions P2'!I4*12 -> 40741.158 | ... BB4: ='Pensions P2'!AY4*12 -> 51702.703 | BI4: 39241.656
A5: Personal Allowance | B5: 51600 | D5: Post Pension | E5: =E3-E4 -> 728333.76 | F5: =F3-F4 -> 728333.76 | G5: =G3-G4 -> 728333.76 | H5: =H3-H4 -> 750859.55 | I5: =I3-I4 -> 750859.55 | J5: =J3-J4 -> 750859.55 | K5: =K3-K4 -> 750859.55 | L5: =L3-L4 -> 774082.01 | ... BB5: =BB3-BB4 -> 982351.36 | BI5: 39241.656
A6: Bottom-Bracket State Tax rate (%) | B6: 0.1201 | D6: Post ATP | E6: =E5-$B$14 -> 727145.76 | F6: =F5-$B$14 -> 727145.76 | G6: =G5-$B$14 -> 727145.76 | H6: =H5-$B$14 -> 749671.55 | I6: =I5-$B$14 -> 749671.55 | J6: =J5-$B$14 -> 749671.55 | K6: =K5-$B$14 -> 749671.55 | L6: =L5-$B$14 -> 772894.01 | ... BB6: =BB5-$B$14 -> 981163.36 | BI6: 39241.656
A7: Top-bracket State Tax rate (%) | B7: 0.15 | D7: Post AM (Taxable Personal Income) | E7: =E6*(1-$B$4) -> 668974.1 | F7: =F6*(1-$B$4) -> 668974.1 | G7: =G6*(1-$B$4) -> 668974.1 | H7: =H6*(1-$B$4) -> 689697.82 | I7: =I6*(1-$B$4) -> 689697.82 | J7: =J6*(1-$B$4) -> 689697.82 | K7: =K6*(1-$B$4) -> 689697.82 | L7: =L6*(1-$B$4) -> 711062.48 | ... BB7: =BB6*(1-$B$4) -> 902670.29 | BI7: 39241.656
A8: State Tax Bracket Threshold | B8: 618400 | D8: Personal Allowance | E8: =$B$5 -> 51600 | F8: =$B$5 -> 51600 | G8: =$B$5 -> 51600 | H8: =$B$5 -> 51600 | I8: =$B$5 -> 51600 | J8: =$B$5 -> 51600 | K8: =$B$5 -> 51600 | L8: =$B$5 -> 51600 | ... BB8: =$B$5 -> 51600 | BI8: 40176.974
A9: Municipal Tax (%) | B9: 0.25 | D9: TPI exceed PA | E9: =E7-E8 -> 617374.1 | F9: =F7-F8 -> 617374.1 | G9: =G7-G8 -> 617374.1 | H9: =H7-H8 -> 638097.82 | I9: =I7-I8 -> 638097.82 | J9: =J7-J8 -> 638097.82 | K9: =K7-K8 -> 638097.82 | L9: =L7-L8 -> 659462.48 | ... BB9: =BB7-BB8 -> 851070.29 | BI9: 40176.974
A10: Capital Gains < 67,500DKK | B10: 0.27 | D10: Municipal Tax | E10: =E7*$B$9 -> 167243.52 | F10: =F7*$B$9 -> 167243.52 | G10: =G7*$B$9 -> 167243.52 | H10: =H7*$B$9 -> 172424.46 | I10: =I7*$B$9 -> 172424.46 | J10: =J7*$B$9 -> 172424.46 | K10: =K7*$B$9 -> 172424.46 | L10: =L7*$B$9 -> 177765.62 | ... BB10: =BB7*$B$9 -> 225667.57 | BI10: 40176.974
A11: Capital Gains > 67,500DKK | B11: 0.42 | D11: Top State Tax | E11: =MAX(E9-$B$8,0)*$B$7 -> 0 | F11: =MAX(F9-$B$8,0)*$B$7 -> 0 | G11: =MAX(G9-$B$8,0)*$B$7 -> 0 | H11: =MAX(H9-$B$8,0)*$B$7 -> 2954.6732 | I11: =MAX(I9-$B$8,0)*$B$7 -> 2954.6732 | J11: =MAX(J9-$B$8,0)*$B$7 -> 2954.6732 | K11: =MAX(K9-$B$8,0)*$B$7 -> 2954.6732 | L11: =MAX(L9-$B$8,0)*$B$7 -> 6159.3727 | ... BB11: =MAX(BB9-$B$8,0)*$B$7 -> 34900.544 | BI11: 40176.974
A12: Capital Gains Threshold | B12: 67500 | D12: Bottom State Tax | E12: =E9*$B$6 -> 74146.629 | F12: =F9*$B$6 -> 74146.629 | G12: =G9*$B$6 -> 74146.629 | H12: =H9*$B$6 -> 76635.548 | I12: =I9*$B$6 -> 76635.548 | J12: =J9*$B$6 -> 76635.548 | K12: =K9*$B$6 -> 76635.548 | L12: =L9*$B$6 -> 79201.444 | ... BB12: =BB9*$B$6 -> 102213.54 | BI12: 41140.351
A13: ATP monthly | B13: 99 | D13: Total Tax | E13: =SUM(E10:E12) -> 241390.15 | F13: =SUM(F10:F12) -> 241390.15 | G13: =SUM(G10:G12) -> 241390.15 | H13: =SUM(H10:H12) -> 252014.68 | I13: =SUM(I10:I12) -> 252014.68 | J13: =SUM(J10:J12) -> 252014.68 | K13: =SUM(K10:K12) -> 252014.68 | L13: =SUM(L10:L12) -> 263126.44 | ... BB13: =SUM(BB10:BB12) -> 362781.66 | BI13: 41140.351
A14: ATP yearly | B14: =B13*12 -> 1188 | D14: Post Tax Salary | E14: =E7-E13 -> 427583.94 | F14: =F7-F13 -> 427583.94 | G14: =G7-G13 -> 427583.94 | H14: =H7-H13 -> 437683.14 | I14: =I7-I13 -> 437683.14 | J14: =J7-J13 -> 437683.14 | K14: =K7-K13 -> 437683.14 | L14: =L7-L13 -> 447936.05 | ... BB14: =BB7-BB13 -> 539888.63 | BI14: 41140.351
D15: Alderopsparing | E15: =$B$2 -> 9400 | F15: =$B$2 -> 9400 | G15: =$B$2 -> 9400 | H15: =$B$2 -> 9400 | I15: =$B$2 -> 9400 | J15: =$B$2 -> 9400 | K15: =$B$2 -> 9400 | L15: =$B$2 -> 9400 | ... BB15: =$B$2 -> 9400 | BI15: 42132.63
D16: Net Salary (Yearly) | E16: =E14-E15 -> 418183.94 | F16: =F14-F15 -> 418183.94 | G16: =G14-G15 -> 418183.94 | H16: =H14-H15 -> 428283.14 | I16: =I14-I15 -> 428283.14 | J16: =J14-J15 -> 428283.14 | K16: =K14-K15 -> 428283.14 | L16: =L14-L15 -> 438536.05 | ... BB16: =BB14-BB15 -> 530488.63 | BI16: 42132.63
D17: Net Salary (Monthly) | E17: =E16/12 -> 34848.662 | F17: =F16/12 -> 34848.662 | G17: =G16/12 -> 34848.662 | H17: =H16/12 -> 35690.262 | I17: =I16/12 -> 35690.262 | J17: =J16/12 -> 35690.262 | K17: =K16/12 -> 35690.262 | L17: =L16/12 -> 36544.671 | ... BB17: =BB16/12 -> 44207.386 | BI17: 42132.63
BI18: 42132.63
BI19: 42132.63
BI20: 43154.677
D21: Year | E21: 2060 | F21: 2061 | G21: 2061 | H21: 2061 | I21: 2061 | J21: 2061 | K21: 2061 | L21: 2061 | M21: 2061 | N21: 2061 | O21: 2061 | P21: 2061 | Q21: 2061 | R21: 2061 | S21: 2061 | T21: 2061 | U21: 2061 | V21: 2061 | W21: 2061 | X21: 2061 | Y21: 2061 | Z21: 2061 | AA21: 2061 | AB21: 2061 | AC21: 2061 | BI21: 43154.677
D22: Monthly Salary | E22: ='Pensions P2'!$B$18+'Pensions P2'!$B$22+'Pensions P2'!$B$31 -> 53532.052 | F22: ='Pensions P2'!$B$18+'Pensions P2'!$B$22+'Pensions P2'!$B$31 -> 53532.052 | G22: ='Pensions P2'!$B$18+'Pensions P2'!$B$22+'Pensions P2'!$B$31 -> 53532.052 | H22: ='Pensions P2'!$B$18+'Pensions P2'!$B$22+'Pensions P2'!$B$31 -> 53532.052 | I22: ='Pensions P2'!$B$18+'Pensions P2'!$B$22+'Pensions P2'!$B$31 -> 53532.052 | J22: ='Pensions P2'!$B$18+'Pensions P2'!$B$22+'Pensions P2'!$B$31 -> 53532.052 | K22: ='Pensions P2'!$B$18+'Pensions P2'!$B$22+'Pensions P2'!$B$31 -> 53532.052 | L22: ='Pensions P2'!$B$18+'Pensions P2'!$B$22+'Pensions P2'!$B$31 -> 53532.052 | ... AC22: ='Pensions P2'!$B$18+'Pensions P2'!$B$22+'Pensions P2'!$B$31 -> 53532.052 | BI22: 43154.677
BI23: 43154.677
D24: Yearly Salary Inflation Adjusted | E24: =E22*12 -> 642384.62 | F24: =F22*12 -> 642384.62 | G24: =G22*12 -> 642384.62 | H24: =H22*12 -> 642384.62 | I24: =I22*12 -> 642384.62 | J24: =J22*12 -> 642384.62 | K24: =K22*12 -> 642384.62 | L24: =L22*12 -> 642384.62 | ... AC24: =AC22*12 -> 642384.62 | BI24: 44207.386
D25: Municipal Tax | E25: =E24*$B$9 -> 160596.16 | F25: =F24*$B$9 -> 160596.16 | G25: =G24*$B$9 -> 160596.16 | H25: =H24*$B$9 -> 160596.16 | I25: =I24*$B$9 -> 160596.16 | J25: =J24*$B$9 -> 160596.16 | K25: =K24*$B$9 -> 160596.16 | L25: =L24*$B$9 -> 160596.16 | ... AC25: =AC24*$B$9 -> 160596.16 | BI25: 44207.386
D26: Top State Tax | E26: =MAX(E24-$B$8,0)*$B$7 -> 3597.6936 | F26: =MAX(F24-$B$8,0)*$B$7 -> 3597.6936 | G26: =MAX(G24-$B$8,0)*$B$7 -> 3597.6936 | H26: =MAX(H24-$B$8,0)*$B$7 -> 3597.6936 | I26: =MAX(I24-$B$8,0)*$B$7 -> 3597.6936 | J26: =MAX(J24-$B$8,0)*$B$7 -> 3597.6936 | K26: =MAX(K24-$B$8,0)*$B$7 -> 3597.6936 | L26: =MAX(L24-$B$8,0)*$B$7 -> 3597.6936 | ... AC26: =MAX(AC24-$B$8,0)*$B$7 -> 3597.6936 | BI26: 44207.386
D27: Bottom State Tax | E27: =E24*$B$6 -> 77150.393 | F27: =F24*$B$6 -> 77150.393 | G27: =G24*$B$6 -> 77150.393 | H27: =H24*$B$6 -> 77150.393 | I27: =I24*$B$6 -> 77150.393 | J27: =J24*$B$6 -> 77150.393 | K27: =K24*$B$6 -> 77150.393 | L27: =L24*$B$6 -> 77150.393 | ... AC27: =AC24*$B$6 -> 77150.393 | BI27: 44207.386
D28: Total Tax | E28: =SUM(E25:E27) -> 241344.24 | F28: =SUM(F25:F27) -> 241344.24 | G28: =SUM(G25:G27) -> 241344.24 | H28: =SUM(H25:H27) -> 241344.24 | I28: =SUM(I25:I27) -> 241344.24 | J28: =SUM(J25:J27) -> 241344.24 | K28: =SUM(K25:K27) -> 241344.24 | L28: =SUM(L25:L27) -> 241344.24 | ... AC28: =SUM(AC25:AC27) -> 241344.24 | BI28: 44207.386
D29: Post Tax Salary | E29: =E24-E28 -> 401040.38 | F29: =F24-F28 -> 401040.38 | G29: =G24-G28 -> 401040.38 | H29: =H24-H28 -> 401040.38 | I29: =I24-I28 -> 401040.38 | J29: =J24-J28 -> 401040.38 | K29: =K24-K28 -> 401040.38 | L29: =L24-L28 -> 401040.38 | ... AC29: =AC24-AC28 -> 401040.38 | BI29: 44207.386
D30: Aldersopsparing | E30: ='Pensions P2'!$B$13 -> 3169.3646 | F30: ='Pensions P2'!$B$13 -> 3169.3646 | G30: ='Pensions P2'!$B$13 -> 3169.3646 | H30: ='Pensions P2'!$B$13 -> 3169.3646 | I30: ='Pensions P2'!$B$13 -> 3169.3646 | J30: ='Pensions P2'!$B$13 -> 3169.3646 | K30: ='Pensions P2'!$B$13 -> 3169.3646 | L30: ='Pensions P2'!$B$13 -> 3169.3646 | ... AC30: ='Pensions P2'!$B$13 -> 3169.3646 | BI30: 44207.386
D31: Net Salary (Monthly) | E31: =(E29/12)+E30 -> 36589.396 | F31: =(F29/12)+F30 -> 36589.396 | G31: =(G29/12)+G30 -> 36589.396 | H31: =(H29/12)+H30 -> 36589.396 | I31: =(I29/12)+I30 -> 36589.396 | J31: =(J29/12)+J30 -> 36589.396 | K31: =(K29/12)+K30 -> 36589.396 | L31: =(L29/12)+L30 -> 36589.396 | ... AC31: =(AC29/12)+AC30 -> 36589.396 | BI31: 44207.386
D32: Last Net Income from Work | E32: =Income!$L$37 -> 35365.909 | F32: =Income!$L$37 -> 35365.909 | G32: =Income!$L$37 -> 35365.909 | H32: =Income!$L$37 -> 35365.909 | I32: =Income!$L$37 -> 35365.909 | J32: =Income!$L$37 -> 35365.909 | K32: =Income!$L$37 -> 35365.909 | L32: =Income!$L$37 -> 35365.909 | ... AC32: =Income!$L$37 -> 35365.909 | BI32: 44207.386
D33: Diff | E33: =E32-E31 -> -1223.4874 | F33: =F32-F31 -> -1223.4874 | G33: =G32-G31 -> -1223.4874 | H33: =H32-H31 -> -1223.4874 | I33: =I32-I31 -> -1223.4874 | J33: =J32-J31 -> -1223.4874 | K33: =K32-K31 -> -1223.4874 | L33: =L32-L31 -> -1223.4874 | ... AC33: =AC32-AC31 -> -1223.4874 | BI33: 44207.386
D34: Monthly Target | E34: =E33*(1+$B$10) -> -1553.829 | F34: =F33*(1+$B$10) -> -1553.829 | G34: =G33*(1+$B$10) -> -1553.829 | H34: =H33*(1+$B$10) -> -1553.829 | I34: =I33*(1+$B$10) -> -1553.829 | J34: =J33*(1+$B$10) -> -1553.829 | K34: =K33*(1+$B$10) -> -1553.829 | L34: =L33*(1+$B$10) -> -1553.829 | ... AC34: =AC33*(1+$B$10) -> -1553.829 | BI34: 44207.386
D35: Yearly Target | E35: =E34*12 -> -18645.948 | F35: =F34*12 -> -18645.948 | G35: =G34*12 -> -18645.948 | H35: =H34*12 -> -18645.948 | I35: =I34*12 -> -18645.948 | J35: =J34*12 -> -18645.948 | K35: =K34*12 -> -18645.948 | L35: =L34*12 -> -18645.948 | ... AC35: =AC34*12 -> -18645.948 | BI35: 44207.386
BI36: 44207.386
D37: To be financed | E37: =SUM(E35:AC35) -> -466148.71 | BI37: 0
E39: =1500000 -> 1500000 | F39: =E39/25 -> 60000

Sheet Net Salary P1
A1: Inflation | B1: ='Salary Variables'!$C$2 -> 0.03 | D1: Year | E1: 2025 | F1: 2026 | G1: 2027 | H1: 2028 | I1: 2029 | J1: 2030 | K1: 2031 | L1: 2032 | M1: 2033 | N1: 2034 | O1: 2035 | P1: 2036 | Q1: 2037 | R1: 2038 | S1: 2039 | T1: 2040 | U1: 2041 | V1: 2042 | W1: 2043 | X1: 2044 | Y1: 2045 | Z1: 2046 | AA1: 2047 | AB1: 2048 | AC1: 2049 | AD1: 2050 | AE1: 2051 | AF1: 2052 | AG1: 2053 | AH1: 2054 | AI1: 2055 | AJ1: 2056 | AK1: 2057 | AL1: 2058 | AM1: 2059 | AN1: 2060 | AO1: 2061 | AP1: 2062 | AQ1: 2063 | AR1: 2064 | AS1: 2065 | AT1: 2066 | AU1: 2067 | AV1: 2068 | AW1: 2069 | AX1: 2070 | AY1: 2071 | AZ1: 2072 | BA1: 2073 | BB1: 2074
A2: Aldersopsparing max | B2: ='Salary Variables'!$C$14 -> 9400 | D2: Month Salary (Inflation Adjusted) | E2: {=TRANSPOSE(Income!O3:O52)} -> 43000 | F2: 43000 | G2: 44290 | H2: 44290 | I2: 44290 | J2: 44290 | K2: 45618.7 | L2: 45618.7 | M2: 45618.7 | N2: 45618.7 | O2: 46987.261 | P2: 46987.261 | Q2: 46987.261 | R2: 48396.879 | S2: 48396.879 | T2: 48396.879 | U2: 48396.879 | V2: 48396.879 | W2: 49848.785 | X2: 49848.785 | Y2: 49848.785 | Z2: 49848.785 | AA2: 51344.249 | AB2: 51344.249 | AC2: 51344.249 | AD2: 51344.249 | AE2: 51344.249 | AF2: 51344.249 | AG2: 51344.249 | AH2: 51344.249 | AI2: 51344.249 | AJ2: 51344.249 | AK2: 51344.249 | AL2: 51344.249 | AM2: 51344.249 | AN2: 52884.576 | AO2: 52884.576 | AP2: 52884.576 | AQ2: 52884.576 | AR2: 52884.576 | AS2: 52884.576 | AT2: 52884.576 | AU2: 52884.576 | AV2: 52884.576 | AW2: 52884.576 | AX2: 52884.576 | AY2: 52884.576 | AZ2: 52884.576 | BA2: 52884.576 | BB2: 52884.576 | BH2: helper for other column, do not remove --> | BI2: {=TRANSPOSE(E17:BC17)} -> 23348.627
D3: Yearly Salary | E3: =E2*12 -> 516000 | F3: =F2*12 -> 516000 | G3: =G2*12 -> 531480 | H3: =H2*12 -> 531480 | I3: =I2*12 -> 531480 | J3: =J2*12 -> 531480 | K3: =K2*12 -> 547424.4 | L3: =L2*12 -> 547424.4 | ... BB3: =BB2*12 -> 634614.91 | BI3: 23348.627
A4: {='Salary Variables'!$B$16:$C$24} -> AM (%) | B4: 0.08 | D4: Work Pension | E4: ='Pensions P1'!B4*12 -> 25800 | F4: ='Pensions P1'!C4*12 -> 25800 | G4: ='Pensions P1'!D4*12 -> 26574 | H4: ='Pensions P1'!E4*12 -> 26574 | I4: ='Pensions P1'!F4*12 -> 26574 | J4: ='Pensions P1'!G4*12 -> 26574 | K4: ='Pensions P1'!H4*12 -> 27371.22 | L4: ='Pensions P1'!I4*12 -> 27371.22 | ... BB4: ='Pensions P1'!AY4*12 -> 31730.746 | BI4: 24058.814
A5: Personal Allowance | B5: 51600 | D5: Post Pension | E5: =E3-E4 -> 490200 | F5: =F3-F4 -> 490200 | G5: =G3-G4 -> 504906 | H5: =H3-H4 -> 504906 | I5: =I3-I4 -> 504906 | J5: =J3-J4 -> 504906 | K5: =K3-K4 -> 520053.18 | L5: =L3-L4 -> 520053.18 | ... BB5: =BB3-BB4 -> 602884.17 | BI5: 24058.814
A6: Bottom-Bracket State Tax rate (%) | B6: 0.1201 | D6: Post ATP | E6: =E5-$B$14 -> 489012 | F6: =F5-$B$14 -> 489012 | G6: =G5-$B$14 -> 503718 | H6: =H5-$B$14 -> 503718 | I6: =I5-$B$14 -> 503718 | J6: =J5-$B$14 -> 503718 | K6: =K5-$B$14 -> 518865.18 | L6: =L5-$B$14 -> 518865.18 | ... BB6: =BB5-$B$14 -> 601696.17 | BI6: 24058.814
A7: Top-bracket State Tax rate (%) | B7: 0.15 | D7: Post AM (Taxable Personal Income) | E7: =E6*(1-$B$4) -> 449891.04 | F7: =F6*(1-$B$4) -> 449891.04 | G7: =G6*(1-$B$4) -> 463420.56 | H7: =H6*(1-$B$4) -> 463420.56 | I7: =I6*(1-$B$4) -> 463420.56 | J7: =J6*(1-$B$4) -> 463420.56 | K7: =K6*(1-$B$4) -> 477355.97 | L7: =L6*(1-$B$4) -> 477355.97 | ... BB7: =BB6*(1-$B$4) -> 553560.48 | BI7: 24058.814
A8: State Tax Bracket Threshold | B8: 618400 | D8: Personal Allowance | E8: =$B$5 -> 51600 | F8: =$B$5 -> 51600 | G8: =$B$5 -> 51600 | H8: =$B$5 -> 51600 | I8: =$B$5 -> 51600 | J8: =$B$5 -> 51600 | K8: =$B$5 -> 51600 | L8: =$B$5 -> 51600 | ... BB8: =$B$5 -> 51600 | BI8: 24790.307
A9: Municipal Tax (%) | B9: 0.25 | D9: TPI exceed PA | E9: =E7-E8 -> 398291.04 | F9: =F7-F8 -> 398291.04 | G9: =G7-G8 -> 411820.56 | H9: =H7-H8 -> 411820.56 | I9: =I7-I8 -> 411820.56 | J9: =J7-J8 -> 411820.56 | K9: =K7-K8 -> 425755.97 | L9: =L7-L8 -> 425755.97 | ... BB9: =BB7-BB8 -> 501960.48 | BI9: 24790.307
A10: Capital Gains < 67,500DKK | B10: 0.27 | D10: Municipal Tax | E10: =E7*$B$9 -> 112472.76 | F10: =F7*$B$9 -> 112472.76 | G10: =G7*$B$9 -> 115855.14 | H10: =H7*$B$9 -> 115855.14 | I10: =I7*$B$9 -> 115855.14 | J10: =J7*$B$9 -> 115855.14 | K10: =K7*$B$9 -> 119338.99 | L10: =L7*$B$9 -> 119338.99 | ... BB10: =BB7*$B$9 -> 138390.12 | BI10: 24790.307
A11: Capital Gains > 67,500DKK | B11: 0.42 | D11: Top State Tax | E11: =MAX(E9-$B$8,0)*$B$7 -> 0 | F11: =MAX(F9-$B$8,0)*$B$7 -> 0 | G11: =MAX(G9-$B$8,0)*$B$7 -> 0 | H11: =MAX(H9-$B$8,0)*$B$7 -> 0 | I11: =MAX(I9-$B$8,0)*$B$7 -> 0 | J11: =MAX(J9-$B$8,0)*$B$7 -> 0 | K11: =MAX(K9-$B$8,0)*$B$7 -> 0 | L11: =MAX(L9-$B$8,0)*$B$7 -> 0 | ... BB11: =MAX(BB9-$B$8,0)*$B$7 -> 0 | BI11: 24790.307
A12: Capital Gains Threshold | B12: 67500 | D12: Bottom State Tax | E12: =E9*$B$6 -> 47834.754 | F12: =F9*$B$6 -> 47834.754 | G12: =G9*$B$6 -> 49459.649 | H12: =H9*$B$6 -> 49459.649 | I12: =I9*$B$6 -> 49459.649 | J12: =J9*$B$6 -> 49459.649 | K12: =K9*$B$6 -> 51133.291 | L12: =L9*$B$6 -> 51133.291 | ... BB12: =BB9*$B$6 -> 60285.453 | BI12: 25543.744
A13: ATP monthly | B13: 99 | D13: Total Tax | E13: =SUM(E10:E12) -> 160307.51 | F13: =SUM(F10:F12) -> 160307.51 | G13: =SUM(G10:G12) -> 165314.79 | H13: =SUM(H10:H12) -> 165314.79 | I13: =SUM(I10:I12) -> 165314.79 | J13: =SUM(J10:J12) -> 165314.79 | K13: =SUM(K10:K12) -> 170472.28 | L13: =SUM(L10:L12) -> 170472.28 | ... BB13: =SUM(BB10:BB12) -> 198675.57 | BI13: 25543.744
A14: ATP yearly | B14: =B13*12 -> 1188 | D14: Post Tax Salary | E14: =E7-E13 -> 289583.53 | F14: =F7-F13 -> 289583.53 | G14: =G7-G13 -> 298105.77 | H14: =H7-H13 -> 298105.77 | I14: =I7-I13 -> 298105.77 | J14: =J7-J13 -> 298105.77 | K14: =K7-K13 -> 306883.68 | L14: =L7-L13 -> 306883.68 | ... BB14: =BB7-BB13 -> 354884.9 | BI14: 25543.744
D15: Alderopsparing | E15: =$B$2 -> 9400 | F15: =$B$2 -> 9400 | G15: =$B$2 -> 9400 | H15: =$B$2 -> 9400 | I15: =$B$2 -> 9400 | J15: =$B$2 -> 9400 | K15: =$B$2 -> 9400 | L15: =$B$2 -> 9400 | ... BB15: =$B$2 -> 9400 | BI15: 26319.785
D16: Net Salary (Yearly) | E16: =E14-E15 -> 280183.53 | F16: =F14-F15 -> 280183.53 | G16: =G14-G15 -> 288705.77 | H16: =H14-H15 -> 288705.77 | I16: =I14-I15 -> 288705.77 | J16: =J14-J15 -> 288705.77 | K16: =K14-K15 -> 297483.68 | L16: =L14-L15 -> 297483.68 | ... BB16: =BB14-BB15 -> 345484.9 | BI16: 26319.785
D17: Net Salary (Monthly) | E17: =E16/12 -> 23348.627 | F17: =F16/12 -> 23348.627 | G17: =G16/12 -> 24058.814 | H17: =H16/12 -> 24058.814 | I17: =I16/12 -> 24058.814 | J17: =J16/12 -> 24058.814 | K17: =K16/12 -> 24790.307 | L17: =L16/12 -> 24790.307 | ... BB17: =BB16/12 -> 28790.409 | BI17: 26319.785
BI18: 26319.785
BI19: 26319.785
BI20: 27119.107
D21: Year | E21: 2075 | F21: 2076 | G21: 2077 | H21: 2078 | I21: 2079 | J21: 2080 | K21: 2081 | L21: 2082 | M21: 2083 | N21: 2084 | O21: 2085 | P21: 2086 | Q21: 2087 | R21: 2088 | S21: 2089 | T21: 2090 | U21: 2091 | V21: 2092 | W21: 2093 | X21: 2094 | Y21: 2095 | Z21: 2096 | AA21: 2097 | AB21: 2098 | AC21: 2099 | BI21: 27119.107
D22: Monthly Salary | E22: ='Pensions P1'!$B$18+'Pensions P1'!$B$22+'Pensions P1'!$B$31 -> 37942.01 | F22: ='Pensions P1'!$B$18+'Pensions P1'!$B$22+'Pensions P1'!$B$31 -> 37942.01 | G22: ='Pensions P1'!$B$18+'Pensions P1'!$B$22+'Pensions P1'!$B$31 -> 37942.01 | H22: ='Pensions P1'!$B$18+'Pensions P1'!$B$22+'Pensions P1'!$B$31 -> 37942.01 | I22: ='Pensions P1'!$B$18+'Pensions P1'!$B$22+'Pensions P1'!$B$31 -> 37942.01 | J22: ='Pensions P1'!$B$18+'Pensions P1'!$B$22+'Pensions P1'!$B$31 -> 37942.01 | K22: ='Pensions P1'!$B$18+'Pensions P1'!$B$22+'Pensions P1'!$B$31 -> 37942.01 | L22: ='Pensions P1'!$B$18+'Pensions P1'!$B$22+'Pensions P1'!$B$31 -> 37942.01 | ... AC22: ='Pensions P1'!$B$18+'Pensions P1'!$B$22+'Pensions P1'!$B$31 -> 37942.01 | BI22: 27119.107
BI23: 27119.107
D24: Yearly Salary Inflation Adjusted | E24: =E22*12 -> 455304.13 | F24: =F22*12 -> 455304.13 | G24: =G22*12 -> 455304.13 | H24: =H22*12 -> 455304.13 | I24: =I22*12 -> 455304.13 | J24: =J22*12 -> 455304.13 | K24: =K22*12 -> 455304.13 | L24: =L22*12 -> 455304.13 | ... AC24: =AC22*12 -> 455304.13 | BI24: 27942.408
D25: Municipal Tax | E25: =E24*$B$9 -> 113826.03 | F25: =F24*$B$9 -> 113826.03 | G25: =G24*$B$9 -> 113826.03 | H25: =H24*$B$9 -> 113826.03 | I25: =I24*$B$9 -> 113826.03 | J25: =J24*$B$9 -> 113826.03 | K25: =K24*$B$9 -> 113826.03 | L25: =L24*$B$9 -> 113826.03 | ... AC25: =AC24*$B$9 -> 113826.03 | BI25: 27942.408
D26: Top State Tax | E26: =MAX(E24-$B$8,0)*$B$7 -> 0 | F26: =MAX(F24-$B$8,0)*$B$7 -> 0 | G26: =MAX(G24-$B$8,0)*$B$7 -> 0 | H26: =MAX(H24-$B$8,0)*$B$7 -> 0 | I26: =MAX(I24-$B$8,0)*$B$7 -> 0 | J26: =MAX(J24-$B$8,0)*$B$7 -> 0 | K26: =MAX(K24-$B$8,0)*$B$7 -> 0 | L26: =MAX(L24-$B$8,0)*$B$7 -> 0 | ... AC26: =MAX(AC24-$B$8,0)*$B$7 -> 0 | BI26: 27942.408
D27: Bottom State Tax | E27: =E24*$B$6 -> 54682.025 | F27: =F24*$B$6 -> 54682.025 | G27: =G24*$B$6 -> 54682.025 | H27: =H24*$B$6 -> 54682.025 | I27: =I24*$B$6 -> 54682.025 | J27: =J24*$B$6 -> 54682.025 | K27: =K24*$B$6 -> 54682.025 | L27: =L24*$B$6 -> 54682.025 | ... AC27: =AC24*$B$6 -> 54682.025 | BI27: 27942.408
D28: Total Tax | E28: =SUM(E25:E27) -> 168508.06 | F28: =SUM(F25:F27) -> 168508.06 | G28: =SUM(G25:G27) -> 168508.06 | H28: =SUM(H25:H27) -> 168508.06 | I28: =SUM(I25:I27) -> 168508.06 | J28: =SUM(J25:J27) -> 168508.06 | K28: =SUM(K25:K27) -> 168508.06 | L28: =SUM(L25:L27) -> 168508.06 | ... AC28: =SUM(AC25:AC27) -> 168508.06 | BI28: 27942.408
D29: Post Tax Salary | E29: =E24-E28 -> 286796.07 | F29: =F24-F28 -> 286796.07 | G29: =G24-G28 -> 286796.07 | H29: =H24-H28 -> 286796.07 | I29: =I24-I28 -> 286796.07 | J29: =J24-J28 -> 286796.07 | K29: =K24-K28 -> 286796.07 | L29: =L24-L28 -> 286796.07 | ... AC29: =AC24-AC28 -> 286796.07 | BI29: 27942.408
D30: Aldersopsparing | E30: ='Pensions P1'!$B$13 -> 3169.3646 | F30: ='Pensions P1'!$B$13 -> 3169.3646 | G30: ='Pensions P1'!$B$13 -> 3169.3646 | H30: ='Pensions P1'!$B$13 -> 3169.3646 | I30: ='Pensions P1'!$B$13 -> 3169.3646 | J30: ='Pensions P1'!$B$13 -> 3169.3646 | K30: ='Pensions P1'!$B$13 -> 3169.3646 | L30: ='Pensions P1'!$B$13 -> 3169.3646 | ... AC30: ='Pensions P1'!$B$13 -> 3169.3646 | BI30: 27942.408
D31: Net Salary (Monthly) | E31: =(E29/12)+E30 -> 27069.037 | F31: =(F29/12)+F30 -> 27069.037 | G31: =(G29/12)+G30 -> 27069.037 | H31: =(H29/12)+H30 -> 27069.037 | I31: =(I29/12)+I30 -> 27069.037 | J31: =(J29/12)+J30 -> 27069.037 | K31: =(K29/12)+K30 -> 27069.037 | L31: =(L29/12)+L30 -> 27069.037 | ... AC31: =(AC29/12)+AC30 -> 27069.037 | BI31: 27942.408
D32: Last Net Income from Work | E32: =Income!$K$52 -> 23032.327 | F32: =Income!$K$52 -> 23032.327 | G32: =Income!$K$52 -> 23032.327 | H32: =Income!$K$52 -> 23032.327 | I32: =Income!$K$52 -> 23032.327 | J32: =Income!$K$52 -> 23032.327 | K32: =Income!$K$52 -> 23032.327 | L32: =Income!$K$52 -> 23032.327 | ... AC32: =Income!$K$52 -> 23032.327 | BI32: 27942.408
D33: Diff | E33: =E32-E31 -> -4036.7101 | F33: =F32-F31 -> -4036.7101 | G33: =G32-G31 -> -4036.7101 | H33: =H32-H31 -> -4036.7101 | I33: =I32-I31 -> -4036.7101 | J33: =J32-J31 -> -4036.7101 | K33: =K32-K31 -> -4036.7101 | L33: =L32-L31 -> -4036.7101 | ... AC33: =AC32-AC31 -> -4036.7101 | BI33: 27942.408
D34: Monthly Target | E34: =E33*(1+$B$10) -> -5126.6218 | F34: =F33*(1+$B$10) -> -5126.6218 | G34: =G33*(1+$B$10) -> -5126.6218 | H34: =H33*(1+$B$10) -> -5126.6218 | I34: =I33*(1+$B$10) -> -5126.6218 | J34: =J33*(1+$B$10) -> -5126.6218 | K34: =K33*(1+$B$10) -> -5126.6218 | L34: =L33*(1+$B$10) -> -5126.6218 | ... AC34: =AC33*(1+$B$10) -> -5126.6218 | BI34: 27942.408
D35: Yearly Target | E35: =E34*12 -> -61519.461 | F35: =F34*12 -> -61519.461 | G35: =G34*12 -> -61519.461 | H35: =H34*12 -> -61519.461 | I35: =I34*12 -> -61519.461 | J35: =J34*12 -> -61519.461 | K35: =K34*12 -> -61519.461 | L35: =L34*12 -> -61519.461 | ... AC35: =AC34*12 -> -61519.461 | BI35: 27942.408
BI36: 27942.408
D37: To be financed | E37: =SUM(E35:AC35) -> -1537986.5 | BI37: 28790.409
BI38: 28790.409
E39: =1500000 -> 1500000 | F39: =E39/25 -> 60000 | BI39: 28790.409
BI40: 28790.409
BI41: 28790.409
BI42: 28790.409
BI43: 28790.409
BI44: 28790.409
BI45: 28790.409
BI46: 28790.409
BI47: 28790.409
BI48: 28790.409
BI49: 28790.409
BI50: 28790.409
BI51: 28790.409
BI52: 0

Sheet Job Hopping
B2: Age | C2: Age Group | D2: FH/FW | E2: Switch | F2: SwitchP1Static | G2: SwitchP2Static | M2: Year | N2: Age Group | O2: Finance Workers | P2: Finance Hoppers | Q2: FH/FW | S2: Age Group | T2: FH/FV
B3: 25 | C3: =IF(B3<30, "25-29 år", IF(B3<35, "30-34 år", IF(B3<40, "35-39 år", IF(B3<45, "40-44 år", IF(B3<50, "45-49 år", IF(B3<55, "50-54 år", IF(B3<60, "55-59 år", IF(B3<65, "60-64 år", "65+ år")))))))) -> 25-29 år | D3: =_xlfn.XLOOKUP(C3,S:S,T:T) -> 0.51651948 | E3: =IF(OR(JobHopping[[#This Row],[Age]]=25,JobHopping[[#This Row],[Age]]>69),"N",IF(AND(E1="N",E2="N", RAND()<=D3), "Y", "N")) -> N | F3: N | G3: N | M3: 2013 | N3: 25-29 år | O3: =_xlfn.XLOOKUP(M3&"-"&N3,'Djøf Finance Workers'!D:D,'Djøf Finance Workers'!C:C,0,1) -> 6202 | P3: =_xlfn.XLOOKUP(M3&"-"&N3,'Djøf Finance Hoppers'!D:D,'Djøf Finance Hoppers'!C:C,0,1) -> 2524 | Q3: =IF(O3>0, P3/O3, 0) -> 0.4069655 | S3: 25-29 år | T3: =SUMIFS(Q:Q,N:N,S3)/(MAX($M$3:$M$101)-MIN($M$3:$M$101)) -> 0.51651948
B4: 26 | C4: =IF(B4<30, "25-29 år", IF(B4<35, "30-34 år", IF(B4<40, "35-39 år", IF(B4<45, "40-44 år", IF(B4<50, "45-49 år", IF(B4<55, "50-54 år", IF(B4<60, "55-59 år", IF(B4<65, "60-64 år", "65+ år")))))))) -> 25-29 år | D4: =_xlfn.XLOOKUP(C4,S:S,T:T) -> 0.51651948 | E4: =IF(OR(JobHopping[[#This Row],[Age]]=25,JobHopping[[#This Row],[Age]]>69),"N",IF(AND(E2="N",E3="N", RAND()<=D4), "Y", "N")) -> N | F4: N | G4: N | M4: 2013 | N4: 30-34 år | O4: =_xlfn.XLOOKUP(M4&"-"&N4,'Djøf Finance Workers'!D:D,'Djøf Finance Workers'!C:C,0,1) -> 8560 | P4: =_xlfn.XLOOKUP(M4&"-"&N4,'Djøf Finance Hoppers'!D:D,'Djøf Finance Hoppers'!C:C,0,1) -> 2176 | Q4: =IF(O4>0, P4/O4, 0) -> 0.25420561 | S4: 30-34 år | T4: =SUMIFS(Q:Q,N:N,S4)/(MAX($M$3:$M$101)-MIN($M$3:$M$101)) -> 0.3390802
B5: 27 | C5: =IF(B5<30, "25-29 år", IF(B5<35, "30-34 år", IF(B5<40, "35-39 år", IF(B5<45, "40-44 år", IF(B5<50, "45-49 år", IF(B5<55, "50-54 år", IF(B5<60, "55-59 år", IF(B5<65, "60-64 år", "65+ år")))))))) -> 25-29 år | D5: =_xlfn.XLOOKUP(C5,S:S,T:T) -> 0.51651948 | E5: =IF(OR(JobHopping[[#This Row],[Age]]=25,JobHopping[[#This Row],[Age]]>69),"N",IF(AND(E3="N",E4="N", RAND()<=D5), "Y", "N")) -> N | F5: Y | G5: Y | M5: 2013 | N5: 35-39 år | O5: =_xlfn.XLOOKUP(M5&"-"&N5,'Djøf Finance Workers'!D:D,'Djøf Finance Workers'!C:C,0,1) -> 9790 | P5: =_xlfn.XLOOKUP(M5&"-"&N5,'Djøf Finance Hoppers'!D:D,'Djøf Finance Hoppers'!C:C,0,1) -> 1896 | Q5: =IF(O5>0, P5/O5, 0) -> 0.19366701 | S5: 35-39 år | T5: =SUMIFS(Q:Q,N:N,S5)/(MAX($M$3:$M$101)-MIN($M$3:$M$101)) -> 0.26240269
B6: 28 | C6: =IF(B6<30, "25-29 år", IF(B6<35, "30-34 år", IF(B6<40, "35-39 år", IF(B6<45, "40-44 år", IF(B6<50, "45-49 år", IF(B6<55, "50-54 år", IF(B6<60, "55-59 år", IF(B6<65, "60-64 år", "65+ år")))))))) -> 25-29 år | D6: =_xlfn.XLOOKUP(C6,S:S,T:T) -> 0.51651948 | E6: =IF(OR(JobHopping[[#This Row],[Age]]=25,JobHopping[[#This Row],[Age]]>69),"N",IF(AND(E4="N",E5="N", RAND()<=D6), "Y", "N")) -> Y | F6: N | G6: N | M6: 2013 | N6: 40-44 år | O6: =_xlfn.XLOOKUP(M6&"-"&N6,'Djøf Finance Workers'!D:D,'Djøf Finance Workers'!C:C,0,1) -> 9383 | P6: =_xlfn.XLOOKUP(M6&"-"&N6,'Djøf Finance Hoppers'!D:D,'Djøf Finance Hoppers'!C:C,0,1) -> 1579 | Q6: =IF(O6>0, P6/O6, 0) -> 0.16828307 | S6: 40-44 år | T6: =SUMIFS(Q:Q,N:N,S6)/(MAX($M$3:$M$101)-MIN($M$3:$M$101)) -> 0.22131873
B7: 29 | C7: =IF(B7<30, "25-29 år", IF(B7<35, "30-34 år", IF(B7<40, "35-39 år", IF(B7<45, "40-44 år", IF(B7<50, "45-49 år", IF(B7<55, "50-54 år", IF(B7<60, "55-59 år", IF(B7<65, "60-64 år", "65+ år")))))))) -> 25-29 år | D7: =_xlfn.XLOOKUP(C7,S:S,T:T) -> 0.51651948 | E7: =IF(OR(JobHopping[[#This Row],[Age]]=25,JobHopping[[#This Row],[Age]]>69),"N",IF(AND(E5="N",E6="N", RAND()<=D7), "Y", "N")) -> N | F7: N | G7: N | M7: 2013 | N7: 45-49 år | O7: =_xlfn.XLOOKUP(M7&"-"&N7,'Djøf Finance Workers'!D:D,'Djøf Finance Workers'!C:C,0,1) -> 12762 | P7: =_xlfn.XLOOKUP(M7&"-"&N7,'Djøf Finance Hoppers'!D:D,'Djøf Finance Hoppers'!C:C,0,1) -> 1915 | Q7: =IF(O7>0, P7/O7, 0) -> 0.15005485 | S7: 45-49 år | T7: =SUMIFS(Q:Q,N:N,S7)/(MAX($M$3:$M$101)-MIN($M$3:$M$101)) -> 0.1992948
B8: 30 | C8: =IF(B8<30, "25-29 år", IF(B8<35, "30-34 år", IF(B8<40, "35-39 år", IF(B8<45, "40-44 år", IF(B8<50, "45-49 år", IF(B8<55, "50-54 år", IF(B8<60, "55-59 år", IF(B8<65, "60-64 år", "65+ år")))))))) -> 30-34 år | D8: =_xlfn.XLOOKUP(C8,S:S,T:T) -> 0.3390802 | E8: =IF(OR(JobHopping[[#This Row],[Age]]=25,JobHopping[[#This Row],[Age]]>69),"N",IF(AND(E6="N",E7="N", RAND()<=D8), "Y", "N")) -> N | F8: N | G8: N | M8: 2013 | N8: 50-54 år | O8: =_xlfn.XLOOKUP(M8&"-"&N8,'Djøf Finance Workers'!D:D,'Djøf Finance Workers'!C:C,0,1) -> 10587 | P8: =_xlfn.XLOOKUP(M8&"-"&N8,'Djøf Finance Hoppers'!D:D,'Djøf Finance Hoppers'!C:C,0,1) -> 1462 | Q8: =IF(O8>0, P8/O8, 0) -> 0.13809389 | S8: 50-54 år | T8: =SUMIFS(Q:Q,N:N,S8)/(MAX($M$3:$M$101)-MIN($M$3:$M$101)) -> 0.17668929
B9: 31 | C9: =IF(B9<30, "25-29 år", IF(B9<35, "30-34 år", IF(B9<40, "35-39 år", IF(B9<45, "40-44 år", IF(B9<50, "45-49 år", IF(B9<55, "50-54 år", IF(B9<60, "55-59 år", IF(B9<65, "60-64 år", "65+ år")))))))) -> 30-34 år | D9: =_xlfn.XLOOKUP(C9,S:S,T:T) -> 0.3390802 | E9: =IF(OR(JobHopping[[#This Row],[Age]]=25,JobHopping[[#This Row],[Age]]>69),"N",IF(AND(E7="N",E8="N", RAND()<=D9), "Y", "N")) -> N | F9: Y | G9: Y | M9: 2013 | N9: 55-59 år | O9: =_xlfn.XLOOKUP(M9&"-"&N9,'Djøf Finance Workers'!D:D,'Djøf Finance Workers'!C:C,0,1) -> 8811 | P9: =_xlfn.XLOOKUP(M9&"-"&N9,'Djøf Finance Hoppers'!D:D,'Djøf Finance Hoppers'!C:C,0,1) -> 1227 | Q9: =IF(O9>0, P9/O9, 0) -> 0.13925775 | S9: 55-59 år | T9: =SUMIFS(Q:Q,N:N,S9)/(MAX($M$3:$M$101)-MIN($M$3:$M$101)) -> 0.15515675
B10: 32 | C10: =IF(B10<30, "25-29 år", IF(B10<35, "30-34 år", IF(B10<40, "35-39 år", IF(B10<45, "40-44 år", IF(B10<50, "45-49 år", IF(B10<55, "50-54 år", IF(B10<60, "55-59 år", IF(B10<65, "60-64 år", "65+ år")))))))) -> 30-34 år | D10: =_xlfn.XLOOKUP(C10,S:S,T:T) -> 0.3390802 | E10: =IF(OR(JobHopping[[#This Row],[Age]]=25,JobHopping[[#This Row],[Age]]>69),"N",IF(AND(E8="N",E9="N", RAND()<=D10), "Y", "N")) -> Y | F10: N | G10: N | M10: 2013 | N10: 60-64 år | O10: =_xlfn.XLOOKUP(M10&"-"&N10,'Djøf Finance Workers'!D:D,'Djøf Finance Workers'!C:C,0,1) -> 5072 | P10: =_xlfn.XLOOKUP(M10&"-"&N10,'Djøf Finance Hoppers'!D:D,'Djøf Finance Hoppers'!C:C,0,1) -> 667 | Q10: =IF(O10>0, P10/O10, 0) -> 0.13150631 | S10: 60-64 år | T10: =SUMIFS(Q:Q,N:N,S10)/(MAX($M$3:$M$101)-MIN($M$3:$M$101)) -> 0.13997312
B11: 33 | C11: =IF(B11<30, "25-29 år", IF(B11<35, "30-34 år", IF(B11<40, "35-39 år", IF(B11<45, "40-44 år", IF(B11<50, "45-49 år", IF(B11<55, "50-54 år", IF(B11<60, "55-59 år", IF(B11<65, "60-64 år", "65+ år")))))))) -> 30-34 år | D11: =_xlfn.XLOOKUP(C11,S:S,T:T) -> 0.3390802 | E11: =IF(OR(JobHopping[[#This Row],[Age]]=25,JobHopping[[#This Row],[Age]]>69),"N",IF(AND(E9="N",E10="N", RAND()<=D11), "Y", "N")) -> N | F11: N | G11: N | M11: 2013 | N11: 65+ år | O11: =_xlfn.XLOOKUP(M11&"-"&N11,'Djøf Finance Workers'!D:D,'Djøf Finance Workers'!C:C,0,1) -> 1539 | P11: =_xlfn.XLOOKUP(M11&"-"&N11,'Djøf Finance Hoppers'!D:D,'Djøf Finance Hoppers'!C:C,0,1) -> 224 | Q11: =IF(O11>0, P11/O11, 0) -> 0.14554906 | S11: 65+ år | T11: =SUMIFS(Q:Q,N:N,S11)/(MAX($M$3:$M$101)-MIN($M$3:$M$101)) -> 0.11691873
B12: 34 | C12: =IF(B12<30, "25-29 år", IF(B12<35, "30-34 år", IF(B12<40, "35-39 år", IF(B12<45, "40-44 år", IF(B12<50, "45-49 år", IF(B12<55, "50-54 år", IF(B12<60, "55-59 år", IF(B12<65, "60-64 år", "65+ år")))))))) -> 30-34 år | D12: =_xlfn.XLOOKUP(C12,S:S,T:T) -> 0.3390802 | E12: =IF(OR(JobHopping[[#This Row],[Age]]=25,JobHopping[[#This Row],[Age]]>69),"N",IF(AND(E10="N",E11="N", RAND()<=D12), "Y", "N")) -> N | F12: N | G12: N | M12: 2014 | N12: 25-29 år | O12: =_xlfn.XLOOKUP(M12&"-"&N12,'Djøf Finance Workers'!D:D,'Djøf Finance Workers'!C:C,0,1) -> 6041 | P12: =_xlfn.XLOOKUP(M12&"-"&N12,'Djøf Finance Hoppers'!D:D,'Djøf Finance Hoppers'!C:C,0,1) -> 2521 | Q12: =IF(O12>0, P12/O12, 0) -> 0.41731501
B13: 35 | C13: =IF(B13<30, "25-29 år", IF(B13<35, "30-34 år", IF(B13<40, "35-39 år", IF(B13<45, "40-44 år", IF(B13<50, "45-49 år", IF(B13<55, "50-54 år", IF(B13<60, "55-59 år", IF(B13<65, "60-64 år", "65+ år")))))))) -> 35-39 år | D13: =_xlfn.XLOOKUP(C13,S:S,T:T) -> 0.26240269 | E13: =IF(OR(JobHopping[[#This Row],[Age]]=25,JobHopping[[#This Row],[Age]]>69),"N",IF(AND(E11="N",E12="N", RAND()<=D13), "Y", "N")) -> N | F13: Y | G13: Y | M13: 2014 | N13: 30-34 år | O13: =_xlfn.XLOOKUP(M13&"-"&N13,'Djøf Finance Workers'!D:D,'Djøf Finance Workers'!C:C,0,1) -> 8203 | P13: =_xlfn.XLOOKUP(M13&"-"&N13,'Djøf Finance Hoppers'!D:D,'Djøf Finance Hoppers'!C:C,0,1) -> 2178 | Q13: =IF(O13>0, P13/O13, 0) -> 0.26551262
B14: 36 | C14: =IF(B14<30, "25-29 år", IF(B14<35, "30-34 år", IF(B14<40, "35-39 år", IF(B14<45, "40-44 år", IF(B14<50, "45-49 år", IF(B14<55, "50-54 år", IF(B14<60, "55-59 år", IF(B14<65, "60-64 år", "65+ år")))))))) -> 35-39 år | D14: =_xlfn.XLOOKUP(C14,S:S,T:T) -> 0.26240269 | E14: =IF(OR(JobHopping[[#This Row],[Age]]=25,JobHopping[[#This Row],[Age]]>69),"N",IF(AND(E12="N",E13="N", RAND()<=D14), "Y", "N")) -> N | F14: N | G14: N | M14: 2014 | N14: 35-39 år | O14: =_xlfn.XLOOKUP(M14&"-"&N14,'Djøf Finance Workers'!D:D,'Djøf Finance Workers'!C:C,0,1) -> 9972 | P14: =_xlfn.XLOOKUP(M14&"-"&N14,'Djøf Finance Hoppers'!D:D,'Djøf Finance Hoppers'!C:C,0,1) -> 2066 | Q14: =IF(O14>0, P14/O14, 0) -> 0.2071801
B15: 37 | C15: =IF(B15<30, "25-29 år", IF(B15<35, "30-34 år", IF(B15<40, "35-39 år", IF(B15<45, "40-44 år", IF(B15<50, "45-49 år", IF(B15<55, "50-54 år", IF(B15<60, "55-59 år", IF(B15<65, "60-64 år", "65+ år")))))))) -> 35-39 år | D15: =_xlfn.XLOOKUP(C15,S:S,T:T) -> 0.26240269 | E15: =IF(OR(JobHopping[[#This Row],[Age]]=25,JobHopping[[#This Row],[Age]]>69),"N",IF(AND(E13="N",E14="N", RAND()<=D15), "Y", "N")) -> Y | F15: N | G15: N | M15: 2014 | N15: 40-44 år | O15: =_xlfn.XLOOKUP(M15&"-"&N15,'Djøf Finance Workers'!D:D,'Djøf Finance Workers'!C:C,0,1) -> 9409 | P15: =_xlfn.XLOOKUP(M15&"-"&N15,'Djøf Finance Hoppers'!D:D,'Djøf Finance Hoppers'!C:C,0,1) -> 1647 | Q15: =IF(O15>0, P15/O15, 0) -> 0.17504517
B16: 38 | C16: =IF(B16<30, "25-29 år", IF(B16<35, "30-34 år", IF(B16<40, "35-39 år", IF(B16<45, "40-44 år", IF(B16<50, "45-49 år", IF(B16<55, "50-54 år", IF(B16<60, "55-59 år", IF(B16<65, "60-64 år", "65+ år")))))))) -> 35-39 år | D16: =_xlfn.XLOOKUP(C16,S:S,T:T) -> 0.26240269 | E16: =IF(OR(JobHopping[[#This Row],[Age]]=25,JobHopping[[#This Row],[Age]]>69),"N",IF(AND(E14="N",E15="N", RAND()<=D16), "Y", "N")) -> N | F16: Y | G16: Y | M16: 2014 | N16: 45-49 år | O16: =_xlfn.XLOOKUP(M16&"-"&N16,'Djøf Finance Workers'!D:D,'Djøf Finance Workers'!C:C,0,1) -> 12377 | P16: =_xlfn.XLOOKUP(M16&"-"&N16,'Djøf Finance Hoppers'!D:D,'Djøf Finance Hoppers'!C:C,0,1) -> 1953 | Q16: =IF(O16>0, P16/O16, 0) -> 0.15779268
B17: 39 | C17: =IF(B17<30, "25-29 år", IF(B17<35, "30-34 år", IF(B17<40, "35-39 år", IF(B17<45, "40-44 år", IF(B17<50, "45-49 år", IF(B17<55, "50-54 år", IF(B17<60, "55-59 år", IF(B17<65, "60-64 år", "65+ år")))))))) -> 35-39 år | D17: =_xlfn.XLOOKUP(C17,S:S,T:T) -> 0.26240269 | E17: =IF(OR(JobHopping[[#This Row],[Age]]=25,JobHopping[[#This Row],[Age]]>69),"N",IF(AND(E15="N",E16="N", RAND()<=D17), "Y", "N")) -> N | F17: N | G17: N | M17: 2014 | N17: 50-54 år | O17: =_xlfn.XLOOKUP(M17&"-"&N17,'Djøf Finance Workers'!D:D,'Djøf Finance Workers'!C:C,0,1) -> 10828 | P17: =_xlfn.XLOOKUP(M17&"-"&N17,'Djøf Finance Hoppers'!D:D,'Djøf Finance Hoppers'!C:C,0,1) -> 1636 | Q17: =IF(O17>0, P17/O17, 0) -> 0.15108977
B18: 40 | C18: =IF(B18<30, "25-29 år", IF(B18<35, "30-34 år", IF(B18<40, "35-39 år", IF(B18<45, "40-44 år", IF(B18<50, "45-49 år", IF(B18<55, "50-54 år", IF(B18<60, "55-59 år", IF(B18<65, "60-64 år", "65+ år")))))))) -> 40-44 år | D18: =_xlfn.XLOOKUP(C18,S:S,T:T) -> 0.22131873 | E18: =IF(OR(JobHopping[[#This Row],[Age]]=25,JobHopping[[#This Row],[Age]]>69),"N",IF(AND(E16="N",E17="N", RAND()<=D18), "Y", "N")) -> Y | F18: N | G18: N | M18: 2014 | N18: 55-59 år | O18: =_xlfn.XLOOKUP(M18&"-"&N18,'Djøf Finance Workers'!D:D,'Djøf Finance Workers'!C:C,0,1) -> 8888 | P18: =_xlfn.XLOOKUP(M18&"-"&N18,'Djøf Finance Hoppers'!D:D,'Djøf Finance Hoppers'!C:C,0,1) -> 1231 | Q18: =IF(O18>0, P18/O18, 0) -> 0.13850135
B19: 41 | C19: =IF(B19<30, "25-29 år", IF(B19<35, "30-34 år", IF(B19<40, "35-39 år", IF(B19<45, "40-44 år", IF(B19<50, "45-49 år", IF(B19<55, "50-54 år", IF(B19<60, "55-59 år", IF(B19<65, "60-64 år", "65+ år")))))))) -> 40-44 år | D19: =_xlfn.XLOOKUP(C19,S:S,T:T) -> 0.22131873 | E19: =IF(OR(JobHopping[[#This Row],[Age]]=25,JobHopping[[#This Row],[Age]]>69),"N",IF(AND(E17="N",E18="N", RAND()<=D19), "Y", "N")) -> N | F19: N | G19: N | M19: 2014 | N19: 60-64 år | O19: =_xlfn.XLOOKUP(M19&"-"&N19,'Djøf Finance Workers'!D:D,'Djøf Finance Workers'!C:C,0,1) -> 5141 | P19: =_xlfn.XLOOKUP(M19&"-"&N19,'Djøf Finance Hoppers'!D:D,'Djøf Finance Hoppers'!C:C,0,1) -> 706 | Q19: =IF(O19>0, P19/O19, 0) -> 0.13732737
B20: 42 | C20: =IF(B20<30, "25-29 år", IF(B20<35, "30-34 år", IF(B20<40, "35-39 år", IF(B20<45, "40-44 år", IF(B20<50, "45-49 år", IF(B20<55, "50-54 år", IF(B20<60, "55-59 år", IF(B20<65, "60-64 år", "65+ år")))))))) -> 40-44 år | D20: =_xlfn.XLOOKUP(C20,S:S,T:T) -> 0.22131873 | E20: =IF(OR(JobHopping[[#This Row],[Age]]=25,JobHopping[[#This Row],[Age]]>69),"N",IF(AND(E18="N",E19="N", RAND()<=D20), "Y", "N")) -> N | F20: N | G20: N | M20: 2014 | N20: 65+ år | O20: =_xlfn.XLOOKUP(M20&"-"&N20,'Djøf Finance Workers'!D:D,'Djøf Finance Workers'!C:C,0,1) -> 1600 | P20: =_xlfn.XLOOKUP(M20&"-"&N20,'Djøf Finance Hoppers'!D:D,'Djøf Finance Hoppers'!C:C,0,1) -> 204 | Q20: =IF(O20>0, P20/O20, 0) -> 0.1275
B21: 43 | C21: =IF(B21<30, "25-29 år", IF(B21<35, "30-34 år", IF(B21<40, "35-39 år", IF(B21<45, "40-44 år", IF(B21<50, "45-49 år", IF(B21<55, "50-54 år", IF(B21<60, "55-59 år", IF(B21<65, "60-64 år", "65+ år")))))))) -> 40-44 år | D21: =_xlfn.XLOOKUP(C21,S:S,T:T) -> 0.22131873 | E21: =IF(OR(JobHopping[[#This Row],[Age]]=25,JobHopping[[#This Row],[Age]]>69),"N",IF(AND(E19="N",E20="N", RAND()<=D21), "Y", "N")) -> N | F21: Y | G21: Y | M21: 2015 | N21: 25-29 år | O21: =_xlfn.XLOOKUP(M21&"-"&N21,'Djøf Finance Workers'!D:D,'Djøf Finance Workers'!C:C,0,1) -> 5834 | P21: =_xlfn.XLOOKUP(M21&"-"&N21,'Djøf Finance Hoppers'!D:D,'Djøf Finance Hoppers'!C:C,0,1) -> 2715 | Q21: =IF(O21>0, P21/O21, 0) -> 0.46537539
B22: 44 | C22: =IF(B22<30, "25-29 år", IF(B22<35, "30-34 år", IF(B22<40, "35-39 år", IF(B22<45, "40-44 år", IF(B22<50, "45-49 år", IF(B22<55, "50-54 år", IF(B22<60, "55-59 år", IF(B22<65, "60-64 år", "65+ år")))))))) -> 40-44 år | D22: =_xlfn.XLOOKUP(C22,S:S,T:T) -> 0.22131873 | E22: =IF(OR(JobHopping[[#This Row],[Age]]=25,JobHopping[[#This Row],[Age]]>69),"N",IF(AND(E20="N",E21="N", RAND()<=D22), "Y", "N")) -> N | F22: N | G22: N | M22: 2015 | N22: 30-34 år | O22: =_xlfn.XLOOKUP(M22&"-"&N22,'Djøf Finance Workers'!D:D,'Djøf Finance Workers'!C:C,0,1) -> 7834 | P22: =_xlfn.XLOOKUP(M22&"-"&N22,'Djøf Finance Hoppers'!D:D,'Djøf Finance Hoppers'!C:C,0,1) -> 2473 | Q22: =IF(O22>0, P22/O22, 0) -> 0.31567526
B23: 45 | C23: =IF(B23<30, "25-29 år", IF(B23<35, "30-34 år", IF(B23<40, "35-39 år", IF(B23<45, "40-44 år", IF(B23<50, "45-49 år", IF(B23<55, "50-54 år", IF(B23<60, "55-59 år", IF(B23<65, "60-64 år", "65+ år")))))))) -> 45-49 år | D23: =_xlfn.XLOOKUP(C23,S:S,T:T) -> 0.1992948 | E23: =IF(OR(JobHopping[[#This Row],[Age]]=25,JobHopping[[#This Row],[Age]]>69),"N",IF(AND(E21="N",E22="N", RAND()<=D23), "Y", "N")) -> Y | F23: N | G23: N | M23: 2015 | N23: 35-39 år | O23: =_xlfn.XLOOKUP(M23&"-"&N23,'Djøf Finance Workers'!D:D,'Djøf Finance Workers'!C:C,0,1) -> 9897 | P23: =_xlfn.XLOOKUP(M23&"-"&N23,'Djøf Finance Hoppers'!D:D,'Djøf Finance Hoppers'!C:C,0,1) -> 2378 | Q23: =IF(O23>0, P23/O23, 0) -> 0.24027483
... B78: 100 | C78: =IF(B78<30, "25-29 år", IF(B78<35, "30-34 år", IF(B78<40, "35-39 år", IF(B78<45, "40-44 år", IF(B78<50, "45-49 år", IF(B78<55, "50-54 år", IF(B78<60, "55-59 år", IF(B78<65, "60-64 år", "65+ år")))))))) -> 65+ år | D78: =_xlfn.XLOOKUP(C78,S:S,T:T) -> 0.11691873 | E78: =IF(OR(JobHopping[[#This Row],[Age]]=25,JobHopping[[#This Row],[Age]]>69),"N",IF(AND(E76="N",E77="N", RAND()<=D78), "Y", "N")) -> N | F78: N | G78: N | M78: 2021 | N78: 40-44 år | O78: =_xlfn.XLOOKUP(M78&"-"&N78,'Djøf Finance Workers'!D:D,'Djøf Finance Workers'!C:C,0,1) -> 10002 | P78: =_xlfn.XLOOKUP(M78&"-"&N78,'Djøf Finance Hoppers'!D:D,'Djøf Finance Hoppers'!C:C,0,1) -> 2220 | Q78: =IF(O78>0, P78/O78, 0) -> 0.22195561
M79: 2021 | N79: 45-49 år | O79: =_xlfn.XLOOKUP(M79&"-"&N79,'Djøf Finance Workers'!D:D,'Djøf Finance Workers'!C:C,0,1) -> 10036 | P79: =_xlfn.XLOOKUP(M79&"-"&N79,'Djøf Finance Hoppers'!D:D,'Djøf Finance Hoppers'!C:C,0,1) -> 1980 | Q79: =IF(O79>0, P79/O79, 0) -> 0.19728976
M80: 2021 | N80: 50-54 år | O80: =_xlfn.XLOOKUP(M80&"-"&N80,'Djøf Finance Workers'!D:D,'Djøf Finance Workers'!C:C,0,1) -> 10467 | P80: =_xlfn.XLOOKUP(M80&"-"&N80,'Djøf Finance Hoppers'!D:D,'Djøf Finance Hoppers'!C:C,0,1) -> 1810 | Q80: =IF(O80>0, P80/O80, 0) -> 0.17292443
M81: 2021 | N81: 55-59 år | O81: =_xlfn.XLOOKUP(M81&"-"&N81,'Djøf Finance Workers'!D:D,'Djøf Finance Workers'!C:C,0,1) -> 10749 | P81: =_xlfn.XLOOKUP(M81&"-"&N81,'Djøf Finance Hoppers'!D:D,'Djøf Finance Hoppers'!C:C,0,1) -> 1631 | Q81: =IF(O81>0, P81/O81, 0) -> 0.15173505
M82: 2021 | N82: 60-64 år | O82: =_xlfn.XLOOKUP(M82&"-"&N82,'Djøf Finance Workers'!D:D,'Djøf Finance Workers'!C:C,0,1) -> 6688 | P82: =_xlfn.XLOOKUP(M82&"-"&N82,'Djøf Finance Hoppers'!D:D,'Djøf Finance Hoppers'!C:C,0,1) -> 962 | Q82: =IF(O82>0, P82/O82, 0) -> 0.14383971
M83: 2021 | N83: 65+ år | O83: =_xlfn.XLOOKUP(M83&"-"&N83,'Djøf Finance Workers'!D:D,'Djøf Finance Workers'!C:C,0,1) -> 2522 | P83: =_xlfn.XLOOKUP(M83&"-"&N83,'Djøf Finance Hoppers'!D:D,'Djøf Finance Hoppers'!C:C,0,1) -> 216 | Q83: =IF(O83>0, P83/O83, 0) -> 0.085646312
M84: 2022 | N84: 25-29 år | O84: =_xlfn.XLOOKUP(M84&"-"&N84,'Djøf Finance Workers'!D:D,'Djøf Finance Workers'!C:C,0,1) -> 8107 | P84: =_xlfn.XLOOKUP(M84&"-"&N84,'Djøf Finance Hoppers'!D:D,'Djøf Finance Hoppers'!C:C,0,1) -> 3870 | Q84: =IF(O84>0, P84/O84, 0) -> 0.47736524
M85: 2022 | N85: 30-34 år | O85: =_xlfn.XLOOKUP(M85&"-"&N85,'Djøf Finance Workers'!D:D,'Djøf Finance Workers'!C:C,0,1) -> 9307 | P85: =_xlfn.XLOOKUP(M85&"-"&N85,'Djøf Finance Hoppers'!D:D,'Djøf Finance Hoppers'!C:C,0,1) -> 3004 | Q85: =IF(O85>0, P85/O85, 0) -> 0.32276781
M86: 2022 | N86: 35-39 år | O86: =_xlfn.XLOOKUP(M86&"-"&N86,'Djøf Finance Workers'!D:D,'Djøf Finance Workers'!C:C,0,1) -> 9287 | P86: =_xlfn.XLOOKUP(M86&"-"&N86,'Djøf Finance Hoppers'!D:D,'Djøf Finance Hoppers'!C:C,0,1) -> 2511 | Q86: =IF(O86>0, P86/O86, 0) -> 0.27037795
M87: 2022 | N87: 40-44 år | O87: =_xlfn.XLOOKUP(M87&"-"&N87,'Djøf Finance Workers'!D:D,'Djøf Finance Workers'!C:C,0,1) -> 9808 | P87: =_xlfn.XLOOKUP(M87&"-"&N87,'Djøf Finance Hoppers'!D:D,'Djøf Finance Hoppers'!C:C,0,1) -> 2191 | Q87: =IF(O87>0, P87/O87, 0) -> 0.22338907
M88: 2022 | N88: 45-49 år | O88: =_xlfn.XLOOKUP(M88&"-"&N88,'Djøf Finance Workers'!D:D,'Djøf Finance Workers'!C:C,0,1) -> 10063 | P88: =_xlfn.XLOOKUP(M88&"-"&N88,'Djøf Finance Hoppers'!D:D,'Djøf Finance Hoppers'!C:C,0,1) -> 2044 | Q88: =IF(O88>0, P88/O88, 0) -> 0.20312034
M89: 2022 | N89: 50-54 år | O89: =_xlfn.XLOOKUP(M89&"-"&N89,'Djøf Finance Workers'!D:D,'Djøf Finance Workers'!C:C,0,1) -> 9799 | P89: =_xlfn.XLOOKUP(M89&"-"&N89,'Djøf Finance Hoppers'!D:D,'Djøf Finance Hoppers'!C:C,0,1) -> 1683 | Q89: =IF(O89>0, P89/O89, 0) -> 0.17175222
M90: 2022 | N90: 55-59 år | O90: =_xlfn.XLOOKUP(M90&"-"&N90,'Djøf Finance Workers'!D:D,'Djøf Finance Workers'!C:C,0,1) -> 11340 | P90: =_xlfn.XLOOKUP(M90&"-"&N90,'Djøf Finance Hoppers'!D:D,'Djøf Finance Hoppers'!C:C,0,1) -> 1578 | Q90: =IF(O90>0, P90/O90, 0) -> 0.13915344
... M101: 2023 | N101: 65+ år | O101: =_xlfn.XLOOKUP(M101&"-"&N101,'Djøf Finance Workers'!D:D,'Djøf Finance Workers'!C:C,0,1) -> 3139 | P101: =_xlfn.XLOOKUP(M101&"-"&N101,'Djøf Finance Hoppers'!D:D,'Djøf Finance Hoppers'!C:C,0,1) -> 295 | Q101: =IF(O101>0, P101/O101, 0) -> 0.093978974

Sheet Djøf Finance Hoppers
A1: Status på arbejdsmarkedet/ Beskæftigelse og jobskifte/ Antal personer der har skiftet eller startet i nyt job (jobomsætning)
C2: Hele landet
C3: Privat sektor
C4: Herkomst i alt
C5: Køn i alt
C6: Finansiering og forsikring
C7: Jobomsætning
A8: 2009 | B8: 25-29 år | C8: 3410 | D8: =A8&"-"&B8 -> 2009-25-29 år
A9: 2009 | B9: 30-34 år | C9: 3525 | D9: =A9&"-"&B9 -> 2009-30-34 år
A10: 2009 | B10: 35-39 år | C10: 3090 | D10: =A10&"-"&B10 -> 2009-35-39 år
A11: 2009 | B11: 40-44 år | C11: 4180 | D11: =A11&"-"&B11 -> 2009-40-44 år
A12: 2009 | B12: 45-49 år | C12: 3533 | D12: =A12&"-"&B12 -> 2009-45-49 år
A13: 2009 | B13: 50-54 år | C13: 2940 | D13: =A13&"-"&B13 -> 2009-50-54 år
A14: 2009 | B14: 55-59 år | C14: 2419 | D14: =A14&"-"&B14 -> 2009-55-59 år
A15: 2009 | B15: 60-64 år | C15: 1263 | D15: =A15&"-"&B15 -> 2009-60-64 år
A16: 2009 | B16: 65-69 år | C16: 196 | D16: =A16&"-"&B16 -> 2009-65-69 år
A17: 2010 | B17: 25-29 år | C17: 2457 | D17: =A17&"-"&B17 -> 2010-25-29 år
A18: 2010 | B18: 30-34 år | C18: 2382 | D18: =A18&"-"&B18 -> 2010-30-34 år
A19: 2010 | B19: 35-39 år | C19: 1880 | D19: =A19&"-"&B19 -> 2010-35-39 år
... A142: 2023 | B142: 65-69 år | C142: 295 | D142: =A142&"-"&B142 -> 2023-65-69 år
A145: Kilde: CPR-registeret, CVR-registeret og DetailCOR
A146: Anm.: Pga. efterregistreringer kan tallene for især den seneste periode stige ved næste opdatering.

Sheet Djøf Finance Workers
A1: Status på arbejdsmarkedet/ Beskæftigelse og jobskifte/ Antal lønmodtagere efter bopæl
C2: Hele landet
C3: Herkomst i alt
C4: Køn i alt
C5: Finansiering og forsikring
C6: Antal fuldtidsbeskæftigede lønmodtagere efter bopæl
A7: 2008 | B7: 25-29 år | C7: 6876 | D7: =A7&"-"&B7 -> 2008-25-29 år
A8: 2008 | B8: 30-34 år | C8: 8541 | D8: =A8&"-"&B8 -> 2008-30-34 år
A9: 2008 | B9: 35-39 år | C9: 8222 | D9: =A9&"-"&B9 -> 2008-35-39 år
A10: 2008 | B10: 40-44 år | C10: 11172 | D10: =A10&"-"&B10 -> 2008-40-44 år
A11: 2008 | B11: 45-49 år | C11: 9399 | D11: =A11&"-"&B11 -> 2008-45-49 år
A12: 2008 | B12: 50-54 år | C12: 8459 | D12: =A12&"-"&B12 -> 2008-50-54 år
A13: 2008 | B13: 55-59 år | C13: 7916 | D13: =A13&"-"&B13 -> 2008-55-59 år
A14: 2008 | B14: 60-64 år | C14: 4371 | D14: =A14&"-"&B14 -> 2008-60-64 år
A15: 2008 | B15: 65+ år | C15: 857 | D15: =A15&"-"&B15 -> 2008-65+ år
A16: 2009 | B16: 25-29 år | C16: 7284 | D16: =A16&"-"&B16 -> 2009-25-29 år
A17: 2009 | B17: 30-34 år | C17: 9750 | D17: =A17&"-"&B17 -> 2009-30-34 år
A18: 2009 | B18: 35-39 år | C18: 9328 | D18: =A18&"-"&B18 -> 2009-35-39 år
... A159: 2024 | B159: 65+ år | C159: 3573 | D159: =A159&"-"&B159 -> 2024-65+ år
A162: Kilde: CPR-registeret, CVR-registeret og DetailCOR
A163: Anm.: Pga. efterregistreringer kan tallene for især den seneste periode stige ved næste opdatering.

Sheet Goals
B2: Goal Info | C2: GOAL A | D2: GOAL B | E2: GOAL C | F2: GOAL D | G2: P1
B3: Value Ratio | C3: 1 | D3: 0.75 | E3: 0.5 | F3: 0.25
B4: Funding Requirement | C4: 1864268.1 | D4: =3500000*0.2 -> 700000 | E4: 72530 | F4: =2500000*0.3 -> 750000
B5: Time Horizon | C5: 50 | D5: 10 | E5: 20 | F5: 30
B7: Goal Info | C7: GOAL A | D7: GOAL B | E7: GOAL C | F7: GOAL D | G7: P2
B8: Value Ratio | C8: 1 | D8: 0.75 | E8: 0.5 | F8: 0.25
B9: Funding Requirement | C9: 4212659.3 | D9: =3500000*0.2 -> 700000 | E9: 75176 | F9: =2500000*0.3 -> 750000
B10: Time Horizon | C10: 35 | D10: 10 | E10: 5 | F10: 15

Sheet Loop
B2: N | C2: Year | D2: AgeP1 | E2: AgeP2 | F2: LoopStatus
B3: 1 | C3: 2025 | D3: 25 | E3: 40 | F3: N
B4: 2 | C4: 2026 | D4: =D3+1 -> 26 | E4: =E3+1 -> 41 | F4: N
B5: 3 | C5: 2027 | D5: =D4+1 -> 27 | E5: =E4+1 -> 42 | F5: N
B6: 4 | C6: 2028 | D6: =D5+1 -> 28 | E6: =E5+1 -> 43 | F6: N
B7: 5 | C7: 2029 | D7: =D6+1 -> 29 | E7: =E6+1 -> 44 | F7: N
B8: 6 | C8: 2030 | D8: =D7+1 -> 30 | E8: =E7+1 -> 45 | F8: N
B9: 7 | C9: 2031 | D9: =D8+1 -> 31 | E9: =E8+1 -> 46 | F9: N
B10: 8 | C10: 2032 | D10: =D9+1 -> 32 | E10: =E9+1 -> 47 | F10: N
B11: 9 | C11: 2033 | D11: =D10+1 -> 33 | E11: =E10+1 -> 48 | F11: N
B12: 10 | C12: 2034 | D12: =D11+1 -> 34 | E12: =E11+1 -> 49 | F12: N
B13: 11 | C13: 2035 | D13: =D12+1 -> 35 | E13: =E12+1 -> 50 | F13: N
B14: 12 | C14: 2036 | D14: =D13+1 -> 36 | E14: =E13+1 -> 51 | F14: N
B15: 13 | C15: 2037 | D15: =D14+1 -> 37 | E15: =E14+1 -> 52 | F15: N
... B53: 51 | C53: 2075 | D53: =D52+1 -> 75 | E53: =E52+1 -> 90 | F53: N

Sheet Aktiesparekonto Increase
A1: https://skat.dk/borger/aktier-og-andre-vaerdipapirer/aktiesparekonto?
A2: Year | B2: Max cap | C2: Change (%)
A3: 2019 | B3: 50000
A4: 2020 | B4: =100000 -> 100000 | C4: =(B4-B3)/B3 -> 1
A5: 2021 | B5: 102300 | C5: =(B5-B4)/B4 -> 0.023
A6: 2022 | B6: 103500 | C6: =(B6-B5)/B5 -> 0.011730205 | E6: median: | F6: without 2020:
A7: 2023 | B7: 106600 | C7: =(B7-B6)/B6 -> 0.029951691 | E7: =MEDIAN(C4:C9) -> 0.12645487 | F7: =MEDIAN(C5:C9) -> 0.029951691
A8: 2024 | B8: 135900 | C8: =(B8-B7)/B7 -> 0.27485929
A9: 2025 | B9: 166200 | C9: =(B9-B8)/B8 -> 0.22295806

Sheet Salary
B1: 2025 | C1: 2026 | D1: 2027 | E1: 2028 | F1: 2029 | G1: 2030 | H1: 2031 | I1: 2032 | J1: 2033 | K1: 2034 | L1: 2035 | M1: 2036 | N1: 2037 | O1: 2038 | P1: 2039 | Q1: 2040 | R1: 2041 | S1: 2042 | T1: 2043 | U1: 2044 | V1: 2045 | W1: 2046 | X1: 2047 | Y1: 2048 | Z1: 2049 | AA1: 2050 | AB1: 2051 | AC1: 2052 | AD1: 2053 | AE1: 2054 | AF1: 2055 | AG1: 2056 | AH1: 2057 | AI1: 2058 | AJ1: 2059 | AK1: 2060 | AL1: 2061 | AM1: 2062 | AN1: 2063 | AO1: 2064 | AP1: 2065 | AQ1: 2066 | AR1: 2067 | AS1: 2068 | AT1: 2069 | AU1: 2070 | AV1: 2071 | AW1: 2072 | AX1: 2073 | AY1: 2074 | AZ1: 2075
A2: P1 | B2: 0 | C2: {=TRANSPOSE(TableIncome[InvestmentP1])} -> 56036.705 | D2: 56036.705 | E2: 57741.154 | F2: 57741.154 | G2: 57741.154 | H2: 57741.154 | I2: 59496.737 | J2: 59496.737 | K2: 59496.737 | L2: 59496.737 | M2: 61304.986 | N2: 61304.986 | O2: 61304.986 | P2: 63167.484 | Q2: 63167.484 | R2: 63167.484 | S2: 63167.484 | T2: 63167.484 | U2: 65085.856 | V2: 65085.856 | W2: 65085.856 | X2: 65085.856 | Y2: 67061.78 | Z2: 67061.78 | AA2: 67061.78 | AB2: 67061.78 | AC2: 67061.78 | AD2: 67061.78 | AE2: 67061.78 | AF2: 67061.78 | AG2: 67061.78 | AH2: 67061.78 | AI2: 67061.78 | AJ2: 67061.78 | AK2: 67061.78 | AL2: 69096.981 | AM2: 69096.981 | AN2: 69096.981 | AO2: 69096.981 | AP2: 69096.981 | AQ2: 69096.981 | AR2: 69096.981 | AS2: 69096.981 | AT2: 69096.981 | AU2: 69096.981 | AV2: 69096.981 | AW2: 69096.981 | AX2: 69096.981 | AY2: 69096.981 | AZ2: 69096.981 | BA2: 0
A3: P2 | B3: 200000 | C3: {=TRANSPOSE(TableIncome[InvestmentP2])} -> 92000.592 | D3: 92000.592 | E3: 94179.973 | F3: 94179.973 | G3: 94179.973 | H3: 94179.973 | I3: 96424.737 | J3: 96424.737 | K3: 96424.737 | L3: 96424.737 | M3: 98736.843 | N3: 98736.843 | O3: 98736.843 | P3: 101118.31 | Q3: 101118.31 | R3: 101118.31 | S3: 101118.31 | T3: 101118.31 | U3: 103571.23 | V3: 103571.23 | W3: 103571.23 | X3: 103571.23 | Y3: 106097.73 | Z3: 106097.73 | AA3: 106097.73 | AB3: 106097.73 | AC3: 106097.73 | AD3: 106097.73 | AE3: 106097.73 | AF3: 106097.73 | AG3: 106097.73 | AH3: 106097.73 | AI3: 106097.73 | AJ3: 106097.73 | AK3: 106097.73 | AL3: 0 | AM3: 0 | AN3: 0 | AO3: 0 | AP3: 0 | AQ3: 0 | AR3: 0 | AS3: 0 | AT3: 0 | AU3: 0 | AV3: 0 | AW3: 0 | AX3: 0 | AY3: 0 | AZ3: 0 | BA3: 0

Sheet Wealth
B1: 2025 | C1: 2026 | D1: 2027 | E1: 2028 | F1: 2029 | G1: 2030 | H1: 2031 | I1: 2032 | J1: 2033 | K1: 2034 | L1: 2035 | M1: 2036 | N1: 2037 | O1: 2038 | P1: 2039 | Q1: 2040 | R1: 2041 | S1: 2042 | T1: 2043 | U1: 2044 | V1: 2045 | W1: 2046 | X1: 2047 | Y1: 2048 | Z1: 2049 | AA1: 2050 | AB1: 2051 | AC1: 2052 | AD1: 2053 | AE1: 2054 | AF1: 2055 | AG1: 2056 | AH1: 2057 | AI1: 2058 | AJ1: 2059 | AK1: 2060 | AL1: 2061 | AM1: 2062 | AN1: 2063 | AO1: 2064 | AP1: 2065 | AQ1: 2066 | AR1: 2067 | AS1: 2068 | AT1: 2069 | AU1: 2070 | AV1: 2071 | AW1: 2072 | AX1: 2073 | AY1: 2074 | AZ1: 2075
A2: P1 | B2: =SUMIF(TableIncome[Year], "<=" & B1, TableIncome[InvestmentP1]) -> 56036.705 | C2: =SUMIF(TableIncome[Year], "<=" & C1, TableIncome[InvestmentP1]) -> 112073.41 | D2: =SUMIF(TableIncome[Year], "<=" & D1, TableIncome[InvestmentP1]) -> 169814.56 | E2: =SUMIF(TableIncome[Year], "<=" & E1, TableIncome[InvestmentP1]) -> 227555.72 | F2: =SUMIF(TableIncome[Year], "<=" & F1, TableIncome[InvestmentP1]) -> 285296.87 | G2: =SUMIF(TableIncome[Year], "<=" & G1, TableIncome[InvestmentP1]) -> 343038.03 | H2: =SUMIF(TableIncome[Year], "<=" & H1, TableIncome[InvestmentP1]) -> 402534.76 | I2: =SUMIF(TableIncome[Year], "<=" & I1, TableIncome[InvestmentP1]) -> 462031.5 | ... AZ2: =SUMIF(TableIncome[Year], "<=" & AZ1, TableIncome[InvestmentP1]) -> 3249378.6
A3: P2 | B3: =SUMIF(TableIncome[Year], "<=" & B1, TableIncome[InvestmentP2]) -> 92000.592 | C3: =SUMIF(TableIncome[Year], "<=" & C1, TableIncome[InvestmentP2]) -> 184001.18 | D3: =SUMIF(TableIncome[Year], "<=" & D1, TableIncome[InvestmentP2]) -> 278181.16 | E3: =SUMIF(TableIncome[Year], "<=" & E1, TableIncome[InvestmentP2]) -> 372361.13 | F3: =SUMIF(TableIncome[Year], "<=" & F1, TableIncome[InvestmentP2]) -> 466541.1 | G3: =SUMIF(TableIncome[Year], "<=" & G1, TableIncome[InvestmentP2]) -> 560721.08 | H3: =SUMIF(TableIncome[Year], "<=" & H1, TableIncome[InvestmentP2]) -> 657145.81 | I3: =SUMIF(TableIncome[Year], "<=" & I1, TableIncome[InvestmentP2]) -> 753570.55 | ... AZ3: =SUMIF(TableIncome[Year], "<=" & AZ1, TableIncome[InvestmentP2]) -> 3541777.5

Sheet notes next time talk
B3: Excel side:
B4: Goal calculation
B5: Investment income calculation
B6: For retirement goal: Calculate what the amount needed is and also research from denmark statistik what is the median returns by retirement age.
B7: Returns input with samsseewfwfuweerhugf for long term, and simulation for short term
B9: Python side:
B13: Question for Johan:
B14: Vasicek ready, what do we use bond simulation for? How does it correlate to bond ETF
B18: From last meeting Johan mentioned you can put the tax money back into the account???? What does this mean I am not sure: Saxo bank shows this below which might explain
B37: Update: I KNOW WHAT HE MEANT AHAHAHA IM A GENIOUS!!!! So basically it means that (from what I understand) the 17% tax deducts from your available input amount, allowing to deposit more into the account.
C41: Here
D42: Return | E42: Vol
C43: ZC Bond | D43: 0.03 | E43: 0.01 | H43: 2025 | I43: 2026 | J43: 2027 | M43: Use value simulated for each year or the average | N43: Split each goal into a per year goal, so achieve a % of the total goal in that year, and then the model would actually work as is
C44: SP | D44: 0.1 | E44: 0.03 | H44: 0.03 | I44: 0.04 | J44: 0.06 | K44: 0.07 | L44: 0.1
H46: =AVERAGE(H44:L44) -> 0.06 | I46: =AVERAGE(I44:L44) -> 0.0675
J51: Goal: House | L51: in 10 years
J53: 2025 | K53: 2026 | L53: 2027 | M53: 2028 | N53: 2029 | O53: 2030 | P53: 2031 | Q53: 2032 | R53: 2033 | S53: 2034 | U53: Total
J54: =$U$54*10% -> 200000 | K54: =$U$54*10% -> 200000 | L54: =$U$54*10% -> 200000 | M54: =$U$54*10% -> 200000 | N54: =$U$54*10% -> 200000 | O54: =$U$54*10% -> 200000 | P54: =$U$54*10% -> 200000 | Q54: =$U$54*10% -> 200000 | ... S54: =$U$54*10% -> 200000 | U54: 2000000
B57: Task for the master file

Sheet Real Returns
B1: 2025 | C1: 2026 | D1: 2027 | E1: 2028 | F1: 2029 | G1: 2030 | H1: 2031 | I1: 2032 | J1: 2033 | K1: 2034 | L1: 2035 | M1: 2036 | N1: 2037 | O1: 2038 | P1: 2039 | Q1: 2040 | R1: 2041 | S1: 2042 | T1: 2043 | U1: 2044 | V1: 2045 | W1: 2046 | X1: 2047 | Y1: 2048 | Z1: 2049 | AA1: 2050 | AB1: 2051 | AC1: 2052 | AD1: 2053 | AE1: 2054 | AF1: 2055 | AG1: 2056 | AH1: 2057 | AI1: 2058 | AJ1: 2059 | AK1: 2060 | AL1: 2061 | AM1: 2062 | AN1: 2063 | AO1: 2064 | AP1: 2065 | AQ1: 2066 | AR1: 2067 | AS1: 2068 | AT1: 2069 | AU1: 2070 | AV1: 2071 | AW1: 2072 | AX1: 2073 | AY1: 2074 | AZ1: 2075
A2: Emerging Markets - Equities | B2: 0.001 | C2: =B2 -> 0.001 | D2: =C2 -> 0.001 | E2: =D2 -> 0.001 | F2: =E2 -> 0.001 | G2: =F2 -> 0.001 | H2: =G2 -> 0.001 | I2: =H2 -> 0.001 | J2: =I2 -> 0.001 | K2: =J2 -> 0.001 | L2: 0.04 | M2: =L2 -> 0.04 | N2: =M2 -> 0.04 | O2: =N2 -> 0.04 | P2: =O2 -> 0.04 | Q2: =P2 -> 0.04 | R2: =Q2 -> 0.04 | S2: =R2 -> 0.04 | T2: =S2 -> 0.04 | ... AZ2: =AY2 -> 0.04
A3: Developed Markets - Equities | B3: 0.001 | C3: =B3 -> 0.001 | D3: =C3 -> 0.001 | E3: =D3 -> 0.001 | F3: =E3 -> 0.001 | G3: =F3 -> 0.001 | H3: =G3 -> 0.001 | I3: =H3 -> 0.001 | J3: =I3 -> 0.001 | K3: =J3 -> 0.001 | L3: 0.04 | M3: =L3 -> 0.04 | N3: =M3 -> 0.04 | O3: =N3 -> 0.04 | P3: =O3 -> 0.04 | Q3: =P3 -> 0.04 | R3: =Q3 -> 0.04 | S3: =R3 -> 0.04 | T3: =S3 -> 0.04 | ... AZ3: =AY3 -> 0.04
A4: Emerging Markets State - Obligations | B4: 0.001 | C4: =B4 -> 0.001 | D4: =C4 -> 0.001 | E4: =D4 -> 0.001 | F4: =E4 -> 0.001 | G4: =F4 -> 0.001 | H4: =G4 -> 0.001 | I4: =H4 -> 0.001 | J4: =I4 -> 0.001 | K4: =J4 -> 0.001 | L4: 0.04 | M4: =L4 -> 0.04 | N4: =M4 -> 0.04 | O4: =N4 -> 0.04 | P4: =O4 -> 0.04 | Q4: =P4 -> 0.04 | R4: =Q4 -> 0.04 | S4: =R4 -> 0.04 | T4: =S4 -> 0.04 | ... AZ4: =AY4 -> 0.04
A5: High Yield Bonds - Obligations | B5: 0.001 | C5: =B5 -> 0.001 | D5: =C5 -> 0.001 | E5: =D5 -> 0.001 | F5: =E5 -> 0.001 | G5: =F5 -> 0.001 | H5: =G5 -> 0.001 | I5: =H5 -> 0.001 | J5: =I5 -> 0.001 | K5: =J5 -> 0.001 | L5: 0.04 | M5: =L5 -> 0.04 | N5: =M5 -> 0.04 | O5: =N5 -> 0.04 | P5: =O5 -> 0.04 | Q5: =P5 -> 0.04 | R5: =Q5 -> 0.04 | S5: =R5 -> 0.04 | T5: =S5 -> 0.04 | ... AZ5: =AY5 -> 0.04
A6: Investment Grade Bonds - Obligations | B6: 0.001 | C6: =B6 -> 0.001 | D6: =C6 -> 0.001 | E6: =D6 -> 0.001 | F6: =E6 -> 0.001 | G6: =F6 -> 0.001 | H6: =G6 -> 0.001 | I6: =H6 -> 0.001 | J6: =I6 -> 0.001 | K6: =J6 -> 0.001 | L6: 0.04 | M6: =L6 -> 0.04 | N6: =M6 -> 0.04 | O6: =N6 -> 0.04 | P6: =O6 -> 0.04 | Q6: =P6 -> 0.04 | R6: =Q6 -> 0.04 | S6: =R6 -> 0.04 | T6: =S6 -> 0.04 | ... AZ6: =AY6 -> 0.04
A7: Government ZC Bonds - Obligations | B7: 0.001 | C7: =B7 -> 0.001 | D7: =C7 -> 0.001 | E7: =D7 -> 0.001 | F7: =E7 -> 0.001 | G7: =F7 -> 0.001 | H7: =G7 -> 0.001 | I7: =H7 -> 0.001 | J7: =I7 -> 0.001 | K7: =J7 -> 0.001 | L7: 0.04 | M7: =L7 -> 0.04 | N7: =M7 -> 0.04 | O7: =N7 -> 0.04 | P7: =O7 -> 0.04 | Q7: =P7 -> 0.04 | R7: =Q7 -> 0.04 | S7: =R7 -> 0.04 | T7: =S7 -> 0.04 | ... AZ7: =AY7 -> 0.04

Sheet Returns
B1: 2025 | C1: 2026 | D1: 2027 | E1: 2028 | F1: 2029 | G1: 2030 | H1: 2031 | I1: 2032 | J1: 2033 | K1: 2034 | L1: 2035 | M1: 2036 | N1: 2037 | O1: 2038 | P1: 2039 | Q1: 2040 | R1: 2041 | S1: 2042 | T1: 2043 | U1: 2044 | V1: 2045 | W1: 2046 | X1: 2047 | Y1: 2048 | Z1: 2049 | AA1: 2050 | AB1: 2051 | AC1: 2052 | AD1: 2053 | AE1: 2054 | AF1: 2055 | AG1: 2056 | AH1: 2057 | AI1: 2058 | AJ1: 2059 | AK1: 2060 | AL1: 2061 | AM1: 2062 | AN1: 2063 | AO1: 2064 | AP1: 2065 | AQ1: 2066 | AR1: 2067 | AS1: 2068 | AT1: 2069 | AU1: 2070 | AV1: 2071 | AW1: 2072 | AX1: 2073 | AY1: 2074 | AZ1: 2075
A2: Emerging Markets - Equities | B2: =8.6%-_xlfn.XLOOKUP(A2,BasisPointCost!$A:$A,BasisPointCost!$B:$B) -> 0.084 | C2: =B2 -> 0.084 | D2: =C2 -> 0.084 | E2: =D2 -> 0.084 | F2: =E2 -> 0.084 | G2: =F2 -> 0.084 | H2: =G2 -> 0.084 | I2: =H2 -> 0.084 | J2: =I2 -> 0.084 | K2: =J2 -> 0.084 | L2: =6.5%-0.2% -> 0.063 | M2: =L2 -> 0.063 | N2: =M2 -> 0.063 | O2: =N2 -> 0.063 | P2: =O2 -> 0.063 | Q2: =P2 -> 0.063 | R2: =Q2 -> 0.063 | S2: =R2 -> 0.063 | T2: =S2 -> 0.063 | ... AZ2: =AY2 -> 0.063
A3: Developed Markets - Equities | B3: =7%-_xlfn.XLOOKUP(A3,BasisPointCost!$A:$A,BasisPointCost!$B:$B) -> 0.068 | C3: =B3 -> 0.068 | D3: =C3 -> 0.068 | E3: =D3 -> 0.068 | F3: =E3 -> 0.068 | G3: =F3 -> 0.068 | H3: =G3 -> 0.068 | I3: =H3 -> 0.068 | J3: =I3 -> 0.068 | K3: =J3 -> 0.068 | L3: =6.5%-0.2% -> 0.063 | M3: =L3 -> 0.063 | N3: =M3 -> 0.063 | O3: =N3 -> 0.063 | P3: =O3 -> 0.063 | Q3: =P3 -> 0.063 | R3: =Q3 -> 0.063 | S3: =R3 -> 0.063 | T3: =S3 -> 0.063 | ... AZ3: =AY3 -> 0.063
A4: Emerging Markets State - Obligations | B4: =4.9%-_xlfn.XLOOKUP(A4,BasisPointCost!$A:$A,BasisPointCost!$B:$B) -> 0.0483 | C4: =B4 -> 0.0483 | D4: =C4 -> 0.0483 | E4: =D4 -> 0.0483 | F4: =E4 -> 0.0483 | G4: =F4 -> 0.0483 | H4: =G4 -> 0.0483 | I4: =H4 -> 0.0483 | J4: =I4 -> 0.0483 | K4: =J4 -> 0.0483 | L4: =3.5%-0.07% -> 0.0343 | M4: =L4 -> 0.0343 | N4: =M4 -> 0.0343 | O4: =N4 -> 0.0343 | P4: =O4 -> 0.0343 | Q4: =P4 -> 0.0343 | R4: =Q4 -> 0.0343 | S4: =R4 -> 0.0343 | T4: =S4 -> 0.0343 | ... AZ4: =AY4 -> 0.0343
A5: High Yield Bonds - Obligations | B5: =5%-_xlfn.XLOOKUP(A5,BasisPointCost!$A:$A,BasisPointCost!$B:$B) -> 0.0493 | C5: =B5 -> 0.0493 | D5: =C5 -> 0.0493 | E5: =D5 -> 0.0493 | F5: =E5 -> 0.0493 | G5: =F5 -> 0.0493 | H5: =G5 -> 0.0493 | I5: =H5 -> 0.0493 | J5: =I5 -> 0.0493 | K5: =J5 -> 0.0493 | L5: =3.5%-0.07% -> 0.0343 | M5: =L5 -> 0.0343 | N5: =M5 -> 0.0343 | O5: =N5 -> 0.0343 | P5: =O5 -> 0.0343 | Q5: =P5 -> 0.0343 | R5: =Q5 -> 0.0343 | S5: =R5 -> 0.0343 | T5: =S5 -> 0.0343 | ... AZ5: =AY5 -> 0.0343
A6: Investment Grade Bonds - Obligations | B6: =3.7%-_xlfn.XLOOKUP(A6,BasisPointCost!$A:$A,BasisPointCost!$B:$B) -> 0.0363 | C6: =B6 -> 0.0363 | D6: =C6 -> 0.0363 | E6: =D6 -> 0.0363 | F6: =E6 -> 0.0363 | G6: =F6 -> 0.0363 | H6: =G6 -> 0.0363 | I6: =H6 -> 0.0363 | J6: =I6 -> 0.0363 | K6: =J6 -> 0.0363 | L6: =3.5%-0.07% -> 0.0343 | M6: =L6 -> 0.0343 | N6: =M6 -> 0.0343 | O6: =N6 -> 0.0343 | P6: =O6 -> 0.0343 | Q6: =P6 -> 0.0343 | R6: =Q6 -> 0.0343 | S6: =R6 -> 0.0343 | T6: =S6 -> 0.0343 | ... AZ6: =AY6 -> 0.0343
A7: Government ZC Bonds - Obligations | B7: =2.9%-_xlfn.XLOOKUP($A7,BasisPointCost!$A:$A,BasisPointCost!$B:$B) -> 0.0283 | C7: =B7 -> 0.0283 | D7: =C7 -> 0.0283 | E7: =D7 -> 0.0283 | F7: =E7 -> 0.0283 | G7: =F7 -> 0.0283 | H7: =G7 -> 0.0283 | I7: =H7 -> 0.0283 | J7: =I7 -> 0.0283 | K7: =J7 -> 0.0283 | L7: =3.5%-0.07% -> 0.0343 | M7: =L7 -> 0.0343 | N7: =M7 -> 0.0343 | O7: =N7 -> 0.0343 | P7: =O7 -> 0.0343 | Q7: =P7 -> 0.0343 | R7: =Q7 -> 0.0343 | S7: =R7 -> 0.0343 | T7: =S7 -> 0.0343 | ... AZ7: =AY7 -> 0.0343

Sheet BasisPointCost
A1: Asset | B1: Cost (Basis Point) | C1: Link
A2: Emerging Markets - Equities | B2: =0.2% -> 0.002
A3: Developed Markets - Equities | B3: =0.2% -> 0.002
A4: Emerging Markets State - Obligations | B4: =0.07% -> 0.0007
A5: High Yield Bonds - Obligations | B5: =0.07% -> 0.0007
A6: Investment Grade Bonds - Obligations | B6: =0.07% -> 0.0007
A7: Government ZC Bonds - Obligations | B7: =0.07% -> 0.0007

Sheet Returns2
B1: 2035 | C1: 2036 | D1: 2037 | E1: 2038 | F1: 2039 | G1: 2040 | H1: 2041 | I1: 2042 | J1: 2043 | K1: 2044 | L1: 2045 | M1: 2046 | N1: 2047 | O1: 2048 | P1: 2049 | Q1: 2050 | R1: 2051 | S1: 2052 | T1: 2053 | U1: 2054 | V1: 2055 | W1: 2056 | X1: 2057 | Y1: 2058 | Z1: 2059 | AA1: 2060 | AB1: 2061 | AC1: 2062 | AD1: 2063 | AE1: 2064 | AF1: 2065 | AG1: 2066 | AH1: 2067 | AI1: 2068 | AJ1: 2069 | AK1: 2070 | AL1: 2071 | AM1: 2072 | AN1: 2073 | AO1: 2074 | AP1: 2075
A2: Equities | B2: =6.5%-0.2% -> 0.063 | C2: =B2 -> 0.063 | D2: =C2 -> 0.063 | E2: =D2 -> 0.063 | F2: =E2 -> 0.063 | G2: =F2 -> 0.063 | H2: =G2 -> 0.063 | I2: =H2 -> 0.063 | J2: =I2 -> 0.063 | ... AP2: =AO2 -> 0.063
A3: Obligations | B3: =3.5%-0.07% -> 0.0343 | C3: =B3 -> 0.0343 | D3: =C3 -> 0.0343 | E3: =D3 -> 0.0343 | F3: =E3 -> 0.0343 | G3: =F3 -> 0.0343 | H3: =G3 -> 0.0343 | I3: =H3 -> 0.0343 | J3: =I3 -> 0.0343 | ... AP3: =AO3 -> 0.0343

Sheet Volatilities
B1: volatility
A2: Emerging Markets - Equities | B2: 0.086
A3: Developed Markets - Equities | B3: 0.07
A4: Emerging Markets State - Obligations | B4: 0.049
A5: High Yield Bonds - Obligations | B5: 0.05
A6: Investment Grade Bonds - Obligations | B6: 0.037
A7: Government ZC Bonds - Obligations | B7: 0.029

Sheet Volatilities2
B1: volatility
A2: Equities | B2: 0.18
A3: Obligations | B3: 0.08

Sheet Correlation
B1: Government ZC Bonds - Obligations | C1: Investment Grade Bonds - Obligations | D1: High Yield Bonds - Obligations | E1: Emerging Markets State - Obligations | F1: Developed Markets - Equities | G1: Emerging Markets - Equities
A2: Government ZC Bonds - Obligations | B2: 1 | C2: 0.6 | D2: 0.2 | E2: 0.4 | F2: 0 | G2: 0
A3: Investment Grade Bonds - Obligations | B3: 0.6 | C3: 1 | D3: 0.7 | E3: 0.6 | F3: 0.3 | G3: 0.3
A4: High Yield Bonds - Obligations | B4: 0.2 | C4: 0.7 | D4: 1 | E4: 0.7 | F4: 0.7 | G4: 0.6
A5: Emerging Markets State - Obligations | B5: 0.4 | C5: 0.6 | D5: 0.7 | E5: 1 | F5: 0.5 | G5: 0.7
A6: Developed Markets - Equities | B6: 0 | C6: 0.3 | D6: 0.7 | E6: 0.5 | F6: 1 | G6: 0.7
A7: Emerging Markets - Equities | B7: 0 | C7: 0.3 | D7: 0.6 | E7: 0.7 | F7: 0.7 | G7: 1

Sheet Correlation2
B1: Obligations | C1: Equities
A2: {=TRANSPOSE(B1:C1)} -> Obligations | B2: 1 | C2: 0
A3: Equities | B3: 0 | C3: 1
