Workbook
Name _DLX1: [1]Rates!#REF!
Name _DLX1.INC: '[2]Car Air'!#REF!
Name _DLX10.INC: '[3]US&Europe'!#REF!
Name _DLX10_INC: #REF!
Name _DLX100.INC: '[3]Bonds Data BIS'!#REF!
Name _DLX14.INC: #REF!
Name _DLX15.INC: '[3]Bonds Data BIS'!#REF!
Name _DLX16.INC: '[3]Bonds Data BIS'!#REF!
Name _DLX2.INC: #REF!
Name _DLX20.INC: #REF!
Name _DLX3.INC: #REF!
Name _DLX4.INC: #REF!
Name _DLX5.INC: #REF!
Name _DLX5_INC: #REF!
Name _DLX50.INC: '[3]US&Europe'!#REF!
Name _DLX52.INC: #REF!
Name _DLX53.INC: '[3]US&Europe'!#REF!
Name _DLX54.INC: '[3]US&Europe'!#REF!
Name _DLX56.INC: '[3]US&Europe'!#REF!
Name _DLX6.INC: #REF!
Name _DLX60.INC: #REF!
Name _DLX7.INC: '[3]US&Europe'!#REF!
Name _DLX8.INC: '[3]US&Europe'!#REF!
Name _DLX80.INC: '[3]Bonds Data BIS'!#REF!
Name _DLX9.INC: '[3]US&Europe'!#REF!
Name AUD_Nom: #REF!
Name AUD_Tenor: #REF!
Name AUD_yr: #REF!
Name CAD_Nom: #REF!
Name CAD_Tenor: #REF!
Name CAD_yr: #REF!
Name CHF_Nom: #REF!
Name CHF_Tenor: #REF!
Name CHF_yr: #REF!
Name cn_asia: [4]Weights!$J$5
Name code: [5]CONSTANT!#REF!
Name Currency_cusip: '[6]Currency bucketing mapping'!$B$35:$B$160
Name Currency_name: '[6]Currency bucketing mapping'!$B$35:$BF$35
Name Currency_table: '[6]Currency bucketing mapping'!$B$35:$BF$160
Name D_0: #REF!
Name D_0_DE: #REF!
Name D_0_FR: #REF!
Name D_0_IT: #REF!
Name D_0_JP: #REF!
Name D_0_UK: #REF!
Name DaysInYear: [7]C!$B$29
Name DE_gwth: #REF!
Name DE_S: #REF!
Name ERP: [8]CF20!$C$18
Name EUR_Nom: #REF!
Name EUR_Tenor: #REF!
Name EUR_yr: #REF!
Name FR_gwth: #REF!
Name FR_S: #REF!
Name GBP_Nom: #REF!
Name GBP_Tenor: #REF!
Name GBP_yr: #REF!
Name gGDP: [8]CF20!$C$14
Name hk_asia: [4]Weights!$J$6
Name hk_nie: [4]Weights!$K$6

Sheet Front Page
B1: Description
B5: TOC Colour Coding
B6: Inputs
B7: Calculation
B8: Raw Report | C8: <-- If we download a report from a source, ex: Djøf, we will store it here and will not directly edit it
B9: Raw Report with Key | C9: <-- Raw Report but a column has been added for lookups
B11: Table Colors
B12: Uploaded to Python
B13: Not Uploaded to Python
B16: Table of Contents
B17: Salary Model
B18: Model Parameters
B19: Modelling the salary path for both investors
B20: Calculating the pension contributions for P1
B21: Calculating the pension contributions for P2
B22: Net Salary Calculation for P1
B23: Net Salary Calculation for P2
B24: Job hopping modelled
... B28: Loop used when executing the python script

Sheet Salary Variables
B2: Inflation | C2: 0.02
B3: Salary Growth
B4: Salary Raise | C4: 0.03
B5: Real Salary Raise | C5: =C4-C2 -> 0.01
B6: Job Hopping "Bonus" | C6: 0.06
B7: Real Job Hopping "Bonus" | C7: =C6-C2 -> 0.04
B8: % of salary dedicated to investments | C8: 0.1
B9: Initial Salary P1 | C9: 43871
B10: Initial Salary P2 | C10: 64001
B11: Contribution to pension
B12: Personal | C12: 0.05
B13: Company | C13: 0.1
B14: Aldersopsparing maximum contribution | C14: 9400
B15: Tax
B16: AM (%) | C16: 0.08
B17: Personal Allowance | C17: 51600
B18: Bottom-Bracket State Tax rate (%) | C18: 0.1201
B19: Top-bracket State Tax rate (%) | C19: 0.15
B20: State Tax Bracket Threshold | C20: 618400
B21: Municipal Tax (%) | C21: 0.25
B22: Capital Gains < 67,500DKK | C22: 0.27
B23: Capital Gains > 67,500DKK | C23: 0.42
B24: Capital Gains Threshold | C24: 67500

Sheet Income
A1: Income!A1
B2: Year | C2: SalaryP1 | D2: SalaryP2 | E2: InvestmentP1 | F2: InvestmentP2 | H2: Inflation | I2: ='Salary Variables'!$C$2 -> 0.02 | L2: NetMonthlySalaryP1 | M2: NetMonthlySalaryP2 | N2: GrossMonthlyInflationAdjustedP1 | O2: GrossMonthlyInflationAdjustedP2 | P2: GrossMonthlySalaryP1 | Q2: GrossMonthlySalaryP2 | R2: SwitchP1 | S2: SwitchP2
B3: 2025 | C3: =(TableIncomeCalculations[[#This Row],[NetMonthlySalaryP1]]*12) -> 286626.15 | D3: =(TableIncomeCalculations[[#This Row],[NetMonthlySalaryP2]]*12) -> 419426.43 | E3: =TableIncome[[#This Row],[SalaryP1]]*$I$7 -> 28662.615 | F3: =TableIncome[[#This Row],[SalaryP2]]*$I$7 -> 41942.643 | H3: Salary Raise | I3: {='Salary Variables'!$C$4:$C$8} -> 0.03 | L3: ='Net Salary P1'!BI2 -> 23885.512 | M3: ='Net Salary P2'!AT2 -> 34952.202 | N3: 43871 | O3: 64001 | P3: 43871 | Q3: 64001 | R3: =_xlfn.XLOOKUP(_xlfn.XLOOKUP(TableIncome[[#This Row],[Year]],Loop!C:C,Loop!D:D),'Job Hopping'!B:B,'Job Hopping'!F:F) -> N | S3: =_xlfn.XLOOKUP(_xlfn.XLOOKUP(TableIncome[[#This Row],[Year]],Loop!C:C,Loop!E:E),'Job Hopping'!B:B,'Job Hopping'!G:G) -> N
B4: 2026 | C4: =(TableIncomeCalculations[[#This Row],[NetMonthlySalaryP1]]*12) -> 289708.75 | D4: =(TableIncomeCalculations[[#This Row],[NetMonthlySalaryP2]]*12) -> 422832.04 | E4: =TableIncome[[#This Row],[SalaryP1]]*$I$7 -> 28970.875 | F4: =TableIncome[[#This Row],[SalaryP2]]*$I$7 -> 42283.204 | H4: Real Salary Raise | I4: 0.01 | L4: ='Net Salary P1'!BI3 -> 24142.396 | M4: ='Net Salary P2'!AT3 -> 35236.003 | N4: =IF(_xlfn.XLOOKUP(TableIncome[[#This Row],[Year]],Loop!C:C,Loop!D:D)<70,(N3*(1+$I$4))+IF(TableIncomeCalculations[[#This Row],[SwitchP1]]="Y",N3*$I$6,0),0) -> 44309.71 | O4: =IF(_xlfn.XLOOKUP(TableIncome[[#This Row],[Year]],Loop!C:C,Loop!E:E)<70,(O3*(1+$I$4))+IF(TableIncomeCalculations[[#This Row],[SwitchP2]]="Y",Q3*$I$6,0),0) -> 64641.01 | P4: =IF(_xlfn.XLOOKUP(TableIncome[[#This Row],[Year]],Loop!C:C,Loop!D:D)<70,(P3*(1+$I$3))+IF(TableIncomeCalculations[[#This Row],[SwitchP1]]="Y",P3*$I$5,0),0) -> 45187.13 | Q4: =IF(_xlfn.XLOOKUP(TableIncome[[#This Row],[Year]],Loop!C:C,Loop!E:E)<70,(Q3*(1+$I$3))+IF(TableIncomeCalculations[[#This Row],[SwitchP2]]="Y",Q3*$I$5,0),0) -> 65921.03 | R4: =_xlfn.XLOOKUP(_xlfn.XLOOKUP(TableIncome[[#This Row],[Year]],Loop!C:C,Loop!D:D),'Job Hopping'!B:B,'Job Hopping'!F:F) -> N | S4: =_xlfn.XLOOKUP(_xlfn.XLOOKUP(TableIncome[[#This Row],[Year]],Loop!C:C,Loop!E:E),'Job Hopping'!B:B,'Job Hopping'!G:G) -> N
B5: 2027 | C5: =(TableIncomeCalculations[[#This Row],[NetMonthlySalaryP1]]*12) -> 304525.82 | D5: =(TableIncomeCalculations[[#This Row],[NetMonthlySalaryP2]]*12) -> 426266.24 | E5: =TableIncome[[#This Row],[SalaryP1]]*$I$7 -> 30452.582 | F5: =TableIncome[[#This Row],[SalaryP2]]*$I$7 -> 42626.624 | H5: Job Hopping "Bonus" | I5: 0.06 | L5: ='Net Salary P1'!BI4 -> 25377.151 | M5: ='Net Salary P2'!AT4 -> 35522.187 | N5: =IF(_xlfn.XLOOKUP(TableIncome[[#This Row],[Year]],Loop!C:C,Loop!D:D)<70,(N4*(1+$I$4))+IF(TableIncomeCalculations[[#This Row],[SwitchP1]]="Y",N4*$I$6,0),0) -> 46525.195 | O5: =IF(_xlfn.XLOOKUP(TableIncome[[#This Row],[Year]],Loop!C:C,Loop!E:E)<70,(O4*(1+$I$4))+IF(TableIncomeCalculations[[#This Row],[SwitchP2]]="Y",Q4*$I$6,0),0) -> 65287.42 | P5: =IF(_xlfn.XLOOKUP(TableIncome[[#This Row],[Year]],Loop!C:C,Loop!D:D)<70,(P4*(1+$I$3))+IF(TableIncomeCalculations[[#This Row],[SwitchP1]]="Y",P4*$I$5,0),0) -> 49253.972 | Q5: =IF(_xlfn.XLOOKUP(TableIncome[[#This Row],[Year]],Loop!C:C,Loop!E:E)<70,(Q4*(1+$I$3))+IF(TableIncomeCalculations[[#This Row],[SwitchP2]]="Y",Q4*$I$5,0),0) -> 67898.661 | R5: =_xlfn.XLOOKUP(_xlfn.XLOOKUP(TableIncome[[#This Row],[Year]],Loop!C:C,Loop!D:D),'Job Hopping'!B:B,'Job Hopping'!F:F) -> Y | S5: =_xlfn.XLOOKUP(_xlfn.XLOOKUP(TableIncome[[#This Row],[Year]],Loop!C:C,Loop!E:E),'Job Hopping'!B:B,'Job Hopping'!G:G) -> N
B6: 2028 | C6: =(TableIncomeCalculations[[#This Row],[NetMonthlySalaryP1]]*12) -> 307776.61 | D6: =(TableIncomeCalculations[[#This Row],[NetMonthlySalaryP2]]*12) -> 443399.32 | E6: =TableIncome[[#This Row],[SalaryP1]]*$I$7 -> 30777.661 | F6: =TableIncome[[#This Row],[SalaryP2]]*$I$7 -> 44339.932 | H6: Real Job Hopping "Bonus" | I6: 0.04 | L6: ='Net Salary P1'!BI5 -> 25648.051 | M6: ='Net Salary P2'!AT5 -> 36949.943 | N6: =IF(_xlfn.XLOOKUP(TableIncome[[#This Row],[Year]],Loop!C:C,Loop!D:D)<70,(N5*(1+$I$4))+IF(TableIncomeCalculations[[#This Row],[SwitchP1]]="Y",N5*$I$6,0),0) -> 46990.447 | O6: =IF(_xlfn.XLOOKUP(TableIncome[[#This Row],[Year]],Loop!C:C,Loop!E:E)<70,(O5*(1+$I$4))+IF(TableIncomeCalculations[[#This Row],[SwitchP2]]="Y",Q5*$I$6,0),0) -> 68656.241 | P6: =IF(_xlfn.XLOOKUP(TableIncome[[#This Row],[Year]],Loop!C:C,Loop!D:D)<70,(P5*(1+$I$3))+IF(TableIncomeCalculations[[#This Row],[SwitchP1]]="Y",P5*$I$5,0),0) -> 50731.591 | Q6: =IF(_xlfn.XLOOKUP(TableIncome[[#This Row],[Year]],Loop!C:C,Loop!E:E)<70,(Q5*(1+$I$3))+IF(TableIncomeCalculations[[#This Row],[SwitchP2]]="Y",Q5*$I$5,0),0) -> 74009.54 | R6: =_xlfn.XLOOKUP(_xlfn.XLOOKUP(TableIncome[[#This Row],[Year]],Loop!C:C,Loop!D:D),'Job Hopping'!B:B,'Job Hopping'!F:F) -> N | S6: =_xlfn.XLOOKUP(_xlfn.XLOOKUP(TableIncome[[#This Row],[Year]],Loop!C:C,Loop!E:E),'Job Hopping'!B:B,'Job Hopping'!G:G) -> Y
B7: 2029 | C7: =(TableIncomeCalculations[[#This Row],[NetMonthlySalaryP1]]*12) -> 311054.66 | D7: =(TableIncomeCalculations[[#This Row],[NetMonthlySalaryP2]]*12) -> 447028.6 | E7: =TableIncome[[#This Row],[SalaryP1]]*$I$7 -> 31105.466 | F7: =TableIncome[[#This Row],[SalaryP2]]*$I$7 -> 44702.86 | H7: % of salary dedicated to investments | I7: 0.1 | L7: ='Net Salary P1'!BI6 -> 25921.222 | M7: ='Net Salary P2'!AT6 -> 37252.383 | N7: =IF(_xlfn.XLOOKUP(TableIncome[[#This Row],[Year]],Loop!C:C,Loop!D:D)<70,(N6*(1+$I$4))+IF(TableIncomeCalculations[[#This Row],[SwitchP1]]="Y",N6*$I$6,0),0) -> 47460.352 | O7: =IF(_xlfn.XLOOKUP(TableIncome[[#This Row],[Year]],Loop!C:C,Loop!E:E)<70,(O6*(1+$I$4))+IF(TableIncomeCalculations[[#This Row],[SwitchP2]]="Y",Q6*$I$6,0),0) -> 69342.803 | P7: =IF(_xlfn.XLOOKUP(TableIncome[[#This Row],[Year]],Loop!C:C,Loop!D:D)<70,(P6*(1+$I$3))+IF(TableIncomeCalculations[[#This Row],[SwitchP1]]="Y",P6*$I$5,0),0) -> 52253.539 | Q7: =IF(_xlfn.XLOOKUP(TableIncome[[#This Row],[Year]],Loop!C:C,Loop!E:E)<70,(Q6*(1+$I$3))+IF(TableIncomeCalculations[[#This Row],[SwitchP2]]="Y",Q6*$I$5,0),0) -> 76229.827 | R7: =_xlfn.XLOOKUP(_xlfn.XLOOKUP(TableIncome[[#This Row],[Year]],Loop!C:C,Loop!D:D),'Job Hopping'!B:B,'Job Hopping'!F:F) -> N | S7: =_xlfn.XLOOKUP(_xlfn.XLOOKUP(TableIncome[[#This Row],[Year]],Loop!C:C,Loop!E:E),'Job Hopping'!B:B,'Job Hopping'!G:G) -> N
B8: 2030 | C8: =(TableIncomeCalculations[[#This Row],[NetMonthlySalaryP1]]*12) -> 333849.92 | D8: =(TableIncomeCalculations[[#This Row],[NetMonthlySalaryP2]]*12) -> 474386.82 | E8: =TableIncome[[#This Row],[SalaryP1]]*$I$7 -> 33384.992 | F8: =TableIncome[[#This Row],[SalaryP2]]*$I$7 -> 47438.682 | L8: ='Net Salary P1'!BI9 -> 27820.827 | M8: ='Net Salary P2'!AT9 -> 39532.235 | N8: =IF(_xlfn.XLOOKUP(TableIncome[[#This Row],[Year]],Loop!C:C,Loop!D:D)<70,(N7*(1+$I$4))+IF(TableIncomeCalculations[[#This Row],[SwitchP1]]="Y",N7*$I$6,0),0) -> 47934.955 | O8: =IF(_xlfn.XLOOKUP(TableIncome[[#This Row],[Year]],Loop!C:C,Loop!E:E)<70,(O7*(1+$I$4))+IF(TableIncomeCalculations[[#This Row],[SwitchP2]]="Y",Q7*$I$6,0),0) -> 70036.231 | P8: =IF(_xlfn.XLOOKUP(TableIncome[[#This Row],[Year]],Loop!C:C,Loop!D:D)<70,(P7*(1+$I$3))+IF(TableIncomeCalculations[[#This Row],[SwitchP1]]="Y",P7*$I$5,0),0) -> 53821.145 | Q8: =IF(_xlfn.XLOOKUP(TableIncome[[#This Row],[Year]],Loop!C:C,Loop!E:E)<70,(Q7*(1+$I$3))+IF(TableIncomeCalculations[[#This Row],[SwitchP2]]="Y",Q7*$I$5,0),0) -> 78516.721 | R8: =_xlfn.XLOOKUP(_xlfn.XLOOKUP(TableIncome[[#This Row],[Year]],Loop!C:C,Loop!D:D),'Job Hopping'!B:B,'Job Hopping'!F:F) -> N | S8: =_xlfn.XLOOKUP(_xlfn.XLOOKUP(TableIncome[[#This Row],[Year]],Loop!C:C,Loop!E:E),'Job Hopping'!B:B,'Job Hopping'!G:G) -> N
B9: 2031 | C9: =(TableIncomeCalculations[[#This Row],[NetMonthlySalaryP1]]*12) -> 337368.74 | D9: =(TableIncomeCalculations[[#This Row],[NetMonthlySalaryP2]]*12) -> 478306 | E9: =TableIncome[[#This Row],[SalaryP1]]*$I$7 -> 33736.874 | F9: =TableIncome[[#This Row],[SalaryP2]]*$I$7 -> 47830.6 | L9: ='Net Salary P1'!BI10 -> 28114.062 | M9: ='Net Salary P2'!AT10 -> 39858.834 | N9: =IF(_xlfn.XLOOKUP(TableIncome[[#This Row],[Year]],Loop!C:C,Loop!D:D)<70,(N8*(1+$I$4))+IF(TableIncomeCalculations[[#This Row],[SwitchP1]]="Y",N8*$I$6,0),0) -> 50331.703 | O9: =IF(_xlfn.XLOOKUP(TableIncome[[#This Row],[Year]],Loop!C:C,Loop!E:E)<70,(O8*(1+$I$4))+IF(TableIncomeCalculations[[#This Row],[SwitchP2]]="Y",Q8*$I$6,0),0) -> 70736.593 | P9: =IF(_xlfn.XLOOKUP(TableIncome[[#This Row],[Year]],Loop!C:C,Loop!D:D)<70,(P8*(1+$I$3))+IF(TableIncomeCalculations[[#This Row],[SwitchP1]]="Y",P8*$I$5,0),0) -> 58665.048 | Q9: =IF(_xlfn.XLOOKUP(TableIncome[[#This Row],[Year]],Loop!C:C,Loop!E:E)<70,(Q8*(1+$I$3))+IF(TableIncomeCalculations[[#This Row],[SwitchP2]]="Y",Q8*$I$5,0),0) -> 80872.223 | R9: =_xlfn.XLOOKUP(_xlfn.XLOOKUP(TableIncome[[#This Row],[Year]],Loop!C:C,Loop!D:D),'Job Hopping'!B:B,'Job Hopping'!F:F) -> Y | S9: =_xlfn.XLOOKUP(_xlfn.XLOOKUP(TableIncome[[#This Row],[Year]],Loop!C:C,Loop!E:E),'Job Hopping'!B:B,'Job Hopping'!G:G) -> N
B10: 2032 | C10: =(TableIncomeCalculations[[#This Row],[NetMonthlySalaryP1]]*12) -> 340918 | D10: =(TableIncomeCalculations[[#This Row],[NetMonthlySalaryP2]]*12) -> 482259.63 | E10: =TableIncome[[#This Row],[SalaryP1]]*$I$7 -> 34091.8 | F10: =TableIncome[[#This Row],[SalaryP2]]*$I$7 -> 48225.963 | L10: ='Net Salary P1'!BI11 -> 28409.833 | M10: ='Net Salary P2'!AT11 -> 40188.302 | N10: =IF(_xlfn.XLOOKUP(TableIncome[[#This Row],[Year]],Loop!C:C,Loop!D:D)<70,(N9*(1+$I$4))+IF(TableIncomeCalculations[[#This Row],[SwitchP1]]="Y",N9*$I$6,0),0) -> 50835.02 | O10: =IF(_xlfn.XLOOKUP(TableIncome[[#This Row],[Year]],Loop!C:C,Loop!E:E)<70,(O9*(1+$I$4))+IF(TableIncomeCalculations[[#This Row],[SwitchP2]]="Y",Q9*$I$6,0),0) -> 74678.848 | P10: =IF(_xlfn.XLOOKUP(TableIncome[[#This Row],[Year]],Loop!C:C,Loop!D:D)<70,(P9*(1+$I$3))+IF(TableIncomeCalculations[[#This Row],[SwitchP1]]="Y",P9*$I$5,0),0) -> 60424.999 | Q10: =IF(_xlfn.XLOOKUP(TableIncome[[#This Row],[Year]],Loop!C:C,Loop!E:E)<70,(Q9*(1+$I$3))+IF(TableIncomeCalculations[[#This Row],[SwitchP2]]="Y",Q9*$I$5,0),0) -> 88150.723 | R10: =_xlfn.XLOOKUP(_xlfn.XLOOKUP(TableIncome[[#This Row],[Year]],Loop!C:C,Loop!D:D),'Job Hopping'!B:B,'Job Hopping'!F:F) -> N | S10: =_xlfn.XLOOKUP(_xlfn.XLOOKUP(TableIncome[[#This Row],[Year]],Loop!C:C,Loop!E:E),'Job Hopping'!B:B,'Job Hopping'!G:G) -> Y
B11: 2033 | C11: =(TableIncomeCalculations[[#This Row],[NetMonthlySalaryP1]]*12) -> 358201.54 | D11: =(TableIncomeCalculations[[#This Row],[NetMonthlySalaryP2]]*12) -> 486248.13 | E11: =TableIncome[[#This Row],[SalaryP1]]*$I$7 -> 35820.154 | F11: =TableIncome[[#This Row],[SalaryP2]]*$I$7 -> 48624.813 | L11: ='Net Salary P1'!BI12 -> 29850.128 | M11: ='Net Salary P2'!AT12 -> 40520.678 | N11: =IF(_xlfn.XLOOKUP(TableIncome[[#This Row],[Year]],Loop!C:C,Loop!D:D)<70,(N10*(1+$I$4))+IF(TableIncomeCalculations[[#This Row],[SwitchP1]]="Y",N10*$I$6,0),0) -> 51343.37 | O11: =IF(_xlfn.XLOOKUP(TableIncome[[#This Row],[Year]],Loop!C:C,Loop!E:E)<70,(O10*(1+$I$4))+IF(TableIncomeCalculations[[#This Row],[SwitchP2]]="Y",Q10*$I$6,0),0) -> 75425.637 | P11: =IF(_xlfn.XLOOKUP(TableIncome[[#This Row],[Year]],Loop!C:C,Loop!D:D)<70,(P10*(1+$I$3))+IF(TableIncomeCalculations[[#This Row],[SwitchP1]]="Y",P10*$I$5,0),0) -> 62237.749 | Q11: =IF(_xlfn.XLOOKUP(TableIncome[[#This Row],[Year]],Loop!C:C,Loop!E:E)<70,(Q10*(1+$I$3))+IF(TableIncomeCalculations[[#This Row],[SwitchP2]]="Y",Q10*$I$5,0),0) -> 90795.245 | R11: =_xlfn.XLOOKUP(_xlfn.XLOOKUP(TableIncome[[#This Row],[Year]],Loop!C:C,Loop!D:D),'Job Hopping'!B:B,'Job Hopping'!F:F) -> N | S11: =_xlfn.XLOOKUP(_xlfn.XLOOKUP(TableIncome[[#This Row],[Year]],Loop!C:C,Loop!E:E),'Job Hopping'!B:B,'Job Hopping'!G:G) -> N
B12: 2034 | C12: =(TableIncomeCalculations[[#This Row],[NetMonthlySalaryP1]]*12) -> 361949.9 | D12: =(TableIncomeCalculations[[#This Row],[NetMonthlySalaryP2]]*12) -> 490271.96 | E12: =TableIncome[[#This Row],[SalaryP1]]*$I$7 -> 36194.99 | F12: =TableIncome[[#This Row],[SalaryP2]]*$I$7 -> 49027.196 | L12: ='Net Salary P1'!BI13 -> 30162.491 | M12: ='Net Salary P2'!AT13 -> 40855.996 | N12: =IF(_xlfn.XLOOKUP(TableIncome[[#This Row],[Year]],Loop!C:C,Loop!D:D)<70,(N11*(1+$I$4))+IF(TableIncomeCalculations[[#This Row],[SwitchP1]]="Y",N11*$I$6,0),0) -> 51856.804 | O12: =IF(_xlfn.XLOOKUP(TableIncome[[#This Row],[Year]],Loop!C:C,Loop!E:E)<70,(O11*(1+$I$4))+IF(TableIncomeCalculations[[#This Row],[SwitchP2]]="Y",Q11*$I$6,0),0) -> 76179.893 | P12: =IF(_xlfn.XLOOKUP(TableIncome[[#This Row],[Year]],Loop!C:C,Loop!D:D)<70,(P11*(1+$I$3))+IF(TableIncomeCalculations[[#This Row],[SwitchP1]]="Y",P11*$I$5,0),0) -> 64104.882 | Q12: =IF(_xlfn.XLOOKUP(TableIncome[[#This Row],[Year]],Loop!C:C,Loop!E:E)<70,(Q11*(1+$I$3))+IF(TableIncomeCalculations[[#This Row],[SwitchP2]]="Y",Q11*$I$5,0),0) -> 93519.102 | R12: =_xlfn.XLOOKUP(_xlfn.XLOOKUP(TableIncome[[#This Row],[Year]],Loop!C:C,Loop!D:D),'Job Hopping'!B:B,'Job Hopping'!F:F) -> N | S12: =_xlfn.XLOOKUP(_xlfn.XLOOKUP(TableIncome[[#This Row],[Year]],Loop!C:C,Loop!E:E),'Job Hopping'!B:B,'Job Hopping'!G:G) -> N
B13: 2035 | C13: =(TableIncomeCalculations[[#This Row],[NetMonthlySalaryP1]]*12) -> 365731.26 | D13: =(TableIncomeCalculations[[#This Row],[NetMonthlySalaryP2]]*12) -> 494331.54 | E13: =TableIncome[[#This Row],[SalaryP1]]*$I$7 -> 36573.126 | F13: =TableIncome[[#This Row],[SalaryP2]]*$I$7 -> 49433.154 | L13: ='Net Salary P1'!BI14 -> 30477.605 | M13: ='Net Salary P2'!AT14 -> 41194.295 | N13: =IF(_xlfn.XLOOKUP(TableIncome[[#This Row],[Year]],Loop!C:C,Loop!D:D)<70,(N12*(1+$I$4))+IF(TableIncomeCalculations[[#This Row],[SwitchP1]]="Y",N12*$I$6,0),0) -> 54449.644 | O13: =IF(_xlfn.XLOOKUP(TableIncome[[#This Row],[Year]],Loop!C:C,Loop!E:E)<70,(O12*(1+$I$4))+IF(TableIncomeCalculations[[#This Row],[SwitchP2]]="Y",Q12*$I$6,0),0) -> 76941.692 | P13: =IF(_xlfn.XLOOKUP(TableIncome[[#This Row],[Year]],Loop!C:C,Loop!D:D)<70,(P12*(1+$I$3))+IF(TableIncomeCalculations[[#This Row],[SwitchP1]]="Y",P12*$I$5,0),0) -> 69874.321 | Q13: =IF(_xlfn.XLOOKUP(TableIncome[[#This Row],[Year]],Loop!C:C,Loop!E:E)<70,(Q12*(1+$I$3))+IF(TableIncomeCalculations[[#This Row],[SwitchP2]]="Y",Q12*$I$5,0),0) -> 96324.675 | R13: =_xlfn.XLOOKUP(_xlfn.XLOOKUP(TableIncome[[#This Row],[Year]],Loop!C:C,Loop!D:D),'Job Hopping'!B:B,'Job Hopping'!F:F) -> Y | S13: =_xlfn.XLOOKUP(_xlfn.XLOOKUP(TableIncome[[#This Row],[Year]],Loop!C:C,Loop!E:E),'Job Hopping'!B:B,'Job Hopping'!G:G) -> N
B14: 2036 | C14: =(TableIncomeCalculations[[#This Row],[NetMonthlySalaryP1]]*12) -> 369546.05 | D14: =(TableIncomeCalculations[[#This Row],[NetMonthlySalaryP2]]*12) -> 498427.34 | E14: =TableIncome[[#This Row],[SalaryP1]]*$I$7 -> 36954.605 | F14: =TableIncome[[#This Row],[SalaryP2]]*$I$7 -> 49842.734 | L14: ='Net Salary P1'!BI15 -> 30795.504 | M14: ='Net Salary P2'!AT15 -> 41535.611 | N14: =IF(_xlfn.XLOOKUP(TableIncome[[#This Row],[Year]],Loop!C:C,Loop!D:D)<70,(N13*(1+$I$4))+IF(TableIncomeCalculations[[#This Row],[SwitchP1]]="Y",N13*$I$6,0),0) -> 54994.141 | O14: =IF(_xlfn.XLOOKUP(TableIncome[[#This Row],[Year]],Loop!C:C,Loop!E:E)<70,(O13*(1+$I$4))+IF(TableIncomeCalculations[[#This Row],[SwitchP2]]="Y",Q13*$I$6,0),0) -> 77711.109 | P14: =IF(_xlfn.XLOOKUP(TableIncome[[#This Row],[Year]],Loop!C:C,Loop!D:D)<70,(P13*(1+$I$3))+IF(TableIncomeCalculations[[#This Row],[SwitchP1]]="Y",P13*$I$5,0),0) -> 71970.551 | Q14: =IF(_xlfn.XLOOKUP(TableIncome[[#This Row],[Year]],Loop!C:C,Loop!E:E)<70,(Q13*(1+$I$3))+IF(TableIncomeCalculations[[#This Row],[SwitchP2]]="Y",Q13*$I$5,0),0) -> 99214.415 | R14: =_xlfn.XLOOKUP(_xlfn.XLOOKUP(TableIncome[[#This Row],[Year]],Loop!C:C,Loop!D:D),'Job Hopping'!B:B,'Job Hopping'!F:F) -> N | S14: =_xlfn.XLOOKUP(_xlfn.XLOOKUP(TableIncome[[#This Row],[Year]],Loop!C:C,Loop!E:E),'Job Hopping'!B:B,'Job Hopping'!G:G) -> N
B15: 2037 | C15: =(TableIncomeCalculations[[#This Row],[NetMonthlySalaryP1]]*12) -> 388219.3 | D15: =(TableIncomeCalculations[[#This Row],[NetMonthlySalaryP2]]*12) -> 502559.78 | E15: =TableIncome[[#This Row],[SalaryP1]]*$I$7 -> 38821.93 | F15: =TableIncome[[#This Row],[SalaryP2]]*$I$7 -> 50255.978 | L15: ='Net Salary P1'!BI16 -> 32351.608 | M15: ='Net Salary P2'!AT16 -> 41879.982 | N15: =IF(_xlfn.XLOOKUP(TableIncome[[#This Row],[Year]],Loop!C:C,Loop!D:D)<70,(N14*(1+$I$4))+IF(TableIncomeCalculations[[#This Row],[SwitchP1]]="Y",N14*$I$6,0),0) -> 55544.082 | O15: =IF(_xlfn.XLOOKUP(TableIncome[[#This Row],[Year]],Loop!C:C,Loop!E:E)<70,(O14*(1+$I$4))+IF(TableIncomeCalculations[[#This Row],[SwitchP2]]="Y",Q14*$I$6,0),0) -> 78488.22 | P15: =IF(_xlfn.XLOOKUP(TableIncome[[#This Row],[Year]],Loop!C:C,Loop!D:D)<70,(P14*(1+$I$3))+IF(TableIncomeCalculations[[#This Row],[SwitchP1]]="Y",P14*$I$5,0),0) -> 74129.667 | Q15: =IF(_xlfn.XLOOKUP(TableIncome[[#This Row],[Year]],Loop!C:C,Loop!E:E)<70,(Q14*(1+$I$3))+IF(TableIncomeCalculations[[#This Row],[SwitchP2]]="Y",Q14*$I$5,0),0) -> 102190.85 | R15: =_xlfn.XLOOKUP(_xlfn.XLOOKUP(TableIncome[[#This Row],[Year]],Loop!C:C,Loop!D:D),'Job Hopping'!B:B,'Job Hopping'!F:F) -> N | S15: =_xlfn.XLOOKUP(_xlfn.XLOOKUP(TableIncome[[#This Row],[Year]],Loop!C:C,Loop!E:E),'Job Hopping'!B:B,'Job Hopping'!G:G) -> N
B16: 2038 | C16: =(TableIncomeCalculations[[#This Row],[NetMonthlySalaryP1]]*12) -> 392250.45 | D16: =(TableIncomeCalculations[[#This Row],[NetMonthlySalaryP2]]*12) -> 506729.34 | E16: =TableIncome[[#This Row],[SalaryP1]]*$I$7 -> 39225.045 | F16: =TableIncome[[#This Row],[SalaryP2]]*$I$7 -> 50672.934 | L16: ='Net Salary P1'!BI17 -> 32687.537 | M16: ='Net Salary P2'!AT17 -> 42227.445 | N16: =IF(_xlfn.XLOOKUP(TableIncome[[#This Row],[Year]],Loop!C:C,Loop!D:D)<70,(N15*(1+$I$4))+IF(TableIncomeCalculations[[#This Row],[SwitchP1]]="Y",N15*$I$6,0),0) -> 56099.523 | O16: =IF(_xlfn.XLOOKUP(TableIncome[[#This Row],[Year]],Loop!C:C,Loop!E:E)<70,(O15*(1+$I$4))+IF(TableIncomeCalculations[[#This Row],[SwitchP2]]="Y",Q15*$I$6,0),0) -> 79273.102 | P16: =IF(_xlfn.XLOOKUP(TableIncome[[#This Row],[Year]],Loop!C:C,Loop!D:D)<70,(P15*(1+$I$3))+IF(TableIncomeCalculations[[#This Row],[SwitchP1]]="Y",P15*$I$5,0),0) -> 76353.557 | Q16: =IF(_xlfn.XLOOKUP(TableIncome[[#This Row],[Year]],Loop!C:C,Loop!E:E)<70,(Q15*(1+$I$3))+IF(TableIncomeCalculations[[#This Row],[SwitchP2]]="Y",Q15*$I$5,0),0) -> 105256.57 | R16: =_xlfn.XLOOKUP(_xlfn.XLOOKUP(TableIncome[[#This Row],[Year]],Loop!C:C,Loop!D:D),'Job Hopping'!B:B,'Job Hopping'!F:F) -> N | S16: =_xlfn.XLOOKUP(_xlfn.XLOOKUP(TableIncome[[#This Row],[Year]],Loop!C:C,Loop!E:E),'Job Hopping'!B:B,'Job Hopping'!G:G) -> N
B17: 2039 | C17: =(TableIncomeCalculations[[#This Row],[NetMonthlySalaryP1]]*12) -> 396317.77 | D17: =(TableIncomeCalculations[[#This Row],[NetMonthlySalaryP2]]*12) -> 510936.45 | E17: =TableIncome[[#This Row],[SalaryP1]]*$I$7 -> 39631.777 | F17: =TableIncome[[#This Row],[SalaryP2]]*$I$7 -> 51093.645 | L17: ='Net Salary P1'!BI18 -> 33026.481 | M17: ='Net Salary P2'!AT18 -> 42578.037 | N17: =IF(_xlfn.XLOOKUP(TableIncome[[#This Row],[Year]],Loop!C:C,Loop!D:D)<70,(N16*(1+$I$4))+IF(TableIncomeCalculations[[#This Row],[SwitchP1]]="Y",N16*$I$6,0),0) -> 58904.499 | O17: =IF(_xlfn.XLOOKUP(TableIncome[[#This Row],[Year]],Loop!C:C,Loop!E:E)<70,(O16*(1+$I$4))+IF(TableIncomeCalculations[[#This Row],[SwitchP2]]="Y",Q16*$I$6,0),0) -> 80065.833 | P17: =IF(_xlfn.XLOOKUP(TableIncome[[#This Row],[Year]],Loop!C:C,Loop!D:D)<70,(P16*(1+$I$3))+IF(TableIncomeCalculations[[#This Row],[SwitchP1]]="Y",P16*$I$5,0),0) -> 83225.377 | Q17: =IF(_xlfn.XLOOKUP(TableIncome[[#This Row],[Year]],Loop!C:C,Loop!E:E)<70,(Q16*(1+$I$3))+IF(TableIncomeCalculations[[#This Row],[SwitchP2]]="Y",Q16*$I$5,0),0) -> 108414.27 | R17: =_xlfn.XLOOKUP(_xlfn.XLOOKUP(TableIncome[[#This Row],[Year]],Loop!C:C,Loop!D:D),'Job Hopping'!B:B,'Job Hopping'!F:F) -> Y | S17: =_xlfn.XLOOKUP(_xlfn.XLOOKUP(TableIncome[[#This Row],[Year]],Loop!C:C,Loop!E:E),'Job Hopping'!B:B,'Job Hopping'!G:G) -> N
B18: 2040 | C18: =(TableIncomeCalculations[[#This Row],[NetMonthlySalaryP1]]*12) -> 400421.71 | D18: =(TableIncomeCalculations[[#This Row],[NetMonthlySalaryP2]]*12) -> 515181.58 | E18: =TableIncome[[#This Row],[SalaryP1]]*$I$7 -> 40042.171 | F18: =TableIncome[[#This Row],[SalaryP2]]*$I$7 -> 51518.158 | L18: ='Net Salary P1'!BI19 -> 33368.476 | M18: ='Net Salary P2'!AT19 -> 42931.798 | N18: =IF(_xlfn.XLOOKUP(TableIncome[[#This Row],[Year]],Loop!C:C,Loop!D:D)<70,(N17*(1+$I$4))+IF(TableIncomeCalculations[[#This Row],[SwitchP1]]="Y",N17*$I$6,0),0) -> 59493.544 | O18: =IF(_xlfn.XLOOKUP(TableIncome[[#This Row],[Year]],Loop!C:C,Loop!E:E)<70,(O17*(1+$I$4))+IF(TableIncomeCalculations[[#This Row],[SwitchP2]]="Y",Q17*$I$6,0),0) -> 80866.492 | P18: =IF(_xlfn.XLOOKUP(TableIncome[[#This Row],[Year]],Loop!C:C,Loop!D:D)<70,(P17*(1+$I$3))+IF(TableIncomeCalculations[[#This Row],[SwitchP1]]="Y",P17*$I$5,0),0) -> 85722.139 | Q18: =IF(_xlfn.XLOOKUP(TableIncome[[#This Row],[Year]],Loop!C:C,Loop!E:E)<70,(Q17*(1+$I$3))+IF(TableIncomeCalculations[[#This Row],[SwitchP2]]="Y",Q17*$I$5,0),0) -> 111666.7 | R18: =_xlfn.XLOOKUP(_xlfn.XLOOKUP(TableIncome[[#This Row],[Year]],Loop!C:C,Loop!D:D),'Job Hopping'!B:B,'Job Hopping'!F:F) -> N | S18: =_xlfn.XLOOKUP(_xlfn.XLOOKUP(TableIncome[[#This Row],[Year]],Loop!C:C,Loop!E:E),'Job Hopping'!B:B,'Job Hopping'!G:G) -> N
B19: 2041 | C19: =(TableIncomeCalculations[[#This Row],[NetMonthlySalaryP1]]*12) -> 420600.23 | D19: =(TableIncomeCalculations[[#This Row],[NetMonthlySalaryP2]]*12) -> 519465.18 | E19: =TableIncome[[#This Row],[SalaryP1]]*$I$7 -> 42060.023 | F19: =TableIncome[[#This Row],[SalaryP2]]*$I$7 -> 51946.518 | L19: ='Net Salary P1'!BI20 -> 35050.019 | M19: ='Net Salary P2'!AT20 -> 43288.765 | N19: =IF(_xlfn.XLOOKUP(TableIncome[[#This Row],[Year]],Loop!C:C,Loop!D:D)<70,(N18*(1+$I$4))+IF(TableIncomeCalculations[[#This Row],[SwitchP1]]="Y",N18*$I$6,0),0) -> 60088.48 | O19: =IF(_xlfn.XLOOKUP(TableIncome[[#This Row],[Year]],Loop!C:C,Loop!E:E)<70,(O18*(1+$I$4))+IF(TableIncomeCalculations[[#This Row],[SwitchP2]]="Y",Q18*$I$6,0),0) -> 81675.157 | P19: =IF(_xlfn.XLOOKUP(TableIncome[[#This Row],[Year]],Loop!C:C,Loop!D:D)<70,(P18*(1+$I$3))+IF(TableIncomeCalculations[[#This Row],[SwitchP1]]="Y",P18*$I$5,0),0) -> 88293.803 | Q19: =IF(_xlfn.XLOOKUP(TableIncome[[#This Row],[Year]],Loop!C:C,Loop!E:E)<70,(Q18*(1+$I$3))+IF(TableIncomeCalculations[[#This Row],[SwitchP2]]="Y",Q18*$I$5,0),0) -> 115016.7 | R19: =_xlfn.XLOOKUP(_xlfn.XLOOKUP(TableIncome[[#This Row],[Year]],Loop!C:C,Loop!D:D),'Job Hopping'!B:B,'Job Hopping'!F:F) -> N | S19: =_xlfn.XLOOKUP(_xlfn.XLOOKUP(TableIncome[[#This Row],[Year]],Loop!C:C,Loop!E:E),'Job Hopping'!B:B,'Job Hopping'!G:G) -> N
... B48: 2070 | C48: =(TableIncomeCalculations[[#This Row],[NetMonthlySalaryP1]]*12) -> 0 | D48: =(TableIncomeCalculations[[#This Row],[NetMonthlySalaryP2]]*12) -> 0 | E48: =TableIncome[[#This Row],[SalaryP1]]*$I$7 -> 0 | F48: =TableIncome[[#This Row],[SalaryP2]]*$I$7 -> 0 | L48: ='Net Salary P1'!BI49 -> 0 | M48: ='Net Salary P2'!AT49 -> 0 | N48: =IF(_xlfn.XLOOKUP(TableIncome[[#This Row],[Year]],Loop!C:C,Loop!D:D)<70,(N47*(1+$I$4))+IF(TableIncomeCalculations[[#This Row],[SwitchP1]]="Y",N47*$I$6,0),0) -> 0 | O48: =IF(_xlfn.XLOOKUP(TableIncome[[#This Row],[Year]],Loop!C:C,Loop!E:E)<70,(O47*(1+$I$4))+IF(TableIncomeCalculations[[#This Row],[SwitchP2]]="Y",Q47*$I$6,0),0) -> 0 | P48: =IF(_xlfn.XLOOKUP(TableIncome[[#This Row],[Year]],Loop!C:C,Loop!D:D)<70,(P47*(1+$I$3))+IF(TableIncomeCalculations[[#This Row],[SwitchP1]]="Y",P47*$I$5,0),0) -> 0 | Q48: =IF(_xlfn.XLOOKUP(TableIncome[[#This Row],[Year]],Loop!C:C,Loop!E:E)<70,(Q47*(1+$I$3))+IF(TableIncomeCalculations[[#This Row],[SwitchP2]]="Y",Q47*$I$5,0),0) -> 0 | R48: =_xlfn.XLOOKUP(_xlfn.XLOOKUP(TableIncome[[#This Row],[Year]],Loop!C:C,Loop!D:D),'Job Hopping'!B:B,'Job Hopping'!F:F) -> N | S48: =_xlfn.XLOOKUP(_xlfn.XLOOKUP(TableIncome[[#This Row],[Year]],Loop!C:C,Loop!E:E),'Job Hopping'!B:B,'Job Hopping'!G:G) -> N

Sheet Pensions P1
A1: Year | B1: 2025 | C1: 2026 | D1: 2027 | E1: 2028 | F1: 2029 | G1: 2030 | H1: 2031 | I1: 2032 | J1: 2033 | K1: 2034 | L1: 2035 | M1: 2036 | N1: 2037 | O1: 2038 | P1: 2039 | Q1: 2040 | R1: 2041 | S1: 2042 | T1: 2043 | U1: 2044 | V1: 2045 | W1: 2046 | X1: 2047 | Y1: 2048 | Z1: 2049 | AA1: 2050 | AB1: 2051 | AC1: 2052 | AD1: 2053 | AE1: 2054 | AF1: 2055 | AG1: 2056 | AH1: 2057 | AI1: 2058 | AJ1: 2059 | AK1: 2060 | AL1: 2061 | AM1: 2062 | AN1: 2063 | AO1: 2064 | AP1: 2065 | AQ1: 2066 | AR1: 2067 | AS1: 2068 | AT1: 2069
A2: Month Salary | B2: {=TRANSPOSE(Income!N3:N47)} -> 43871 | C2: 44309.71 | D2: 46525.195 | E2: 46990.447 | F2: 47460.352 | G2: 47934.955 | H2: 50331.703 | I2: 50835.02 | J2: 51343.37 | K2: 51856.804 | L2: 54449.644 | M2: 54994.141 | N2: 55544.082 | O2: 56099.523 | P2: 58904.499 | Q2: 59493.544 | R2: 60088.48 | S2: 60689.364 | T2: 63723.833 | U2: 64361.071 | V2: 65004.682 | W2: 65654.728 | X2: 68937.465 | Y2: 69626.84 | Z2: 70323.108 | AA2: 71026.339 | AB2: 71736.602 | AC2: 72453.968 | AD2: 73178.508 | AE2: 73910.293 | AF2: 74649.396 | AG2: 75395.89 | AH2: 76149.849 | AI2: 76911.348 | AJ2: 77680.461 | AK2: 81564.484 | AL2: 82380.129 | AM2: 83203.93 | AN2: 84035.969 | AO2: 84876.329 | AP2: 85725.092 | AQ2: 86582.343 | AR2: 87448.167 | AS2: 88322.648 | AT2: 89205.875
A3: Personal Contribution (%) | B3: ='Salary Variables'!$C$12 -> 0.05 | C3: ='Salary Variables'!$C$12 -> 0.05 | D3: ='Salary Variables'!$C$12 -> 0.05 | E3: ='Salary Variables'!$C$12 -> 0.05 | F3: ='Salary Variables'!$C$12 -> 0.05 | G3: ='Salary Variables'!$C$12 -> 0.05 | H3: ='Salary Variables'!$C$12 -> 0.05 | I3: ='Salary Variables'!$C$12 -> 0.05 | ... AT3: ='Salary Variables'!$C$12 -> 0.05
A4: Personal Contribution | B4: =B3*B2 -> 2193.55 | C4: =C3*C2 -> 2215.4855 | D4: =D3*D2 -> 2326.2598 | E4: =E3*E2 -> 2349.5224 | F4: =F3*F2 -> 2373.0176 | G4: =G3*G2 -> 2396.7478 | H4: =H3*H2 -> 2516.5852 | I4: =I3*I2 -> 2541.751 | ... AT4: =AT3*AT2 -> 4460.2937
A5: Company Contribution (%) | B5: ='Salary Variables'!$C$13 -> 0.1 | C5: ='Salary Variables'!$C$13 -> 0.1 | D5: ='Salary Variables'!$C$13 -> 0.1 | E5: ='Salary Variables'!$C$13 -> 0.1 | F5: ='Salary Variables'!$C$13 -> 0.1 | G5: ='Salary Variables'!$C$13 -> 0.1 | H5: ='Salary Variables'!$C$13 -> 0.1 | I5: ='Salary Variables'!$C$13 -> 0.1 | ... AT5: ='Salary Variables'!$C$13 -> 0.1
A6: Company Contribution | B6: =B2*B5 -> 4387.1 | C6: =C4*2 -> 4430.971 | D6: =D4*2 -> 4652.5195 | E6: =E4*2 -> 4699.0447 | F6: =F4*2 -> 4746.0352 | G6: =G4*2 -> 4793.4955 | H6: =H4*2 -> 5033.1703 | I6: =I4*2 -> 5083.502 | J6: =J4*2 -> 5134.337 | ... AT6: =AT4*2 -> 8920.5875
A7: Total Contribution (Monthly) | B7: =SUM(B6,B4) -> 6580.65 | C7: =SUM(C6,C4) -> 6646.4565 | D7: =SUM(D6,D4) -> 6978.7793 | E7: =SUM(E6,E4) -> 7048.5671 | F7: =SUM(F6,F4) -> 7119.0528 | G7: =SUM(G6,G4) -> 7190.2433 | H7: =SUM(H6,H4) -> 7549.7555 | I7: =SUM(I6,I4) -> 7625.253 | ... AT7: =SUM(AT6,AT4) -> 13380.881
A8: Total Contribution (Yearly) | B8: =B7*12 -> 78967.8 | C8: =C7*12 -> 79757.478 | D8: =D7*12 -> 83745.352 | E8: =E7*12 -> 84582.805 | F8: =F7*12 -> 85428.633 | G8: =G7*12 -> 86282.92 | H8: =H7*12 -> 90597.066 | I8: =I7*12 -> 91503.036 | ... AT8: =AT7*12 -> 160570.57
A12: Total Contribution (ratepension) | B12: =SUM(B8:AT8) -> 5410424.1
A13: Divided by 25 years | B13: =B12/25 -> 216416.97 | C13: per year
A14: Monthly | B14: =B13/12 -> 18034.747 | C14: per month (gross)
A15: Taxed in Retirement? | B15: Yes | C15: Income tax
A17: Aldersopsparing | B17: =SUM('Net Salary P1'!E14:AW14) -> 282751.65 | C17: taken from sum of Net Salary P1 page
A18: Divided by 25 years | B18: =B17/25 -> 11310.066
A19: Monthly | B19: =B18/12 -> 942.50551
A20: Taxed in Retirement? | B20: No
A22: Public Pension Average Monthly | B22: 9500
A23: Public Pension Average Yearly | B23: =B22*12 -> 114000
A24: Taxed in Retirement? | B24: Yes
A25: Inflation | B25: ='Salary Variables'!C2 -> 0.02
A27: Year | B27: 2070 | C27: 2071 | D27: 2072 | E27: 2073 | F27: 2074 | G27: 2075 | H27: 2076 | I27: 2077 | J27: 2078 | K27: 2079 | L27: 2080 | M27: 2081 | N27: 2082 | O27: 2083 | P27: 2084 | Q27: 2085 | R27: 2086 | S27: 2087 | T27: 2088 | U27: 2089 | V27: 2090 | W27: 2091 | X27: 2092 | Y27: 2093 | Z27: 2094

Sheet Pensions P2
A1: Year | B1: 2025 | C1: 2026 | D1: 2027 | E1: 2028 | F1: 2029 | G1: 2030 | H1: 2031 | I1: 2032 | J1: 2033 | K1: 2034 | L1: 2035 | M1: 2036 | N1: 2037 | O1: 2038 | P1: 2039 | Q1: 2040 | R1: 2041 | S1: 2042 | T1: 2043 | U1: 2044 | V1: 2045 | W1: 2046 | X1: 2047 | Y1: 2048 | Z1: 2049 | AA1: 2050 | AB1: 2051 | AC1: 2052 | AD1: 2053 | AE1: 2054
A2: Month Salary | B2: {=TRANSPOSE(Income!O3:O32)} -> 64001 | C2: 64641.01 | D2: 65287.42 | E2: 68656.241 | F2: 69342.803 | G2: 70036.231 | H2: 70736.593 | I2: 74678.848 | J2: 75425.637 | K2: 76179.893 | L2: 76941.692 | M2: 77711.109 | N2: 78488.22 | O2: 79273.102 | P2: 80065.833 | Q2: 80866.492 | R2: 81675.157 | S2: 82491.908 | T2: 83316.827 | U2: 84149.996 | V2: 90018.77 | W2: 90918.957 | X2: 91828.147 | Y2: 92746.428 | Z2: 93673.893 | AA2: 94610.632 | AB2: 95556.738 | AC2: 96512.305 | AD2: 97477.428 | AE2: 98452.203
A3: Personal Contribution (%) | B3: ='Salary Variables'!$C$12 -> 0.05 | C3: ='Salary Variables'!$C$12 -> 0.05 | D3: ='Salary Variables'!$C$12 -> 0.05 | E3: ='Salary Variables'!$C$12 -> 0.05 | F3: ='Salary Variables'!$C$12 -> 0.05 | G3: ='Salary Variables'!$C$12 -> 0.05 | H3: ='Salary Variables'!$C$12 -> 0.05 | I3: ='Salary Variables'!$C$12 -> 0.05 | ... AT3: ='Salary Variables'!$C$12 -> 0.05
A4: Personal Contribution | B4: =B3*B2 -> 3200.05 | C4: =C3*C2 -> 3232.0505 | D4: =D3*D2 -> 3264.371 | E4: =E3*E2 -> 3432.812 | F4: =F3*F2 -> 3467.1402 | G4: =G3*G2 -> 3501.8116 | H4: =H3*H2 -> 3536.8297 | I4: =I3*I2 -> 3733.9424 | ... AT4: =AT3*AT2 -> 0
A5: Company Contribution (%) | B5: ='Salary Variables'!$C$13 -> 0.1 | C5: ='Salary Variables'!$C$13 -> 0.1 | D5: ='Salary Variables'!$C$13 -> 0.1 | E5: ='Salary Variables'!$C$13 -> 0.1 | F5: ='Salary Variables'!$C$13 -> 0.1 | G5: ='Salary Variables'!$C$13 -> 0.1 | H5: ='Salary Variables'!$C$13 -> 0.1 | I5: ='Salary Variables'!$C$13 -> 0.1 | ... AT5: ='Salary Variables'!$C$13 -> 0.1
A6: Company Contribution | B6: =B2*B5 -> 6400.1 | C6: =C4*2 -> 6464.101 | D6: =D4*2 -> 6528.742 | E6: =E4*2 -> 6865.6241 | F6: =F4*2 -> 6934.2803 | G6: =G4*2 -> 7003.6231 | H6: =H4*2 -> 7073.6593 | I6: =I4*2 -> 7467.8848 | J6: =J4*2 -> 7542.5637 | ... AT6: =AT4*2 -> 0
A7: Total Contribution (Monthly) | B7: =SUM(B6,B4) -> 9600.15 | C7: =SUM(C6,C4) -> 9696.1515 | D7: =SUM(D6,D4) -> 9793.113 | E7: =SUM(E6,E4) -> 10298.436 | F7: =SUM(F6,F4) -> 10401.42 | G7: =SUM(G6,G4) -> 10505.435 | H7: =SUM(H6,H4) -> 10610.489 | I7: =SUM(I6,I4) -> 11201.827 | ... AT7: =SUM(AT6,AT4) -> 0
A8: Total Contribution (Yearly) | B8: =B7*12 -> 115201.8 | C8: =C7*12 -> 116353.82 | D8: =D7*12 -> 117517.36 | E8: =E7*12 -> 123581.23 | F8: =F7*12 -> 124817.05 | G8: =G7*12 -> 126065.22 | H8: =H7*12 -> 127325.87 | I8: =I7*12 -> 134421.93 | ... AT8: =AT7*12 -> 0
A12: Total Contribution (ratepension) | B12: =SUM(B8:AT8) -> 4402370.7
A13: Divided by 25 years | B13: =B12/25 -> 176094.83 | C13: per year
A14: Monthly | B14: =B13/12 -> 14674.569 | C14: per month (gross)
A15: Taxed in Retirement? | B15: Yes | C15: Income tax
A17: Aldersopsparing | B17: =SUM('Net Salary P2'!E14:AW14) -> 255931.51 | C17: taken from sum of Net Salary P1 page
A18: Divided by 25 years | B18: =B17/25 -> 10237.26
A19: Monthly | B19: =B18/12 -> 853.10504
A20: Taxed in Retirement? | B20: No
A22: Public Pension Average Monthly | B22: 9500
A23: Public Pension Average Yearly | B23: =B22*12 -> 114000
A24: Taxed in Retirement? | B24: Yes
A25: Inflation | B25: ='Salary Variables'!$C$2 -> 0.02
A27: Year | B27: 2070 | C27: 2071 | D27: 2072 | E27: 2073 | F27: 2074 | G27: 2075 | H27: 2076 | I27: 2077 | J27: 2078 | K27: 2079 | L27: 2080 | M27: 2081 | N27: 2082 | O27: 2083 | P27: 2084 | Q27: 2085 | R27: 2086 | S27: 2087 | T27: 2088 | U27: 2089 | V27: 2090 | W27: 2091 | X27: 2092 | Y27: 2093 | Z27: 2094

Sheet Net Salary P1
A1: Inflation | B1: ='Salary Variables'!$C$2 -> 0.02 | D1: Year | E1: 2025 | F1: 2026 | G1: 2027 | H1: 2028 | I1: 2029 | J1: 2030 | K1: 2031 | L1: 2032 | M1: 2033 | N1: 2034 | O1: 2035 | P1: 2036 | Q1: 2037 | R1: 2038 | S1: 2039 | T1: 2040 | U1: 2041 | V1: 2042 | W1: 2043 | X1: 2044 | Y1: 2045 | Z1: 2046 | AA1: 2047 | AB1: 2048 | AC1: 2049 | AD1: 2050 | AE1: 2051 | AF1: 2052 | AG1: 2053 | AH1: 2054 | AI1: 2055 | AJ1: 2056 | AK1: 2057 | AL1: 2058 | AM1: 2059 | AN1: 2060 | AO1: 2061 | AP1: 2062 | AQ1: 2063 | AR1: 2064 | AS1: 2065 | AT1: 2066 | AU1: 2067 | AV1: 2068 | AW1: 2069
A2: Aldersopsparing max | B2: ='Salary Variables'!$C$14 -> 9400 | D2: Month Salary (Inflation Adjusted) | E2: {=TRANSPOSE(Income!N3:N47)} -> 43871 | F2: 44309.71 | G2: 46525.195 | H2: 46990.447 | I2: 47460.352 | J2: 47934.955 | K2: 50331.703 | L2: 50835.02 | M2: 51343.37 | N2: 51856.804 | O2: 54449.644 | P2: 54994.141 | Q2: 55544.082 | R2: 56099.523 | S2: 58904.499 | T2: 59493.544 | U2: 60088.48 | V2: 60689.364 | W2: 63723.833 | X2: 64361.071 | Y2: 65004.682 | Z2: 65654.728 | AA2: 68937.465 | AB2: 69626.84 | AC2: 70323.108 | AD2: 71026.339 | AE2: 71736.602 | AF2: 72453.968 | AG2: 73178.508 | AH2: 73910.293 | AI2: 74649.396 | AJ2: 75395.89 | AK2: 76149.849 | AL2: 76911.348 | AM2: 77680.461 | AN2: 81564.484 | AO2: 82380.129 | AP2: 83203.93 | AQ2: 84035.969 | AR2: 84876.329 | AS2: 85725.092 | AT2: 86582.343 | AU2: 87448.167 | AV2: 88322.648 | AW2: 89205.875 | BH2: helper for other column, do not remove --> | BI2: {=TRANSPOSE(E16:AW16)} -> 23885.512
D3: Yearly Salary | E3: =E2*12 -> 526452 | F3: =F2*12 -> 531716.52 | G3: =G2*12 -> 558302.35 | H3: =H2*12 -> 563885.37 | I3: =I2*12 -> 569524.22 | J3: =J2*12 -> 575219.47 | K3: =K2*12 -> 603980.44 | L3: =L2*12 -> 610020.24 | ... AW3: =AW2*12 -> 1070470.5 | BI3: 24142.396
A4: {='Salary Variables'!$B$16:$C$24} -> AM (%) | B4: 0.08 | D4: Ratepension | E4: ='Pensions P1'!B4*12 -> 26322.6 | F4: ='Pensions P1'!C4*12 -> 26585.826 | G4: ='Pensions P1'!D4*12 -> 27915.117 | H4: ='Pensions P1'!E4*12 -> 28194.268 | I4: ='Pensions P1'!F4*12 -> 28476.211 | J4: ='Pensions P1'!G4*12 -> 28760.973 | K4: ='Pensions P1'!H4*12 -> 30199.022 | L4: ='Pensions P1'!I4*12 -> 30501.012 | ... AW4: ='Pensions P1'!AT4*12 -> 53523.525 | BI4: 25377.151
A5: Personal Allowance | B5: 51600 | D5: Post Pension | E5: =E3-E4 -> 500129.4 | F5: =F3-F4 -> 505130.69 | G5: =G3-G4 -> 530387.23 | H5: =H3-H4 -> 535691.1 | I5: =I3-I4 -> 541048.01 | J5: =J3-J4 -> 546458.49 | K5: =K3-K4 -> 573781.42 | L5: =L3-L4 -> 579519.23 | ... AW5: =AW3-AW4 -> 1016947 | BI5: 25648.051
A6: Bottom-Bracket State Tax rate (%) | B6: 0.1201 | D6: Post AM (Taxable Personal Income) | E6: =E5*(1-$B$4) -> 460119.05 | F6: =F5*(1-$B$4) -> 464720.24 | G6: =G5*(1-$B$4) -> 487956.25 | H6: =H5*(1-$B$4) -> 492835.81 | I6: =I5*(1-$B$4) -> 497764.17 | J6: =J5*(1-$B$4) -> 502741.81 | K6: =K5*(1-$B$4) -> 527878.9 | L6: =L5*(1-$B$4) -> 533157.69 | ... AW6: =AW5*(1-$B$4) -> 935591.22 | BI6: 25921.222
A7: Top-bracket State Tax rate (%) | B7: 0.15 | D7: Personal Allowance | E7: =$B$5 -> 51600 | F7: =$B$5 -> 51600 | G7: =$B$5 -> 51600 | H7: =$B$5 -> 51600 | I7: =$B$5 -> 51600 | J7: =$B$5 -> 51600 | K7: =$B$5 -> 51600 | L7: =$B$5 -> 51600 | ... AW7: =$B$5 -> 51600 | BI7: 26196.697
A8: State Tax Bracket Threshold | B8: 618400 | D8: TPI exceed PA | E8: =E6-E7 -> 408519.05 | F8: =F6-F7 -> 413120.24 | G8: =G6-G7 -> 436356.25 | H8: =H6-H7 -> 441235.81 | I8: =I6-I7 -> 446164.17 | J8: =J6-J7 -> 451141.81 | K8: =K6-K7 -> 476278.9 | L8: =L6-L7 -> 481557.69 | ... AW8: =AW6-AW7 -> 883991.22 | BI8: 27530.096
A9: Municipal Tax (%) | B9: 0.25 | D9: Municipal Tax | E9: =E6*$B$9 -> 115029.76 | F9: =F6*$B$9 -> 116180.06 | G9: =G6*$B$9 -> 121989.06 | H9: =H6*$B$9 -> 123208.95 | I9: =I6*$B$9 -> 124441.04 | J9: =J6*$B$9 -> 125685.45 | K9: =K6*$B$9 -> 131969.73 | L9: =L6*$B$9 -> 133289.42 | ... AW9: =AW6*$B$9 -> 233897.8 | BI9: 27820.827
A10: Capital Gains < 67,500DKK | B10: 0.27 | D10: Top State Tax | E10: =MAX(E8-$B$8,0)*$B$7 -> 0 | F10: =MAX(F8-$B$8,0)*$B$7 -> 0 | G10: =MAX(G8-$B$8,0)*$B$7 -> 0 | H10: =MAX(H8-$B$8,0)*$B$7 -> 0 | I10: =MAX(I8-$B$8,0)*$B$7 -> 0 | J10: =MAX(J8-$B$8,0)*$B$7 -> 0 | K10: =MAX(K8-$B$8,0)*$B$7 -> 0 | L10: =MAX(L8-$B$8,0)*$B$7 -> 0 | ... AW10: =MAX(AW8-$B$8,0)*$B$7 -> 39838.683 | BI10: 28114.062
A11: Capital Gains > 67,500DKK | B11: 0.42 | D11: Bottom State Tax | E11: =E8*$B$6 -> 49063.138 | F11: =F8*$B$6 -> 49615.741 | G11: =G8*$B$6 -> 52406.386 | H11: =H8*$B$6 -> 52992.421 | I11: =I8*$B$6 -> 53584.317 | J11: =J8*$B$6 -> 54182.132 | K11: =K8*$B$6 -> 57201.096 | L11: =L8*$B$6 -> 57835.079 | ... AW11: =AW8*$B$6 -> 106167.35 | BI11: 28409.833
A12: Capital Gains Threshold | B12: 67500 | D12: Total Tax | E12: =SUM(E9:E11) -> 164092.9 | F12: =SUM(F9:F11) -> 165795.8 | G12: =SUM(G9:G11) -> 174395.45 | H12: =SUM(H9:H11) -> 176201.37 | I12: =SUM(I9:I11) -> 178025.36 | J12: =SUM(J9:J11) -> 179867.58 | K12: =SUM(K9:K11) -> 189170.82 | L12: =SUM(L9:L11) -> 191124.5 | ... AW12: =SUM(AW9:AW11) -> 379903.83 | BI12: 29850.128
D13: Post Tax Salary | E13: =E6-E12 -> 296026.15 | F13: =F6-F12 -> 298924.44 | G13: =G6-G12 -> 313560.8 | H13: =H6-H12 -> 316634.44 | I13: =I6-I12 -> 319738.81 | J13: =J6-J12 -> 322874.23 | K13: =K6-K12 -> 338708.08 | L13: =L6-L12 -> 342033.19 | ... AW13: =AW6-AW12 -> 555687.38 | BI13: 30162.491
D14: Aldersopsparing | E14: =$B$2/(1+$B$1)^(E1-$E$1) -> 9400 | F14: =$B$2/(1+$B$1)^(F1-$E$1) -> 9215.6863 | G14: =$B$2/(1+$B$1)^(G1-$E$1) -> 9034.9865 | H14: =$B$2/(1+$B$1)^(H1-$E$1) -> 8857.8299 | I14: =$B$2/(1+$B$1)^(I1-$E$1) -> 8684.147 | J14: =$B$2/(1+$B$1)^(J1-$E$1) -> 8513.8696 | K14: =$B$2/(1+$B$1)^(K1-$E$1) -> 8346.931 | L14: =$B$2/(1+$B$1)^(L1-$E$1) -> 8183.2657 | ... AW14: =$B$2/(1+$B$1)^(AW1-$E$1) -> 3932.9669 | BI14: 30477.605
D15: Net Salary (Yearly) | E15: =E13-E14 -> 286626.15 | F15: =F13-F14 -> 289708.75 | G15: =G13-G14 -> 304525.82 | H15: =H13-H14 -> 307776.61 | I15: =I13-I14 -> 311054.66 | J15: =J13-J14 -> 314360.36 | K15: =K13-K14 -> 330361.15 | L15: =L13-L14 -> 333849.92 | ... AW15: =AW13-AW14 -> 551754.42 | BI15: 30795.504
D16: Net Salary (Monthly) | E16: =E15/12 -> 23885.512 | F16: =F15/12 -> 24142.396 | G16: =G15/12 -> 25377.151 | H16: =H15/12 -> 25648.051 | I16: =I15/12 -> 25921.222 | J16: =J15/12 -> 26196.697 | K16: =K15/12 -> 27530.096 | L16: =L15/12 -> 27820.827 | ... AW16: =AW15/12 -> 45979.535 | BI16: 32351.608
BI17: 32687.537
BI18: 33026.481
BI19: 33368.476
BI20: 35050.019
D21: Year | E21: 2070 | F21: 2071 | G21: 2072 | H21: 2073 | I21: 2074 | J21: 2075 | K21: 2076 | L21: 2077 | M21: 2078 | N21: 2079 | O21: 2080 | P21: 2081 | Q21: 2082 | R21: 2083 | S21: 2084 | T21: 2085 | U21: 2086 | V21: 2087 | W21: 2088 | X21: 2089 | Y21: 2090 | Z21: 2091 | AA21: 2092 | AB21: 2093 | AC21: 2094 | BI21: 35348.857
D22: Monthly Salary | E22: ='Pensions P1'!$B$14+'Pensions P1'!$B$22 -> 27534.747 | F22: ='Pensions P1'!$B$14+'Pensions P1'!$B$22 -> 27534.747 | G22: ='Pensions P1'!$B$14+'Pensions P1'!$B$22 -> 27534.747 | H22: ='Pensions P1'!$B$14+'Pensions P1'!$B$22 -> 27534.747 | I22: ='Pensions P1'!$B$14+'Pensions P1'!$B$22 -> 27534.747 | J22: ='Pensions P1'!$B$14+'Pensions P1'!$B$22 -> 27534.747 | K22: ='Pensions P1'!$B$14+'Pensions P1'!$B$22 -> 27534.747 | L22: ='Pensions P1'!$B$14+'Pensions P1'!$B$22 -> 27534.747 | ... AC22: ='Pensions P1'!$B$14+'Pensions P1'!$B$22 -> 27534.747 | BI22: 35629.352
BI23: 35912.339
D24: Yearly Salary Inflation Adjusted | E24: =E22*12 -> 330416.97 | F24: =F22*12 -> 330416.97 | G24: =G22*12 -> 330416.97 | H24: =H22*12 -> 330416.97 | I24: =I22*12 -> 330416.97 | J24: =J22*12 -> 330416.97 | K24: =K22*12 -> 330416.97 | L24: =L22*12 -> 330416.97 | ... AC24: =AC22*12 -> 330416.97 | BI24: 37299.36
D25: Municipal Tax | E25: =E24*$B$11 -> 138775.13 | F25: =F24*$B$11 -> 138775.13 | G25: =G24*$B$11 -> 138775.13 | H25: =H24*$B$11 -> 138775.13 | I25: =I24*$B$11 -> 138775.13 | J25: =J24*$B$11 -> 138775.13 | K25: =K24*$B$11 -> 138775.13 | L25: =L24*$B$11 -> 138775.13 | ... AC25: =AC24*$B$11 -> 138775.13 | BI25: 37598.441
D26: Top State Tax | E26: =MAX(E24-$B$10,0)*$B$9 -> 82604.174 | F26: =MAX(F24-$B$10,0)*$B$9 -> 82604.174 | G26: =MAX(G24-$B$10,0)*$B$9 -> 82604.174 | H26: =MAX(H24-$B$10,0)*$B$9 -> 82604.174 | I26: =MAX(I24-$B$10,0)*$B$9 -> 82604.174 | J26: =MAX(J24-$B$10,0)*$B$9 -> 82604.174 | K26: =MAX(K24-$B$10,0)*$B$9 -> 82604.174 | L26: =MAX(L24-$B$10,0)*$B$9 -> 82604.174 | ... AC26: =MAX(AC24-$B$10,0)*$B$9 -> 82604.174 | BI26: 37900.219
D27: Bottom State Tax | E27: =E24*$B$6 -> 39683.078 | F27: =F24*$B$6 -> 39683.078 | G27: =G24*$B$6 -> 39683.078 | H27: =H24*$B$6 -> 39683.078 | I27: =I24*$B$6 -> 39683.078 | J27: =J24*$B$6 -> 39683.078 | K27: =K24*$B$6 -> 39683.078 | L27: =L24*$B$6 -> 39683.078 | ... AC27: =AC24*$B$6 -> 39683.078 | BI27: 38204.726
D28: Total Tax | E28: =SUM(E25:E27) -> 261062.38 | F28: =SUM(F25:F27) -> 261062.38 | G28: =SUM(G25:G27) -> 261062.38 | H28: =SUM(H25:H27) -> 261062.38 | I28: =SUM(I25:I27) -> 261062.38 | J28: =SUM(J25:J27) -> 261062.38 | K28: =SUM(K25:K27) -> 261062.38 | L28: =SUM(L25:L27) -> 261062.38 | ... AC28: =SUM(AC25:AC27) -> 261062.38 | BI28: 38511.996
D29: Post Tax Salary | E29: =E24-E28 -> 69354.589 | F29: =F24-F28 -> 69354.589 | G29: =G24-G28 -> 69354.589 | H29: =H24-H28 -> 69354.589 | I29: =I24-I28 -> 69354.589 | J29: =J24-J28 -> 69354.589 | K29: =K24-K28 -> 69354.589 | L29: =L24-L28 -> 69354.589 | ... AC29: =AC24-AC28 -> 69354.589 | BI29: 38822.061
D30: Aldersopsparing benefit | E30: ='Pensions P1'!$B$18 -> 11310.066 | F30: ='Pensions P1'!$B$18 -> 11310.066 | G30: ='Pensions P1'!$B$18 -> 11310.066 | H30: ='Pensions P1'!$B$18 -> 11310.066 | I30: ='Pensions P1'!$B$18 -> 11310.066 | J30: ='Pensions P1'!$B$18 -> 11310.066 | K30: ='Pensions P1'!$B$18 -> 11310.066 | L30: ='Pensions P1'!$B$18 -> 11310.066 | ... AC30: ='Pensions P1'!$B$18 -> 11310.066 | BI30: 39134.955
D31: Net Salary (Yearly) | E31: =E30+E29 -> 80664.655 | F31: =F30+F29 -> 80664.655 | G31: =G30+G29 -> 80664.655 | H31: =H30+H29 -> 80664.655 | I31: =I30+I29 -> 80664.655 | J31: =J30+J29 -> 80664.655 | K31: =K30+K29 -> 80664.655 | L31: =L30+L29 -> 80664.655 | ... AC31: =AC30+AC29 -> 80664.655 | BI31: 39450.712
D32: Net Salary (Monthly) | E32: =E31/12 -> 6722.0546 | F32: =F31/12 -> 6722.0546 | G32: =G31/12 -> 6722.0546 | H32: =H31/12 -> 6722.0546 | I32: =I31/12 -> 6722.0546 | J32: =J31/12 -> 6722.0546 | K32: =K31/12 -> 6722.0546 | L32: =L31/12 -> 6722.0546 | ... AC32: =AC31/12 -> 6722.0546 | BI32: 39769.365
D33: Last Yearly Income from Work | E33: =$AW$16 -> 45979.535 | F33: =$AW$16 -> 45979.535 | G33: =$AW$16 -> 45979.535 | H33: =$AW$16 -> 45979.535 | I33: =$AW$16 -> 45979.535 | J33: =$AW$16 -> 45979.535 | K33: =$AW$16 -> 45979.535 | L33: =$AW$16 -> 45979.535 | ... AC33: =$AW$16 -> 45979.535 | BI33: 40090.948
D34: Diff | E34: =E33-E32 -> 39257.48 | F34: =F33-F32 -> 39257.48 | G34: =G33-G32 -> 39257.48 | H34: =H33-H32 -> 39257.48 | I34: =I33-I32 -> 39257.48 | J34: =J33-J32 -> 39257.48 | K34: =K33-K32 -> 39257.48 | L34: =L33-L32 -> 39257.48 | ... AC34: =AC33-AC32 -> 39257.48 | BI34: 40415.496
E35: =E34*(1+$B$10) -> 49857 | F35: =F34*(1+$B$10) -> 49857 | G35: =G34*(1+$B$10) -> 49857 | H35: =H34*(1+$B$10) -> 49857 | I35: =I34*(1+$B$10) -> 49857 | J35: =J34*(1+$B$10) -> 49857 | K35: =K34*(1+$B$10) -> 49857 | L35: =L34*(1+$B$10) -> 49857 | ... AC35: =AC34*(1+$B$10) -> 49857 | BI35: 40743.044
BI36: 41073.626
BI37: 42710.545
D38: To be financed | E38: =SUM(E35:AC35) -> 1246425 | BI38: 43060.334
BI39: 43413.392
BI40: 43769.759
BI41: 44129.47
BI42: 44492.564
BI43: 44859.079
BI44: 45229.054
BI45: 45602.526
BI46: 45979.535

Sheet Net Salary P2
A1: Inflation | B1: =Income!I2 -> 0.02 | D1: Year | E1: 2025 | F1: 2026 | G1: 2027 | H1: 2028 | I1: 2029 | J1: 2030 | K1: 2031 | L1: 2032 | M1: 2033 | N1: 2034 | O1: 2035 | P1: 2036 | Q1: 2037 | R1: 2038 | S1: 2039 | T1: 2040 | U1: 2041 | V1: 2042 | W1: 2043 | X1: 2044 | Y1: 2045 | Z1: 2046 | AA1: 2047 | AB1: 2048 | AC1: 2049 | AD1: 2050 | AE1: 2051 | AF1: 2052 | AG1: 2053 | AH1: 2054
A2: Aldersopsparing max | B2: 9400 | D2: Month Salary (Inflation Adjusted) | E2: {=TRANSPOSE(Income!O3:O32)} -> 64001 | F2: 64641.01 | G2: 65287.42 | H2: 68656.241 | I2: 69342.803 | J2: 70036.231 | K2: 70736.593 | L2: 74678.848 | M2: 75425.637 | N2: 76179.893 | O2: 76941.692 | P2: 77711.109 | Q2: 78488.22 | R2: 79273.102 | S2: 80065.833 | T2: 80866.492 | U2: 81675.157 | V2: 82491.908 | W2: 83316.827 | X2: 84149.996 | Y2: 90018.77 | Z2: 90918.957 | AA2: 91828.147 | AB2: 92746.428 | AC2: 93673.893 | AD2: 94610.632 | AE2: 95556.738 | AF2: 96512.305 | AG2: 97477.428 | AH2: 98452.203 | AS2: helper for other column, do not remove --> | AT2: {=TRANSPOSE(E16:AH16)} -> 34952.202
D3: Yearly Salary | E3: =E2*12 -> 768012 | F3: =F2*12 -> 775692.12 | G3: =G2*12 -> 783449.04 | H3: =H2*12 -> 823874.89 | I3: =I2*12 -> 832113.64 | J3: =J2*12 -> 840434.77 | K3: =K2*12 -> 848839.12 | L3: =L2*12 -> 896146.18 | ... AH3: =AH2*12 -> 1181426.4 | AT3: 35236.003
A4: {='Salary Variables'!$B$16:$C$24} -> AM (%) | B4: 0.08 | D4: Ratepension | E4: ='Pensions P2'!B4*12 -> 38400.6 | F4: ='Pensions P2'!C4*12 -> 38784.606 | G4: ='Pensions P2'!D4*12 -> 39172.452 | H4: ='Pensions P2'!E4*12 -> 41193.744 | I4: ='Pensions P2'!F4*12 -> 41605.682 | J4: ='Pensions P2'!G4*12 -> 42021.739 | K4: ='Pensions P2'!H4*12 -> 42441.956 | L4: ='Pensions P2'!I4*12 -> 44807.309 | ... AH4: ='Pensions P2'!AE4*12 -> 59071.322 | AT4: 35522.187
A5: Personal Allowance | B5: 51600 | D5: Post Pension | E5: =E3-E4 -> 729611.4 | F5: =F3-F4 -> 736907.51 | G5: =G3-G4 -> 744276.59 | H5: =H3-H4 -> 782681.14 | I5: =I3-I4 -> 790507.96 | J5: =J3-J4 -> 798413.04 | K5: =K3-K4 -> 806397.17 | L5: =L3-L4 -> 851338.87 | ... AH5: =AH3-AH4 -> 1122355.1 | AT5: 36949.943
A6: Bottom-Bracket State Tax rate (%) | B6: 0.1201 | D6: Post AM (Taxable Personal Income) | E6: =E5*(1-$B$4) -> 671242.49 | F6: =F5*(1-$B$4) -> 677954.91 | G6: =G5*(1-$B$4) -> 684734.46 | H6: =H5*(1-$B$4) -> 720066.65 | I6: =I5*(1-$B$4) -> 727267.32 | J6: =J5*(1-$B$4) -> 734539.99 | K6: =K5*(1-$B$4) -> 741885.39 | L6: =L5*(1-$B$4) -> 783231.76 | ... AH6: =AH5*(1-$B$4) -> 1032566.7 | AT6: 37252.383
A7: Top-bracket State Tax rate (%) | B7: 0.15 | D7: Personal Allowance | E7: =$B$5 -> 51600 | F7: =$B$5 -> 51600 | G7: =$B$5 -> 51600 | H7: =$B$5 -> 51600 | I7: =$B$5 -> 51600 | J7: =$B$5 -> 51600 | K7: =$B$5 -> 51600 | L7: =$B$5 -> 51600 | ... AH7: =$B$5 -> 51600 | AT7: 37557.419
A8: State Tax Bracket Threshold | B8: 618400 | D8: TPI exceed PA | E8: =E6-E7 -> 619642.49 | F8: =F6-F7 -> 626354.91 | G8: =G6-G7 -> 633134.46 | H8: =H6-H7 -> 668466.65 | I8: =I6-I7 -> 675667.32 | J8: =J6-J7 -> 682939.99 | K8: =K6-K7 -> 690285.39 | L8: =L6-L7 -> 731631.76 | ... AH8: =AH6-AH7 -> 980966.7 | AT8: 37865.086
A9: Municipal Tax (%) | B9: 0.25 | D9: Municipal Tax | E9: =E6*$B$9 -> 167810.62 | F9: =F6*$B$9 -> 169488.73 | G9: =G6*$B$9 -> 171183.62 | H9: =H6*$B$9 -> 180016.66 | I9: =I6*$B$9 -> 181816.83 | J9: =J6*$B$9 -> 183635 | K9: =K6*$B$9 -> 185471.35 | L9: =L6*$B$9 -> 195807.94 | ... AH9: =AH6*$B$9 -> 258141.68 | AT9: 39532.235
A10: Capital Gains < 67,500DKK | B10: 0.27 | D10: Top State Tax | E10: =MAX(E8-$B$8,0)*$B$7 -> 186.3732 | F10: =MAX(F8-$B$8,0)*$B$7 -> 1193.2369 | G10: =MAX(G8-$B$8,0)*$B$7 -> 2210.1693 | H10: =MAX(H8-$B$8,0)*$B$7 -> 7509.9979 | I10: =MAX(I8-$B$8,0)*$B$7 -> 8590.0979 | J10: =MAX(J8-$B$8,0)*$B$7 -> 9680.9989 | K10: =MAX(K8-$B$8,0)*$B$7 -> 10782.809 | L10: =MAX(L8-$B$8,0)*$B$7 -> 16984.764 | ... AH10: =MAX(AH8-$B$8,0)*$B$7 -> 54385.005 | AT10: 39858.834
A11: Capital Gains > 67,500DKK | B11: 0.42 | D11: Bottom State Tax | E11: =E8*$B$6 -> 74419.063 | F11: =F8*$B$6 -> 75225.225 | G11: =G8*$B$6 -> 76039.449 | H11: =H8*$B$6 -> 80282.845 | I11: =I8*$B$6 -> 81147.645 | J11: =J8*$B$6 -> 82021.093 | K11: =K8*$B$6 -> 82903.276 | L11: =L8*$B$6 -> 87868.975 | ... AH11: =AH8*$B$6 -> 117814.1 | AT11: 40188.302
A12: Capital Gains Threshold | B12: 67500 | D12: Total Tax | E12: =SUM(E9:E11) -> 242416.06 | F12: =SUM(F9:F11) -> 245907.19 | G12: =SUM(G9:G11) -> 249433.23 | H12: =SUM(H9:H11) -> 267809.51 | I12: =SUM(I9:I11) -> 271554.57 | J12: =SUM(J9:J11) -> 275337.09 | K12: =SUM(K9:K11) -> 279157.43 | L12: =SUM(L9:L11) -> 300661.68 | ... AH12: =SUM(AH9:AH11) -> 430340.78 | AT12: 40520.678
D13: Post Tax Salary | E13: =E6-E12 -> 428826.43 | F13: =F6-F12 -> 432047.72 | G13: =G6-G12 -> 435301.23 | H13: =H6-H12 -> 452257.15 | I13: =I6-I12 -> 455712.75 | J13: =J6-J12 -> 459202.9 | K13: =K6-K12 -> 462727.96 | L13: =L6-L12 -> 482570.08 | ... AH13: =AH6-AH12 -> 602225.92 | AT13: 40855.996
D14: Aldersopsparing | E14: =$B$2/(1+$B$1)^(E1-$E$1) -> 9400 | F14: =$B$2/(1+$B$1)^(F1-$E$1) -> 9215.6863 | G14: =$B$2/(1+$B$1)^(G1-$E$1) -> 9034.9865 | H14: =$B$2/(1+$B$1)^(H1-$E$1) -> 8857.8299 | I14: =$B$2/(1+$B$1)^(I1-$E$1) -> 8684.147 | J14: =$B$2/(1+$B$1)^(J1-$E$1) -> 8513.8696 | K14: =$B$2/(1+$B$1)^(K1-$E$1) -> 8346.931 | L14: =$B$2/(1+$B$1)^(L1-$E$1) -> 8183.2657 | ... AH14: =$B$2/(1+$B$1)^(AH1-$E$1) -> 5293.2557 | AT14: 41194.295
D15: Net Salary (Yearly) | E15: =E13-E14 -> 419426.43 | F15: =F13-F14 -> 422832.04 | G15: =G13-G14 -> 426266.24 | H15: =H13-H14 -> 443399.32 | I15: =I13-I14 -> 447028.6 | J15: =J13-J14 -> 450689.03 | K15: =K13-K14 -> 454381.03 | L15: =L13-L14 -> 474386.82 | ... AH15: =AH13-AH14 -> 596932.66 | AT15: 41535.611
D16: Net Salary (Monthly) | E16: =E15/12 -> 34952.202 | F16: =F15/12 -> 35236.003 | G16: =G15/12 -> 35522.187 | H16: =H15/12 -> 36949.943 | I16: =I15/12 -> 37252.383 | J16: =J15/12 -> 37557.419 | K16: =K15/12 -> 37865.086 | L16: =L15/12 -> 39532.235 | ... AH16: =AH15/12 -> 49744.389 | AT16: 41879.982
AT17: 42227.445
AT18: 42578.037
AT19: 42931.798
AT20: 43288.765
D21: Year | E21: 2055 | F21: 2056 | G21: 2057 | H21: 2058 | I21: 2059 | J21: 2060 | K21: 2061 | L21: 2062 | M21: 2063 | N21: 2064 | O21: 2065 | P21: 2066 | Q21: 2067 | R21: 2068 | S21: 2069 | T21: 2070 | U21: 2071 | V21: 2072 | W21: 2073 | X21: 2074 | Y21: 2075 | Z21: 2076 | AA21: 2077 | AB21: 2078 | AC21: 2079 | AT21: 43648.977
D22: Monthly Salary | E22: ='Pensions P2'!$B$14+'Pensions P2'!$B$22 -> 24174.569 | F22: ='Pensions P2'!$B$14+'Pensions P2'!$B$22 -> 24174.569 | G22: ='Pensions P2'!$B$14+'Pensions P2'!$B$22 -> 24174.569 | H22: ='Pensions P2'!$B$14+'Pensions P2'!$B$22 -> 24174.569 | I22: ='Pensions P2'!$B$14+'Pensions P2'!$B$22 -> 24174.569 | J22: ='Pensions P2'!$B$14+'Pensions P2'!$B$22 -> 24174.569 | K22: ='Pensions P2'!$B$14+'Pensions P2'!$B$22 -> 24174.569 | L22: ='Pensions P2'!$B$14+'Pensions P2'!$B$22 -> 24174.569 | ... AC22: ='Pensions P2'!$B$14+'Pensions P2'!$B$22 -> 24174.569 | AT22: 46121.076
AT23: 46508.98
D24: Yearly Salary Inflation Adjusted | E24: =E22*12 -> 290094.83 | F24: =F22*12 -> 290094.83 | G24: =G22*12 -> 290094.83 | H24: =H22*12 -> 290094.83 | I24: =I22*12 -> 290094.83 | J24: =J22*12 -> 290094.83 | K24: =K22*12 -> 290094.83 | L24: =L22*12 -> 290094.83 | ... AC24: =AC22*12 -> 290094.83 | AT24: 46900.458
D25: Municipal Tax | E25: =E24*$B$11 -> 121839.83 | F25: =F24*$B$11 -> 121839.83 | G25: =G24*$B$11 -> 121839.83 | H25: =H24*$B$11 -> 121839.83 | I25: =I24*$B$11 -> 121839.83 | J25: =J24*$B$11 -> 121839.83 | K25: =K24*$B$11 -> 121839.83 | L25: =L24*$B$11 -> 121839.83 | ... AC25: =AC24*$B$11 -> 121839.83 | AT25: 47295.55
D26: Top State Tax | E26: =MAX(E24-$B$10,0)*$B$9 -> 72523.64 | F26: =MAX(F24-$B$10,0)*$B$9 -> 72523.64 | G26: =MAX(G24-$B$10,0)*$B$9 -> 72523.64 | H26: =MAX(H24-$B$10,0)*$B$9 -> 72523.64 | I26: =MAX(I24-$B$10,0)*$B$9 -> 72523.64 | J26: =MAX(J24-$B$10,0)*$B$9 -> 72523.64 | K26: =MAX(K24-$B$10,0)*$B$9 -> 72523.64 | L26: =MAX(L24-$B$10,0)*$B$9 -> 72523.64 | ... AC26: =MAX(AC24-$B$10,0)*$B$9 -> 72523.64 | AT26: 47694.299
D27: Bottom State Tax | E27: =E24*$B$6 -> 34840.389 | F27: =F24*$B$6 -> 34840.389 | G27: =G24*$B$6 -> 34840.389 | H27: =H24*$B$6 -> 34840.389 | I27: =I24*$B$6 -> 34840.389 | J27: =J24*$B$6 -> 34840.389 | K27: =K24*$B$6 -> 34840.389 | L27: =L24*$B$6 -> 34840.389 | ... AC27: =AC24*$B$6 -> 34840.389 | AT27: 48096.747
D28: Total Tax | E28: =SUM(E25:E27) -> 229203.86 | F28: =SUM(F25:F27) -> 229203.86 | G28: =SUM(G25:G27) -> 229203.86 | H28: =SUM(H25:H27) -> 229203.86 | I28: =SUM(I25:I27) -> 229203.86 | J28: =SUM(J25:J27) -> 229203.86 | K28: =SUM(K25:K27) -> 229203.86 | L28: =SUM(L25:L27) -> 229203.86 | ... AC28: =SUM(AC25:AC27) -> 229203.86 | AT28: 48502.937
D29: Post Tax Salary | E29: =E24-E28 -> 60890.972 | F29: =F24-F28 -> 60890.972 | G29: =G24-G28 -> 60890.972 | H29: =H24-H28 -> 60890.972 | I29: =I24-I28 -> 60890.972 | J29: =J24-J28 -> 60890.972 | K29: =K24-K28 -> 60890.972 | L29: =L24-L28 -> 60890.972 | ... AC29: =AC24-AC28 -> 60890.972 | AT29: 48912.912
D30: Aldersopsparing benefit | E30: ='Pensions P2'!$B$18 -> 10237.26 | F30: ='Pensions P2'!$B$18 -> 10237.26 | G30: ='Pensions P2'!$B$18 -> 10237.26 | H30: ='Pensions P2'!$B$18 -> 10237.26 | I30: ='Pensions P2'!$B$18 -> 10237.26 | J30: ='Pensions P2'!$B$18 -> 10237.26 | K30: ='Pensions P2'!$B$18 -> 10237.26 | L30: ='Pensions P2'!$B$18 -> 10237.26 | ... AC30: ='Pensions P2'!$B$18 -> 10237.26 | AT30: 49326.714
D31: Net Salary (Yearly) | E31: =E30+E29 -> 71128.233 | F31: =F30+F29 -> 71128.233 | G31: =G30+G29 -> 71128.233 | H31: =H30+H29 -> 71128.233 | I31: =I30+I29 -> 71128.233 | J31: =J30+J29 -> 71128.233 | K31: =K30+K29 -> 71128.233 | L31: =L30+L29 -> 71128.233 | ... AC31: =AC30+AC29 -> 71128.233 | AT31: 49744.389
D32: Net Salary (Monthly) | E32: =E31/12 -> 5927.3527 | F32: =F31/12 -> 5927.3527 | G32: =G31/12 -> 5927.3527 | H32: =H31/12 -> 5927.3527 | I32: =I31/12 -> 5927.3527 | J32: =J31/12 -> 5927.3527 | K32: =K31/12 -> 5927.3527 | L32: =L31/12 -> 5927.3527 | ... AC32: =AC31/12 -> 5927.3527
D33: Last Yearly Income from Work | E33: =$AH$16 -> 49744.389 | F33: =$AH$16 -> 49744.389 | G33: =$AH$16 -> 49744.389 | H33: =$AH$16 -> 49744.389 | I33: =$AH$16 -> 49744.389 | J33: =$AH$16 -> 49744.389 | K33: =$AH$16 -> 49744.389 | L33: =$AH$16 -> 49744.389 | ... AC33: =$AH$16 -> 49744.389
D34: Diff | E34: =E33-E32 -> 43817.036 | F34: =F33-F32 -> 43817.036 | G34: =G33-G32 -> 43817.036 | H34: =H33-H32 -> 43817.036 | I34: =I33-I32 -> 43817.036 | J34: =J33-J32 -> 43817.036 | K34: =K33-K32 -> 43817.036 | L34: =L33-L32 -> 43817.036 | ... AC34: =AC33-AC32 -> 43817.036
E35: =E34*(1+$B$10) -> 55647.636 | F35: =F34*(1+$B$10) -> 55647.636 | G35: =G34*(1+$B$10) -> 55647.636 | H35: =H34*(1+$B$10) -> 55647.636 | I35: =I34*(1+$B$10) -> 55647.636 | J35: =J34*(1+$B$10) -> 55647.636 | K35: =K34*(1+$B$10) -> 55647.636 | L35: =L34*(1+$B$10) -> 55647.636 | ... AC35: =AC34*(1+$B$10) -> 55647.636
D38: To be financed | E38: =SUM(E35:AC35) -> 1391190.9

Sheet Job Hopping
B2: Age | C2: Age Group | D2: FH/FW | E2: Switch | F2: SwitchP1Static | G2: SwitchP2Static | M2: Year | N2: Age Group | O2: Finance Workers | P2: Finance Hoppers | Q2: FH/FW | S2: Age Group | T2: FH/FV
B3: 25 | C3: =IF(B3<30, "25-29 år", IF(B3<35, "30-34 år", IF(B3<40, "35-39 år", IF(B3<45, "40-44 år", IF(B3<50, "45-49 år", IF(B3<55, "50-54 år", IF(B3<60, "55-59 år", IF(B3<65, "60-64 år", "65+ år")))))))) -> 25-29 år | D3: =_xlfn.XLOOKUP(C3,S:S,T:T) -> 0.51651948 | E3: =IF(OR(JobHopping[[#This Row],[Age]]=25,JobHopping[[#This Row],[Age]]>69),"N",IF(AND(E1="N",E2="N", RAND()<=D3), "Y", "N")) -> N | F3: N | G3: =IF(JobHopping[[#This Row],[Age]]<40,"",JobHopping[[#This Row],[SwitchP1Static]]) | M3: 2013 | N3: 25-29 år | O3: =_xlfn.XLOOKUP(M3&"-"&N3,'Djøf Finance Workers'!D:D,'Djøf Finance Workers'!C:C,0,1) -> 6202 | P3: =_xlfn.XLOOKUP(M3&"-"&N3,'Djøf Finance Hoppers'!D:D,'Djøf Finance Hoppers'!C:C,0,1) -> 2524 | Q3: =IF(O3>0, P3/O3, 0) -> 0.4069655 | S3: 25-29 år | T3: =SUMIFS(Q:Q,N:N,S3)/(MAX($M$3:$M$101)-MIN($M$3:$M$101)) -> 0.51651948
B4: 26 | C4: =IF(B4<30, "25-29 år", IF(B4<35, "30-34 år", IF(B4<40, "35-39 år", IF(B4<45, "40-44 år", IF(B4<50, "45-49 år", IF(B4<55, "50-54 år", IF(B4<60, "55-59 år", IF(B4<65, "60-64 år", "65+ år")))))))) -> 25-29 år | D4: =_xlfn.XLOOKUP(C4,S:S,T:T) -> 0.51651948 | E4: =IF(OR(JobHopping[[#This Row],[Age]]=25,JobHopping[[#This Row],[Age]]>69),"N",IF(AND(E2="N",E3="N", RAND()<=D4), "Y", "N")) -> N | F4: N | G4: =IF(JobHopping[[#This Row],[Age]]<40,"",JobHopping[[#This Row],[SwitchP1Static]]) | M4: 2013 | N4: 30-34 år | O4: =_xlfn.XLOOKUP(M4&"-"&N4,'Djøf Finance Workers'!D:D,'Djøf Finance Workers'!C:C,0,1) -> 8560 | P4: =_xlfn.XLOOKUP(M4&"-"&N4,'Djøf Finance Hoppers'!D:D,'Djøf Finance Hoppers'!C:C,0,1) -> 2176 | Q4: =IF(O4>0, P4/O4, 0) -> 0.25420561 | S4: 30-34 år | T4: =SUMIFS(Q:Q,N:N,S4)/(MAX($M$3:$M$101)-MIN($M$3:$M$101)) -> 0.3390802
B5: 27 | C5: =IF(B5<30, "25-29 år", IF(B5<35, "30-34 år", IF(B5<40, "35-39 år", IF(B5<45, "40-44 år", IF(B5<50, "45-49 år", IF(B5<55, "50-54 år", IF(B5<60, "55-59 år", IF(B5<65, "60-64 år", "65+ år")))))))) -> 25-29 år | D5: =_xlfn.XLOOKUP(C5,S:S,T:T) -> 0.51651948 | E5: =IF(OR(JobHopping[[#This Row],[Age]]=25,JobHopping[[#This Row],[Age]]>69),"N",IF(AND(E3="N",E4="N", RAND()<=D5), "Y", "N")) -> Y | F5: Y | G5: =IF(JobHopping[[#This Row],[Age]]<40,"",JobHopping[[#This Row],[SwitchP1Static]]) | M5: 2013 | N5: 35-39 år | O5: =_xlfn.XLOOKUP(M5&"-"&N5,'Djøf Finance Workers'!D:D,'Djøf Finance Workers'!C:C,0,1) -> 9790 | P5: =_xlfn.XLOOKUP(M5&"-"&N5,'Djøf Finance Hoppers'!D:D,'Djøf Finance Hoppers'!C:C,0,1) -> 1896 | Q5: =IF(O5>0, P5/O5, 0) -> 0.19366701 | S5: 35-39 år | T5: =SUMIFS(Q:Q,N:N,S5)/(MAX($M$3:$M$101)-MIN($M$3:$M$101)) -> 0.26240269
B6: 28 | C6: =IF(B6<30, "25-29 år", IF(B6<35, "30-34 år", IF(B6<40, "35-39 år", IF(B6<45, "40-44 år", IF(B6<50, "45-49 år", IF(B6<55, "50-54 år", IF(B6<60, "55-59 år", IF(B6<65, "60-64 år", "65+ år")))))))) -> 25-29 år | D6: =_xlfn.XLOOKUP(C6,S:S,T:T) -> 0.51651948 | E6: =IF(OR(JobHopping[[#This Row],[Age]]=25,JobHopping[[#This Row],[Age]]>69),"N",IF(AND(E4="N",E5="N", RAND()<=D6), "Y", "N")) -> N | F6: N | G6: =IF(JobHopping[[#This Row],[Age]]<40,"",JobHopping[[#This Row],[SwitchP1Static]]) | M6: 2013 | N6: 40-44 år | O6: =_xlfn.XLOOKUP(M6&"-"&N6,'Djøf Finance Workers'!D:D,'Djøf Finance Workers'!C:C,0,1) -> 9383 | P6: =_xlfn.XLOOKUP(M6&"-"&N6,'Djøf Finance Hoppers'!D:D,'Djøf Finance Hoppers'!C:C,0,1) -> 1579 | Q6: =IF(O6>0, P6/O6, 0) -> 0.16828307 | S6: 40-44 år | T6: =SUMIFS(Q:Q,N:N,S6)/(MAX($M$3:$M$101)-MIN($M$3:$M$101)) -> 0.22131873
B7: 29 | C7: =IF(B7<30, "25-29 år", IF(B7<35, "30-34 år", IF(B7<40, "35-39 år", IF(B7<45, "40-44 år", IF(B7<50, "45-49 år", IF(B7<55, "50-54 år", IF(B7<60, "55-59 år", IF(B7<65, "60-64 år", "65+ år")))))))) -> 25-29 år | D7: =_xlfn.XLOOKUP(C7,S:S,T:T) -> 0.51651948 | E7: =IF(OR(JobHopping[[#This Row],[Age]]=25,JobHopping[[#This Row],[Age]]>69),"N",IF(AND(E5="N",E6="N", RAND()<=D7), "Y", "N")) -> N | F7: N | G7: =IF(JobHopping[[#This Row],[Age]]<40,"",JobHopping[[#This Row],[SwitchP1Static]]) | M7: 2013 | N7: 45-49 år | O7: =_xlfn.XLOOKUP(M7&"-"&N7,'Djøf Finance Workers'!D:D,'Djøf Finance Workers'!C:C,0,1) -> 12762 | P7: =_xlfn.XLOOKUP(M7&"-"&N7,'Djøf Finance Hoppers'!D:D,'Djøf Finance Hoppers'!C:C,0,1) -> 1915 | Q7: =IF(O7>0, P7/O7, 0) -> 0.15005485 | S7: 45-49 år | T7: =SUMIFS(Q:Q,N:N,S7)/(MAX($M$3:$M$101)-MIN($M$3:$M$101)) -> 0.1992948
B8: 30 | C8: =IF(B8<30, "25-29 år", IF(B8<35, "30-34 år", IF(B8<40, "35-39 år", IF(B8<45, "40-44 år", IF(B8<50, "45-49 år", IF(B8<55, "50-54 år", IF(B8<60, "55-59 år", IF(B8<65, "60-64 år", "65+ år")))))))) -> 30-34 år | D8: =_xlfn.XLOOKUP(C8,S:S,T:T) -> 0.3390802 | E8: =IF(OR(JobHopping[[#This Row],[Age]]=25,JobHopping[[#This Row],[Age]]>69),"N",IF(AND(E6="N",E7="N", RAND()<=D8), "Y", "N")) -> N | F8: N | G8: =IF(JobHopping[[#This Row],[Age]]<40,"",JobHopping[[#This Row],[SwitchP1Static]]) | M8: 2013 | N8: 50-54 år | O8: =_xlfn.XLOOKUP(M8&"-"&N8,'Djøf Finance Workers'!D:D,'Djøf Finance Workers'!C:C,0,1) -> 10587 | P8: =_xlfn.XLOOKUP(M8&"-"&N8,'Djøf Finance Hoppers'!D:D,'Djøf Finance Hoppers'!C:C,0,1) -> 1462 | Q8: =IF(O8>0, P8/O8, 0) -> 0.13809389 | S8: 50-54 år | T8: =SUMIFS(Q:Q,N:N,S8)/(MAX($M$3:$M$101)-MIN($M$3:$M$101)) -> 0.17668929
B9: 31 | C9: =IF(B9<30, "25-29 år", IF(B9<35, "30-34 år", IF(B9<40, "35-39 år", IF(B9<45, "40-44 år", IF(B9<50, "45-49 år", IF(B9<55, "50-54 år", IF(B9<60, "55-59 år", IF(B9<65, "60-64 år", "65+ år")))))))) -> 30-34 år | D9: =_xlfn.XLOOKUP(C9,S:S,T:T) -> 0.3390802 | E9: =IF(OR(JobHopping[[#This Row],[Age]]=25,JobHopping[[#This Row],[Age]]>69),"N",IF(AND(E7="N",E8="N", RAND()<=D9), "Y", "N")) -> Y | F9: Y | G9: =IF(JobHopping[[#This Row],[Age]]<40,"",JobHopping[[#This Row],[SwitchP1Static]]) | M9: 2013 | N9: 55-59 år | O9: =_xlfn.XLOOKUP(M9&"-"&N9,'Djøf Finance Workers'!D:D,'Djøf Finance Workers'!C:C,0,1) -> 8811 | P9: =_xlfn.XLOOKUP(M9&"-"&N9,'Djøf Finance Hoppers'!D:D,'Djøf Finance Hoppers'!C:C,0,1) -> 1227 | Q9: =IF(O9>0, P9/O9, 0) -> 0.13925775 | S9: 55-59 år | T9: =SUMIFS(Q:Q,N:N,S9)/(MAX($M$3:$M$101)-MIN($M$3:$M$101)) -> 0.15515675
B10: 32 | C10: =IF(B10<30, "25-29 år", IF(B10<35, "30-34 år", IF(B10<40, "35-39 år", IF(B10<45, "40-44 år", IF(B10<50, "45-49 år", IF(B10<55, "50-54 år", IF(B10<60, "55-59 år", IF(B10<65, "60-64 år", "65+ år")))))))) -> 30-34 år | D10: =_xlfn.XLOOKUP(C10,S:S,T:T) -> 0.3390802 | E10: =IF(OR(JobHopping[[#This Row],[Age]]=25,JobHopping[[#This Row],[Age]]>69),"N",IF(AND(E8="N",E9="N", RAND()<=D10), "Y", "N")) -> N | F10: N | G10: =IF(JobHopping[[#This Row],[Age]]<40,"",JobHopping[[#This Row],[SwitchP1Static]]) | M10: 2013 | N10: 60-64 år | O10: =_xlfn.XLOOKUP(M10&"-"&N10,'Djøf Finance Workers'!D:D,'Djøf Finance Workers'!C:C,0,1) -> 5072 | P10: =_xlfn.XLOOKUP(M10&"-"&N10,'Djøf Finance Hoppers'!D:D,'Djøf Finance Hoppers'!C:C,0,1) -> 667 | Q10: =IF(O10>0, P10/O10, 0) -> 0.13150631 | S10: 60-64 år | T10: =SUMIFS(Q:Q,N:N,S10)/(MAX($M$3:$M$101)-MIN($M$3:$M$101)) -> 0.13997312
B11: 33 | C11: =IF(B11<30, "25-29 år", IF(B11<35, "30-34 år", IF(B11<40, "35-39 år", IF(B11<45, "40-44 år", IF(B11<50, "45-49 år", IF(B11<55, "50-54 år", IF(B11<60, "55-59 år", IF(B11<65, "60-64 år", "65+ år")))))))) -> 30-34 år | D11: =_xlfn.XLOOKUP(C11,S:S,T:T) -> 0.3390802 | E11: =IF(OR(JobHopping[[#This Row],[Age]]=25,JobHopping[[#This Row],[Age]]>69),"N",IF(AND(E9="N",E10="N", RAND()<=D11), "Y", "N")) -> N | F11: N | G11: =IF(JobHopping[[#This Row],[Age]]<40,"",JobHopping[[#This Row],[SwitchP1Static]]) | M11: 2013 | N11: 65+ år | O11: =_xlfn.XLOOKUP(M11&"-"&N11,'Djøf Finance Workers'!D:D,'Djøf Finance Workers'!C:C,0,1) -> 1539 | P11: =_xlfn.XLOOKUP(M11&"-"&N11,'Djøf Finance Hoppers'!D:D,'Djøf Finance Hoppers'!C:C,0,1) -> 224 | Q11: =IF(O11>0, P11/O11, 0) -> 0.14554906 | S11: 65+ år | T11: =SUMIFS(Q:Q,N:N,S11)/(MAX($M$3:$M$101)-MIN($M$3:$M$101)) -> 0.11691873
B12: 34 | C12: =IF(B12<30, "25-29 år", IF(B12<35, "30-34 år", IF(B12<40, "35-39 år", IF(B12<45, "40-44 år", IF(B12<50, "45-49 år", IF(B12<55, "50-54 år", IF(B12<60, "55-59 år", IF(B12<65, "60-64 år", "65+ år")))))))) -> 30-34 år | D12: =_xlfn.XLOOKUP(C12,S:S,T:T) -> 0.3390802 | E12: =IF(OR(JobHopping[[#This Row],[Age]]=25,JobHopping[[#This Row],[Age]]>69),"N",IF(AND(E10="N",E11="N", RAND()<=D12), "Y", "N")) -> Y | F12: N | G12: =IF(JobHopping[[#This Row],[Age]]<40,"",JobHopping[[#This Row],[SwitchP1Static]]) | M12: 2014 | N12: 25-29 år | O12: =_xlfn.XLOOKUP(M12&"-"&N12,'Djøf Finance Workers'!D:D,'Djøf Finance Workers'!C:C,0,1) -> 6041 | P12: =_xlfn.XLOOKUP(M12&"-"&N12,'Djøf Finance Hoppers'!D:D,'Djøf Finance Hoppers'!C:C,0,1) -> 2521 | Q12: =IF(O12>0, P12/O12, 0) -> 0.41731501
B13: 35 | C13: =IF(B13<30, "25-29 år", IF(B13<35, "30-34 år", IF(B13<40, "35-39 år", IF(B13<45, "40-44 år", IF(B13<50, "45-49 år", IF(B13<55, "50-54 år", IF(B13<60, "55-59 år", IF(B13<65, "60-64 år", "65+ år")))))))) -> 35-39 år | D13: =_xlfn.XLOOKUP(C13,S:S,T:T) -> 0.26240269 | E13: =IF(OR(JobHopping[[#This Row],[Age]]=25,JobHopping[[#This Row],[Age]]>69),"N",IF(AND(E11="N",E12="N", RAND()<=D13), "Y", "N")) -> N | F13: Y | G13: =IF(JobHopping[[#This Row],[Age]]<40,"",JobHopping[[#This Row],[SwitchP1Static]]) | M13: 2014 | N13: 30-34 år | O13: =_xlfn.XLOOKUP(M13&"-"&N13,'Djøf Finance Workers'!D:D,'Djøf Finance Workers'!C:C,0,1) -> 8203 | P13: =_xlfn.XLOOKUP(M13&"-"&N13,'Djøf Finance Hoppers'!D:D,'Djøf Finance Hoppers'!C:C,0,1) -> 2178 | Q13: =IF(O13>0, P13/O13, 0) -> 0.26551262
B14: 36 | C14: =IF(B14<30, "25-29 år", IF(B14<35, "30-34 år", IF(B14<40, "35-39 år", IF(B14<45, "40-44 år", IF(B14<50, "45-49 år", IF(B14<55, "50-54 år", IF(B14<60, "55-59 år", IF(B14<65, "60-64 år", "65+ år")))))))) -> 35-39 år | D14: =_xlfn.XLOOKUP(C14,S:S,T:T) -> 0.26240269 | E14: =IF(OR(JobHopping[[#This Row],[Age]]=25,JobHopping[[#This Row],[Age]]>69),"N",IF(AND(E12="N",E13="N", RAND()<=D14), "Y", "N")) -> N | F14: N | G14: =IF(JobHopping[[#This Row],[Age]]<40,"",JobHopping[[#This Row],[SwitchP1Static]]) | M14: 2014 | N14: 35-39 år | O14: =_xlfn.XLOOKUP(M14&"-"&N14,'Djøf Finance Workers'!D:D,'Djøf Finance Workers'!C:C,0,1) -> 9972 | P14: =_xlfn.XLOOKUP(M14&"-"&N14,'Djøf Finance Hoppers'!D:D,'Djøf Finance Hoppers'!C:C,0,1) -> 2066 | Q14: =IF(O14>0, P14/O14, 0) -> 0.2071801
B15: 37 | C15: =IF(B15<30, "25-29 år", IF(B15<35, "30-34 år", IF(B15<40, "35-39 år", IF(B15<45, "40-44 år", IF(B15<50, "45-49 år", IF(B15<55, "50-54 år", IF(B15<60, "55-59 år", IF(B15<65, "60-64 år", "65+ år")))))))) -> 35-39 år | D15: =_xlfn.XLOOKUP(C15,S:S,T:T) -> 0.26240269 | E15: =IF(OR(JobHopping[[#This Row],[Age]]=25,JobHopping[[#This Row],[Age]]>69),"N",IF(AND(E13="N",E14="N", RAND()<=D15), "Y", "N")) -> N | F15: N | G15: =IF(JobHopping[[#This Row],[Age]]<40,"",JobHopping[[#This Row],[SwitchP1Static]]) | M15: 2014 | N15: 40-44 år | O15: =_xlfn.XLOOKUP(M15&"-"&N15,'Djøf Finance Workers'!D:D,'Djøf Finance Workers'!C:C,0,1) -> 9409 | P15: =_xlfn.XLOOKUP(M15&"-"&N15,'Djøf Finance Hoppers'!D:D,'Djøf Finance Hoppers'!C:C,0,1) -> 1647 | Q15: =IF(O15>0, P15/O15, 0) -> 0.17504517
B16: 38 | C16: =IF(B16<30, "25-29 år", IF(B16<35, "30-34 år", IF(B16<40, "35-39 år", IF(B16<45, "40-44 år", IF(B16<50, "45-49 år", IF(B16<55, "50-54 år", IF(B16<60, "55-59 år", IF(B16<65, "60-64 år", "65+ år")))))))) -> 35-39 år | D16: =_xlfn.XLOOKUP(C16,S:S,T:T) -> 0.26240269 | E16: =IF(OR(JobHopping[[#This Row],[Age]]=25,JobHopping[[#This Row],[Age]]>69),"N",IF(AND(E14="N",E15="N", RAND()<=D16), "Y", "N")) -> N | F16: N | G16: =IF(JobHopping[[#This Row],[Age]]<40,"",JobHopping[[#This Row],[SwitchP1Static]]) | M16: 2014 | N16: 45-49 år | O16: =_xlfn.XLOOKUP(M16&"-"&N16,'Djøf Finance Workers'!D:D,'Djøf Finance Workers'!C:C,0,1) -> 12377 | P16: =_xlfn.XLOOKUP(M16&"-"&N16,'Djøf Finance Hoppers'!D:D,'Djøf Finance Hoppers'!C:C,0,1) -> 1953 | Q16: =IF(O16>0, P16/O16, 0) -> 0.15779268
B17: 39 | C17: =IF(B17<30, "25-29 år", IF(B17<35, "30-34 år", IF(B17<40, "35-39 år", IF(B17<45, "40-44 år", IF(B17<50, "45-49 år", IF(B17<55, "50-54 år", IF(B17<60, "55-59 år", IF(B17<65, "60-64 år", "65+ år")))))))) -> 35-39 år | D17: =_xlfn.XLOOKUP(C17,S:S,T:T) -> 0.26240269 | E17: =IF(OR(JobHopping[[#This Row],[Age]]=25,JobHopping[[#This Row],[Age]]>69),"N",IF(AND(E15="N",E16="N", RAND()<=D17), "Y", "N")) -> N | F17: Y | G17: =IF(JobHopping[[#This Row],[Age]]<40,"",JobHopping[[#This Row],[SwitchP1Static]]) | M17: 2014 | N17: 50-54 år | O17: =_xlfn.XLOOKUP(M17&"-"&N17,'Djøf Finance Workers'!D:D,'Djøf Finance Workers'!C:C,0,1) -> 10828 | P17: =_xlfn.XLOOKUP(M17&"-"&N17,'Djøf Finance Hoppers'!D:D,'Djøf Finance Hoppers'!C:C,0,1) -> 1636 | Q17: =IF(O17>0, P17/O17, 0) -> 0.15108977
B18: 40 | C18: =IF(B18<30, "25-29 år", IF(B18<35, "30-34 år", IF(B18<40, "35-39 år", IF(B18<45, "40-44 år", IF(B18<50, "45-49 år", IF(B18<55, "50-54 år", IF(B18<60, "55-59 år", IF(B18<65, "60-64 år", "65+ år")))))))) -> 40-44 år | D18: =_xlfn.XLOOKUP(C18,S:S,T:T) -> 0.22131873 | E18: =IF(OR(JobHopping[[#This Row],[Age]]=25,JobHopping[[#This Row],[Age]]>69),"N",IF(AND(E16="N",E17="N", RAND()<=D18), "Y", "N")) -> Y | F18: N | G18: =IF(JobHopping[[#This Row],[Age]]<40,"",JobHopping[[#This Row],[SwitchP1Static]]) -> N | M18: 2014 | N18: 55-59 år | O18: =_xlfn.XLOOKUP(M18&"-"&N18,'Djøf Finance Workers'!D:D,'Djøf Finance Workers'!C:C,0,1) -> 8888 | P18: =_xlfn.XLOOKUP(M18&"-"&N18,'Djøf Finance Hoppers'!D:D,'Djøf Finance Hoppers'!C:C,0,1) -> 1231 | Q18: =IF(O18>0, P18/O18, 0) -> 0.13850135
B19: 41 | C19: =IF(B19<30, "25-29 år", IF(B19<35, "30-34 år", IF(B19<40, "35-39 år", IF(B19<45, "40-44 år", IF(B19<50, "45-49 år", IF(B19<55, "50-54 år", IF(B19<60, "55-59 år", IF(B19<65, "60-64 år", "65+ år")))))))) -> 40-44 år | D19: =_xlfn.XLOOKUP(C19,S:S,T:T) -> 0.22131873 | E19: =IF(OR(JobHopping[[#This Row],[Age]]=25,JobHopping[[#This Row],[Age]]>69),"N",IF(AND(E17="N",E18="N", RAND()<=D19), "Y", "N")) -> N | F19: N | G19: =IF(JobHopping[[#This Row],[Age]]<40,"",JobHopping[[#This Row],[SwitchP1Static]]) -> N | M19: 2014 | N19: 60-64 år | O19: =_xlfn.XLOOKUP(M19&"-"&N19,'Djøf Finance Workers'!D:D,'Djøf Finance Workers'!C:C,0,1) -> 5141 | P19: =_xlfn.XLOOKUP(M19&"-"&N19,'Djøf Finance Hoppers'!D:D,'Djøf Finance Hoppers'!C:C,0,1) -> 706 | Q19: =IF(O19>0, P19/O19, 0) -> 0.13732737
B20: 42 | C20: =IF(B20<30, "25-29 år", IF(B20<35, "30-34 år", IF(B20<40, "35-39 år", IF(B20<45, "40-44 år", IF(B20<50, "45-49 år", IF(B20<55, "50-54 år", IF(B20<60, "55-59 år", IF(B20<65, "60-64 år", "65+ år")))))))) -> 40-44 år | D20: =_xlfn.XLOOKUP(C20,S:S,T:T) -> 0.22131873 | E20: =IF(OR(JobHopping[[#This Row],[Age]]=25,JobHopping[[#This Row],[Age]]>69),"N",IF(AND(E18="N",E19="N", RAND()<=D20), "Y", "N")) -> N | F20: N | G20: =IF(JobHopping[[#This Row],[Age]]<40,"",JobHopping[[#This Row],[SwitchP1Static]]) -> N | M20: 2014 | N20: 65+ år | O20: =_xlfn.XLOOKUP(M20&"-"&N20,'Djøf Finance Workers'!D:D,'Djøf Finance Workers'!C:C,0,1) -> 1600 | P20: =_xlfn.XLOOKUP(M20&"-"&N20,'Djøf Finance Hoppers'!D:D,'Djøf Finance Hoppers'!C:C,0,1) -> 204 | Q20: =IF(O20>0, P20/O20, 0) -> 0.1275
B21: 43 | C21: =IF(B21<30, "25-29 år", IF(B21<35, "30-34 år", IF(B21<40, "35-39 år", IF(B21<45, "40-44 år", IF(B21<50, "45-49 år", IF(B21<55, "50-54 år", IF(B21<60, "55-59 år", IF(B21<65, "60-64 år", "65+ år")))))))) -> 40-44 år | D21: =_xlfn.XLOOKUP(C21,S:S,T:T) -> 0.22131873 | E21: =IF(OR(JobHopping[[#This Row],[Age]]=25,JobHopping[[#This Row],[Age]]>69),"N",IF(AND(E19="N",E20="N", RAND()<=D21), "Y", "N")) -> N | F21: Y | G21: =IF(JobHopping[[#This Row],[Age]]<40,"",JobHopping[[#This Row],[SwitchP1Static]]) -> Y | M21: 2015 | N21: 25-29 år | O21: =_xlfn.XLOOKUP(M21&"-"&N21,'Djøf Finance Workers'!D:D,'Djøf Finance Workers'!C:C,0,1) -> 5834 | P21: =_xlfn.XLOOKUP(M21&"-"&N21,'Djøf Finance Hoppers'!D:D,'Djøf Finance Hoppers'!C:C,0,1) -> 2715 | Q21: =IF(O21>0, P21/O21, 0) -> 0.46537539
B22: 44 | C22: =IF(B22<30, "25-29 år", IF(B22<35, "30-34 år", IF(B22<40, "35-39 år", IF(B22<45, "40-44 år", IF(B22<50, "45-49 år", IF(B22<55, "50-54 år", IF(B22<60, "55-59 år", IF(B22<65, "60-64 år", "65+ år")))))))) -> 40-44 år | D22: =_xlfn.XLOOKUP(C22,S:S,T:T) -> 0.22131873 | E22: =IF(OR(JobHopping[[#This Row],[Age]]=25,JobHopping[[#This Row],[Age]]>69),"N",IF(AND(E20="N",E21="N", RAND()<=D22), "Y", "N")) -> N | F22: N | G22: =IF(JobHopping[[#This Row],[Age]]<40,"",JobHopping[[#This Row],[SwitchP1Static]]) -> N | M22: 2015 | N22: 30-34 år | O22: =_xlfn.XLOOKUP(M22&"-"&N22,'Djøf Finance Workers'!D:D,'Djøf Finance Workers'!C:C,0,1) -> 7834 | P22: =_xlfn.XLOOKUP(M22&"-"&N22,'Djøf Finance Hoppers'!D:D,'Djøf Finance Hoppers'!C:C,0,1) -> 2473 | Q22: =IF(O22>0, P22/O22, 0) -> 0.31567526
B23: 45 | C23: =IF(B23<30, "25-29 år", IF(B23<35, "30-34 år", IF(B23<40, "35-39 år", IF(B23<45, "40-44 år", IF(B23<50, "45-49 år", IF(B23<55, "50-54 år", IF(B23<60, "55-59 år", IF(B23<65, "60-64 år", "65+ år")))))))) -> 45-49 år | D23: =_xlfn.XLOOKUP(C23,S:S,T:T) -> 0.1992948 | E23: =IF(OR(JobHopping[[#This Row],[Age]]=25,JobHopping[[#This Row],[Age]]>69),"N",IF(AND(E21="N",E22="N", RAND()<=D23), "Y", "N")) -> Y | F23: N | G23: =IF(JobHopping[[#This Row],[Age]]<40,"",JobHopping[[#This Row],[SwitchP1Static]]) -> N | M23: 2015 | N23: 35-39 år | O23: =_xlfn.XLOOKUP(M23&"-"&N23,'Djøf Finance Workers'!D:D,'Djøf Finance Workers'!C:C,0,1) -> 9897 | P23: =_xlfn.XLOOKUP(M23&"-"&N23,'Djøf Finance Hoppers'!D:D,'Djøf Finance Hoppers'!C:C,0,1) -> 2378 | Q23: =IF(O23>0, P23/O23, 0) -> 0.24027483
... B78: 100 | C78: =IF(B78<30, "25-29 år", IF(B78<35, "30-34 år", IF(B78<40, "35-39 år", IF(B78<45, "40-44 år", IF(B78<50, "45-49 år", IF(B78<55, "50-54 år", IF(B78<60, "55-59 år", IF(B78<65, "60-64 år", "65+ år")))))))) -> 65+ år | D78: =_xlfn.XLOOKUP(C78,S:S,T:T) -> 0.11691873 | E78: =IF(OR(JobHopping[[#This Row],[Age]]=25,JobHopping[[#This Row],[Age]]>69),"N",IF(AND(E76="N",E77="N", RAND()<=D78), "Y", "N")) -> N | F78: N | G78: =IF(JobHopping[[#This Row],[Age]]<40,"",JobHopping[[#This Row],[SwitchP1Static]]) -> N | M78: 2021 | N78: 40-44 år | O78: =_xlfn.XLOOKUP(M78&"-"&N78,'Djøf Finance Workers'!D:D,'Djøf Finance Workers'!C:C,0,1) -> 10002 | P78: =_xlfn.XLOOKUP(M78&"-"&N78,'Djøf Finance Hoppers'!D:D,'Djøf Finance Hoppers'!C:C,0,1) -> 2220 | Q78: =IF(O78>0, P78/O78, 0) -> 0.22195561
M79: 2021 | N79: 45-49 år | O79: =_xlfn.XLOOKUP(M79&"-"&N79,'Djøf Finance Workers'!D:D,'Djøf Finance Workers'!C:C,0,1) -> 10036 | P79: =_xlfn.XLOOKUP(M79&"-"&N79,'Djøf Finance Hoppers'!D:D,'Djøf Finance Hoppers'!C:C,0,1) -> 1980 | Q79: =IF(O79>0, P79/O79, 0) -> 0.19728976
M80: 2021 | N80: 50-54 år | O80: =_xlfn.XLOOKUP(M80&"-"&N80,'Djøf Finance Workers'!D:D,'Djøf Finance Workers'!C:C,0,1) -> 10467 | P80: =_xlfn.XLOOKUP(M80&"-"&N80,'Djøf Finance Hoppers'!D:D,'Djøf Finance Hoppers'!C:C,0,1) -> 1810 | Q80: =IF(O80>0, P80/O80, 0) -> 0.17292443
M81: 2021 | N81: 55-59 år | O81: =_xlfn.XLOOKUP(M81&"-"&N81,'Djøf Finance Workers'!D:D,'Djøf Finance Workers'!C:C,0,1) -> 10749 | P81: =_xlfn.XLOOKUP(M81&"-"&N81,'Djøf Finance Hoppers'!D:D,'Djøf Finance Hoppers'!C:C,0,1) -> 1631 | Q81: =IF(O81>0, P81/O81, 0) -> 0.15173505
M82: 2021 | N82: 60-64 år | O82: =_xlfn.XLOOKUP(M82&"-"&N82,'Djøf Finance Workers'!D:D,'Djøf Finance Workers'!C:C,0,1) -> 6688 | P82: =_xlfn.XLOOKUP(M82&"-"&N82,'Djøf Finance Hoppers'!D:D,'Djøf Finance Hoppers'!C:C,0,1) -> 962 | Q82: =IF(O82>0, P82/O82, 0) -> 0.14383971
M83: 2021 | N83: 65+ år | O83: =_xlfn.XLOOKUP(M83&"-"&N83,'Djøf Finance Workers'!D:D,'Djøf Finance Workers'!C:C,0,1) -> 2522 | P83: =_xlfn.XLOOKUP(M83&"-"&N83,'Djøf Finance Hoppers'!D:D,'Djøf Finance Hoppers'!C:C,0,1) -> 216 | Q83: =IF(O83>0, P83/O83, 0) -> 0.085646312
M84: 2022 | N84: 25-29 år | O84: =_xlfn.XLOOKUP(M84&"-"&N84,'Djøf Finance Workers'!D:D,'Djøf Finance Workers'!C:C,0,1) -> 8107 | P84: =_xlfn.XLOOKUP(M84&"-"&N84,'Djøf Finance Hoppers'!D:D,'Djøf Finance Hoppers'!C:C,0,1) -> 3870 | Q84: =IF(O84>0, P84/O84, 0) -> 0.47736524
M85: 2022 | N85: 30-34 år | O85: =_xlfn.XLOOKUP(M85&"-"&N85,'Djøf Finance Workers'!D:D,'Djøf Finance Workers'!C:C,0,1) -> 9307 | P85: =_xlfn.XLOOKUP(M85&"-"&N85,'Djøf Finance Hoppers'!D:D,'Djøf Finance Hoppers'!C:C,0,1) -> 3004 | Q85: =IF(O85>0, P85/O85, 0) -> 0.32276781
M86: 2022 | N86: 35-39 år | O86: =_xlfn.XLOOKUP(M86&"-"&N86,'Djøf Finance Workers'!D:D,'Djøf Finance Workers'!C:C,0,1) -> 9287 | P86: =_xlfn.XLOOKUP(M86&"-"&N86,'Djøf Finance Hoppers'!D:D,'Djøf Finance Hoppers'!C:C,0,1) -> 2511 | Q86: =IF(O86>0, P86/O86, 0) -> 0.27037795
M87: 2022 | N87: 40-44 år | O87: =_xlfn.XLOOKUP(M87&"-"&N87,'Djøf Finance Workers'!D:D,'Djøf Finance Workers'!C:C,0,1) -> 9808 | P87: =_xlfn.XLOOKUP(M87&"-"&N87,'Djøf Finance Hoppers'!D:D,'Djøf Finance Hoppers'!C:C,0,1) -> 2191 | Q87: =IF(O87>0, P87/O87, 0) -> 0.22338907
M88: 2022 | N88: 45-49 år | O88: =_xlfn.XLOOKUP(M88&"-"&N88,'Djøf Finance Workers'!D:D,'Djøf Finance Workers'!C:C,0,1) -> 10063 | P88: =_xlfn.XLOOKUP(M88&"-"&N88,'Djøf Finance Hoppers'!D:D,'Djøf Finance Hoppers'!C:C,0,1) -> 2044 | Q88: =IF(O88>0, P88/O88, 0) -> 0.20312034
M89: 2022 | N89: 50-54 år | O89: =_xlfn.XLOOKUP(M89&"-"&N89,'Djøf Finance Workers'!D:D,'Djøf Finance Workers'!C:C,0,1) -> 9799 | P89: =_xlfn.XLOOKUP(M89&"-"&N89,'Djøf Finance Hoppers'!D:D,'Djøf Finance Hoppers'!C:C,0,1) -> 1683 | Q89: =IF(O89>0, P89/O89, 0) -> 0.17175222
M90: 2022 | N90: 55-59 år | O90: =_xlfn.XLOOKUP(M90&"-"&N90,'Djøf Finance Workers'!D:D,'Djøf Finance Workers'!C:C,0,1) -> 11340 | P90: =_xlfn.XLOOKUP(M90&"-"&N90,'Djøf Finance Hoppers'!D:D,'Djøf Finance Hoppers'!C:C,0,1) -> 1578 | Q90: =IF(O90>0, P90/O90, 0) -> 0.13915344
... M101: 2023 | N101: 65+ år | O101: =_xlfn.XLOOKUP(M101&"-"&N101,'Djøf Finance Workers'!D:D,'Djøf Finance Workers'!C:C,0,1) -> 3139 | P101: =_xlfn.XLOOKUP(M101&"-"&N101,'Djøf Finance Hoppers'!D:D,'Djøf Finance Hoppers'!C:C,0,1) -> 295 | Q101: =IF(O101>0, P101/O101, 0) -> 0.093978974

Sheet Djøf Finance Hoppers
A1: Status på arbejdsmarkedet/ Beskæftigelse og jobskifte/ Antal personer der har skiftet eller startet i nyt job (jobomsætning)
C2: Hele landet
C3: Privat sektor
C4: Herkomst i alt
C5: Køn i alt
C6: Finansiering og forsikring
C7: Jobomsætning
A8: 2009 | B8: 25-29 år | C8: 3410 | D8: =A8&"-"&B8 -> 2009-25-29 år
A9: 2009 | B9: 30-34 år | C9: 3525 | D9: =A9&"-"&B9 -> 2009-30-34 år
A10: 2009 | B10: 35-39 år | C10: 3090 | D10: =A10&"-"&B10 -> 2009-35-39 år
A11: 2009 | B11: 40-44 år | C11: 4180 | D11: =A11&"-"&B11 -> 2009-40-44 år
A12: 2009 | B12: 45-49 år | C12: 3533 | D12: =A12&"-"&B12 -> 2009-45-49 år
A13: 2009 | B13: 50-54 år | C13: 2940 | D13: =A13&"-"&B13 -> 2009-50-54 år
A14: 2009 | B14: 55-59 år | C14: 2419 | D14: =A14&"-"&B14 -> 2009-55-59 år
A15: 2009 | B15: 60-64 år | C15: 1263 | D15: =A15&"-"&B15 -> 2009-60-64 år
A16: 2009 | B16: 65-69 år | C16: 196 | D16: =A16&"-"&B16 -> 2009-65-69 år
A17: 2010 | B17: 25-29 år | C17: 2457 | D17: =A17&"-"&B17 -> 2010-25-29 år
A18: 2010 | B18: 30-34 år | C18: 2382 | D18: =A18&"-"&B18 -> 2010-30-34 år
A19: 2010 | B19: 35-39 år | C19: 1880 | D19: =A19&"-"&B19 -> 2010-35-39 år
... A142: 2023 | B142: 65-69 år | C142: 295 | D142: =A142&"-"&B142 -> 2023-65-69 år
A145: Kilde: CPR-registeret, CVR-registeret og DetailCOR
A146: Anm.: Pga. efterregistreringer kan tallene for især den seneste periode stige ved næste opdatering.

Sheet Djøf Finance Workers
A1: Status på arbejdsmarkedet/ Beskæftigelse og jobskifte/ Antal lønmodtagere efter bopæl
C2: Hele landet
C3: Herkomst i alt
C4: Køn i alt
C5: Finansiering og forsikring
C6: Antal fuldtidsbeskæftigede lønmodtagere efter bopæl
A7: 2008 | B7: 25-29 år | C7: 6876 | D7: =A7&"-"&B7 -> 2008-25-29 år
A8: 2008 | B8: 30-34 år | C8: 8541 | D8: =A8&"-"&B8 -> 2008-30-34 år
A9: 2008 | B9: 35-39 år | C9: 8222 | D9: =A9&"-"&B9 -> 2008-35-39 år
A10: 2008 | B10: 40-44 år | C10: 11172 | D10: =A10&"-"&B10 -> 2008-40-44 år
A11: 2008 | B11: 45-49 år | C11: 9399 | D11: =A11&"-"&B11 -> 2008-45-49 år
A12: 2008 | B12: 50-54 år | C12: 8459 | D12: =A12&"-"&B12 -> 2008-50-54 år
A13: 2008 | B13: 55-59 år | C13: 7916 | D13: =A13&"-"&B13 -> 2008-55-59 år
A14: 2008 | B14: 60-64 år | C14: 4371 | D14: =A14&"-"&B14 -> 2008-60-64 år
A15: 2008 | B15: 65+ år | C15: 857 | D15: =A15&"-"&B15 -> 2008-65+ år
A16: 2009 | B16: 25-29 år | C16: 7284 | D16: =A16&"-"&B16 -> 2009-25-29 år
A17: 2009 | B17: 30-34 år | C17: 9750 | D17: =A17&"-"&B17 -> 2009-30-34 år
A18: 2009 | B18: 35-39 år | C18: 9328 | D18: =A18&"-"&B18 -> 2009-35-39 år
... A159: 2024 | B159: 65+ år | C159: 3573 | D159: =A159&"-"&B159 -> 2024-65+ år
A162: Kilde: CPR-registeret, CVR-registeret og DetailCOR
A163: Anm.: Pga. efterregistreringer kan tallene for især den seneste periode stige ved næste opdatering.

Sheet Loop
B2: N | C2: Year | D2: AgeP1 | E2: AgeP2 | F2: LoopStatus
B3: 1 | C3: 2025 | D3: 25 | E3: 40 | F3: N
B4: 2 | C4: 2026 | D4: =D3+1 -> 26 | E4: =E3+1 -> 41 | F4: N
B5: 3 | C5: 2027 | D5: =D4+1 -> 27 | E5: =E4+1 -> 42 | F5: N
B6: 4 | C6: 2028 | D6: =D5+1 -> 28 | E6: =E5+1 -> 43 | F6: N
B7: 5 | C7: 2029 | D7: =D6+1 -> 29 | E7: =E6+1 -> 44 | F7: N
B8: 6 | C8: 2030 | D8: =D7+1 -> 30 | E8: =E7+1 -> 45 | F8: N
B9: 7 | C9: 2031 | D9: =D8+1 -> 31 | E9: =E8+1 -> 46 | F9: N
B10: 8 | C10: 2032 | D10: =D9+1 -> 32 | E10: =E9+1 -> 47 | F10: N
B11: 9 | C11: 2033 | D11: =D10+1 -> 33 | E11: =E10+1 -> 48 | F11: N
B12: 10 | C12: 2034 | D12: =D11+1 -> 34 | E12: =E11+1 -> 49 | F12: N
B13: 11 | C13: 2035 | D13: =D12+1 -> 35 | E13: =E12+1 -> 50 | F13: N
B14: 12 | C14: 2036 | D14: =D13+1 -> 36 | E14: =E13+1 -> 51 | F14: N
B15: 13 | C15: 2037 | D15: =D14+1 -> 37 | E15: =E14+1 -> 52 | F15: N
... B53: 51 | C53: 2075 | D53: =D52+1 -> 75 | E53: =E52+1 -> 90 | F53: N

Sheet Goals
B2: Goal Info | C2: GOAL A | D2: GOAL B | E2: GOAL C | F2: GOAL D | G2: P1
B3: Value Ratio | C3: 1 | D3: 0.8 | E3: 0.3 | F3: 0.6
B4: Funding Requirement | C4: ='Net Salary P1'!E38 -> 1246425 | D4: 250000 | E4: 72530 | F4: 2500000
B5: Time Horizon | C5: 50 | D5: 5 | E5: 20 | F5: 30
B7: Goal Info | C7: GOAL A | D7: GOAL B | E7: GOAL C | F7: GOAL D | G7: P2
B8: Value Ratio | C8: 1 | D8: 0.45 | E8: 0.5 | F8: 0.58
B9: Funding Requirement | C9: ='Net Salary P2'!E38 -> 1391190.9 | D9: 75000 | E9: 72530 | F9: 2500000
B10: Time Horizon | C10: 35 | D10: 30 | E10: 5 | F10: 15

Sheet Aktiesparekonto Increase
A1: https://skat.dk/borger/aktier-og-andre-vaerdipapirer/aktiesparekonto?
A2: Year | B2: Max cap | C2: Change (%)
A3: 2019 | B3: 50000
A4: 2020 | B4: =100000 -> 100000 | C4: =(B4-B3)/B3 -> 1
A5: 2021 | B5: 102300 | C5: =(B5-B4)/B4 -> 0.023
A6: 2022 | B6: 103500 | C6: =(B6-B5)/B5 -> 0.011730205 | E6: median: | F6: without 2020:
A7: 2023 | B7: 106600 | C7: =(B7-B6)/B6 -> 0.029951691 | E7: =MEDIAN(C4:C9) -> 0.12645487 | F7: =MEDIAN(C5:C9) -> 0.029951691
A8: 2024 | B8: 135900 | C8: =(B8-B7)/B7 -> 0.27485929
A9: 2025 | B9: 166200 | C9: =(B9-B8)/B8 -> 0.22295806

Sheet Salary
B1: 2025 | C1: 2026 | D1: 2027 | E1: 2028 | F1: 2029 | G1: 2030 | H1: 2031 | I1: 2032 | J1: 2033 | K1: 2034 | L1: 2035 | M1: 2036 | N1: 2037 | O1: 2038 | P1: 2039 | Q1: 2040 | R1: 2041 | S1: 2042 | T1: 2043 | U1: 2044 | V1: 2045 | W1: 2046 | X1: 2047 | Y1: 2048 | Z1: 2049 | AA1: 2050 | AB1: 2051 | AC1: 2052 | AD1: 2053 | AE1: 2054 | AF1: 2055 | AG1: 2056 | AH1: 2057 | AI1: 2058 | AJ1: 2059 | AK1: 2060 | AL1: 2061 | AM1: 2062 | AN1: 2063 | AO1: 2064 | AP1: 2065 | AQ1: 2066 | AR1: 2067 | AS1: 2068 | AT1: 2069 | AU1: 2070 | AV1: 2071 | AW1: 2072 | AX1: 2073 | AY1: 2074 | AZ1: 2075
A2: P1 | B2: 0 | C2: {=TRANSPOSE(TableIncome[InvestmentP1])} -> 28662.615 | D2: 28970.875 | E2: 30452.582 | F2: 30777.661 | G2: 31105.466 | H2: 33384.992 | I2: 33736.874 | J2: 34091.8 | K2: 35820.154 | L2: 36194.99 | M2: 36573.126 | N2: 36954.605 | O2: 38821.93 | P2: 39225.045 | Q2: 39631.777 | R2: 40042.171 | S2: 42060.023 | T2: 42418.629 | U2: 42755.222 | V2: 43094.807 | W2: 44759.231 | X2: 45118.129 | Y2: 45480.263 | Z2: 45845.671 | AA2: 46214.395 | AB2: 46586.473 | AC2: 46961.946 | AD2: 47340.854 | AE2: 47723.238 | AF2: 48109.138 | AG2: 48498.596 | AH2: 48891.653 | AI2: 49288.351 | AJ2: 51252.654 | AK2: 51672.4 | AL2: 52096.071 | AM2: 52523.71 | AN2: 52955.364 | AO2: 53391.077 | AP2: 53830.895 | AQ2: 54274.864 | AR2: 54723.031 | AS2: 55175.442 | AT2: 0 | AU2: 0 | AV2: 0 | AW2: 0 | AX2: 0 | AY2: 0 | AZ2: 0
A3: P2 | B3: 200000 | C3: {=TRANSPOSE(TableIncome[InvestmentP2])} -> 41942.643 | D3: 42283.204 | E3: 42626.624 | F3: 44339.932 | G3: 44702.86 | H3: 47438.682 | I3: 47830.6 | J3: 48225.963 | K3: 48624.813 | L3: 49027.196 | M3: 49433.154 | N3: 49842.734 | O3: 50255.978 | P3: 50672.934 | Q3: 51093.645 | R3: 51518.158 | S3: 51946.518 | T3: 52378.773 | U3: 55345.291 | V3: 55810.776 | W3: 56280.549 | X3: 56754.66 | Y3: 57233.159 | Z3: 57716.097 | AA3: 58203.525 | AB3: 58695.494 | AC3: 59192.057 | AD3: 59693.266 | AE3: 0 | AF3: 0 | AG3: 0 | AH3: 0 | AI3: 0 | AJ3: 0 | AK3: 0 | AL3: 0 | AM3: 0 | AN3: 0 | AO3: 0 | AP3: 0 | AQ3: 0 | AR3: 0 | AS3: 0 | AT3: 0 | AU3: 0 | AV3: 0 | AW3: 0 | AX3: 0 | AY3: 0 | AZ3: 0

Sheet Wealth
B1: 2025 | C1: 2026 | D1: 2027 | E1: 2028 | F1: 2029 | G1: 2030 | H1: 2031 | I1: 2032 | J1: 2033 | K1: 2034 | L1: 2035 | M1: 2036 | N1: 2037 | O1: 2038 | P1: 2039 | Q1: 2040 | R1: 2041 | S1: 2042 | T1: 2043 | U1: 2044 | V1: 2045 | W1: 2046 | X1: 2047 | Y1: 2048 | Z1: 2049 | AA1: 2050 | AB1: 2051 | AC1: 2052 | AD1: 2053 | AE1: 2054 | AF1: 2055 | AG1: 2056 | AH1: 2057 | AI1: 2058 | AJ1: 2059 | AK1: 2060 | AL1: 2061 | AM1: 2062 | AN1: 2063 | AO1: 2064 | AP1: 2065 | AQ1: 2066 | AR1: 2067 | AS1: 2068 | AT1: 2069 | AU1: 2070 | AV1: 2071 | AW1: 2072 | AX1: 2073 | AY1: 2074 | AZ1: 2075
A2: P1 | B2: =SUMIF(TableIncome[Year], "<=" & B1, TableIncome[InvestmentP1]) -> 28662.615 | C2: =SUMIF(TableIncome[Year], "<=" & C1, TableIncome[InvestmentP1]) -> 57633.49 | D2: =SUMIF(TableIncome[Year], "<=" & D1, TableIncome[InvestmentP1]) -> 88086.072 | E2: =SUMIF(TableIncome[Year], "<=" & E1, TableIncome[InvestmentP1]) -> 118863.73 | F2: =SUMIF(TableIncome[Year], "<=" & F1, TableIncome[InvestmentP1]) -> 149969.2 | G2: =SUMIF(TableIncome[Year], "<=" & G1, TableIncome[InvestmentP1]) -> 183354.19 | H2: =SUMIF(TableIncome[Year], "<=" & H1, TableIncome[InvestmentP1]) -> 217091.07 | I2: =SUMIF(TableIncome[Year], "<=" & I1, TableIncome[InvestmentP1]) -> 251182.87 | ... AZ2: =SUMIF(TableIncome[Year], "<=" & AZ1, TableIncome[InvestmentP1]) -> 1867488.8
A3: P2 | B3: =SUMIF(TableIncome[Year], "<=" & B1, TableIncome[InvestmentP2]) -> 41942.643 | C3: =SUMIF(TableIncome[Year], "<=" & C1, TableIncome[InvestmentP2]) -> 84225.847 | D3: =SUMIF(TableIncome[Year], "<=" & D1, TableIncome[InvestmentP2]) -> 126852.47 | E3: =SUMIF(TableIncome[Year], "<=" & E1, TableIncome[InvestmentP2]) -> 171192.4 | F3: =SUMIF(TableIncome[Year], "<=" & F1, TableIncome[InvestmentP2]) -> 215895.26 | G3: =SUMIF(TableIncome[Year], "<=" & G1, TableIncome[InvestmentP2]) -> 263333.94 | H3: =SUMIF(TableIncome[Year], "<=" & H1, TableIncome[InvestmentP2]) -> 311164.54 | I3: =SUMIF(TableIncome[Year], "<=" & I1, TableIncome[InvestmentP2]) -> 359390.51 | ... AZ3: =SUMIF(TableIncome[Year], "<=" & AZ1, TableIncome[InvestmentP2]) -> 1439109.3

Sheet notes next time talk
B3: Excel side:
B4: Goal calculation
B5: Investment income calculation
B6: For retirement goal: Calculate what the amount needed is and also research from denmark statistik what is the median returns by retirement age.
B7: Returns input with samsseewfwfuweerhugf for long term, and simulation for short term
B9: Python side:
B13: Question for Johan:
B14: Vasicek ready, what do we use bond simulation for? How does it correlate to bond ETF
B18: From last meeting Johan mentioned you can put the tax money back into the account???? What does this mean I am not sure: Saxo bank shows this below which might explain
B37: Update: I KNOW WHAT HE MEANT AHAHAHA IM A GENIOUS!!!! So basically it means that (from what I understand) the 17% tax deducts from your available input amount, allowing to deposit more into the account.
C41: Here
D42: Return | E42: Vol
C43: ZC Bond | D43: 0.03 | E43: 0.01 | H43: 2025 | I43: 2026 | J43: 2027 | M43: Use value simulated for each year or the average | N43: Split each goal into a per year goal, so achieve a % of the total goal in that year, and then the model would actually work as is
C44: SP | D44: 0.1 | E44: 0.03 | H44: 0.03 | I44: 0.04 | J44: 0.06 | K44: 0.07 | L44: 0.1
H46: =AVERAGE(H44:L44) -> 0.06 | I46: =AVERAGE(I44:L44) -> 0.0675
J51: Goal: House | L51: in 10 years
J53: 2025 | K53: 2026 | L53: 2027 | M53: 2028 | N53: 2029 | O53: 2030 | P53: 2031 | Q53: 2032 | R53: 2033 | S53: 2034 | U53: Total
J54: =$U$54*10% -> 200000 | K54: =$U$54*10% -> 200000 | L54: =$U$54*10% -> 200000 | M54: =$U$54*10% -> 200000 | N54: =$U$54*10% -> 200000 | O54: =$U$54*10% -> 200000 | P54: =$U$54*10% -> 200000 | Q54: =$U$54*10% -> 200000 | ... S54: =$U$54*10% -> 200000 | U54: 2000000
B57: Task for the master file

Sheet Real Returns
B1: 2025 | C1: 2026 | D1: 2027 | E1: 2028 | F1: 2029 | G1: 2030 | H1: 2031 | I1: 2032 | J1: 2033 | K1: 2034 | L1: 2035 | M1: 2036 | N1: 2037 | O1: 2038 | P1: 2039 | Q1: 2040 | R1: 2041 | S1: 2042 | T1: 2043 | U1: 2044 | V1: 2045 | W1: 2046 | X1: 2047 | Y1: 2048 | Z1: 2049 | AA1: 2050 | AB1: 2051 | AC1: 2052 | AD1: 2053 | AE1: 2054 | AF1: 2055 | AG1: 2056 | AH1: 2057 | AI1: 2058 | AJ1: 2059 | AK1: 2060 | AL1: 2061 | AM1: 2062 | AN1: 2063 | AO1: 2064 | AP1: 2065 | AQ1: 2066 | AR1: 2067 | AS1: 2068 | AT1: 2069 | AU1: 2070 | AV1: 2071 | AW1: 2072 | AX1: 2073 | AY1: 2074 | AZ1: 2075
A2: Emerging Markets - Equities | B2: 0.001 | C2: =B2 -> 0.001 | D2: =C2 -> 0.001 | E2: =D2 -> 0.001 | F2: =E2 -> 0.001 | G2: =F2 -> 0.001 | H2: =G2 -> 0.001 | I2: =H2 -> 0.001 | J2: =I2 -> 0.001 | K2: =J2 -> 0.001 | L2: 0.04 | M2: =L2 -> 0.04 | N2: =M2 -> 0.04 | O2: =N2 -> 0.04 | P2: =O2 -> 0.04 | Q2: =P2 -> 0.04 | R2: =Q2 -> 0.04 | S2: =R2 -> 0.04 | T2: =S2 -> 0.04 | ... AZ2: =AY2 -> 0.04
A3: Developed Markets - Equities | B3: 0.001 | C3: =B3 -> 0.001 | D3: =C3 -> 0.001 | E3: =D3 -> 0.001 | F3: =E3 -> 0.001 | G3: =F3 -> 0.001 | H3: =G3 -> 0.001 | I3: =H3 -> 0.001 | J3: =I3 -> 0.001 | K3: =J3 -> 0.001 | L3: 0.04 | M3: =L3 -> 0.04 | N3: =M3 -> 0.04 | O3: =N3 -> 0.04 | P3: =O3 -> 0.04 | Q3: =P3 -> 0.04 | R3: =Q3 -> 0.04 | S3: =R3 -> 0.04 | T3: =S3 -> 0.04 | ... AZ3: =AY3 -> 0.04
A4: Emerging Markets State - Obligations | B4: 0.001 | C4: =B4 -> 0.001 | D4: =C4 -> 0.001 | E4: =D4 -> 0.001 | F4: =E4 -> 0.001 | G4: =F4 -> 0.001 | H4: =G4 -> 0.001 | I4: =H4 -> 0.001 | J4: =I4 -> 0.001 | K4: =J4 -> 0.001 | L4: 0.04 | M4: =L4 -> 0.04 | N4: =M4 -> 0.04 | O4: =N4 -> 0.04 | P4: =O4 -> 0.04 | Q4: =P4 -> 0.04 | R4: =Q4 -> 0.04 | S4: =R4 -> 0.04 | T4: =S4 -> 0.04 | ... AZ4: =AY4 -> 0.04
A5: High Yield Bonds - Obligations | B5: 0.001 | C5: =B5 -> 0.001 | D5: =C5 -> 0.001 | E5: =D5 -> 0.001 | F5: =E5 -> 0.001 | G5: =F5 -> 0.001 | H5: =G5 -> 0.001 | I5: =H5 -> 0.001 | J5: =I5 -> 0.001 | K5: =J5 -> 0.001 | L5: 0.04 | M5: =L5 -> 0.04 | N5: =M5 -> 0.04 | O5: =N5 -> 0.04 | P5: =O5 -> 0.04 | Q5: =P5 -> 0.04 | R5: =Q5 -> 0.04 | S5: =R5 -> 0.04 | T5: =S5 -> 0.04 | ... AZ5: =AY5 -> 0.04
A6: Investment Grade Bonds - Obligations | B6: 0.001 | C6: =B6 -> 0.001 | D6: =C6 -> 0.001 | E6: =D6 -> 0.001 | F6: =E6 -> 0.001 | G6: =F6 -> 0.001 | H6: =G6 -> 0.001 | I6: =H6 -> 0.001 | J6: =I6 -> 0.001 | K6: =J6 -> 0.001 | L6: 0.04 | M6: =L6 -> 0.04 | N6: =M6 -> 0.04 | O6: =N6 -> 0.04 | P6: =O6 -> 0.04 | Q6: =P6 -> 0.04 | R6: =Q6 -> 0.04 | S6: =R6 -> 0.04 | T6: =S6 -> 0.04 | ... AZ6: =AY6 -> 0.04
A7: Government ZC Bonds - Obligations | B7: 0.001 | C7: =B7 -> 0.001 | D7: =C7 -> 0.001 | E7: =D7 -> 0.001 | F7: =E7 -> 0.001 | G7: =F7 -> 0.001 | H7: =G7 -> 0.001 | I7: =H7 -> 0.001 | J7: =I7 -> 0.001 | K7: =J7 -> 0.001 | L7: 0.04 | M7: =L7 -> 0.04 | N7: =M7 -> 0.04 | O7: =N7 -> 0.04 | P7: =O7 -> 0.04 | Q7: =P7 -> 0.04 | R7: =Q7 -> 0.04 | S7: =R7 -> 0.04 | T7: =S7 -> 0.04 | ... AZ7: =AY7 -> 0.04

Sheet Returns
B1: 2025 | C1: 2026 | D1: 2027 | E1: 2028 | F1: 2029 | G1: 2030 | H1: 2031 | I1: 2032 | J1: 2033 | K1: 2034 | L1: 2035 | M1: 2036 | N1: 2037 | O1: 2038 | P1: 2039 | Q1: 2040 | R1: 2041 | S1: 2042 | T1: 2043 | U1: 2044 | V1: 2045 | W1: 2046 | X1: 2047 | Y1: 2048 | Z1: 2049 | AA1: 2050 | AB1: 2051 | AC1: 2052 | AD1: 2053 | AE1: 2054 | AF1: 2055 | AG1: 2056 | AH1: 2057 | AI1: 2058 | AJ1: 2059 | AK1: 2060 | AL1: 2061 | AM1: 2062 | AN1: 2063 | AO1: 2064 | AP1: 2065 | AQ1: 2066 | AR1: 2067 | AS1: 2068 | AT1: 2069 | AU1: 2070 | AV1: 2071 | AW1: 2072 | AX1: 2073 | AY1: 2074 | AZ1: 2075
A2: Emerging Markets - Equities | B2: =8.6%-_xlfn.XLOOKUP(A2,BasisPointCost!$A:$A,BasisPointCost!$B:$B) -> 0.084 | C2: =B2 -> 0.084 | D2: =C2 -> 0.084 | E2: =D2 -> 0.084 | F2: =E2 -> 0.084 | G2: =F2 -> 0.084 | H2: =G2 -> 0.084 | I2: =H2 -> 0.084 | J2: =I2 -> 0.084 | K2: =J2 -> 0.084 | L2: =6.5%-0.2% -> 0.063 | M2: =L2 -> 0.063 | N2: =M2 -> 0.063 | O2: =N2 -> 0.063 | P2: =O2 -> 0.063 | Q2: =P2 -> 0.063 | R2: =Q2 -> 0.063 | S2: =R2 -> 0.063 | T2: =S2 -> 0.063 | ... AZ2: =AY2 -> 0.063
A3: Developed Markets - Equities | B3: =7%-_xlfn.XLOOKUP(A3,BasisPointCost!$A:$A,BasisPointCost!$B:$B) -> 0.068 | C3: =B3 -> 0.068 | D3: =C3 -> 0.068 | E3: =D3 -> 0.068 | F3: =E3 -> 0.068 | G3: =F3 -> 0.068 | H3: =G3 -> 0.068 | I3: =H3 -> 0.068 | J3: =I3 -> 0.068 | K3: =J3 -> 0.068 | L3: =6.5%-0.2% -> 0.063 | M3: =L3 -> 0.063 | N3: =M3 -> 0.063 | O3: =N3 -> 0.063 | P3: =O3 -> 0.063 | Q3: =P3 -> 0.063 | R3: =Q3 -> 0.063 | S3: =R3 -> 0.063 | T3: =S3 -> 0.063 | ... AZ3: =AY3 -> 0.063
A4: Emerging Markets State - Obligations | B4: =4.9%-_xlfn.XLOOKUP(A4,BasisPointCost!$A:$A,BasisPointCost!$B:$B) -> 0.0483 | C4: =B4 -> 0.0483 | D4: =C4 -> 0.0483 | E4: =D4 -> 0.0483 | F4: =E4 -> 0.0483 | G4: =F4 -> 0.0483 | H4: =G4 -> 0.0483 | I4: =H4 -> 0.0483 | J4: =I4 -> 0.0483 | K4: =J4 -> 0.0483 | L4: =3.5%-0.07% -> 0.0343 | M4: =L4 -> 0.0343 | N4: =M4 -> 0.0343 | O4: =N4 -> 0.0343 | P4: =O4 -> 0.0343 | Q4: =P4 -> 0.0343 | R4: =Q4 -> 0.0343 | S4: =R4 -> 0.0343 | T4: =S4 -> 0.0343 | ... AZ4: =AY4 -> 0.0343
A5: High Yield Bonds - Obligations | B5: =5%-_xlfn.XLOOKUP(A5,BasisPointCost!$A:$A,BasisPointCost!$B:$B) -> 0.0493 | C5: =B5 -> 0.0493 | D5: =C5 -> 0.0493 | E5: =D5 -> 0.0493 | F5: =E5 -> 0.0493 | G5: =F5 -> 0.0493 | H5: =G5 -> 0.0493 | I5: =H5 -> 0.0493 | J5: =I5 -> 0.0493 | K5: =J5 -> 0.0493 | L5: =3.5%-0.07% -> 0.0343 | M5: =L5 -> 0.0343 | N5: =M5 -> 0.0343 | O5: =N5 -> 0.0343 | P5: =O5 -> 0.0343 | Q5: =P5 -> 0.0343 | R5: =Q5 -> 0.0343 | S5: =R5 -> 0.0343 | T5: =S5 -> 0.0343 | ... AZ5: =AY5 -> 0.0343
A6: Investment Grade Bonds - Obligations | B6: =3.7%-_xlfn.XLOOKUP(A6,BasisPointCost!$A:$A,BasisPointCost!$B:$B) -> 0.0363 | C6: =B6 -> 0.0363 | D6: =C6 -> 0.0363 | E6: =D6 -> 0.0363 | F6: =E6 -> 0.0363 | G6: =F6 -> 0.0363 | H6: =G6 -> 0.0363 | I6: =H6 -> 0.0363 | J6: =I6 -> 0.0363 | K6: =J6 -> 0.0363 | L6: =3.5%-0.07% -> 0.0343 | M6: =L6 -> 0.0343 | N6: =M6 -> 0.0343 | O6: =N6 -> 0.0343 | P6: =O6 -> 0.0343 | Q6: =P6 -> 0.0343 | R6: =Q6 -> 0.0343 | S6: =R6 -> 0.0343 | T6: =S6 -> 0.0343 | ... AZ6: =AY6 -> 0.0343
A7: Government ZC Bonds - Obligations | B7: =2.9%-_xlfn.XLOOKUP($A7,BasisPointCost!$A:$A,BasisPointCost!$B:$B) -> 0.0283 | C7: =B7 -> 0.0283 | D7: =C7 -> 0.0283 | E7: =D7 -> 0.0283 | F7: =E7 -> 0.0283 | G7: =F7 -> 0.0283 | H7: =G7 -> 0.0283 | I7: =H7 -> 0.0283 | J7: =I7 -> 0.0283 | K7: =J7 -> 0.0283 | L7: =3.5%-0.07% -> 0.0343 | M7: =L7 -> 0.0343 | N7: =M7 -> 0.0343 | O7: =N7 -> 0.0343 | P7: =O7 -> 0.0343 | Q7: =P7 -> 0.0343 | R7: =Q7 -> 0.0343 | S7: =R7 -> 0.0343 | T7: =S7 -> 0.0343 | ... AZ7: =AY7 -> 0.0343

Sheet BasisPointCost
A1: Asset | B1: Cost (Basis Point) | C1: Link
A2: Emerging Markets - Equities | B2: =0.2% -> 0.002
A3: Developed Markets - Equities | B3: =0.2% -> 0.002
A4: Emerging Markets State - Obligations | B4: =0.07% -> 0.0007
A5: High Yield Bonds - Obligations | B5: =0.07% -> 0.0007
A6: Investment Grade Bonds - Obligations | B6: =0.07% -> 0.0007
A7: Government ZC Bonds - Obligations | B7: =0.07% -> 0.0007

Sheet Returns2
B1: 2035 | C1: 2036 | D1: 2037 | E1: 2038 | F1: 2039 | G1: 2040 | H1: 2041 | I1: 2042 | J1: 2043 | K1: 2044 | L1: 2045 | M1: 2046 | N1: 2047 | O1: 2048 | P1: 2049 | Q1: 2050 | R1: 2051 | S1: 2052 | T1: 2053 | U1: 2054 | V1: 2055 | W1: 2056 | X1: 2057 | Y1: 2058 | Z1: 2059 | AA1: 2060 | AB1: 2061 | AC1: 2062 | AD1: 2063 | AE1: 2064 | AF1: 2065 | AG1: 2066 | AH1: 2067 | AI1: 2068 | AJ1: 2069 | AK1: 2070 | AL1: 2071 | AM1: 2072 | AN1: 2073 | AO1: 2074 | AP1: 2075
A2: Equities | B2: =6.5%-0.2% -> 0.063 | C2: =B2 -> 0.063 | D2: =C2 -> 0.063 | E2: =D2 -> 0.063 | F2: =E2 -> 0.063 | G2: =F2 -> 0.063 | H2: =G2 -> 0.063 | I2: =H2 -> 0.063 | J2: =I2 -> 0.063 | ... AP2: =AO2 -> 0.063
A3: Obligations | B3: =3.5%-0.07% -> 0.0343 | C3: =B3 -> 0.0343 | D3: =C3 -> 0.0343 | E3: =D3 -> 0.0343 | F3: =E3 -> 0.0343 | G3: =F3 -> 0.0343 | H3: =G3 -> 0.0343 | I3: =H3 -> 0.0343 | J3: =I3 -> 0.0343 | ... AP3: =AO3 -> 0.0343

Sheet Volatilities
B1: volatility
A2: Emerging Markets - Equities | B2: 0.086
A3: Developed Markets - Equities | B3: 0.07
A4: Emerging Markets State - Obligations | B4: 0.049
A5: High Yield Bonds - Obligations | B5: 0.05
A6: Investment Grade Bonds - Obligations | B6: 0.037
A7: Government ZC Bonds - Obligations | B7: 0.029

Sheet Volatilities2
B1: volatility
A2: Equities | B2: 0.18
A3: Obligations | B3: 0.08

Sheet Correlation
B1: Government ZC Bonds - Obligations | C1: Investment Grade Bonds - Obligations | D1: High Yield Bonds - Obligations | E1: Emerging Markets State - Obligations | F1: Developed Markets - Equities | G1: Emerging Markets - Equities
A2: Government ZC Bonds - Obligations | B2: 1 | C2: 0.6 | D2: 0.2 | E2: 0.4 | F2: 0 | G2: 0
A3: Investment Grade Bonds - Obligations | B3: 0.6 | C3: 1 | D3: 0.7 | E3: 0.6 | F3: 0.3 | G3: 0.3
A4: High Yield Bonds - Obligations | B4: 0.2 | C4: 0.7 | D4: 1 | E4: 0.7 | F4: 0.7 | G4: 0.6
A5: Emerging Markets State - Obligations | B5: 0.4 | C5: 0.6 | D5: 0.7 | E5: 1 | F5: 0.5 | G5: 0.7
A6: Developed Markets - Equities | B6: 0 | C6: 0.3 | D6: 0.7 | E6: 0.5 | F6: 1 | G6: 0.7
A7: Emerging Markets - Equities | B7: 0 | C7: 0.3 | D7: 0.6 | E7: 0.7 | F7: 0.7 | G7: 1

Sheet Correlation2
B1: Obligations | C1: Equities
A2: {=TRANSPOSE(B1:C1)} -> Obligations | B2: 1 | C2: 0
A3: Equities | B3: 0 | C3: 1
